Workbook

Sheet README
A1: Responsiveness of industrial PROCESS emissions to carbon prices - CBAM sectors
A2: Built 2026-10-02. Companion to ProcessEmissions_CarbonPriceResponse_Report.md/.docx (same folder).
A4: Sheets
A5: Parameters - option-level MACC inputs per sector (yellow cells are editable inputs; all downstream cells are formulas).
A6: Results - % process-emission reduction a(tau) at tau = 20/50/100/150/200 USD2019/tCO2e for the 2030 (deployment-constrained) and long-run horizons, the central case, and implied semi-elasticities.
A7: SemiElasticity - derivation of the iso-semi-elastic model, worked example, bin-consistency check and saturating alternative.
A8: IPCC_Aggregate - benchmark using IPCC AR6 WGIII Table 12.3 (2030 potentials by cost bin) against 2030 reference process emissions.
A9: IPCC_T12_3, IPCC_T11_3, AR4_T7_9 - source extracts.
A10: Econometric - empirical EU ETS evidence (total emissions, for comparison only).
A11: Sources - full reference list.
A13: Model
A14: f_i(tau) = MIN(1, MAX(0, (tau - c_low_i)/(c_high_i - c_low_i))) share of plants for which option i is in the money at carbon price tau (uniform cost heterogeneity).
... A19: Same parameters are applied to Egypt and non-Egypt (user instruction); Egypt-specific remarks in report section 9.

Sheet CPAT_v0.8_Table
A1: Drop-in parameter table for CPAT_Industry_Kernel_Egypt_v0.8.xlsx - 'Manual inputs' rows 39-47 (D: Process, E: Half Elasticity, F: ER at $100)
A2: Kernel convention (reverse-engineered from v0.8 values): Half Elasticity = -LN(1 - ER)/100, positive, fraction per USD/tCO2e; ER at $100 is a fraction (0.10 = 10%). Identical to this report's beta_iso with sign reversed and divided by 100. Recommended column = CENTRAL (see report A5/A11); 2030 and long-run alternatives on the right. Current v0.8 values shown for comparison.
A4: Process | B4: Half Elasticity | C4: ER at $100 (%) | E4: Half Elast. 2030 | F4: ER $100 2030 | G4: Half Elast. LR | H4: ER $100 LR | J4: v0.8 Half Elast. | K4: v0.8 ER $100 | L4: Mapping / note
A5: DRI-EAF steel | B5: =-LN(1-C5)/100 | C5: 0.3433 | E5: =-LN(1-F5)/100 | F5: 0.1133 | G5: =-LN(1-H5)/100 | H5: 0.5734 | J5: 0.0010536052 | K5: 0.1 | L5: Report 7.3. Scope includes NG-reductant CO2, which the kernel classifies as fp (priced with fuel flags); the kernel applies the same half elasticity to fuel and process ER (Mitigation_Industry rows 351 and 362), so the mismatch is immaterial.
A6: Scrap-EAF steel | B6: =-LN(1-C6)/100 | C6: 0.181 | E6: =-LN(1-F6)/100 | F6: 0.0951 | G6: =-LN(1-H6)/100 | H6: 0.2669 | J6: 0.00020202707 | K6: 0.02 | L6: Report 7.4 (electrode/charge carbon and flux CO2).
A7: BF-BOF steel reference | B7: =-LN(1-C7)/100 | C7: 0.2803 | E7: =-LN(1-F7)/100 | F7: 0.1016 | G7: =-LN(1-H7)/100 | H7: 0.4589 | J7: 0.00051293294 | K7: 0.05 | L7: Report 7.2 (coke/limestone CO2; TGR+CCUS, H2-DRI switch, scrap share).
A8: Grey clinker dry-process | B8: =-LN(1-C8)/100 | C8: 0.3352 | E8: =-LN(1-F8)/100 | F8: 0.1925 | G8: =-LN(1-H8)/100 | H8: 0.4779 | J8: 0.00083381609 | K8: 0.08 | L8: Report 7.1 (calcination CO2; clinker substitution, CCUS, alternative binders).
A9: Ammonia net | B9: =-LN(1-C9)/100 | C9: 0.2974 | E9: =-LN(1-F9)/100 | F9: 0.1499 | G9: =-LN(1-H9)/100 | H9: 0.4449 | J9: 0.0019845094 | K9: 0.18 | L9: Report 7.6 (SMR feedstock CO2 = kernel fp; CCS of separated stream, electrolytic H2). Applies to merchant/non-urea NH3.
A10: Urea | B10: =-LN(1-C10)/100 | C10: 0.1158 | E10: =-LN(1-F10)/100 | F10: 0.0479 | G10: =-LN(1-H10)/100 | H10: 0.1838 | J10: 0 | K10: 0 | L10: Report 7.7 (embedded NH3-stage CO2 counted under CBAM; abatement only via surplus-CO2 CCS or electrolytic H2 + alternative CO2). Kernel v0.8 has 0 because own np is floored at 0; use this value only if the embedded-NH3 column (M35) is priced.
A11: AN | B11: =-LN(1-C11)/100 | C11: 0.721 | E11: =-LN(1-F11)/100 | F11: 0.6764 | G11: =-LN(1-H11)/100 | H11: 0.7656 | J11: 0.010498221 | K11: 0.65 | L11: Report 7.9 composite, UNABATED nitric-acid N2O baseline - consistent with kernel S1.no = 0.97 tCO2e/t AN (K36). If Egyptian plants are already catalytically abated, use the 'AN abated' row instead: ER(100) = 32.9%.
A12: Primary aluminium | B12: =-LN(1-C12)/100 | C12: 0.2164 | E12: =-LN(1-F12)/100 | F12: 0.0691 | G12: =-LN(1-H12)/100 | H12: 0.3638 | J12: 0.00083381609 | K12: 0.08 | L12: Report 7.5 (anode CO2 + PFC; PFC control, inert anodes).
A14: How to paste: copy B5:C12 into 'Manual inputs'!E40:F47 (values only, or keep the formula in E so that F remains the single input). Row labels match v0.8 D40:D47 exactly.
A15: Caveat: the kernel reuses this table for fuel-combustion ER (Mitigation_Industry row 351). The values here are derived for process emissions; fuel-combustion responsiveness is governed by the master elasticity table (Data_Elast) elsewhere in CPAT and may warrant a separate row set.
A16: Prices are USD2019/tCO2e; USD100 (2019) ~ USD122 (2024). If the kernel's price path is in nominal/2024 dollars, deflate before applying, or scale ER accordingly (Results sheet gives a(tau) for 20/50/100/150/200).

Sheet Parameters
A1: Option-level MACC parameters (yellow = input). Costs in USD2019/tCO2e. See README for formulas.
A2: Price points tau -> | J2: 20 | K2: 50 | L2: 100 | M2: 150 | N2: 200
A3: Sector key | B3: Sector | C3: Option | D3: c_low | E3: c_high | F3: r (tech. reduction) | G3: s (applicable share) | H3: d_2030 | I3: d_LR | J3: f(tau=20) | K3: f(tau=50) | L3: f(tau=100) | M3: f(tau=150) | N3: f(tau=200) | O3: x2030(tau=20) | P3: x2030(tau=50) | Q3: x2030(tau=100) | R3: x2030(tau=150) | S3: x2030(tau=200) | T3: xLR(tau=20) | U3: xLR(tau=50) | V3: xLR(tau=100) | W3: xLR(tau=150) | X3: xLR(tau=200) | Y3: Source / notes
A4: CEM | B4: Cement clinker / cement / concrete | C4: Clinker substitution (SCMs: slag, fly ash, calcined clay/LC3, limestone filler) and blended cements | D4: 0 | E4: 50 | F4: 0.3 | G4: 1 | H4: 0.55 | I4: 0.85 | J4: =IF(E4<=D4,IF(J$2>=D4,1,0),MIN(1,MAX(0,(J$2-D4)/(E4-D4)))) | K4: =IF(E4<=D4,IF(K$2>=D4,1,0),MIN(1,MAX(0,(K$2-D4)/(E4-D4)))) | L4: =IF(E4<=D4,IF(L$2>=D4,1,0),MIN(1,MAX(0,(L$2-D4)/(E4-D4)))) | M4: =IF(E4<=D4,IF(M$2>=D4,1,0),MIN(1,MAX(0,(M$2-D4)/(E4-D4)))) | N4: =IF(E4<=D4,IF(N$2>=D4,1,0),MIN(1,MAX(0,(N$2-D4)/(E4-D4)))) | O4: =F4*G4*H4*J4 | P4: =F4*G4*H4*K4 | Q4: =F4*G4*H4*L4 | R4: =F4*G4*H4*M4 | S4: =F4*G4*H4*N4 | T4: =F4*G4*I4*J4 | U4: =F4*G4*I4*K4 | V4: =F4*G4*I4*L4 | W4: =F4*G4*I4*M4 | X4: =F4*G4*I4*N4 | Y4: IPCC AR6 Table 11.3: clinker substitution 40-50% reduction of plant GHG at 'near-zero' cost; Table 12.3: cementitious substitution 0.28 Gt in USD20-50 bin (2030); Fig 11.13 FeedCI 20-50. r=0.30 from clinker ratio 0.71 (2019, Ch.11) -> technical floor ~0.50 (IEA G7 2022): 1-0.50/0.71. d2030=0.55 reproduces 0.28 Gt / ~1.65 Gt 2030 reference calcination CO2 (~17%).
A5: CEM | B5: Cement clinker / cement / concrete | C5: Novel binders / alternative chemistries (CSA, belite, alkali-activated) in niche applications | D5: 50 | E5: 150 | F5: 0.5 | G5: 0.2 | H5: 0.1 | I5: 0.5 | J5: =IF(E5<=D5,IF(J$2>=D5,1,0),MIN(1,MAX(0,(J$2-D5)/(E5-D5)))) | K5: =IF(E5<=D5,IF(K$2>=D5,1,0),MIN(1,MAX(0,(K$2-D5)/(E5-D5)))) | L5: =IF(E5<=D5,IF(L$2>=D5,1,0),MIN(1,MAX(0,(L$2-D5)/(E5-D5)))) | M5: =IF(E5<=D5,IF(M$2>=D5,1,0),MIN(1,MAX(0,(M$2-D5)/(E5-D5)))) | N5: =IF(E5<=D5,IF(N$2>=D5,1,0),MIN(1,MAX(0,(N$2-D5)/(E5-D5)))) | O5: =F5*G5*H5*J5 | P5: =F5*G5*H5*K5 | Q5: =F5*G5*H5*L5 | R5: =F5*G5*H5*M5 | S5: =F5*G5*H5*N5 | T5: =F5*G5*I5*J5 | U5: =F5*G5*I5*K5 | V5: =F5*G5*I5*L5 | W5: =F5*G5*I5*M5 | X5: =F5*G5*I5*N5 | Y5: IPCC AR6 SPM C.5.2: 'until new chemistries are mastered'; Ch.11 11.4.1.2. Cost range analyst judgement; niche share s=0.2.
A6: CEM | B6: Cement clinker / cement / concrete | C6: CO2 capture on calcination stream (indirect calcination/LEILAC, oxyfuel, post-combustion) + transport & storage | D6: 50 | E6: 130 | F6: 0.9 | G6: 1 | H6: 0.05 | I6: 0.5 | J6: =IF(E6<=D6,IF(J$2>=D6,1,0),MIN(1,MAX(0,(J$2-D6)/(E6-D6)))) | K6: =IF(E6<=D6,IF(K$2>=D6,1,0),MIN(1,MAX(0,(K$2-D6)/(E6-D6)))) | L6: =IF(E6<=D6,IF(L$2>=D6,1,0),MIN(1,MAX(0,(L$2-D6)/(E6-D6)))) | M6: =IF(E6<=D6,IF(M$2>=D6,1,0),MIN(1,MAX(0,(M$2-D6)/(E6-D6)))) | N6: =IF(E6<=D6,IF(N$2>=D6,1,0),MIN(1,MAX(0,(N$2-D6)/(E6-D6)))) | O6: =F6*G6*H6*J6 | P6: =F6*G6*H6*K6 | Q6: =F6*G6*H6*L6 | R6: =F6*G6*H6*M6 | S6: =F6*G6*H6*N6 | T6: =F6*G6*I6*J6 | U6: =F6*G6*I6*K6 | V6: =F6*G6*I6*L6 | W6: =F6*G6*I6*M6 | X6: =F6*G6*I6*N6 | Y6: IPCC AR6 Table 11.3: CCUS 99% of calcination CO2 at <=USD40 capture (TRL 5-7, 2025) + storage of concentrated CO2 USD10-40 (fn f) -> ~50-80 USD; diluted post-combustion 60-170 (Leeson 2017), most <120; Fig 11.13 cement CCUS 60-130; Rootzen & Johnsson 25-110 EUR; ETC 110-130. Table 12.3 puts 2030 industrial CCUS wholly in USD100-200 bin -> d2030 ~0. dLR=0.5 (storage access; Material Economics CCS share 29-79%, Table 11.5).
A7: BOF | B7: Primary steel: BF-BOF route | C7: Incremental: higher scrap charge in BOF, H2/biomass/plastics injection in BF, top-gas efficiency | D7: 20 | E7: 80 | F7: 0.2 | G7: 1 | H7: 0.3 | I7: 0.7 | J7: =IF(E7<=D7,IF(J$2>=D7,1,0),MIN(1,MAX(0,(J$2-D7)/(E7-D7)))) | K7: =IF(E7<=D7,IF(K$2>=D7,1,0),MIN(1,MAX(0,(K$2-D7)/(E7-D7)))) | L7: =IF(E7<=D7,IF(L$2>=D7,1,0),MIN(1,MAX(0,(L$2-D7)/(E7-D7)))) | M7: =IF(E7<=D7,IF(M$2>=D7,1,0),MIN(1,MAX(0,(M$2-D7)/(E7-D7)))) | N7: =IF(E7<=D7,IF(N$2>=D7,1,0),MIN(1,MAX(0,(N$2-D7)/(E7-D7)))) | O7: =F7*G7*H7*J7 | P7: =F7*G7*H7*K7 | Q7: =F7*G7*H7*L7 | R7: =F7*G7*H7*M7 | S7: =F7*G7*H7*N7 | T7: =F7*G7*I7*J7 | U7: =F7*G7*I7*K7 | V7: =F7*G7*I7*L7 | W7: =F7*G7*I7*M7 | X7: =F7*G7*I7*N7 | Y7: IPCC AR6 Ch.11: H2 co-firing 30-40% max (coke needed for stack integrity); 15% energy-efficiency potential (Fig 11.8); bio-coal limited by biomass demand. Costs: Fig 11.13 steel EE <20, ME/circ 20-50, FeedCI 20-80.
A8: BOF | B8: Primary steel: BF-BOF route | C8: BF-BOF with top-gas recycling + CCUS (retrofit, <=50-60% capture) | D8: 70 | E8: 130 | F8: 0.6 | G8: 1 | H8: 0.03 | I8: 0.4 | J8: =IF(E8<=D8,IF(J$2>=D8,1,0),MIN(1,MAX(0,(J$2-D8)/(E8-D8)))) | K8: =IF(E8<=D8,IF(K$2>=D8,1,0),MIN(1,MAX(0,(K$2-D8)/(E8-D8)))) | L8: =IF(E8<=D8,IF(L$2>=D8,1,0),MIN(1,MAX(0,(L$2-D8)/(E8-D8)))) | M8: =IF(E8<=D8,IF(M$2>=D8,1,0),MIN(1,MAX(0,(M$2-D8)/(E8-D8)))) | N8: =IF(E8<=D8,IF(N$2>=D8,1,0),MIN(1,MAX(0,(N$2-D8)/(E8-D8)))) | O8: =F8*G8*H8*J8 | P8: =F8*G8*H8*K8 | Q8: =F8*G8*H8*L8 | R8: =F8*G8*H8*M8 | S8: =F8*G8*H8*N8 | T8: =F8*G8*I8*J8 | U8: =F8*G8*I8*K8 | V8: =F8*G8*I8*L8 | W8: =F8*G8*I8*M8 | X8: =F8*G8*I8*N8 | Y8: IPCC AR6 Table 11.3: BF-BOF + TGR + CCUS 60% at USD70-130 (2025-30); Ch.11: hard to retrofit beyond 50% capture; Fig 11.13 steel CCUS 60-100. Table 12.3 2030 CCUS in 100-200 bin -> d2030 ~0.
A9: BOF | B9: Primary steel: BF-BOF route | C9: Route switch at relining: H2-DRI-EAF (or HIsarna+CCS, syngas DRI+CCS) | D9: 40 | E9: 120 | F9: 0.95 | G9: 1 | H9: 0.05 | I9: 0.4 | J9: =IF(E9<=D9,IF(J$2>=D9,1,0),MIN(1,MAX(0,(J$2-D9)/(E9-D9)))) | K9: =IF(E9<=D9,IF(K$2>=D9,1,0),MIN(1,MAX(0,(K$2-D9)/(E9-D9)))) | L9: =IF(E9<=D9,IF(L$2>=D9,1,0),MIN(1,MAX(0,(L$2-D9)/(E9-D9)))) | M9: =IF(E9<=D9,IF(M$2>=D9,1,0),MIN(1,MAX(0,(M$2-D9)/(E9-D9)))) | N9: =IF(E9<=D9,IF(N$2>=D9,1,0),MIN(1,MAX(0,(N$2-D9)/(E9-D9)))) | O9: =F9*G9*H9*J9 | P9: =F9*G9*H9*K9 | Q9: =F9*G9*H9*L9 | R9: =F9*G9*H9*M9 | S9: =F9*G9*H9*N9 | T9: =F9*G9*I9*J9 | U9: =F9*G9*I9*K9 | V9: =F9*G9*I9*L9 | W9: =F9*G9*I9*M9 | X9: =F9*G9*I9*N9 | Y9: IPCC AR6 Table 11.3: H2-DRI-EAF up to 99% at USD39-79 (EUR40/MWh electricity); HIsarna+CCS 80-90% at USD40-70; syngas DRI-EAF+CCUS >=90% at >=USD40; ETC steel avg USD60; Material Economics new-process pathway EUR91. Upper bound 120 reflects higher electricity prices. SPM C.5.2: H2-DRI 'near-commercial'. Relining cycle 15-25 yrs -> dLR=0.4 at USD100.
A10: DRI | B10: Primary steel: natural-gas DRI-EAF route (Egypt-type) | C10: CO2 capture on DRI process gas (concentrated top-gas stream) + T&S (Al Reyadah/Emirates Steel type) | D10: 40 | E10: 90 | F10: 0.85 | G10: 0.85 | H10: 0.1 | I10: 0.6 | J10: =IF(E10<=D10,IF(J$2>=D10,1,0),MIN(1,MAX(0,(J$2-D10)/(E10-D10)))) | K10: =IF(E10<=D10,IF(K$2>=D10,1,0),MIN(1,MAX(0,(K$2-D10)/(E10-D10)))) | L10: =IF(E10<=D10,IF(L$2>=D10,1,0),MIN(1,MAX(0,(L$2-D10)/(E10-D10)))) | M10: =IF(E10<=D10,IF(M$2>=D10,1,0),MIN(1,MAX(0,(M$2-D10)/(E10-D10)))) | N10: =IF(E10<=D10,IF(N$2>=D10,1,0),MIN(1,MAX(0,(N$2-D10)/(E10-D10)))) | O10: =F10*G10*H10*J10 | P10: =F10*G10*H10*K10 | Q10: =F10*G10*H10*L10 | R10: =F10*G10*H10*M10 | S10: =F10*G10*H10*N10 | T10: =F10*G10*I10*J10 | U10: =F10*G10*I10*K10 | V10: =F10*G10*I10*L10 | W10: =F10*G10*I10*M10 | X10: =F10*G10*I10*N10 | Y10: IPCC AR6 Table 11.3: syngas DRI-EAF + CCUS >=90% at >=USD40; Ch.11 11.4.1.1 Abu Dhabi DRI capture operating since 2016; concentrated-CO2 storage USD10-40 (fn f). s=0.85 = DRI share of route process emissions.
A11: DRI | B11: Primary steel: natural-gas DRI-EAF route (Egypt-type) | C11: Hydrogen blending <=30% in existing DRI shaft (no process change) | D11: 70 | E11: 400 | F11: 0.3 | G11: 0.85 | H11: 0.3 | I11: 0.8 | J11: =IF(E11<=D11,IF(J$2>=D11,1,0),MIN(1,MAX(0,(J$2-D11)/(E11-D11)))) | K11: =IF(E11<=D11,IF(K$2>=D11,1,0),MIN(1,MAX(0,(K$2-D11)/(E11-D11)))) | L11: =IF(E11<=D11,IF(L$2>=D11,1,0),MIN(1,MAX(0,(L$2-D11)/(E11-D11)))) | M11: =IF(E11<=D11,IF(M$2>=D11,1,0),MIN(1,MAX(0,(M$2-D11)/(E11-D11)))) | N11: =IF(E11<=D11,IF(N$2>=D11,1,0),MIN(1,MAX(0,(N$2-D11)/(E11-D11)))) | O11: =F11*G11*H11*J11 | P11: =F11*G11*H11*K11 | Q11: =F11*G11*H11*L11 | R11: =F11*G11*H11*M11 | S11: =F11*G11*H11*N11 | T11: =F11*G11*I11*J11 | U11: =F11*G11*I11*K11 | V11: =F11*G11*I11*L11 | W11: =F11*G11*I11*M11 | X11: =F11*G11*I11*N11 | Y11: IPCC AR6 Ch.11: <=30% H2 substitutable without process change. Cost = H2 premium: at H2 USD1.0-3.0/kg vs gas USD5/MMBtu, abatement cost ~70-400 USD/tCO2 (own calc.: 1 kg H2 displaces 0.114 MMBtu gas = 6 kgCO2).
A12: DRI | B12: Primary steel: natural-gas DRI-EAF route (Egypt-type) | C12: Full conversion to H2-DRI (electrolytic hydrogen) | D12: 40 | E12: 120 | F12: 0.95 | G12: 0.85 | H12: 0.05 | I12: 0.35 | J12: =IF(E12<=D12,IF(J$2>=D12,1,0),MIN(1,MAX(0,(J$2-D12)/(E12-D12)))) | K12: =IF(E12<=D12,IF(K$2>=D12,1,0),MIN(1,MAX(0,(K$2-D12)/(E12-D12)))) | L12: =IF(E12<=D12,IF(L$2>=D12,1,0),MIN(1,MAX(0,(L$2-D12)/(E12-D12)))) | M12: =IF(E12<=D12,IF(M$2>=D12,1,0),MIN(1,MAX(0,(M$2-D12)/(E12-D12)))) | N12: =IF(E12<=D12,IF(N$2>=D12,1,0),MIN(1,MAX(0,(N$2-D12)/(E12-D12)))) | O12: =F12*G12*H12*J12 | P12: =F12*G12*H12*K12 | Q12: =F12*G12*H12*L12 | R12: =F12*G12*H12*M12 | S12: =F12*G12*H12*N12 | T12: =F12*G12*I12*J12 | U12: =F12*G12*I12*K12 | V12: =F12*G12*I12*L12 | W12: =F12*G12*I12*M12 | X12: =F12*G12*I12*N12 | Y12: IPCC AR6 Table 11.3: H2-DRI-EAF up to 99% at USD39-79 (converted from EUR2018 34-68; EUR40/MWh). Brownfield DRI plants are the easiest conversion candidates.
A13: DRI | B13: Primary steel: natural-gas DRI-EAF route (Egypt-type) | C13: EAF: bio-based charge carbon/electrodes, lime from decarbonised kilns | D13: 50 | E13: 150 | F13: 0.5 | G13: 0.15 | H13: 0.2 | I13: 0.7 | J13: =IF(E13<=D13,IF(J$2>=D13,1,0),MIN(1,MAX(0,(J$2-D13)/(E13-D13)))) | K13: =IF(E13<=D13,IF(K$2>=D13,1,0),MIN(1,MAX(0,(K$2-D13)/(E13-D13)))) | L13: =IF(E13<=D13,IF(L$2>=D13,1,0),MIN(1,MAX(0,(L$2-D13)/(E13-D13)))) | M13: =IF(E13<=D13,IF(M$2>=D13,1,0),MIN(1,MAX(0,(M$2-D13)/(E13-D13)))) | N13: =IF(E13<=D13,IF(N$2>=D13,1,0),MIN(1,MAX(0,(N$2-D13)/(E13-D13)))) | O13: =F13*G13*H13*J13 | P13: =F13*G13*H13*K13 | Q13: =F13*G13*H13*L13 | R13: =F13*G13*H13*M13 | S13: =F13*G13*H13*N13 | T13: =F13*G13*I13*J13 | U13: =F13*G13*I13*K13 | V13: =F13*G13*I13*L13 | W13: =F13*G13*I13*M13 | X13: =F13*G13*I13*N13 | Y13: Analyst judgement; see scrap-EAF row for sources.
A14: EAF | B14: Secondary steel: scrap-EAF | C14: Operational optimisation (electrode consumption, carbon injection control, foamy-slag practice) | D14: 0 | E14: 20 | F14: 0.15 | G14: 0.7 | H14: 0.5 | I14: 0.8 | J14: =IF(E14<=D14,IF(J$2>=D14,1,0),MIN(1,MAX(0,(J$2-D14)/(E14-D14)))) | K14: =IF(E14<=D14,IF(K$2>=D14,1,0),MIN(1,MAX(0,(K$2-D14)/(E14-D14)))) | L14: =IF(E14<=D14,IF(L$2>=D14,1,0),MIN(1,MAX(0,(L$2-D14)/(E14-D14)))) | M14: =IF(E14<=D14,IF(M$2>=D14,1,0),MIN(1,MAX(0,(M$2-D14)/(E14-D14)))) | N14: =IF(E14<=D14,IF(N$2>=D14,1,0),MIN(1,MAX(0,(N$2-D14)/(E14-D14)))) | O14: =F14*G14*H14*J14 | P14: =F14*G14*H14*K14 | Q14: =F14*G14*H14*L14 | R14: =F14*G14*H14*M14 | S14: =F14*G14*H14*N14 | T14: =F14*G14*I14*J14 | U14: =F14*G14*I14*K14 | V14: =F14*G14*I14*L14 | W14: =F14*G14*I14*M14 | X14: =F14*G14*I14*N14 | Y14: Low/no-cost measures; s=0.7 = share of EAF process CO2 from carbon inputs (remainder = flux calcination). Analyst judgement, consistent with IPCC Fig 11.13 steel EE <USD20.
A15: EAF | B15: Secondary steel: scrap-EAF | C15: Bio-based charge carbon / biochar, bio-derived electrodes | D15: 50 | E15: 150 | F15: 0.6 | G15: 0.7 | H15: 0.2 | I15: 0.7 | J15: =IF(E15<=D15,IF(J$2>=D15,1,0),MIN(1,MAX(0,(J$2-D15)/(E15-D15)))) | K15: =IF(E15<=D15,IF(K$2>=D15,1,0),MIN(1,MAX(0,(K$2-D15)/(E15-D15)))) | L15: =IF(E15<=D15,IF(L$2>=D15,1,0),MIN(1,MAX(0,(L$2-D15)/(E15-D15)))) | M15: =IF(E15<=D15,IF(M$2>=D15,1,0),MIN(1,MAX(0,(M$2-D15)/(E15-D15)))) | N15: =IF(E15<=D15,IF(N$2>=D15,1,0),MIN(1,MAX(0,(N$2-D15)/(E15-D15)))) | O15: =F15*G15*H15*J15 | P15: =F15*G15*H15*K15 | Q15: =F15*G15*H15*L15 | R15: =F15*G15*H15*M15 | S15: =F15*G15*H15*N15 | T15: =F15*G15*I15*J15 | U15: =F15*G15*I15*K15 | V15: =F15*G15*I15*L15 | W15: =F15*G15*I15*M15 | X15: =F15*G15*I15*N15 | Y15: IPCC AR6 Ch.11: bio-based fuels can substitute part of coal input but limited by biomass demand; cost range from biochar price premium (analyst calc.).
... A28: HNO3_resid | B28: Nitric acid - residual N2O at already-abated plants (secondary -> tertiary) | C28: Upgrade to tertiary catalyst / optimisation of existing de-N2O | D28: 2 | E28: 10 | F28: 0.5 | G28: 1 | H28: 0.7 | I28: 0.9 | J28: =IF(E28<=D28,IF(J$2>=D28,1,0),MIN(1,MAX(0,(J$2-D28)/(E28-D28)))) | K28: =IF(E28<=D28,IF(K$2>=D28,1,0),MIN(1,MAX(0,(K$2-D28)/(E28-D28)))) | L28: =IF(E28<=D28,IF(L$2>=D28,1,0),MIN(1,MAX(0,(L$2-D28)/(E28-D28)))) | M28: =IF(E28<=D28,IF(M$2>=D28,1,0),MIN(1,MAX(0,(M$2-D28)/(E28-D28)))) | N28: =IF(E28<=D28,IF(N$2>=D28,1,0),MIN(1,MAX(0,(N$2-D28)/(E28-D28)))) | O28: =F28*G28*H28*J28 | P28: =F28*G28*H28*K28 | Q28: =F28*G28*H28*L28 | R28: =F28*G28*H28*M28 | S28: =F28*G28*H28*N28 | T28: =F28*G28*I28*J28 | U28: =F28*G28*I28*K28 | V28: =F28*G28*I28*L28 | W28: =F28*G28*I28*M28 | X28: =F28*G28*I28*N28 | Y28: Analyst assumption: half of residual N2O removable at same cost as primary abatement.

Sheet Results
A1: Process-emission abatement a(tau) by sector and horizon, and implied semi-elasticities (all formulas)
A3: Key | B3: Sector | C3: a_2030(20) | D3: a_2030(50) | E3: a_2030(100) | F3: a_2030(150) | G3: a_2030(200) | H3: a_LR(20) | I3: a_LR(50) | J3: a_LR(100) | K3: a_LR(150) | L3: a_LR(200) | M3: a_central(100) | N3: beta_iso 2030 (%/$) | O3: beta_iso LR (%/$) | P3: beta_iso central (%/$) | Q3: beta_linear central (%/$) | R3: elasticity at $100 (beta*100)
A4: CEM | B4: Cement clinker / cement / concrete | C4: =1-EXP(SUMPRODUCT(LN(1-Parameters!O4:O6))) | D4: =1-EXP(SUMPRODUCT(LN(1-Parameters!P4:P6))) | E4: =1-EXP(SUMPRODUCT(LN(1-Parameters!Q4:Q6))) | F4: =1-EXP(SUMPRODUCT(LN(1-Parameters!R4:R6))) | G4: =1-EXP(SUMPRODUCT(LN(1-Parameters!S4:S6))) | H4: =1-EXP(SUMPRODUCT(LN(1-Parameters!T4:T6))) | I4: =1-EXP(SUMPRODUCT(LN(1-Parameters!U4:U6))) | J4: =1-EXP(SUMPRODUCT(LN(1-Parameters!V4:V6))) | ... L4: =1-EXP(SUMPRODUCT(LN(1-Parameters!X4:X6))) | M4: =AVERAGE(E4,J4) | N4: =100*LN(1-E4)/100 | O4: =100*LN(1-J4)/100 | P4: =100*LN(1-M4)/100 | Q4: =-100*M4/100 | R4: =P4
A5: BOF | B5: Primary steel: BF-BOF route | C5: =1-EXP(SUMPRODUCT(LN(1-Parameters!O7:O9))) | D5: =1-EXP(SUMPRODUCT(LN(1-Parameters!P7:P9))) | E5: =1-EXP(SUMPRODUCT(LN(1-Parameters!Q7:Q9))) | F5: =1-EXP(SUMPRODUCT(LN(1-Parameters!R7:R9))) | G5: =1-EXP(SUMPRODUCT(LN(1-Parameters!S7:S9))) | H5: =1-EXP(SUMPRODUCT(LN(1-Parameters!T7:T9))) | I5: =1-EXP(SUMPRODUCT(LN(1-Parameters!U7:U9))) | J5: =1-EXP(SUMPRODUCT(LN(1-Parameters!V7:V9))) | ... L5: =1-EXP(SUMPRODUCT(LN(1-Parameters!X7:X9))) | M5: =AVERAGE(E5,J5) | N5: =100*LN(1-E5)/100 | O5: =100*LN(1-J5)/100 | P5: =100*LN(1-M5)/100 | Q5: =-100*M5/100 | R5: =P5
A6: DRI | B6: Primary steel: natural-gas DRI-EAF route (Egypt-type) | C6: =1-EXP(SUMPRODUCT(LN(1-Parameters!O10:O13))) | D6: =1-EXP(SUMPRODUCT(LN(1-Parameters!P10:P13))) | E6: =1-EXP(SUMPRODUCT(LN(1-Parameters!Q10:Q13))) | F6: =1-EXP(SUMPRODUCT(LN(1-Parameters!R10:R13))) | G6: =1-EXP(SUMPRODUCT(LN(1-Parameters!S10:S13))) | H6: =1-EXP(SUMPRODUCT(LN(1-Parameters!T10:T13))) | I6: =1-EXP(SUMPRODUCT(LN(1-Parameters!U10:U13))) | J6: =1-EXP(SUMPRODUCT(LN(1-Parameters!V10:V13))) | ... L6: =1-EXP(SUMPRODUCT(LN(1-Parameters!X10:X13))) | M6: =AVERAGE(E6,J6) | N6: =100*LN(1-E6)/100 | O6: =100*LN(1-J6)/100 | P6: =100*LN(1-M6)/100 | Q6: =-100*M6/100 | R6: =P6
A7: EAF | B7: Secondary steel: scrap-EAF | C7: =1-EXP(SUMPRODUCT(LN(1-Parameters!O14:O16))) | D7: =1-EXP(SUMPRODUCT(LN(1-Parameters!P14:P16))) | E7: =1-EXP(SUMPRODUCT(LN(1-Parameters!Q14:Q16))) | F7: =1-EXP(SUMPRODUCT(LN(1-Parameters!R14:R16))) | G7: =1-EXP(SUMPRODUCT(LN(1-Parameters!S14:S16))) | H7: =1-EXP(SUMPRODUCT(LN(1-Parameters!T14:T16))) | I7: =1-EXP(SUMPRODUCT(LN(1-Parameters!U14:U16))) | J7: =1-EXP(SUMPRODUCT(LN(1-Parameters!V14:V16))) | ... L7: =1-EXP(SUMPRODUCT(LN(1-Parameters!X14:X16))) | M7: =AVERAGE(E7,J7) | N7: =100*LN(1-E7)/100 | O7: =100*LN(1-J7)/100 | P7: =100*LN(1-M7)/100 | Q7: =-100*M7/100 | R7: =P7
A8: ALU | B8: Primary aluminium (Hall-Heroult) | C8: =1-EXP(SUMPRODUCT(LN(1-Parameters!O17:O18))) | D8: =1-EXP(SUMPRODUCT(LN(1-Parameters!P17:P18))) | E8: =1-EXP(SUMPRODUCT(LN(1-Parameters!Q17:Q18))) | F8: =1-EXP(SUMPRODUCT(LN(1-Parameters!R17:R18))) | G8: =1-EXP(SUMPRODUCT(LN(1-Parameters!S17:S18))) | H8: =1-EXP(SUMPRODUCT(LN(1-Parameters!T17:T18))) | I8: =1-EXP(SUMPRODUCT(LN(1-Parameters!U17:U18))) | J8: =1-EXP(SUMPRODUCT(LN(1-Parameters!V17:V18))) | ... L8: =1-EXP(SUMPRODUCT(LN(1-Parameters!X17:X18))) | M8: =AVERAGE(E8,J8) | N8: =100*LN(1-E8)/100 | O8: =100*LN(1-J8)/100 | P8: =100*LN(1-M8)/100 | Q8: =-100*M8/100 | R8: =P8
A9: NH3 | B9: Ammonia (natural-gas SMR; merchant and non-urea uses) | C9: =1-EXP(SUMPRODUCT(LN(1-Parameters!O19:O21))) | D9: =1-EXP(SUMPRODUCT(LN(1-Parameters!P19:P21))) | E9: =1-EXP(SUMPRODUCT(LN(1-Parameters!Q19:Q21))) | F9: =1-EXP(SUMPRODUCT(LN(1-Parameters!R19:R21))) | G9: =1-EXP(SUMPRODUCT(LN(1-Parameters!S19:S21))) | H9: =1-EXP(SUMPRODUCT(LN(1-Parameters!T19:T21))) | I9: =1-EXP(SUMPRODUCT(LN(1-Parameters!U19:U21))) | J9: =1-EXP(SUMPRODUCT(LN(1-Parameters!V19:V21))) | ... L9: =1-EXP(SUMPRODUCT(LN(1-Parameters!X19:X21))) | M9: =AVERAGE(E9,J9) | N9: =100*LN(1-E9)/100 | O9: =100*LN(1-J9)/100 | P9: =100*LN(1-M9)/100 | Q9: =-100*M9/100 | R9: =P9
A10: UREA | B10: Urea (ammonia precursor + urea plant) | C10: =1-EXP(SUMPRODUCT(LN(1-Parameters!O22:O24))) | D10: =1-EXP(SUMPRODUCT(LN(1-Parameters!P22:P24))) | E10: =1-EXP(SUMPRODUCT(LN(1-Parameters!Q22:Q24))) | F10: =1-EXP(SUMPRODUCT(LN(1-Parameters!R22:R24))) | G10: =1-EXP(SUMPRODUCT(LN(1-Parameters!S22:S24))) | H10: =1-EXP(SUMPRODUCT(LN(1-Parameters!T22:T24))) | I10: =1-EXP(SUMPRODUCT(LN(1-Parameters!U22:U24))) | J10: =1-EXP(SUMPRODUCT(LN(1-Parameters!V22:V24))) | ... L10: =1-EXP(SUMPRODUCT(LN(1-Parameters!X22:X24))) | M10: =AVERAGE(E10,J10) | N10: =100*LN(1-E10)/100 | O10: =100*LN(1-J10)/100 | P10: =100*LN(1-M10)/100 | Q10: =-100*M10/100 | R10: =P10
A11: HNO3 | B11: Nitric acid (N2O) - component of ammonium nitrate and other N fertilisers | C11: =1-EXP(SUMPRODUCT(LN(1-Parameters!O25:O25))) | D11: =1-EXP(SUMPRODUCT(LN(1-Parameters!P25:P25))) | E11: =1-EXP(SUMPRODUCT(LN(1-Parameters!Q25:Q25))) | F11: =1-EXP(SUMPRODUCT(LN(1-Parameters!R25:R25))) | G11: =1-EXP(SUMPRODUCT(LN(1-Parameters!S25:S25))) | H11: =1-EXP(SUMPRODUCT(LN(1-Parameters!T25:T25))) | I11: =1-EXP(SUMPRODUCT(LN(1-Parameters!U25:U25))) | J11: =1-EXP(SUMPRODUCT(LN(1-Parameters!V25:V25))) | ... L11: =1-EXP(SUMPRODUCT(LN(1-Parameters!X25:X25))) | M11: =AVERAGE(E11,J11) | N11: =100*LN(1-E11)/100 | O11: =100*LN(1-J11)/100 | P11: =100*LN(1-M11)/100 | Q11: =-100*M11/100 | R11: =P11
A12: AN_U | B12: Ammonium nitrate - unabated N2O baseline | C12: =0.82*C11+0.18*C9 | D12: =0.82*D11+0.18*D9 | E12: =0.82*E11+0.18*E9 | F12: =0.82*F11+0.18*F9 | G12: =0.82*G11+0.18*G9 | H12: =0.82*H11+0.18*H9 | I12: =0.82*I11+0.18*I9 | J12: =0.82*J11+0.18*J9 | ... L12: =0.82*L11+0.18*L9 | M12: =AVERAGE(E12,J12) | N12: =100*LN(1-E12)/100 | O12: =100*LN(1-J12)/100 | P12: =100*LN(1-M12)/100 | Q12: =-100*M12/100 | R12: =P12
A13: AN_A | B13: Ammonium nitrate - N2O already ~90% abated (EU / CDM-legacy plants) | C13: =0.31*(1-EXP(SUMPRODUCT(LN(1-Parameters!O28:O28))))+0.69*C9 | D13: =0.31*(1-EXP(SUMPRODUCT(LN(1-Parameters!P28:P28))))+0.69*D9 | E13: =0.31*(1-EXP(SUMPRODUCT(LN(1-Parameters!Q28:Q28))))+0.69*E9 | F13: =0.31*(1-EXP(SUMPRODUCT(LN(1-Parameters!R28:R28))))+0.69*F9 | G13: =0.31*(1-EXP(SUMPRODUCT(LN(1-Parameters!S28:S28))))+0.69*G9 | H13: =0.31*(1-EXP(SUMPRODUCT(LN(1-Parameters!T28:T28))))+0.69*H9 | I13: =0.31*(1-EXP(SUMPRODUCT(LN(1-Parameters!U28:U28))))+0.69*I9 | J13: =0.31*(1-EXP(SUMPRODUCT(LN(1-Parameters!V28:V28))))+0.69*J9 | ... L13: =0.31*(1-EXP(SUMPRODUCT(LN(1-Parameters!X28:X28))))+0.69*L9 | M13: =AVERAGE(E13,J13) | N13: =100*LN(1-E13)/100 | O13: =100*LN(1-J13)/100 | P13: =100*LN(1-M13)/100 | Q13: =-100*M13/100 | R13: =P13
A14: H2 | B14: Hydrogen (merchant, SMR) | C14: =1-EXP(SUMPRODUCT(LN(1-Parameters!O26:O27))) | D14: =1-EXP(SUMPRODUCT(LN(1-Parameters!P26:P27))) | E14: =1-EXP(SUMPRODUCT(LN(1-Parameters!Q26:Q27))) | F14: =1-EXP(SUMPRODUCT(LN(1-Parameters!R26:R27))) | G14: =1-EXP(SUMPRODUCT(LN(1-Parameters!S26:S27))) | H14: =1-EXP(SUMPRODUCT(LN(1-Parameters!T26:T27))) | I14: =1-EXP(SUMPRODUCT(LN(1-Parameters!U26:U27))) | J14: =1-EXP(SUMPRODUCT(LN(1-Parameters!V26:V27))) | ... L14: =1-EXP(SUMPRODUCT(LN(1-Parameters!X26:X27))) | M14: =AVERAGE(E14,J14) | N14: =100*LN(1-E14)/100 | O14: =100*LN(1-J14)/100 | P14: =100*LN(1-M14)/100 | Q14: =-100*M14/100 | R14: =P14
A16: Existing CPAT workbook process semi-elasticity (for comparison) | M16: =1-EXP(P16/100*100) | P16: -0.10401964
A17: IPCC AR6 aggregate industry-process benchmark (2030, <=USD100) - see IPCC_Aggregate | M17: =IPCC_Aggregate!B12 | P17: =100*LN(1-M17)/100
A19: Bin-consistency check: beta_k = 100*ln(1-a(tau_k))/tau_k (central horizon = mean of 2030 and LR), %/$
A20: Key | B20: Sector | C20: beta(20) | D20: beta(50) | E20: beta(100) | F20: beta(150) | G20: beta(200) | H20: Pattern
A21: CEM | B21: Cement clinker / cement / concrete | C21: =IFERROR(100*LN(1-AVERAGE(C4,H4))/20,"") | D21: =IFERROR(100*LN(1-AVERAGE(D4,I4))/50,"") | E21: =IFERROR(100*LN(1-AVERAGE(E4,J4))/100,"") | F21: =IFERROR(100*LN(1-AVERAGE(F4,K4))/150,"") | G21: =IFERROR(100*LN(1-AVERAGE(G4,L4))/200,"") | H21: =IF(ABS(C21)>ABS(E21)+0.02,"|beta| falls with price (cheap options first; concave MACC)",IF(ABS(E21)>ABS(C21)+0.02,"|beta| rises with price (options mostly >USD20; convex MACC)","approx. constant"))
A22: BOF | B22: Primary steel: BF-BOF route | C22: =IFERROR(100*LN(1-AVERAGE(C5,H5))/20,"") | D22: =IFERROR(100*LN(1-AVERAGE(D5,I5))/50,"") | E22: =IFERROR(100*LN(1-AVERAGE(E5,J5))/100,"") | F22: =IFERROR(100*LN(1-AVERAGE(F5,K5))/150,"") | G22: =IFERROR(100*LN(1-AVERAGE(G5,L5))/200,"") | H22: =IF(ABS(C22)>ABS(E22)+0.02,"|beta| falls with price (cheap options first; concave MACC)",IF(ABS(E22)>ABS(C22)+0.02,"|beta| rises with price (options mostly >USD20; convex MACC)","approx. constant"))
A23: DRI | B23: Primary steel: natural-gas DRI-EAF route (Egypt-type) | C23: =IFERROR(100*LN(1-AVERAGE(C6,H6))/20,"") | D23: =IFERROR(100*LN(1-AVERAGE(D6,I6))/50,"") | E23: =IFERROR(100*LN(1-AVERAGE(E6,J6))/100,"") | F23: =IFERROR(100*LN(1-AVERAGE(F6,K6))/150,"") | G23: =IFERROR(100*LN(1-AVERAGE(G6,L6))/200,"") | H23: =IF(ABS(C23)>ABS(E23)+0.02,"|beta| falls with price (cheap options first; concave MACC)",IF(ABS(E23)>ABS(C23)+0.02,"|beta| rises with price (options mostly >USD20; convex MACC)","approx. constant"))
A24: EAF | B24: Secondary steel: scrap-EAF | C24: =IFERROR(100*LN(1-AVERAGE(C7,H7))/20,"") | D24: =IFERROR(100*LN(1-AVERAGE(D7,I7))/50,"") | E24: =IFERROR(100*LN(1-AVERAGE(E7,J7))/100,"") | F24: =IFERROR(100*LN(1-AVERAGE(F7,K7))/150,"") | G24: =IFERROR(100*LN(1-AVERAGE(G7,L7))/200,"") | H24: =IF(ABS(C24)>ABS(E24)+0.02,"|beta| falls with price (cheap options first; concave MACC)",IF(ABS(E24)>ABS(C24)+0.02,"|beta| rises with price (options mostly >USD20; convex MACC)","approx. constant"))
A25: ALU | B25: Primary aluminium (Hall-Heroult) | C25: =IFERROR(100*LN(1-AVERAGE(C8,H8))/20,"") | D25: =IFERROR(100*LN(1-AVERAGE(D8,I8))/50,"") | E25: =IFERROR(100*LN(1-AVERAGE(E8,J8))/100,"") | F25: =IFERROR(100*LN(1-AVERAGE(F8,K8))/150,"") | G25: =IFERROR(100*LN(1-AVERAGE(G8,L8))/200,"") | H25: =IF(ABS(C25)>ABS(E25)+0.02,"|beta| falls with price (cheap options first; concave MACC)",IF(ABS(E25)>ABS(C25)+0.02,"|beta| rises with price (options mostly >USD20; convex MACC)","approx. constant"))
A26: NH3 | B26: Ammonia (natural-gas SMR; merchant and non-urea uses) | C26: =IFERROR(100*LN(1-AVERAGE(C9,H9))/20,"") | D26: =IFERROR(100*LN(1-AVERAGE(D9,I9))/50,"") | E26: =IFERROR(100*LN(1-AVERAGE(E9,J9))/100,"") | F26: =IFERROR(100*LN(1-AVERAGE(F9,K9))/150,"") | G26: =IFERROR(100*LN(1-AVERAGE(G9,L9))/200,"") | H26: =IF(ABS(C26)>ABS(E26)+0.02,"|beta| falls with price (cheap options first; concave MACC)",IF(ABS(E26)>ABS(C26)+0.02,"|beta| rises with price (options mostly >USD20; convex MACC)","approx. constant"))
A27: UREA | B27: Urea (ammonia precursor + urea plant) | C27: =IFERROR(100*LN(1-AVERAGE(C10,H10))/20,"") | D27: =IFERROR(100*LN(1-AVERAGE(D10,I10))/50,"") | E27: =IFERROR(100*LN(1-AVERAGE(E10,J10))/100,"") | F27: =IFERROR(100*LN(1-AVERAGE(F10,K10))/150,"") | G27: =IFERROR(100*LN(1-AVERAGE(G10,L10))/200,"") | H27: =IF(ABS(C27)>ABS(E27)+0.02,"|beta| falls with price (cheap options first; concave MACC)",IF(ABS(E27)>ABS(C27)+0.02,"|beta| rises with price (options mostly >USD20; convex MACC)","approx. constant"))
A28: HNO3 | B28: Nitric acid (N2O) - component of ammonium nitrate and other N fertilisers | C28: =IFERROR(100*LN(1-AVERAGE(C11,H11))/20,"") | D28: =IFERROR(100*LN(1-AVERAGE(D11,I11))/50,"") | E28: =IFERROR(100*LN(1-AVERAGE(E11,J11))/100,"") | F28: =IFERROR(100*LN(1-AVERAGE(F11,K11))/150,"") | G28: =IFERROR(100*LN(1-AVERAGE(G11,L11))/200,"") | H28: =IF(ABS(C28)>ABS(E28)+0.02,"|beta| falls with price (cheap options first; concave MACC)",IF(ABS(E28)>ABS(C28)+0.02,"|beta| rises with price (options mostly >USD20; convex MACC)","approx. constant"))
A29: AN_U | B29: Ammonium nitrate - unabated N2O baseline | C29: =IFERROR(100*LN(1-AVERAGE(C12,H12))/20,"") | D29: =IFERROR(100*LN(1-AVERAGE(D12,I12))/50,"") | E29: =IFERROR(100*LN(1-AVERAGE(E12,J12))/100,"") | F29: =IFERROR(100*LN(1-AVERAGE(F12,K12))/150,"") | G29: =IFERROR(100*LN(1-AVERAGE(G12,L12))/200,"") | H29: =IF(ABS(C29)>ABS(E29)+0.02,"|beta| falls with price (cheap options first; concave MACC)",IF(ABS(E29)>ABS(C29)+0.02,"|beta| rises with price (options mostly >USD20; convex MACC)","approx. constant"))
A30: AN_A | B30: Ammonium nitrate - N2O already ~90% abated (EU / CDM-legacy plants) | C30: =IFERROR(100*LN(1-AVERAGE(C13,H13))/20,"") | D30: =IFERROR(100*LN(1-AVERAGE(D13,I13))/50,"") | E30: =IFERROR(100*LN(1-AVERAGE(E13,J13))/100,"") | F30: =IFERROR(100*LN(1-AVERAGE(F13,K13))/150,"") | G30: =IFERROR(100*LN(1-AVERAGE(G13,L13))/200,"") | H30: =IF(ABS(C30)>ABS(E30)+0.02,"|beta| falls with price (cheap options first; concave MACC)",IF(ABS(E30)>ABS(C30)+0.02,"|beta| rises with price (options mostly >USD20; convex MACC)","approx. constant"))
A31: H2 | B31: Hydrogen (merchant, SMR) | C31: =IFERROR(100*LN(1-AVERAGE(C14,H14))/20,"") | D31: =IFERROR(100*LN(1-AVERAGE(D14,I14))/50,"") | E31: =IFERROR(100*LN(1-AVERAGE(E14,J14))/100,"") | F31: =IFERROR(100*LN(1-AVERAGE(F14,K14))/150,"") | G31: =IFERROR(100*LN(1-AVERAGE(G14,L14))/200,"") | H31: =IF(ABS(C31)>ABS(E31)+0.02,"|beta| falls with price (cheap options first; concave MACC)",IF(ABS(E31)>ABS(C31)+0.02,"|beta| rises with price (options mostly >USD20; convex MACC)","approx. constant"))

Sheet SemiElasticity
A1: Derivation of the iso-semi-elastic (constant semi-elasticity) model
A2: E(tau): process-emission intensity at carbon price tau; E0 = E(0). Abatement fraction a(tau) = 1 - E(tau)/E0.
A3: Semi-elasticity: beta(tau) = (dE/dtau)/E = d ln E / d tau. Iso-semi-elastic assumption: beta constant for all tau.
A4: Hence ln E(tau) = ln E0 + beta*tau => E(tau) = E0*exp(beta*tau) => a(tau) = 1 - exp(beta*tau).
A5: Calibration on one point (a* at tau* = 100): beta = ln(1 - a*)/tau*. In '% per $': 100*beta.
A6: CPAT form: delta I / I = exp(beta*tau) - 1 = -a(tau).
A7: Linear approximation: a(tau) ~ -beta*tau (small |beta*tau|) -> beta_lin = -a*/tau*. Always |beta_iso| >= |beta_lin| because -ln(1-a) >= a.
A8: Price elasticity of emissions in this model: eps(tau) = (dE/dtau)*(tau/E) = beta*tau -> not constant; eps(100) = 100*beta. A constant-elasticity (isoelastic) form E = E0*(tau/tau_ref)^-eps is undefined at tau = 0 and therefore unsuitable for a price starting from zero; the semi-elastic form is the log-linear analogue.
A9: Saturating alternative (two parameters): a(tau) = A*(1 - exp(-tau/tau_s)). From two points: a(200)/a(100) = 1 + exp(-100/tau_s) -> tau_s = -100/ln(a(200)/a(100) - 1); A = a(100)/(1 - exp(-100/tau_s)).
A11: Worked example (edit yellow cell)
A13: a* at tau*=100 | B13: 0.3
A14: tau* (USD/t) | B14: 100
A15: beta_iso (per USD) | B15: =LN(1-B13)/B14
A16: beta_iso (% per USD) | B16: =100*B15
A17: beta_linear (% per USD) | B17: =-100*B13/B14
A18: elasticity at tau* | B18: =B15*B14
A20: tau | B20: a(tau) iso | C20: a(tau) linear | D20: a(tau) saturating (A=0.6, tau_s=120)
A21: 0 | B21: =1-EXP($B$15*A21) | C21: =MIN(1,-$B$17/100*A21) | D21: =0.6*(1-EXP(-A21/120))
A22: 10 | B22: =1-EXP($B$15*A22) | C22: =MIN(1,-$B$17/100*A22) | D22: =0.6*(1-EXP(-A22/120))
A23: 20 | B23: =1-EXP($B$15*A23) | C23: =MIN(1,-$B$17/100*A23) | D23: =0.6*(1-EXP(-A23/120))
A24: 30 | B24: =1-EXP($B$15*A24) | C24: =MIN(1,-$B$17/100*A24) | D24: =0.6*(1-EXP(-A24/120))
A25: 50 | B25: =1-EXP($B$15*A25) | C25: =MIN(1,-$B$17/100*A25) | D25: =0.6*(1-EXP(-A25/120))
A26: 75 | B26: =1-EXP($B$15*A26) | C26: =MIN(1,-$B$17/100*A26) | D26: =0.6*(1-EXP(-A26/120))
A27: 100 | B27: =1-EXP($B$15*A27) | C27: =MIN(1,-$B$17/100*A27) | D27: =0.6*(1-EXP(-A27/120))
A28: 125 | B28: =1-EXP($B$15*A28) | C28: =MIN(1,-$B$17/100*A28) | D28: =0.6*(1-EXP(-A28/120))
A29: 150 | B29: =1-EXP($B$15*A29) | C29: =MIN(1,-$B$17/100*A29) | D29: =0.6*(1-EXP(-A29/120))
A30: 200 | B30: =1-EXP($B$15*A30) | C30: =MIN(1,-$B$17/100*A30) | D30: =0.6*(1-EXP(-A30/120))
A31: 300 | B31: =1-EXP($B$15*A31) | C31: =MIN(1,-$B$17/100*A31) | D31: =0.6*(1-EXP(-A31/120))

Sheet IPCC_Aggregate
A1: IPCC AR6 WGIII Table 12.3 - industry PROCESS-related 2030 potentials <= USD100/tCO2e vs 2030 reference process emissions
A3: Feedstock decarbonisation / process change (50-100 bin) | B3: 0.38
A4: Cementitious material substitution (20-50 bin) | B4: 0.28
A5: Reduction of non-CO2 emissions (0-20 bin) | B5: 0.2
A6: Sum process options <= USD100 (Gt) | B6: =SUM(B3:B5)
A7: Circularity / enhanced recycling (20-50 bin) - route shift, optional add | B7: 0.48
A8: 2019 industrial process GHG (Gt, IPCC AR6 Ch.11 p.1170) | B8: 4.5
A9: Reference growth 2019->2030 (input; 12.SM: industry CO2 +28% 2017-30; IEA cement/steel flatter) | B9: 0.215
A10: 2030 reference process emissions (Gt) | B10: =B8*(1+B9)
A12: a(100) 2030 aggregate, process options only | B12: =B6/B10
A13: a(100) 2030 aggregate, incl. circularity | B13: =(B6+B7)/B10
A14: beta_iso implied (%/$), process only | B14: =100*LN(1-B12)/100
A15: Sensitivity: growth 15% -> a(100) | B15: =B6/(B8*1.15)
A16: Sensitivity: growth 28% -> a(100) | B16: =B6/(B8*1.28)
A17: Note: CCU/CCS 0.15 Gt sits in the USD100-200 bin (not overlap-corrected) and is excluded at <=USD100. Potentials 'cannot be summed across sectors' but within industry are overlap-corrected (Table 12.3 notes). Uncertainty +/-25%.

Sheet IPCC_T12_3
A1: IPCC AR6 WGIII Ch.12 Table 12.3 - Industry (GtCO2-eq, 2030; +/-25%; overlap-corrected except 0.15 Gt CCUS). Source p.1255-1256.
A2: Option | B2: <0 | C2: 0-20 | D2: 20-50 | E2: 50-100 | F2: 100-200 | G2: Classification used here
A3: Energy efficiency (fuels only) | C3: 1.14 | G3: not process
A4: Material efficiency | D4: 0.93 | G4: demand-side (not intensity)
A5: Circularity (enhanced recycling) | D5: 0.48 | G5: route shift (partly process)
A6: Fuel switching | D6: 1.28 | E6: 0.67 | F6: 0.15 | G6: not process
A7: Feedstock decarbonisation, process change | E7: 0.38 | G7: process
A8: CCU and CCS | F8: 0.15 | G8: process (and fuel) - 0.08-0.36 range; not overlap-corrected
A9: Cementitious material substitution | D9: 0.28 | G9: process
A10: Reduction of non-CO2 emissions | C10: 0.2 | G10: process (N2O, PFC, CH4)
A12: Table 12.4: Industry direct potential <USD100 = 5.4 Gt (range 4.0-6.7). All sectors 38 (32-44). Notes: 'Energy efficiency only applies to more efficient use of fuels.'

Sheet IPCC_T11_3
A1: IPCC AR6 WGIII Ch.11 Table 11.3 (p.1197-1198) and section text - key process-emission options (USD2019/tCO2e)
A2: Sector | B2: Option | C2: GHG reduction | D2: Cost (USD/tCO2e) | E2: Availability / TRL | F2: Where
A3: Steel | B3: BF-BOF + top-gas recycling + CCUS | C3: 60% | D3: 70-130 | E3: 2025-30 | F3: Table 11.3
A4: Steel | B4: Syngas DRI-EAF + CCUS | C4: >=90% | D4: >=40 | E4: commercial (Abu Dhabi 2016) | F4: Table 11.3; 11.4.1.1
A5: Steel | B5: HIsarna + CCS | C5: 80-90% | D5: 40-70 | E5: pilot | F5: Table 11.3
A6: Steel | B6: H2-DRI-EAF (electrolytic H2) | C6: up to 99% | D6: 39-79 (EUR2018 34-68; EUR40/MWh) | E6: near-commercial (SPM C.5.2) | F6: Table 11.3 fn d
A7: Steel | B7: Aqueous / molten-oxide electrolysis | C7: ~100% | D7: n/a | E7: TRL 3-5 | F7: Table 11.3
A8: Steel | B8: ETC (2018) average | C8: deep | D8: 60 | F8: 11.4.1.5
A9: Cement | B9: Clinker substitution | C9: 40-50% of plant GHG | D9: near zero | E9: commercial | F9: Table 11.3 fn g
A10: Cement | B10: Design / material efficiency | C10: -24% demand | F10: Table 11.3
A11: Cement | B11: Alternative fuels | C11: 40% of fuel CO2 | F11: Table 11.3
A12: Cement | B12: CCUS | C12: 99% calcination / <=90% heat | D12: <=40 calcination; <=120 heat | E12: TRL 5-7, 2025 | F12: Table 11.3
A13: Cement | B13: Rootzen & Johnsson (2016) CCS | D13: 25-110 EUR | F13: 11.4.1.5
A14: Cement | B14: ETC (2018) average | D14: 110-130 | F14: 11.4.1.5
A15: Cement | B15: Fig 11.13 cost ranges | D15: EE <30; ME 20-50; circ 20-50; FeedCI 20-50; FSW+El 40-100; CCUS 60-130 | F15: Fig 11.13
A16: Aluminium | B16: Inert electrodes (replace graphite anodes, 1.5 tCO2/t) | C16: 100% of process | D16: 'relatively low' | E16: TRL 6-7; 2024 target | F16: Table 11.3 fn h
A17: Aluminium | B17: PFC (up to 2 tCO2e/t) | C17: 'almost eliminated in well-run facilities' | F17: 11.4.1.4
A18: Ammonia | B18: Low-GHG H2 (electrolysis / SMR+CCS) | C18: <=99% | D18: cost of H2; electrolysis ~50 | F18: Table 11.3
A19: Cross-cutting | B19: CCS of concentrated CO2 (process streams) | C19: 99% | D19: <=40 (storage 10-40; 15-40 commercial) | E19: commercial | F19: Table 11.3 fn f; p.1185
A20: Cross-cutting | B20: Post-combustion capture, diluted streams | C20: <=90% | D20: <=120 (Leeson 60-170) | F20: Table 11.3 fn f
A21: Cross-cutting | B21: SMR + CCS | C21: 56% at <=40 (process stream); <=90% at <=120 | F21: Table 11.3
A22: Industry | B22: Overall mitigation cost band | D22: rough range 50-150 | E22: 5-15 yrs innovation needed | F22: Exec. summary p.1163

Sheet AR4_T7_9
A1: IPCC AR4 WGIII Ch.7 Table 7.9 - global mitigation potential in 2030 for non-CO2 industrial gases (MtCO2-eq, US$2000 cost categories)
A2: Source | B2: 2030 baseline | C2: <0 | D2: <20 | E2: <50 | F2: <100 | G2: Share <0 | H2: Share <100
A3: N2O from adipic and nitric acid production | B3: 190 | C3: 158 | D3: 158 | E3: 158 | F3: 174 | G3: =C3/B3 | H3: =F3/B3
A4: PFC from aluminium production | B4: 51 | C4: 1.6 | D4: 7.6 | E4: 8.2 | F4: 8.2 | G4: =C4/B4 | H4: =F4/B4
A6: Text 7.4.3.4: nitric acid catalytic reduction 89% typical, 70% to almost 100%; cost 2.0-5.8 US$2000/tCO2e (20% discount rate). NACAG FAQ 2024: secondary 70-90%, tertiary up to 99%. AR4 7.4.2.1: PFC intensity 4.4 -> 1.2 tCO2e/t Al (1990-2004), 'mainly low or no-cost'.

Sheet Econometric
A1: Empirical EU ETS / carbon-pricing evidence (TOTAL installation emissions - dominated by combustion; NOT process-specific). For comparison only.
A2: Study | B2: Scope | C2: Effect | D2: Price context | E2: Rough implied semi-elasticity (derived here)
A3: Bayer & Aklin 2020 (PNAS) | B3: EU ETS, all covered sectors | C3: -3.8% EU-wide (1.2 GtCO2 2008-16); covered sectors -8.1% to -11.5% vs synthetic control | D3: ~EUR 5-25 (mostly <20) | E3: ~0.2-0.6 %/EUR (total emissions, short-run)
A4: Dechezlepretre, Nachtigall & Venmans 2023 (JEEM) | B4: EU ETS installations FR/NL/NO/UK | C4: ~-10% 2005-12; no effect on profits/employment | D4: EUR 8-30 | E4: ~0.3-0.7 %/EUR
A5: Colmer, Martin, Muuls & Wagner 2024 (REStud) | B5: EU ETS firms (France) | C5: -14% (Phase I), -16% (Phase II); MAC could not have exceeded USD53/t | D5: EUR 8-30 | E5: ~0.5-1.0 %/EUR
A6: Dobbeling-Hildebrandt et al. 2024 (Nat. Commun.) meta-analysis | B6: 21 carbon-pricing schemes | C6: -10.4% average (-6.8% bias-corrected); EU ETS -7.3% at mean USD20/t | D6: mean USD 20 | E6: ~0.35 %/USD (EU ETS); authors judge price-elasticity evidence insufficient

Sheet Sources
A1: Sources
A2: IPCC (2022) AR6 WGIII, Summary for Policymakers: C.5, C.5.2, C.12, C.12.1, Figure SPM.7.
A3: IPCC (2022) AR6 WGIII, Chapter 11 'Industry' (Bashmakov et al.): Executive Summary (p.1163), 11.2 (p.1170 emissions), 11.3.6 (CCS p.1185), 11.4.1.1-11.4.1.5, Table 11.3 (p.1197-1198), Table 11.5, Figure 11.13.
A4: IPCC (2022) AR6 WGIII, Chapter 12 'Cross-sectoral perspectives' (Babiker et al.): 12.2, Table 12.2 (p.1254), Table 12.3 (p.1255-1256), Table 12.4 (p.1257); Chapter 12 Supplementary Material (industry reference scenario note).
A5: IPCC (2007) AR4 WGIII, Chapter 7 'Industry' (Bernstein et al.): 7.4.2.1 (aluminium PFC), 7.4.3.4 (N2O nitric/adipic acid), Table 7.6, Table 7.9.
A6: NACAG / GIZ (2024) Nitric Acid Climate Action Group - FAQ (EN) and Factsheet, nitricacidaction.org.
A7: IEA (2020) Iron and Steel Technology Roadmap; IEA (2021) Ammonia Technology Roadmap (production volumes: urea 177 Mt, AN 49 Mt, 2019); IEA (2022) Achieving Net Zero Heavy Industry Sectors in G7 Members (clinker ratio floor ~0.5).
A8: International Aluminium Institute (2021) Aluminium Sector Greenhouse Gas Pathways to 2050 (process emissions ~15% of sector total); IAI PFC statistics (GWP basis).
A9: European Commission (2023) Implementing Regulation (EU) 2023/1773 (CBAM transitional period) and Guidance No. 5c - Sector-specific guidance document on fertilisers (urea CO2 and nitric-acid N2O provisions).
A10: Material Economics (2019) Industrial Transformation 2050 - as cited in IPCC AR6 Ch.11 (pathway costs EUR 12-91/t; CCS shares).
A11: Energy Transitions Commission (2018) Mission Possible - as cited in IPCC AR6 Ch.11 (steel USD60/t, cement USD110-130/t).
A12: Rootzen & Johnsson (2016); Leeson et al. (2017) - as cited in IPCC AR6 Ch.11.
... A17: CPAT Egypt workbook method note (this repository): TASK-2a_AdHocCalculations_Pseudocode_v0.1.md; InitialResultsAndIssues/Methodological Note.txt (existing process semi-elasticity -0.104 %/USD).
