Workbook
Name CPATStartYear: [1]Dashboard!$J$7

Sheet Settings
A1: CPAT industry kernel - Egypt, final v1.6
A3: Country code | B3: egy | C3: First component of every code; CPAT convention (egy.mit.<var>.<sector>.<fuel>.<type>.<scenario>)
A4: Price group for industry sectors | B4: ind | C4: C2 retail-price group the four sectors read (pow / res / ind / tra)
A5: Elasticity column | B5: Industries | C5: Column of the master elasticity table (Transport / Residential / Industries / Services)
A6: Base year | B6: 2022 | C6: MTInputs FirstYearCalculations; energy in the base year is read from Data_Energy, later years from the kernel
A7: Additional policy-induced efficiency (alpha+) | B7: =INDEX(MTInputs!$F$8:$F$415,MATCH("AdditionalEfficiencyIndustrial",MTInputs!$H$8:$H$415,0)) -> 0 | C7: Read from the MTInputs column by NameOfParameter; this is the only MTInputs dependency of the kernel rows
A8: Carbon price start year (info) | B8: =INDEX(MTInputs!$F$8:$F$415,MATCH("CPIntro",MTInputs!$H$8:$H$415,0)) -> 2026 | C8: For reference: the policy scenario new-policy wedge (nce) starts here
A9: Carbon price target (info) | B9: =INDEX(MTInputs!$F$8:$F$415,MATCH("CPLevelTarget",MTInputs!$H$8:$H$415,0)) -> 50 | C9: $/tCO2
A10: Policy bundle for scenario 2 (EGY) | B10: LEGACY | C10: Bundle run as policy scenario 2 (Scenarios section 2). LEGACY = CPAT default (regression vs v0.3/legacy). Check-sheet legacy comparisons are valid for LEGACY only.
A12: Kernel (every energy cell, year t >= 2023):
A13: F(t) = F(t-1) * (1+g)^(eY*delta) * (1+psi) * (p(t)/p(t-1))^eU * [ (s(t)/s(t-1))^eF / (1 + a + a+) ]^(1+eU)
A14: p = post-tax price (atp), s = shadow price (shp) = atp + sigma*ssc, g = post-policy GDP growth, delta = income-elasticity discount, psi = exogenous shock
A16: Sheets
A17: Manual inputs | C17: Legacy 'Manual inputs' Process Emissions section (rows 18-47, same positions): CBAM process coverage switches, product emission factors, half-elasticities.
A18: Scenarios | C18: EGY: carbon price paths, policy bundles 1A-3C (+LEGACY), active-bundle series mirrored into Data_Prices by code, pass-through factors, interface contract between work streams.
A19: Mitigation_Industry | C19: Kernel sheet in the CPAT Mitigation layout (columns A-AI, years K-AI): 4 CBAM sectors x 2 scenarios, each scenario followed by the 156-row CBAM goods block (legacy Mitigation 5881-6036 / 12198-12353). All formulas; codes built from components.
A20: MTInputs | C20: The 415-row CPAT parameter column, copied unchanged (columns A-I of the MTInputs sheet).
A21: Data_Energy | C21: Base-year energy matrix, fuel x sector, ktoe (Mitigation B4 rows 583-602).
A22: Data_Prices | C22: Pre-tax price before new policies (pbc), new-policy wedge (nce), shadow price (shp), sector coverage (tcf), share of shadow price on efficiency (ssc); both scenarios. Plus carbon price (cptraj) and auctioned ETS price (etstraj) trajectories for the CBAM block. v0.4: scenario-2 cptraj/etstraj/nce read Scenarios; interface rows pptraj, encov, obrsh, obrrb, fundsh, fundsp.
A23: Data_Macro | C23: GDP growth, income-elasticity discount factor, exogenous shock; both scenarios.
A24: Data_Elast | C24: Master elasticity table (income, usage, efficiency, AEEI) by fuel group x sector group, plus the fuel-group map.
A25: Check | C25: Kernel output against the values stored in CPAT_1_0pre_456 for the same rows; max absolute and relative differences. v0.3: plus CBAM block rows vs legacy (rows from 583). v0.4: plus Scenarios regression section. v0.5: Task A identity section (row 1429). v0.6: Task B section (row 1443). v0.7: Task C section (row 1455). v0.8: Task K section (row 1464). v0.9: Task D section (row 1476). v0.10: Task H section (row 1489). v0.11: Task L section (row 1506). v0.12 (Stream 2 merged): Task F section (row 1520), Task I section (row 1552), Task J section (row 1667). v0.13: Task G section (row 1831). v0.14: Task M section (row 1861). v0.15: T1/T5 section (row 1881). v0.16: v0.16 section (row 1907). v0.17: carve-out section (row 1919).
A27: Version log
A28: v0.1 | C28: Initial kernel (egypt+mitigation).
A29: v0.2 | C29: Conformed to NORMS.md: MTInputs used/unused colouring, hidden MT/Dashboard placeholder columns, CPAT colours, title band. No formula changes.
A30: v0.3 | C30: TASK-1: CBAM goods / process emissions block (legacy Mitigation 12198-12353, 156 rows, cols A-AI) added after each scenario; 'Manual inputs' rows 18-47; cptraj/etstraj in Data_Prices; MTInputs F117:F121 linked to Manual inputs row 22. Carbon Tax/ETS rows now read the scenario trajectories (legacy: hard zeros, broken K refs). Legacy WIP bugs fixed: fuel emissions by sector M..AE hard-coded; aluminium fuel-ER relative ref; missing post-policy process total; product-price year header. Kernel rows unchanged (regression diff 0).
A31: v0.4 | B31: 2026-10-02 | C31: Task E: Scenarios sheet (price paths LEGACY/ZERO/FLAT20_2028/RAMP_EG3/RAMP50_2034; bundles LEGACY,1A,2A,2B,3A,3B,3C; selector Settings!B10). Scenario-2 cptraj/etstraj/nce now = active-bundle series (nce = cptraj x encov x factor). New interface rows pptraj/encov/obrsh/obrrb/fundsh/fundsp (both scenarios). CBAM block o4 = fundsp, o5 = fundsh x o155, o6 = obrrb; Additional ER rows o107-o114 read o4 instead of o5. Manual inputs E21 = bundle process flag. LEGACY: regression diff vs v0.3 ~1e-15 (floating point of cptraj x factor).
A32: v0.5 | B32: 2026-10-02 | C32: Task A: CBAM block output codes unique (cpef/cpep, emisf/emisp, emrf/emrp; combined emis/emr in spare rows o135/o136). Revenues fixed: o147-o154 = post-policy fuel CO2 x fuel inclusion + post-policy process x process inclusion (legacy: pre-policy process x fuel inclusion, no fuel revenue); split revf/revp in o137/o138, o155 = sum. Changed by design: scenario-2 revenue rows (LEGACY o155 2030: 1697.5 -> fuel only, process not covered); all other values identical to v0.4.
A33: v0.6 | B33: 2026-10-02 | C33: Task B: 4-way EF split (fc, fp, np, no) with coverage switches per bundle (Scenarios M:P, all 1; block o28). Price rows use covered EFs (fuel group fc+fp, process group np+no); process ER and revenues act on the covered share (o85-o92 I:J). Full process EF floored per category. Post-policy emissions by category in o13-o16 (emisfc/emisfp/emisnp/emisno.cbam.tot). All values identical to v0.5 with switches = 1.
A34: v0.7 | B34: 2026-10-02 | C34: Task C: CBAM process emissions (np + no) priced at pptraj (new block row o63) in the process price rows, process ER, revp, product revenues and np/no emissions; fuel CO2 stays on cptraj (o2). All values identical to v0.6 (every bundle uses the same energy and process path).
A35: v0.8 | B35: 2026-10-02 | C35: Task K: CBAM metrics in block spare rows: cbcov (o39), cbint (o40), cbintch (o41), EU-export-weighted cbintchx (o51) and cbcovx (o52). New rows only; no existing value changes.
A36: v0.9 | B36: 2026-10-02 | C36: Task D: IPCC-inferred process semi-elasticities by product and category (np, no) with technical potential ERmax (Manual inputs rows 53-60); block o118-o125 apply them per category. Selector Manual inputs E50 (IPCC default; ADHOC reproduces v0.8). Anchors are placeholders equal to the ad hoc values (results unchanged) pending the IPCC research report.
A37: v0.10 | B37: 2026-10-02 | C37: Task H: CBAM output responds to the carbon cost net of the output-based rebate, Q = Qbase x (1 + dp_net)^eps (Manual inputs rows 66-73, switch E63; eps placeholder -0.5). New codes cbqch, emrq, emrt; block o75-o82 redefined as the net cost increase. OFF (and the LEGACY bundle) reproduces v0.9.
A38: v0.11 | B38: 2026-10-02 | C38: Task L: CBAM obligations on EU exports (cbobl, cbobl0, cbobch, cbobchu in block o94/o105/o116/o127) with EU price (placeholder 100), CBAM phase-in factor and deduction convention (Manual inputs rows 75-82, selector E76 = FULL).
A39: v0.12 | B39: 2026-10-02 | C39: T2 merge: Stream 2 (branch v0.7 -> Stream2_v1/v2/v3) integrated into the mainline v0.11 by re-applying the branch steps (build_v0_12.py imports build_stream2_v1/v2/v3). Task F: new sheets Data_EF, Emissions_Industry (eco2 = ener x EF), MTInputs EmissionsFactCO2 / EFsAdjustmentNonAnnexI green; check (d) now conditions on the explicit price o2 + o3 (branch used o1, a cascade to the year row). Task I: new sheet Rebate_Industry (Fund-independent output-based rebate per t = MIN(obrrb x EU benchmark, carbon cost per t), sector rebate share, net prices atpn); kernel ener usage term reads atpn (1368 cells, asserted); ppin memo since Task H (v0.10) already deducts obrrb in the output response (basis covered EF; Task I basis EU benchmark -> CAVEATS). Task J: new sheet Fund_Industry (F = phi x pre-fund revenue rev0, shadow price s by 15 Newton rows, RATE|COST rule); process abatement rebuilt for the v0.9 per-category ERmax form (wm = Q x cov x EF x ERmax, wp = wm x e^-beta P, 16 rows np/no); block o5 = F, '+o4' inside the process price term of o118-o125 (np and no) and o15/o16 (440 block cells, asserted against v0.11); Data_Prices shp.<fuel>.ind.2 = s x pass-through, ssc.<sector>.2 = ssc_fund (260 cells); Scenarios fundsp row 49 = s. Check sections F (row 1520), I (row 1552), J (row 1667) store the pre-step values per bundle computed inside this build. Regression vs v0.11: all Check summaries 0 for every bundle; Mitigation_Industry identical to v0.11 for LEGACY, 1A, 2A, 2B, 3A (max |diff| 0); changed by design: 3B 873; 3C 1.9e+03. Sheets list above not extended (keeps row 25 fixed).
A40: v0.13 | B40: 2026-10-02 | C40: Task G: new sheet IPPU_Industry. CPAT IPPU baseline by gas and industrial energy CO2 stored (CPAT Mitigation rows 7566-7570, 6590); CPAT-method IPPU (all IPPU x industrial energy CO2 growth, kernel change only) vs kernel IPPU = block process np+no (o145) + fp counted as IPPU (ammonia feedstock flag) + non-block remainder (CPAT baseline - block baseline; IppuOther NONE holds it, CPAT scales it). Double-count correction row iprdc. Reconciliation of block fuel CO2 with Task F sector energy CO2 by sector (report only). Manual inputs rows 84-95 (switch E85, fp flags E88:E95). Check section row 1831. 2030, bundle 3A scenario 2: CPAT-method IPPU 85.3, kernel IPPU 84.7 MtCO2e (block 34.0, non-block 50.7), correction -0.52. Regression vs v0.12: all prior sheets identical for every bundle (max |diff| 0); new rows only.
A41: v0.14 | B41: 2026-10-02 | C41: Task M: new sheets CPAT_National (CPAT national outputs of runs EG1-EG4 from the TASK-2b csv, stored) and Table2_Industry (bundle -> run mapping; CPAT series of the mapped run; kernel series; Table 2 columns J K L M N O P Q R T U AR per year; live summary row + stored 2030 snapshot of all bundles vs rebuild v0.1 K). Composition in deltas: K = dGHG CPAT + IPPU replacement (Task G kernel IPPU) + industry energy replacement (kernel sectors + non-kernel industry scaled with the run for All sectors). P = gross (CPAT receipts adjusted / kernel sectors) + process revenue - rebates - fund. Q = CPAT deaths x dEnergy CO2 ratio. Check section row 1861. 2030 K: 1A -27.7, 2A -25.7, 2B -27.0, 3A -9.7, 3B -6.6, 3C -17.3. Regression vs v0.13: all prior sheets identical for every bundle (max |diff| 0); new sheets only.
A42: v0.15 | B42: 2026-10-02 | C42: T5: S1 emission factors H30:K37 = Egypt CBAM EF v0.1 (EGY_CBAM_EF_v0.1.xlsx; urea np 0 CBAM rule, M35 1.1256; AN no 0.9944 integrated HNO3 N2O, M36 0.8462); S:V memo restated. T1: Task D semi-elasticities applied (E50 IPCC; rows 53-60 ER at $100 = IPCC AR6 central, USD2019: DRI 0.3433, scrap 0.1810, BF 0.2803, clinker 0.3352, AN no 0.6179 (50 % abatement blend), Al 0.2164 np+no, ammonia/urea 0). Fuel ER (rows 40-47) and fund unchanged. Table 2 snapshot refilled; rebuild column = AdHoc rebuild v0.2. Check row 1881. 2030 K: 1A -29.8 (v0.14 -27.7), 2A -25.8 (v0.14 -25.7), 2B -27.1 (v0.14 -27.0), 3A -11.8 (v0.14 -9.7), 3B -8.6 (v0.14 -6.6), 3C -23.9 (v0.14 -17.3).
... A44: v0.17 | B44: 2026-10-02 | C44: Final Table 2: sheet CarveOut_Table2 = CBAM carve-out v0.3 in live formulas (active bundle) + stored 6-bundle snapshot; O on FULL, NOPHASE memo. No other formulas changed. Check row 1919. 2030 K: 1A -37.4, 2A -33.1, 2B -34.8, 3A -22.8, 3B -19.1, 3C -33.0.
A45: v1.0 | B45: 46299 | C45: Final release: v0.17 relabelled, no formula or value changes. Final Table 2 = sheet CarveOut_Table2 (CBAM carve-out). 2030 K: 1A -37.4, 2A -33.1, 2B -34.8, 3A -22.8, 3B -19.1, 3C -33.0.
A46: v1.4 | B46: 2026-10-04 | C46: T3: CBAM 2024 production, growth, EU exports and pre-policy prices moved from Mitigation_Industry (both blocks) to Manual inputs rows 98-108 and linked. No value changes: max abs difference over all pre-existing cells = 0. Check row 1924 (literal count, expected 0).
A47: v1.5 | B47: 2026-10-04 | C47: 3B rebate to all covered industry (Manual inputs E112; CarveOut_Table2 section G rows 92-98; K, P, Q for 3B only). New sheet Table2_Final: final Table 2, figures as printed in the documents, differences (count 0), obligation memo, live row O. Max abs diff over all other pre-existing cells = 0. Check row 1928. v1.1-v1.3 were relabels of the Egypt deliverable set (no kernel change).
A48: v1.6 | B48: 2026-10-04 | C48: Output elasticity by product (Manual inputs E66:E73): cement -0.10, steel and fertilisers -0.40, aluminium -0.50 (was -0.5 for all; OutputElasticity_Note_v0.1). Fund fixed point re-solved, Task J v2 table, Table2_Industry and CarveOut_Table2 stored snapshots refilled. Every scenario-2 result moves; LEGACY/baseline unchanged. Check row 1935.

Sheet Manual inputs
B1: CPAT Manual inputs
B2: Replicates the legacy 'Manual inputs' tab at the same row/column positions. Only the Process Emissions section (rows 18-47, used by the CBAM block) is ported; other rows are left blank so legacy references port 1:1.
B3: Change only green cells. Row 22 feeds MTInputs F117:F121 (as in legacy).
A18: . | B18: Process Emissions
B19: Non-Fuel Process Emissions Coverage (CBAM goods only) for ETS and Carbon Tax
H20: mining & chemicals | I20: iron and steel | J20: non-ferrous metals | K20: machinery | L20: cement
D21: Include non-fuel process emissions in ETS/CT? (legacy Dashboard!G20; v0.4: set by the active bundle, Scenarios) | E21: =Scenarios!$G$27=1 -> FALSE | H21: TRUE | I21: TRUE | J21: TRUE | L21: TRUE
H22: =AND($E$21,'Manual inputs'!H21) -> FALSE | I22: =AND($E$21,'Manual inputs'!I21) -> FALSE | J22: =AND($E$21,'Manual inputs'!J21) -> FALSE | K22: FALSE | L22: =AND($E$21,'Manual inputs'!L21) -> FALSE
S27: S:V memo (v0.15): implied GJ/t = S1 EF x 1000 / tCO2 per TJ (not read by formulas).
B28: Emission Factors | H28: SCOPE 1 (tCO₂e/t, NH₃ integrated) | O28: SCOPE 2 + TOTALS | S28: EF INPUTS | W28: LATEST MAY 2026 EU DEFAULTS + BENCHMARKS | AD28: CONFIDENCE
D29: Product | E29: Unit | F29: CN codes | G29: Route | H29: S1.fc | I29: S1.fp | J29: S1.np | K29: S1.no | L29: S1 own | M29: Embed NH₃ | N29: S1 incl NH₃ | O29: S2 | P29: S2 in CBAM scope? | Q29: S1+S2 total | R29: CBAM- equiv | S29: fc GJ/t | T29: fc EF | U29: fp GJ/t | V29: fp EF | W29: EU def base | X29: mark up | Y29: EU def 2026 | Z29: EU bench | AA29: Gap vs def | AB29: Gap vs bench | AC29: Latest EU regulatory note (May 2026) | AD29: S1.fc / S1.fp confidence | AE29: S1.np / S1.no confidence
D30: DRI-EAF steel | E30: t crude steel | F30: 7207 10 (D); 7207 12 (D); 7208/7209 flat (partial); 7214 rebar | G30: Midrex NG shaft furnace + EAF | H30: 0.17797725 | I30: 0.39301352 | J30: 0.03790102 | K30: 0 | L30: =SUM(H30:K30) -> 0.60889179 | M30: 0 | N30: =L30+M30 -> 0.60889179 | O30: 0.25 | P30: 0 | Q30: =N30+O30 -> 0.85889179 | R30: =N30+O30*P30 -> 0.60889179 | S30: 3.172 | T30: 56.1 | U30: 7.006 | V30: 56.1 | W30: 1.82 | X30: 0.1 | Y30: =W30*(1+X30) -> 2.002 | Z30: 0.481 | AA30: =R30-Y30 -> -1.3931082 | AB30: =R30-Z30 -> 0.12789179 | AC30: DRI-EAF. Default base 1.820 ×1.10 markup = 2.002 (2026). Benchmark 0.481 (final IR 2025/2620). CAUTION: CBAM default matrix for HRC CN 7208 may assign only BF-BOF route (4.454) — 'DRI default vacancy' risk for flat products. | AD30: v0.15 EF: Egypt CBAM EF v0.1 (egypt+mitigation/EmissionFactors/EGY_CBAM_EF_v0.1.xlsx Products; EGY_CBAM_EF_Methodology_v0.1.md). Prior: S1.fc: Est: Midrex heat:reductant ratio 5:24 GJ/t NG. Total EF Auth (WSA 2023 / S1.fp: Est: Midrex standard ratio; IPCC 2006 Vol2 2C1; WSA 2023. Total Auth; | AE30: v0.15 EF: Egypt CBAM EF v0.1 (egypt+mitigation/EmissionFactors/EGY_CBAM_EF_v0.1.xlsx Products; EGY_CBAM_EF_Methodology_v0.1.md). Prior: S1.np: Auth: IPCC 2006 2C1 — DRI process CO2 = 0 / S1.no: Auth: IPCC 2006 2C1
D31: Scrap-EAF steel | E31: t crude steel | F31: 7206 10; 7207 10 (E); 7214 rebar; 7208 HRC (E-route); 7216 sections | G31: Scrap-EAF | H31: 0.04488 | I31: 0 | J31: 0.04398115 | K31: 0 | L31: =SUM(H31:K31) -> 0.08886115 | M31: 0 | N31: =L31+M31 -> 0.08886115 | O31: 0.25 | P31: 0 | Q31: =N31+O31 -> 0.33886115 | R31: =N31+O31*P31 -> 0.08886115 | S31: 0.8 | T31: 56.1 | U31: 0 | V31: 0 | W31: 0.72 | X31: 0.1 | Y31: =W31*(1+X31) -> 0.792 | Z31: 0.072 | AA31: =R31-Y31 -> -0.70313885 | AB31: =R31-Z31 -> 0.01686115 | AC31: Scrap-EAF. Default base 0.720 ×1.10 = 0.792 (2026). Benchmark 0.072 (final, scrap route). | AD31: v0.15 EF: Egypt CBAM EF v0.1 (egypt+mitigation/EmissionFactors/EGY_CBAM_EF_v0.1.xlsx Products; EGY_CBAM_EF_Methodology_v0.1.md). Prior: S1.fc: Est: IEA Egypt sector average; WSA 2023 scrap-EAF range 2-3 GJ/t. Tota / S1.fp: Auth: no reductant in scrap melting process | AE31: v0.15 EF: Egypt CBAM EF v0.1 (egypt+mitigation/EmissionFactors/EGY_CBAM_EF_v0.1.xlsx Products; EGY_CBAM_EF_Methodology_v0.1.md). Prior: S1.np: Est: IPCC 2006 Vol2 2C1 default 0.01-0.02 tCO2/t for scrap-EAF / S1.no: Auth: IPCC 2006 2C1
D32: BF-BOF steel (reference) | E32: t crude steel | F32: 7206 10 (C); 7207 10 (C); 7209 CR (C-route); 7208 HRC (C-route) | G32: BF-BOF coal/coke | H32: 0.1683 | I32: 1.2566803 | J32: 0.05276542 | K32: 0 | L32: =SUM(H32:K32) -> 1.4777457 | M32: 0 | N32: =L32+M32 -> 1.4777457 | O32: 0.1875 | P32: 0 | Q32: =N32+O32 -> 1.6652457 | R32: =N32+O32*P32 -> 1.4777457 | S32: 1.751 | T32: 96.1 | U32: 13.077 | V32: 96.1 | W32: 2.8 | X32: 0.1 | Y32: =W32*(1+X32) -> 3.08 | Z32: 1.37 | AA32: =R32-Y32 -> -1.6022543 | AB32: =R32-Z32 -> 0.10774569 | AC32: BF-BOF reference. Default base 2.800 ×1.10 = 3.080 (2026). Benchmark 1.370 (final IR 2025/2620). | AD32: v0.15 EF: Egypt CBAM EF v0.1 (egypt+mitigation/EmissionFactors/EGY_CBAM_EF_v0.1.xlsx Products; EGY_CBAM_EF_Methodology_v0.1.md). Prior: S1.fc: Prox: WSA 2023 global BF-BOF average. No Egypt-specific data (no produ / S1.fp: Prox: WSA 2023 BF standard; IPCC 2006 Vol2 2C1. Split Est within proxy | AE32: v0.15 EF: Egypt CBAM EF v0.1 (egypt+mitigation/EmissionFactors/EGY_CBAM_EF_v0.1.xlsx Products; EGY_CBAM_EF_Methodology_v0.1.md). Prior: S1.np: Auth: IPCC 2006 Vol2 2C1 default 0.22-0.28 tCO2/t crude steel / S1.no: Auth: IPCC 2006 2C1
D33: Grey clinker (dry-process) | E33: t clinker | F33: 2523 10 (clinker); 2523 21; 2523 29 Portland cement | G33: Dry rotary kiln | H33: 0.3135685 | I33: 0 | J33: 0.53702616 | K33: 0 | L33: =SUM(H33:K33) -> 0.85059466 | M33: 0 | N33: =L33+M33 -> 0.85059466 | O33: 0.05625 | P33: 1 | Q33: =N33+O33 -> 0.90684466 | R33: =N33+O33*P33 -> 0.90684466 | S33: 3.263 | T33: 96.1 | U33: 0 | V33: 0 | W33: 1.58 | X33: 0.1 | Y33: =W33*(1+X33) -> 1.738 | Z33: 0.666 | AA33: =R33-Y33 -> -0.83115534 | AB33: =R33-Z33 -> 0.24084466 | AC33: Cement clinker. Default base 1.580 ×1.10 = 1.738 (2026). Benchmark 0.666 (col B). S2 IN CBAM scope. | AD33: v0.15 EF: Egypt CBAM EF v0.1 (egypt+mitigation/EmissionFactors/EGY_CBAM_EF_v0.1.xlsx Products; EGY_CBAM_EF_Methodology_v0.1.md). Prior: S1.fc: Est: IEA Egypt cement sector; CSI/GCCA GNR Egypt 2022. Total AukCoa / S1.fp: Auth: cement production has no chemical reductant fuel | AE33: v0.15 EF: Egypt CBAM EF v0.1 (egypt+mitigation/EmissionFactors/EGY_CBAM_EF_v0.1.xlsx Products; EGY_CBAM_EF_Methodology_v0.1.md). Prior: S1.np: Auth: IPCC 2006 2A1 stoichiometric constant (44/100 × fraction CaCO3 i / S1.no: Auth
D34: Ammonia (net merchant) | E34: t NH3 | F34: 2814 10 (anhydrous ammonia) | G34: Steam methane reforming (SMR) + Haber-Bosch synthesis | H34: 0.71247 | I34: 1.26225 | J34: 0 | K34: 0 | L34: =SUM(H34:K34) -> 1.97472 | M34: 0 | N34: =L34+M34 -> 1.97472 | O34: 0.0375 | P34: 1 | Q34: =N34+O34 -> 2.01222 | R34: =N34+O34*P34 -> 2.01222 | S34: 12.7 | T34: 56.1 | U34: 22.5 | V34: 56.1 | W34: 2.05 | X34: 0.01 | Y34: =W34*(1+X34) -> 2.0705 | Z34: 1.484 | AA34: =R34-Y34 -> -0.05828 | AB34: =R34-Z34 -> 0.52822 | AC34: Egypt ammonia 2026 default = 2.07 tCO2e/t (incl 1% fertiliser markup; Argus 17 Dec 2025). Benchmark 1.522 → 1.484 after 2.5% reduction in 2026. S2 IN CBAM scope. | AD34: v0.15 EF: Egypt CBAM EF v0.1 (egypt+mitigation/EmissionFactors/EGY_CBAM_EF_v0.1.xlsx Products; EGY_CBAM_EF_Methodology_v0.1.md). Prior: S1.fc: Est: IFA/EFMA BAT Vol.1; combustion ~6-8 GJ/t NH3. Total Auth (IFA sta / S1.fp: Est: IFA/EFMA BAT Vol.1 standard SMR ~24-28 GJ/t NH3. Total Auth; comb | AE34: v0.15 EF: Egypt CBAM EF v0.1 (egypt+mitigation/EmissionFactors/EGY_CBAM_EF_v0.1.xlsx Products; EGY_CBAM_EF_Methodology_v0.1.md). Prior: S1.np: Auth: NH3 synthesis has no carbon process emissions / S1.no: Auth
D35: Urea | E35: t urea | F35: 3102 10 (urea >= 45% N) | G35: Urea synthesis from captured CO2 + NH3 feedstock | H35: 0.1122 | I35: 0 | J35: 0 | K35: 0 | L35: =SUM(H35:K35) -> 0.1122 | M35: 1.1255904 | N35: =L35+M35 -> 1.2377904 | O35: 0.0375 | P35: 1 | Q35: =N35+O35 -> 1.2752904 | R35: =N35+O35*P35 -> 1.2752904 | S35: 2 | T35: 56.1 | U35: 0 | V35: 0 | W35: 1.39 | X35: 0.01 | Y35: =W35*(1+X35) -> 1.4039 | Z35: 0.902 | AA35: =R35-Y35 -> -0.1286096 | AB35: =R35-Z35 -> 0.3732904 | AC35: NH₃ INTEGRATED in headline. Egypt urea 2026 default = 1.404 tCO2e/t (incl 1% markup; Sandbag Feb 2026). Benchmark col B 0.902 (col A 0.053 for actual-data pathway). SEFA chain uses ammonia benchmark 1.522. S2 IN CBAM scope. | AD35: v0.15 EF: Egypt CBAM EF v0.1 (egypt+mitigation/EmissionFactors/EGY_CBAM_EF_v0.1.xlsx Products; EGY_CBAM_EF_Methodology_v0.1.md). Urea np = 0 (CBAM rule: urea-bound CO2 not deducted; prototype -0.733). Prior: S1.fc: Est: IFA/EFMA; small relative to NH3 chain. ~1.5-2.5 GJ/t urea typical / S1.fp: Auth: no additional reductant/feedstock in urea synthesis itself | AE35: v0.15 EF: Egypt CBAM EF v0.1 (egypt+mitigation/EmissionFactors/EGY_CBAM_EF_v0.1.xlsx Products; EGY_CBAM_EF_Methodology_v0.1.md). Urea np = 0 (CBAM rule: urea-bound CO2 not deducted; prototype -0.733). Prior: S1.np: Auth: IPCC 2006 Vol2 3G stoichiometric constant. 44/60 = 0.733 tCO2 ab / S1.no: Auth
D36: Ammonium nitrate | E36: t AN | F36: 3102 30 (AN >= 28% N); 3102 40 (CAN) | G36: Ostwald process (NH3 → HNO3) + neutralisation (HNO3 + NH3 → NH4NO3) | H36: 0.1122 | I36: 0 | J36: 0 | K36: 0.9944125 | L36: =SUM(H36:K36) -> 1.1066125 | M36: 0.8462122 | N36: =L36+M36 -> 1.9528247 | O36: 0.04375 | P36: 1 | Q36: =N36+O36 -> 1.9965747 | R36: =N36+O36*P36 -> 1.9965747 | S36: 2 | T36: 56.1 | U36: 0 | V36: 0 | W36: 2.64 | X36: 0.01 | Y36: =W36*(1+X36) -> 2.6664 | Z36: 0.302 | AA36: =R36-Y36 -> -0.6698253 | AB36: =R36-Z36 -> 1.6945747 | AC36: NH₃ INTEGRATED in headline. AN/CAN. Default base ~2.64 ×1.01 = 2.666 (2026, N2O-driven). Benchmark 0.302. S2 IN CBAM scope. Default value highly sensitive to assumed N2O abatement. | AD36: v0.15 EF: Egypt CBAM EF v0.1 (egypt+mitigation/EmissionFactors/EGY_CBAM_EF_v0.1.xlsx Products; EGY_CBAM_EF_Methodology_v0.1.md). AN no = integrated HNO3 N2O 0.79 x 1.2588 (kernel convention; EF workbook books it as precursor); 50 % N2O abatement assumed (VERIFY). Prior: S1.fc: Est: IFA/EFMA BAT Vol.3; 1.5-2.5 GJ/t AN typical. Total direct EF less / S1.fp: Auth: HNO3 and neutralisation have no reductant | AE36: v0.15 EF: Egypt CBAM EF v0.1 (egypt+mitigation/EmissionFactors/EGY_CBAM_EF_v0.1.xlsx Products; EGY_CBAM_EF_Methodology_v0.1.md). AN no = integrated HNO3 N2O 0.79 x 1.2588 (kernel convention; EF workbook books it as precursor); 50 % N2O abatement assumed (VERIFY). Prior: S1.np: Auth: AN chemistry (NH4NO3) contains no carbon / S1.no: Est: IPCC 2006 2B2; GWP AR6 AII.1.2. CRITICAL: range 0.21 (with high-e
D37: Primary aluminium | E37: t Al | F37: 7601 10 (unwrought primary); 7601 20 (alloys, semi-finished); 7604 (bars/rods); 7606 (sheet/plate) | G37: Hall-Héroult electrolysis + carbon anode prebaking | H37: 0.12342 | I37: 0 | J37: 1.623493 | K37: 0.774 | L37: =SUM(H37:K37) -> 2.520913 | M37: 0 | N37: =L37+M37 -> 2.520913 | O37: 6.75 | P37: 0 | Q37: =N37+O37 -> 9.270913 | R37: =N37+O37*P37 -> 2.520913 | S37: 1.582 | T37: 78 | U37: 0 | V37: 0 | W37: 2.06 | X37: 0.1 | Y37: =W37*(1+X37) -> 2.266 | Z37: 1.423 | AA37: =R37-Y37 -> 0.25491304 | AB37: =R37-Z37 -> 1.097913 | AC37: Primary aluminium. Default base 2.060 ×1.10 = 2.266 (2026). Benchmark 1.423. S2 NOT in CBAM scope (direct emissions only). | AD37: v0.15 EF: Egypt CBAM EF v0.1 (egypt+mitigation/EmissionFactors/EGY_CBAM_EF_v0.1.xlsx Products; EGY_CBAM_EF_Methodology_v0.1.md). Prior: S1.fc: Est: IAI 2023 smelter profile; 1.5-2.5 GJ/t range. Weighted EF 78 kgCO / S1.fp: Auth: Hall-Héroult is electrolytic; reduction is electrical not fuel-d | AE37: v0.15 EF: Egypt CBAM EF v0.1 (egypt+mitigation/EmissionFactors/EGY_CBAM_EF_v0.1.xlsx Products; EGY_CBAM_EF_Methodology_v0.1.md). Prior: S1.np: Auth: IPCC 2006 Vol2 2C3 default 1.5 tCO2/t Al for prebaked anodes. Ra / S1.no: Est: IAI 2023 Egypt country profile. Global prebaked average 0.38 tCO2
B38: Legacy ad hoc semi-elasticities (AdHocCalculations; one beta for np + no; no documented source). Used only when E50 = ADHOC, and by the fund placeholder (block o107-o114)
D39: Process | E39: Half Elasticity | F39: ER at $100 (%)
D40: DRI-EAF steel | E40: 0.0010536052 | F40: 0.1
D41: Scrap-EAF steel | E41: 0.00020202707 | F41: 0.02
D42: BF-BOF steel reference | E42: 0.00051293294 | F42: 0.05
D43: Grey clinker dry-process | E43: 0.00083381609 | F43: 0.08
D44: Ammonia net | E44: 0.0019845094 | F44: 0.18
D45: Urea | E45: 0 | F45: 0
D46: AN | E46: 0.010498221 | F46: 0.65
D47: Primary aluminium | E47: 0.00083381609 | F47: 0.08
B49: Process-emission semi-elasticities (Task D, v0.9): inferred from IPCC; used by CBAM block rows o118-o125
D50: Semi-elasticity set used by the block (IPCC / ADHOC) | E50: IPCC | F50: ADHOC = rows 40-47 with ERmax = 1 (reproduces v0.8)
D51: ER(P) = ERmax x (1 - exp(-beta x P)); beta = -ln(1 - ER*/ERmax)/P* from the anchor (P*, ER*); semi-elasticity at P = 0 = ERmax x beta. np = non-fuel process CO2, no = non-CO2 process (Manual inputs J, K). ERmax = technical potential by ~2035 with commercial technology; CCS and process change are excluded (no Egyptian CO2 storage or H2-DRI before 2035).
D52: Product | E52: np ERmax | F52: np anchor P* ($/t) | G52: np ER at P* | H52: np beta (1/$) | I52: no ERmax | J52: no anchor P* ($/t) | K52: no ER at P* | L52: no beta (1/$) | M52: np semi-el. at P=0 (%/$) | N52: no semi-el. at P=0 (%/$) | O52: np ER at $20 | P52: no ER at $20 | Q52: np lever and source | R52: no lever and source | S52: Confidence | T52: beta.np used | U52: ERmax.np used | V52: beta.no used | W52: ERmax.no used
D53: DRI-EAF steel | E53: 1 | F53: 122 | G53: 0.3433 | H53: =IF(OR(E53=0,G53=0),0,-LN(1-G53/E53)/F53) -> 0.0034469507 | I53: 0 | J53: 122 | K53: 0 | L53: =IF(OR(I53=0,K53=0),0,-LN(1-K53/I53)/J53) -> 0 | M53: =E53*H53 -> 0.0034469507 | N53: =I53*L53 -> 0 | O53: =E53*(1-EXP(-H53*20)) -> 0.066616398 | P53: =I53*(1-EXP(-L53*20)) -> 0 | Q53: IPCC AR6 WGIII Table 11.3/12.3 cost-bucket MACC, central (mean 2030 & long-run), USD2019; ER at $100 (Option A: ERmax 1, P* 122 = USD2019 100 deflated to USD2024, US GDP deflator ~1.22; v0.16). Derivation: egypt+mitigation/ProcessEmissions_CarbonPrice_Response; spec TASK-D v0.2. Lever: H2/NG-DRI, scrap share, CCS on shaft | R53: n/a (no ERmax 0) | S53: Medium | T53: =IF($E$50="ADHOC",$E$40,H53) -> 0.0034469507 | U53: =IF($E$50="ADHOC",1,E53) -> 1 | V53: =IF($E$50="ADHOC",$E$40,L53) -> 0 | W53: =IF($E$50="ADHOC",1,I53) -> 0
D54: Scrap-EAF steel | E54: 1 | F54: 122 | G54: 0.181 | H54: =IF(OR(E54=0,G54=0),0,-LN(1-G54/E54)/F54) -> 0.0016366491 | I54: 0 | J54: 122 | K54: 0 | L54: =IF(OR(I54=0,K54=0),0,-LN(1-K54/I54)/J54) -> 0 | M54: =E54*H54 -> 0.0016366491 | N54: =I54*L54 -> 0 | O54: =E54*(1-EXP(-H54*20)) -> 0.032203056 | P54: =I54*(1-EXP(-L54*20)) -> 0 | Q54: IPCC AR6 WGIII Table 11.3/12.3 cost-bucket MACC, central (mean 2030 & long-run), USD2019; ER at $100 (Option A: ERmax 1, P* 122 = USD2019 100 deflated to USD2024, US GDP deflator ~1.22; v0.16). Derivation: egypt+mitigation/ProcessEmissions_CarbonPrice_Response; spec TASK-D v0.2. Lever: electrode / carbon-input efficiency | R54: n/a (no ERmax 0) | S54: Low | T54: =IF($E$50="ADHOC",$E$41,H54) -> 0.0016366491 | U54: =IF($E$50="ADHOC",1,E54) -> 1 | V54: =IF($E$50="ADHOC",$E$41,L54) -> 0 | W54: =IF($E$50="ADHOC",1,I54) -> 0
D55: BF-BOF steel (reference) | E55: 1 | F55: 122 | G55: 0.2803 | H55: =IF(OR(E55=0,G55=0),0,-LN(1-G55/E55)/F55) -> 0.0026960723 | I55: 0 | J55: 122 | K55: 0 | L55: =IF(OR(I55=0,K55=0),0,-LN(1-K55/I55)/J55) -> 0 | M55: =E55*H55 -> 0.0026960723 | N55: =I55*L55 -> 0 | O55: =E55*(1-EXP(-H55*20)) -> 0.052493466 | P55: =I55*(1-EXP(-L55*20)) -> 0 | Q55: IPCC AR6 WGIII Table 11.3/12.3 cost-bucket MACC, central (mean 2030 & long-run), USD2019; ER at $100 (Option A: ERmax 1, P* 122 = USD2019 100 deflated to USD2024, US GDP deflator ~1.22; v0.16). Derivation: egypt+mitigation/ProcessEmissions_CarbonPrice_Response; spec TASK-D v0.2. Lever: top-gas recycling, DRI substitution, CCS | R55: n/a (no ERmax 0) | S55: Medium | T55: =IF($E$50="ADHOC",$E$42,H55) -> 0.0026960723 | U55: =IF($E$50="ADHOC",1,E55) -> 1 | V55: =IF($E$50="ADHOC",$E$42,L55) -> 0 | W55: =IF($E$50="ADHOC",1,I55) -> 0
D56: Grey clinker (dry-process) | E56: 1 | F56: 122 | G56: 0.3352 | H56: =IF(OR(E56=0,G56=0),0,-LN(1-G56/E56)/F56) -> 0.0033464675 | I56: 0 | J56: 122 | K56: 0 | L56: =IF(OR(I56=0,K56=0),0,-LN(1-K56/I56)/J56) -> 0 | M56: =E56*H56 -> 0.0033464675 | N56: =I56*L56 -> 0 | O56: =E56*(1-EXP(-H56*20)) -> 0.064738725 | P56: =I56*(1-EXP(-L56*20)) -> 0 | Q56: IPCC AR6 WGIII Table 11.3/12.3 cost-bucket MACC, central (mean 2030 & long-run), USD2019; ER at $100 (Option A: ERmax 1, P* 122 = USD2019 100 deflated to USD2024, US GDP deflator ~1.22; v0.16). Derivation: egypt+mitigation/ProcessEmissions_CarbonPrice_Response; spec TASK-D v0.2. Lever: clinker substitution (SCMs, LC3), CCS | R56: n/a (no ERmax 0) | S56: Medium | T56: =IF($E$50="ADHOC",$E$43,H56) -> 0.0033464675 | U56: =IF($E$50="ADHOC",1,E56) -> 1 | V56: =IF($E$50="ADHOC",$E$43,L56) -> 0 | W56: =IF($E$50="ADHOC",1,I56) -> 0
D57: Ammonia (net merchant) | E57: 0 | F57: 122 | G57: 0 | H57: =IF(OR(E57=0,G57=0),0,-LN(1-G57/E57)/F57) -> 0 | I57: 0 | J57: 122 | K57: 0 | L57: =IF(OR(I57=0,K57=0),0,-LN(1-K57/I57)/J57) -> 0 | M57: =E57*H57 -> 0 | N57: =I57*L57 -> 0 | O57: =E57*(1-EXP(-H57*20)) -> 0 | P57: =I57*(1-EXP(-L57*20)) -> 0 | Q57: n/a (np ERmax 0): none: np = 0 (SMR feedstock CO2 is fp; CCS / blue lever not routed to fp - caveat) | R57: n/a (no ERmax 0) | S57: Low | T57: =IF($E$50="ADHOC",$E$44,H57) -> 0 | U57: =IF($E$50="ADHOC",1,E57) -> 0 | V57: =IF($E$50="ADHOC",$E$44,L57) -> 0 | W57: =IF($E$50="ADHOC",1,I57) -> 0
D58: Urea | E58: 0 | F58: 122 | G58: 0 | H58: =IF(OR(E58=0,G58=0),0,-LN(1-G58/E58)/F58) -> 0 | I58: 0 | J58: 122 | K58: 0 | L58: =IF(OR(I58=0,K58=0),0,-LN(1-K58/I58)/J58) -> 0 | M58: =E58*H58 -> 0 | N58: =I58*L58 -> 0 | O58: =E58*(1-EXP(-H58*20)) -> 0 | P58: =I58*(1-EXP(-L58*20)) -> 0 | Q58: n/a (np ERmax 0): none: inherits ammonia (np = 0 under CBAM rule) | R58: n/a (no ERmax 0) | S58: Low | T58: =IF($E$50="ADHOC",$E$45,H58) -> 0 | U58: =IF($E$50="ADHOC",1,E58) -> 0 | V58: =IF($E$50="ADHOC",$E$45,L58) -> 0 | W58: =IF($E$50="ADHOC",1,I58) -> 0
D59: Ammonium nitrate | E59: 0 | F59: 122 | G59: 0 | H59: =IF(OR(E59=0,G59=0),0,-LN(1-G59/E59)/F59) -> 0 | I59: 1 | J59: 122 | K59: 0.6179 | L59: =IF(OR(I59=0,K59=0),0,-LN(1-K59/I59)/J59) -> 0.0078858436 | M59: =E59*H59 -> 0 | N59: =I59*L59 -> 0.0078858436 | O59: =E59*(1-EXP(-H59*20)) -> 0 | P59: =I59*(1-EXP(-L59*20)) -> 0.14590844 | Q59: n/a (np ERmax 0): - | R59: IPCC AR6 WGIII Table 11.3/12.3 cost-bucket MACC, central (mean 2030 & long-run), USD2019; ER at $100 (Option A: ERmax 1, P* 122 = USD2019 100 deflated to USD2024, US GDP deflator ~1.22; v0.16). Derivation: egypt+mitigation/ProcessEmissions_CarbonPrice_Response; spec TASK-D v0.2. Lever: tertiary N2O abatement in HNO3 (blend: unabated 0.7210 / abated 0.3292 at 50 % abated share, N2O-weighted) | S59: Medium | T59: =IF($E$50="ADHOC",$E$46,H59) -> 0 | U59: =IF($E$50="ADHOC",1,E59) -> 0 | V59: =IF($E$50="ADHOC",$E$46,L59) -> 0.0078858436 | W59: =IF($E$50="ADHOC",1,I59) -> 1
D60: Primary aluminium | E60: 1 | F60: 122 | G60: 0.2164 | H60: =IF(OR(E60=0,G60=0),0,-LN(1-G60/E60)/F60) -> 0.0019988245 | I60: 1 | J60: 122 | K60: 0.2164 | L60: =IF(OR(I60=0,K60=0),0,-LN(1-K60/I60)/J60) -> 0.0019988245 | M60: =E60*H60 -> 0.0019988245 | N60: =I60*L60 -> 0.0019988245 | O60: =E60*(1-EXP(-H60*20)) -> 0.039187973 | P60: =I60*(1-EXP(-L60*20)) -> 0.039187973 | Q60: IPCC AR6 WGIII Table 11.3/12.3 cost-bucket MACC, central (mean 2030 & long-run), USD2019; ER at $100 (Option A: ERmax 1, P* 122 = USD2019 100 deflated to USD2024, US GDP deflator ~1.22; v0.16). Derivation: egypt+mitigation/ProcessEmissions_CarbonPrice_Response; spec TASK-D v0.2. Lever: inert / improved anodes, PFC control (combined central, applied to np and no) | R60: IPCC AR6 WGIII Table 11.3/12.3 cost-bucket MACC, central (mean 2030 & long-run), USD2019; ER at $100 (Option A: ERmax 1, P* 122 = USD2019 100 deflated to USD2024, US GDP deflator ~1.22; v0.16). Derivation: egypt+mitigation/ProcessEmissions_CarbonPrice_Response; spec TASK-D v0.2. Lever: inert / improved anodes, PFC control (combined central) | S60: Low | T60: =IF($E$50="ADHOC",$E$47,H60) -> 0.0019988245 | U60: =IF($E$50="ADHOC",1,E60) -> 1 | V60: =IF($E$50="ADHOC",$E$47,L60) -> 0.0019988245 | W60: =IF($E$50="ADHOC",1,I60) -> 1
B62: Output response to the net product cost increase (Task H, v0.10): used by CBAM block production rows o31-o38
D63: Output response switch (ON / OFF) | E63: ON | F63: OFF = eps 0, production on the fixed growth path (reproduces v0.9). Always off for the LEGACY bundle (regression vs CPAT)
D64: Q = Qbase x (1 + dp_net)^eps; dp_net = (carbon cost per t - OBR rebate per t) / pre-policy product price (block o75-o82). The rebate obrrb (theta x cptraj) is paid on the pre-policy covered EF, so theta = 1 (3B) leaves output unchanged; intensity still responds to the full price. eps by product from v1.6 (OutputElasticity_Note_v0.1); cement -0.10, steel and fertilisers -0.40, aluminium -0.50.
D65: Product | E65: Output elasticity eps (input) | F65: Source / rationale | G65: Confidence | K65: eps used
D66: DRI-EAF steel | E66: -0.4 | F66: Steel: demand -0.2 to -0.3, pass-through about 0.5 (EU studies 0.06-1.2), import competition (GTAP Armington about 3). Replaces the uniform -0.5 placeholder; carbon cost is only 1-3% of the price, so the result is insensitive. Evidence note: egypt/supporting/OutputElasticity_Note_v0.1. | G66: low-medium | K66: =IF(AND($E$63="ON",Settings!$B$10<>"LEGACY"),E66,0) -> 0
D67: Scrap-EAF steel | E67: -0.4 | F67: Steel: demand -0.2 to -0.3, pass-through about 0.5 (EU studies 0.06-1.2), import competition (GTAP Armington about 3). Replaces the uniform -0.5 placeholder; carbon cost is only 1-3% of the price, so the result is insensitive. Evidence note: egypt/supporting/OutputElasticity_Note_v0.1. | G67: low-medium | K67: =IF(AND($E$63="ON",Settings!$B$10<>"LEGACY"),E67,0) -> 0
D68: BF-BOF steel (reference) | E68: -0.4 | F68: Steel: demand -0.2 to -0.3, pass-through about 0.5 (EU studies 0.06-1.2), import competition (GTAP Armington about 3). Replaces the uniform -0.5 placeholder; carbon cost is only 1-3% of the price, so the result is insensitive. Evidence note: egypt/supporting/OutputElasticity_Note_v0.1. | G68: low-medium | K68: =IF(AND($E$63="ON",Settings!$B$10<>"LEGACY"),E68,0) -> 0
D69: Grey clinker (dry-process) | E69: -0.1 | F69: Cement: market demand -0.02 to -0.16, pass-through 0.2-0.4 (EC / CE Delft-Oeko), small trade exposure (1.6% of output to the EU). The only product for which eps matters (carbon cost 15% of price). Evidence note: egypt/supporting/OutputElasticity_Note_v0.1. | G69: low-medium | K69: =IF(AND($E$63="ON",Settings!$B$10<>"LEGACY"),E69,0) -> 0
D70: Ammonia (net merchant) | E70: -0.4 | F70: Fertiliser: inelastic demand; exporters are price takers. Carbon cost under 3% of the price, so the result is insensitive. Evidence note: egypt/supporting/OutputElasticity_Note_v0.1. | G70: low-medium | K70: =IF(AND($E$63="ON",Settings!$B$10<>"LEGACY"),E70,0) -> 0
D71: Urea | E71: -0.4 | F71: Fertiliser: inelastic demand; exporters are price takers. Carbon cost under 3% of the price, so the result is insensitive. Evidence note: egypt/supporting/OutputElasticity_Note_v0.1. | G71: low-medium | K71: =IF(AND($E$63="ON",Settings!$B$10<>"LEGACY"),E71,0) -> 0
D72: Ammonium nitrate | E72: -0.4 | F72: Fertiliser: inelastic demand; exporters are price takers. Carbon cost under 3% of the price, so the result is insensitive. Evidence note: egypt/supporting/OutputElasticity_Note_v0.1. | G72: low-medium | K72: =IF(AND($E$63="ON",Settings!$B$10<>"LEGACY"),E72,0) -> 0
D73: Primary aluminium | E73: -0.5 | F73: Aluminium: world-priced metal, 56% exported; no better evidence found, kept at -0.5 (range -0.3 to -1.5). Cost under 1% of price: insensitive. Evidence note: egypt/supporting/OutputElasticity_Note_v0.1. | G73: low-medium | K73: =IF(AND($E$63="ON",Settings!$B$10<>"LEGACY"),E73,0) -> 0
B75: CBAM obligations (Task L, v0.11): EU ETS price and CBAM phase-in; used by CBAM block rows o94, o105, o116, o127
D76: CBAM obligation convention (FULL / SCALED / NOPHASE) | E76: FULL | F76: FULL: CBF phase-in, domestic price paid deducted in full; SCALED: deduction x CBF; NOPHASE: CBF = 1 (EgyptResultsInitial / ad hoc convention)
D77: Obligation per t exported = max(0, CBF x P_EU x embedded intensity - S x price effectively paid per t, net of OBR rebates). Direct emissions only (fc + fp + np + no); EU exports scale with production.
D78: Series | E78: Unit | F78: Source | L78: 2022 | M78: 2023 | N78: 2024 | O78: 2025 | P78: 2026 | Q78: 2027 | R78: 2028 | S78: 2029 | T78: 2030 | U78: 2031 | V78: 2032 | W78: 2033 | X78: 2034 | Y78: 2035 | Z78: 2036 | AA78: 2037 | AB78: 2038 | AC78: 2039 | AD78: 2040 | AE78: 2041
D79: EU ETS / CBAM certificate price | E79: $/tCO2e real | F79: PLACEHOLDER 100 flat (EgyptResultsInitial / AdHocCalculations assumption); replace with an EU ETS outlook | L79: 100 | M79: 100 | N79: 100 | O79: 100 | P79: 100 | Q79: 100 | R79: 100 | S79: 100 | T79: 100 | U79: 100 | V79: 100 | W79: 100 | X79: 100 | Y79: 100 | Z79: 100 | AA79: 100 | AB79: 100 | AC79: 100 | AD79: 100 | AE79: 100
D80: CBAM factor = 1 - EU free allocation share (input) | E80: share | F80: Directive 2003/87/EC Art. 10a(1a) as amended 2023 (CBAM Reg. 2023/956 Art. 31): 2.5% 2026 ... 100% 2034 | L80: 0 | M80: 0 | N80: 0 | O80: 0 | P80: 0.025 | Q80: 0.05 | R80: 0.1 | S80: 0.225 | T80: 0.485 | U80: 0.61 | V80: 0.735 | W80: 0.86 | X80: 1 | Y80: 1 | Z80: 1 | AA80: 1 | AB80: 1 | AC80: 1 | AD80: 1 | AE80: 1
D81: CBAM factor used | E81: share | F81: 1 if NOPHASE, else the input row | L81: =IF($E$76="NOPHASE",1,L80) -> 0 | M81: =IF($E$76="NOPHASE",1,M80) -> 0 | N81: =IF($E$76="NOPHASE",1,N80) -> 0 | O81: =IF($E$76="NOPHASE",1,O80) -> 0 | P81: =IF($E$76="NOPHASE",1,P80) -> 0.025 | Q81: =IF($E$76="NOPHASE",1,Q80) -> 0.05 | R81: =IF($E$76="NOPHASE",1,R80) -> 0.1 | S81: =IF($E$76="NOPHASE",1,S80) -> 0.225 | ... AE81: =IF($E$76="NOPHASE",1,AE80) -> 1
D82: Deduction scaling used (S) | E82: share | F82: CBF used if SCALED, else 1 | L82: =IF($E$76="SCALED",L81,1) -> 1 | M82: =IF($E$76="SCALED",M81,1) -> 1 | N82: =IF($E$76="SCALED",N81,1) -> 1 | O82: =IF($E$76="SCALED",O81,1) -> 1 | P82: =IF($E$76="SCALED",P81,1) -> 1 | Q82: =IF($E$76="SCALED",Q81,1) -> 1 | R82: =IF($E$76="SCALED",R81,1) -> 1 | S82: =IF($E$76="SCALED",S81,1) -> 1 | ... AE82: =IF($E$76="SCALED",AE81,1) -> 1
B84: IPPU accounting (Task G, v0.13)
D85: Non-block IPPU response (IppuOther: NONE / CPAT) | E85: NONE | F85: NONE (default, MajorIssues #17): IPPU outside the CBAM block held at baseline in the policy scenario. CPAT: scaled with industrial energy CO2 as in CPAT. Code egy.in.ippuoth
D86: IPPU_Industry: kernel IPPU = block process (np + no, post-policy) + fp flagged below + non-block remainder (CPAT IPPU baseline - block IPPU baseline); replaces CPAT's proportional IPPU row
D87: Product | E87: fp counted as IPPU (1/0) | F87: Source / rationale | G87: Confidence | H87: Code
D88: DRI-EAF steel | E88: 0 | F88: 0: DRI reductant gas stays in energy CO2 (IEA/CPAT iron & steel final consumption; block steel fc+fp < CPAT irn) | G88: assumption | H88: egy.in.ippufp.stl.drg
D89: Scrap-EAF steel | E89: 0 | F89: 0: no fp | G89: assumption | H89: egy.in.ippufp.stl.scr
D90: BF-BOF steel (reference) | E90: 0 | F90: 0: BF-BOF coke/coal reductant counted with energy (not produced in Egypt, Q = 0) | G90: assumption | H90: egy.in.ippufp.stl.bof
D91: Grey clinker (dry-process) | E91: 0 | F91: 0: no fp | G91: assumption | H91: egy.in.ippufp.cmt.dry
D92: Ammonia (net merchant) | E92: 1 | F92: 1: SMR feedstock gas = IEA non-energy use (not in CPAT energy CO2; CPAT mch = 0) and IPCC 2B1 IPPU | G92: assumption | H92: egy.in.ippufp.frt.amc
D93: Urea | E93: 0 | F93: 0: no fp | G93: assumption | H93: egy.in.ippufp.frt.ure
D94: Ammonium nitrate | E94: 0 | F94: 0: no fp | G94: assumption | H94: egy.in.ippufp.frt.nit
D95: Primary aluminium | E95: 0 | F95: 0: no fp | G95: assumption | H95: egy.in.ippufp.alu.prp
B98: CBAM product market data (Task T3, v1.4)
D99: 2024 production, growth, EU exports and pre-policy price, entered once and linked from both scenario blocks of Mitigation_Industry (F:G, I of rows 276-283 / 675-682; G of rows 288-295 / 687-694). Values are the v0.7 ad hoc assumptions (Low confidence).
D100: Product | E100: 2024 production (kt) | F100: Production growth (%/yr) | G100: 2024 total exports (kt) - placeholder, not linked | H100: 2024 EU exports (kt) | I100: Pre-policy price (USD/t) | J100: Codes | K100: Source / rationale | L100: Confidence
D101: DRI-EAF steel | E101: 5100 | F101: 0.044 | H101: 580 | I101: 750 | J101: egy.in.prod.stl.drg | egy.in.prodg.stl.drg | egy.in.expeu.stl.drg | all.in.ppx.stl.drg.--- | K101: v0.7 ad hoc assumption (EgyptResultsInitial / AdHocCalculations), unsourced. Replace with CAPMAS / UN Comtrade (CN codes in Mitigation_Industry rows 288-295 labels). | L101: Low
D102: Scrap-EAF steel | E102: 4800 | F102: 0.044 | H102: 300 | I102: 680 | J102: egy.in.prod.stl.scr | egy.in.prodg.stl.scr | egy.in.expeu.stl.scr | all.in.ppx.stl.scr.--- | K102: v0.7 ad hoc assumption (EgyptResultsInitial / AdHocCalculations), unsourced. Replace with CAPMAS / UN Comtrade (CN codes in Mitigation_Industry rows 288-295 labels). | L102: Low
D103: BF-BOF steel (reference) | E103: 0 | F103: 0 | H103: 0 | I103: 620 | J103: egy.in.prod.stl.bof | egy.in.prodg.stl.bof | egy.in.expeu.stl.bof | all.in.ppx.stl.bof.--- | K103: v0.7 ad hoc assumption (EgyptResultsInitial / AdHocCalculations), unsourced. Replace with CAPMAS / UN Comtrade (CN codes in Mitigation_Industry rows 288-295 labels). | L103: Low
D104: Grey clinker (dry-process) | E104: 50000 | F104: 0.033 | H104: 800 | I104: 110 | J104: egy.in.prod.cmt.dry | egy.in.prodg.cmt.dry | egy.in.expeu.cmt.dry | all.in.ppx.cmt.dry.--- | K104: v0.7 ad hoc assumption (EgyptResultsInitial / AdHocCalculations), unsourced. Replace with CAPMAS / UN Comtrade (CN codes in Mitigation_Industry rows 288-295 labels). | L104: Low
D105: Ammonia (net merchant) | E105: 1785 | F105: 0.022 | H105: 120 | I105: 450 | J105: egy.in.prod.frt.amc | egy.in.prodg.frt.amc | egy.in.expeu.frt.amc | all.in.ppx.frt.amc.--- | K105: v0.7 ad hoc assumption (EgyptResultsInitial / AdHocCalculations), unsourced. Replace with CAPMAS / UN Comtrade (CN codes in Mitigation_Industry rows 288-295 labels). | L105: Low
D106: Urea | E106: 2800 | F106: 0.022 | H106: 1600 | I106: 380 | J106: egy.in.prod.frt.ure | egy.in.prodg.frt.ure | egy.in.expeu.frt.ure | all.in.ppx.frt.ure.--- | K106: v0.7 ad hoc assumption (EgyptResultsInitial / AdHocCalculations), unsourced. Replace with CAPMAS / UN Comtrade (CN codes in Mitigation_Industry rows 288-295 labels). | L106: Low
D107: Ammonium nitrate | E107: 600 | F107: 0.022 | H107: 80 | I107: 320 | J107: egy.in.prod.frt.nit | egy.in.prodg.frt.nit | egy.in.expeu.frt.nit | all.in.ppx.frt.nit.--- | K107: v0.7 ad hoc assumption (EgyptResultsInitial / AdHocCalculations), unsourced. Replace with CAPMAS / UN Comtrade (CN codes in Mitigation_Industry rows 288-295 labels). | L107: Low
D108: Primary aluminium | E108: 300 | F108: 0.055 | H108: 167 | I108: 2400 | J108: egy.in.prod.alu.prp | egy.in.prodg.alu.prp | egy.in.expeu.alu.prp | all.in.ppx.alu.prp.--- | K108: v0.7 ad hoc assumption (EgyptResultsInitial / AdHocCalculations), unsourced. Replace with CAPMAS / UN Comtrade (CN codes in Mitigation_Industry rows 288-295 labels). | L108: Low
B111: Final Table 2 conventions (v1.5)
D112: 3B output-based rebate also covers non-CBAM covered industry (1 = all covered industry; 0 = CBAM block only) | E112: 1 | F112: Decision 2026-10-04 (CAVEATS): rebate to all covered industry; same switch as ThetaOther in the AdHoc rebuild. Used by CarveOut_Table2 section G (3B only). | G112: Medium | H112: egy.in.thetao.---
D113: CBAM obligation conventions (rows 76-82) stay a memo: FULL = 2030 phase-in (CBAM factor 0.485), NOPHASE = no phase-in (factor 1). Table 2 row O is the CBAM-product intensity change and does not depend on them.

Sheet CPAT_National
B1: Fuel | C1: Sector | D1: Description | E1: Unit | F1: Source | G1: Input Code | H1: Output Code | I1: Note | J1: Helper | K1: 2021 | L1: 2022 | M1: 2023 | N1: 2024 | O1: 2025 | P1: 2026 | Q1: 2027 | R1: 2028 | S1: 2029 | T1: 2030 | U1: 2031 | V1: 2032 | W1: 2033 | X1: 2034 | Y1: 2035 | Z1: 2036 | AA1: 2037 | AB1: 2038 | AC1: 2039 | AD1: 2040 | AE1: 2041 | AF1: 2042 | AG1: 2043 | AH1: 2044 | AI1: 2045
B2: Main CPAT - Egypt: national outputs of the CPAT runs EG1-EG4 used by Task M (stored values)
B3: A. CPAT national outputs by run, linked by INDEX/MATCH to sheet CPAT_Results (key = CPAT code & "_" & run, year = row 5); EG1 = 1A/2A, EG2 = 2B, EG3 = 3A-3C, EG4 unused
B5: Key (code|run) | C5: Run | D5: Description | E5: Unit | F5: Source | H5: CPAT code | I5: Note | K5: 2021 | L5: 2022 | M5: 2023 | N5: 2024 | O5: 2025 | P5: 2026 | Q5: 2027 | R5: 2028 | S5: 2029 | T5: 2030 | U5: 2031 | V5: 2032 | W5: 2033 | X5: 2034 | Y5: 2035 | Z5: 2036 | AA5: 2037 | AB5: 2038 | AC5: 2039 | AD5: 2040 | AE5: 2041 | AF5: 2042 | AG5: 2043 | AH5: 2044 | AI5: 2045
B6: egy.air.ada.2464|EG1 | C6: EG1 | D6: Averted deaths by age group: 25 to 64 years | E6: deaths | F6: CPAT_Results (EG1) | H6: egy.air.ada.2464 | L6: =INDEX(CPAT_Results!$A:$AD,MATCH($H6&"_"&$C6,CPAT_Results!$F:$F,0),MATCH(L$5,CPAT_Results!$1:$1,0)) -> 0 | M6: =INDEX(CPAT_Results!$A:$AD,MATCH($H6&"_"&$C6,CPAT_Results!$F:$F,0),MATCH(M$5,CPAT_Results!$1:$1,0)) -> -1 | N6: =INDEX(CPAT_Results!$A:$AD,MATCH($H6&"_"&$C6,CPAT_Results!$F:$F,0),MATCH(N$5,CPAT_Results!$1:$1,0)) -> -1 | O6: =INDEX(CPAT_Results!$A:$AD,MATCH($H6&"_"&$C6,CPAT_Results!$F:$F,0),MATCH(O$5,CPAT_Results!$1:$1,0)) -> -1 | P6: =INDEX(CPAT_Results!$A:$AD,MATCH($H6&"_"&$C6,CPAT_Results!$F:$F,0),MATCH(P$5,CPAT_Results!$1:$1,0)) -> 802 | Q6: =INDEX(CPAT_Results!$A:$AD,MATCH($H6&"_"&$C6,CPAT_Results!$F:$F,0),MATCH(Q$5,CPAT_Results!$1:$1,0)) -> 673 | R6: =INDEX(CPAT_Results!$A:$AD,MATCH($H6&"_"&$C6,CPAT_Results!$F:$F,0),MATCH(R$5,CPAT_Results!$1:$1,0)) -> 626 | S6: =INDEX(CPAT_Results!$A:$AD,MATCH($H6&"_"&$C6,CPAT_Results!$F:$F,0),MATCH(S$5,CPAT_Results!$1:$1,0)) -> 582 | ... AE6: =INDEX(CPAT_Results!$A:$AD,MATCH($H6&"_"&$C6,CPAT_Results!$F:$F,0),MATCH(AE$5,CPAT_Results!$1:$1,0)) -> 0
B7: egy.air.ada.2464|EG2 | C7: EG2 | D7: Averted deaths by age group: 25 to 64 years | E7: deaths | F7: CPAT_Results (EG2) | H7: egy.air.ada.2464 | L7: =INDEX(CPAT_Results!$A:$AD,MATCH($H7&"_"&$C7,CPAT_Results!$F:$F,0),MATCH(L$5,CPAT_Results!$1:$1,0)) -> 0 | M7: =INDEX(CPAT_Results!$A:$AD,MATCH($H7&"_"&$C7,CPAT_Results!$F:$F,0),MATCH(M$5,CPAT_Results!$1:$1,0)) -> 0 | N7: =INDEX(CPAT_Results!$A:$AD,MATCH($H7&"_"&$C7,CPAT_Results!$F:$F,0),MATCH(N$5,CPAT_Results!$1:$1,0)) -> 0 | O7: =INDEX(CPAT_Results!$A:$AD,MATCH($H7&"_"&$C7,CPAT_Results!$F:$F,0),MATCH(O$5,CPAT_Results!$1:$1,0)) -> 0 | P7: =INDEX(CPAT_Results!$A:$AD,MATCH($H7&"_"&$C7,CPAT_Results!$F:$F,0),MATCH(P$5,CPAT_Results!$1:$1,0)) -> 0 | Q7: =INDEX(CPAT_Results!$A:$AD,MATCH($H7&"_"&$C7,CPAT_Results!$F:$F,0),MATCH(Q$5,CPAT_Results!$1:$1,0)) -> 0 | R7: =INDEX(CPAT_Results!$A:$AD,MATCH($H7&"_"&$C7,CPAT_Results!$F:$F,0),MATCH(R$5,CPAT_Results!$1:$1,0)) -> 0 | S7: =INDEX(CPAT_Results!$A:$AD,MATCH($H7&"_"&$C7,CPAT_Results!$F:$F,0),MATCH(S$5,CPAT_Results!$1:$1,0)) -> 29 | ... AE7: =INDEX(CPAT_Results!$A:$AD,MATCH($H7&"_"&$C7,CPAT_Results!$F:$F,0),MATCH(AE$5,CPAT_Results!$1:$1,0)) -> 0
B8: egy.air.ada.2464|EG3 | C8: EG3 | D8: Averted deaths by age group: 25 to 64 years | E8: deaths | F8: CPAT_Results (EG3) | H8: egy.air.ada.2464 | L8: =INDEX(CPAT_Results!$A:$AD,MATCH($H8&"_"&$C8,CPAT_Results!$F:$F,0),MATCH(L$5,CPAT_Results!$1:$1,0)) -> 0 | M8: =INDEX(CPAT_Results!$A:$AD,MATCH($H8&"_"&$C8,CPAT_Results!$F:$F,0),MATCH(M$5,CPAT_Results!$1:$1,0)) -> 1 | N8: =INDEX(CPAT_Results!$A:$AD,MATCH($H8&"_"&$C8,CPAT_Results!$F:$F,0),MATCH(N$5,CPAT_Results!$1:$1,0)) -> 1 | O8: =INDEX(CPAT_Results!$A:$AD,MATCH($H8&"_"&$C8,CPAT_Results!$F:$F,0),MATCH(O$5,CPAT_Results!$1:$1,0)) -> 1 | P8: =INDEX(CPAT_Results!$A:$AD,MATCH($H8&"_"&$C8,CPAT_Results!$F:$F,0),MATCH(P$5,CPAT_Results!$1:$1,0)) -> 223 | Q8: =INDEX(CPAT_Results!$A:$AD,MATCH($H8&"_"&$C8,CPAT_Results!$F:$F,0),MATCH(Q$5,CPAT_Results!$1:$1,0)) -> 84 | R8: =INDEX(CPAT_Results!$A:$AD,MATCH($H8&"_"&$C8,CPAT_Results!$F:$F,0),MATCH(R$5,CPAT_Results!$1:$1,0)) -> 113 | S8: =INDEX(CPAT_Results!$A:$AD,MATCH($H8&"_"&$C8,CPAT_Results!$F:$F,0),MATCH(S$5,CPAT_Results!$1:$1,0)) -> 183 | ... AE8: =INDEX(CPAT_Results!$A:$AD,MATCH($H8&"_"&$C8,CPAT_Results!$F:$F,0),MATCH(AE$5,CPAT_Results!$1:$1,0)) -> 0
B9: egy.air.ada.2464|EG4 | C9: EG4 | D9: Averted deaths by age group: 25 to 64 years | E9: deaths | F9: CPAT_Results (EG4) | H9: egy.air.ada.2464 | L9: =INDEX(CPAT_Results!$A:$AD,MATCH($H9&"_"&$C9,CPAT_Results!$F:$F,0),MATCH(L$5,CPAT_Results!$1:$1,0)) -> 0 | M9: =INDEX(CPAT_Results!$A:$AD,MATCH($H9&"_"&$C9,CPAT_Results!$F:$F,0),MATCH(M$5,CPAT_Results!$1:$1,0)) -> 0 | N9: =INDEX(CPAT_Results!$A:$AD,MATCH($H9&"_"&$C9,CPAT_Results!$F:$F,0),MATCH(N$5,CPAT_Results!$1:$1,0)) -> 0 | O9: =INDEX(CPAT_Results!$A:$AD,MATCH($H9&"_"&$C9,CPAT_Results!$F:$F,0),MATCH(O$5,CPAT_Results!$1:$1,0)) -> 0 | P9: =INDEX(CPAT_Results!$A:$AD,MATCH($H9&"_"&$C9,CPAT_Results!$F:$F,0),MATCH(P$5,CPAT_Results!$1:$1,0)) -> 0 | Q9: =INDEX(CPAT_Results!$A:$AD,MATCH($H9&"_"&$C9,CPAT_Results!$F:$F,0),MATCH(Q$5,CPAT_Results!$1:$1,0)) -> 0 | R9: =INDEX(CPAT_Results!$A:$AD,MATCH($H9&"_"&$C9,CPAT_Results!$F:$F,0),MATCH(R$5,CPAT_Results!$1:$1,0)) -> 2 | S9: =INDEX(CPAT_Results!$A:$AD,MATCH($H9&"_"&$C9,CPAT_Results!$F:$F,0),MATCH(S$5,CPAT_Results!$1:$1,0)) -> 6 | ... AE9: =INDEX(CPAT_Results!$A:$AD,MATCH($H9&"_"&$C9,CPAT_Results!$F:$F,0),MATCH(AE$5,CPAT_Results!$1:$1,0)) -> 0
B10: egy.air.ada.65|EG1 | C10: EG1 | D10: Averted deaths by age group: 65+ years | E10: deaths | F10: CPAT_Results (EG1) | H10: egy.air.ada.65 | L10: =INDEX(CPAT_Results!$A:$AD,MATCH($H10&"_"&$C10,CPAT_Results!$F:$F,0),MATCH(L$5,CPAT_Results!$1:$1,0)) -> 0 | M10: =INDEX(CPAT_Results!$A:$AD,MATCH($H10&"_"&$C10,CPAT_Results!$F:$F,0),MATCH(M$5,CPAT_Results!$1:$1,0)) -> -1 | N10: =INDEX(CPAT_Results!$A:$AD,MATCH($H10&"_"&$C10,CPAT_Results!$F:$F,0),MATCH(N$5,CPAT_Results!$1:$1,0)) -> -1 | O10: =INDEX(CPAT_Results!$A:$AD,MATCH($H10&"_"&$C10,CPAT_Results!$F:$F,0),MATCH(O$5,CPAT_Results!$1:$1,0)) -> -1 | P10: =INDEX(CPAT_Results!$A:$AD,MATCH($H10&"_"&$C10,CPAT_Results!$F:$F,0),MATCH(P$5,CPAT_Results!$1:$1,0)) -> 1410 | Q10: =INDEX(CPAT_Results!$A:$AD,MATCH($H10&"_"&$C10,CPAT_Results!$F:$F,0),MATCH(Q$5,CPAT_Results!$1:$1,0)) -> 1187 | R10: =INDEX(CPAT_Results!$A:$AD,MATCH($H10&"_"&$C10,CPAT_Results!$F:$F,0),MATCH(R$5,CPAT_Results!$1:$1,0)) -> 1105 | S10: =INDEX(CPAT_Results!$A:$AD,MATCH($H10&"_"&$C10,CPAT_Results!$F:$F,0),MATCH(S$5,CPAT_Results!$1:$1,0)) -> 1034 | ... AE10: =INDEX(CPAT_Results!$A:$AD,MATCH($H10&"_"&$C10,CPAT_Results!$F:$F,0),MATCH(AE$5,CPAT_Results!$1:$1,0)) -> 0
B11: egy.air.ada.65|EG2 | C11: EG2 | D11: Averted deaths by age group: 65+ years | E11: deaths | F11: CPAT_Results (EG2) | H11: egy.air.ada.65 | L11: =INDEX(CPAT_Results!$A:$AD,MATCH($H11&"_"&$C11,CPAT_Results!$F:$F,0),MATCH(L$5,CPAT_Results!$1:$1,0)) -> 0 | M11: =INDEX(CPAT_Results!$A:$AD,MATCH($H11&"_"&$C11,CPAT_Results!$F:$F,0),MATCH(M$5,CPAT_Results!$1:$1,0)) -> 0 | N11: =INDEX(CPAT_Results!$A:$AD,MATCH($H11&"_"&$C11,CPAT_Results!$F:$F,0),MATCH(N$5,CPAT_Results!$1:$1,0)) -> 0 | O11: =INDEX(CPAT_Results!$A:$AD,MATCH($H11&"_"&$C11,CPAT_Results!$F:$F,0),MATCH(O$5,CPAT_Results!$1:$1,0)) -> 0 | P11: =INDEX(CPAT_Results!$A:$AD,MATCH($H11&"_"&$C11,CPAT_Results!$F:$F,0),MATCH(P$5,CPAT_Results!$1:$1,0)) -> 0 | Q11: =INDEX(CPAT_Results!$A:$AD,MATCH($H11&"_"&$C11,CPAT_Results!$F:$F,0),MATCH(Q$5,CPAT_Results!$1:$1,0)) -> 0 | R11: =INDEX(CPAT_Results!$A:$AD,MATCH($H11&"_"&$C11,CPAT_Results!$F:$F,0),MATCH(R$5,CPAT_Results!$1:$1,0)) -> 0 | S11: =INDEX(CPAT_Results!$A:$AD,MATCH($H11&"_"&$C11,CPAT_Results!$F:$F,0),MATCH(S$5,CPAT_Results!$1:$1,0)) -> 53 | ... AE11: =INDEX(CPAT_Results!$A:$AD,MATCH($H11&"_"&$C11,CPAT_Results!$F:$F,0),MATCH(AE$5,CPAT_Results!$1:$1,0)) -> 0
B12: egy.air.ada.65|EG3 | C12: EG3 | D12: Averted deaths by age group: 65+ years | E12: deaths | F12: CPAT_Results (EG3) | H12: egy.air.ada.65 | L12: =INDEX(CPAT_Results!$A:$AD,MATCH($H12&"_"&$C12,CPAT_Results!$F:$F,0),MATCH(L$5,CPAT_Results!$1:$1,0)) -> 0 | M12: =INDEX(CPAT_Results!$A:$AD,MATCH($H12&"_"&$C12,CPAT_Results!$F:$F,0),MATCH(M$5,CPAT_Results!$1:$1,0)) -> 1 | N12: =INDEX(CPAT_Results!$A:$AD,MATCH($H12&"_"&$C12,CPAT_Results!$F:$F,0),MATCH(N$5,CPAT_Results!$1:$1,0)) -> 1 | O12: =INDEX(CPAT_Results!$A:$AD,MATCH($H12&"_"&$C12,CPAT_Results!$F:$F,0),MATCH(O$5,CPAT_Results!$1:$1,0)) -> 1 | P12: =INDEX(CPAT_Results!$A:$AD,MATCH($H12&"_"&$C12,CPAT_Results!$F:$F,0),MATCH(P$5,CPAT_Results!$1:$1,0)) -> 394 | Q12: =INDEX(CPAT_Results!$A:$AD,MATCH($H12&"_"&$C12,CPAT_Results!$F:$F,0),MATCH(Q$5,CPAT_Results!$1:$1,0)) -> 151 | R12: =INDEX(CPAT_Results!$A:$AD,MATCH($H12&"_"&$C12,CPAT_Results!$F:$F,0),MATCH(R$5,CPAT_Results!$1:$1,0)) -> 203 | S12: =INDEX(CPAT_Results!$A:$AD,MATCH($H12&"_"&$C12,CPAT_Results!$F:$F,0),MATCH(S$5,CPAT_Results!$1:$1,0)) -> 334 | ... AE12: =INDEX(CPAT_Results!$A:$AD,MATCH($H12&"_"&$C12,CPAT_Results!$F:$F,0),MATCH(AE$5,CPAT_Results!$1:$1,0)) -> 0
B13: egy.air.ada.65|EG4 | C13: EG4 | D13: Averted deaths by age group: 65+ years | E13: deaths | F13: CPAT_Results (EG4) | H13: egy.air.ada.65 | L13: =INDEX(CPAT_Results!$A:$AD,MATCH($H13&"_"&$C13,CPAT_Results!$F:$F,0),MATCH(L$5,CPAT_Results!$1:$1,0)) -> 0 | M13: =INDEX(CPAT_Results!$A:$AD,MATCH($H13&"_"&$C13,CPAT_Results!$F:$F,0),MATCH(M$5,CPAT_Results!$1:$1,0)) -> 0 | N13: =INDEX(CPAT_Results!$A:$AD,MATCH($H13&"_"&$C13,CPAT_Results!$F:$F,0),MATCH(N$5,CPAT_Results!$1:$1,0)) -> 0 | O13: =INDEX(CPAT_Results!$A:$AD,MATCH($H13&"_"&$C13,CPAT_Results!$F:$F,0),MATCH(O$5,CPAT_Results!$1:$1,0)) -> 0 | P13: =INDEX(CPAT_Results!$A:$AD,MATCH($H13&"_"&$C13,CPAT_Results!$F:$F,0),MATCH(P$5,CPAT_Results!$1:$1,0)) -> 0 | Q13: =INDEX(CPAT_Results!$A:$AD,MATCH($H13&"_"&$C13,CPAT_Results!$F:$F,0),MATCH(Q$5,CPAT_Results!$1:$1,0)) -> 0 | R13: =INDEX(CPAT_Results!$A:$AD,MATCH($H13&"_"&$C13,CPAT_Results!$F:$F,0),MATCH(R$5,CPAT_Results!$1:$1,0)) -> 4 | S13: =INDEX(CPAT_Results!$A:$AD,MATCH($H13&"_"&$C13,CPAT_Results!$F:$F,0),MATCH(S$5,CPAT_Results!$1:$1,0)) -> 10 | ... AE13: =INDEX(CPAT_Results!$A:$AD,MATCH($H13&"_"&$C13,CPAT_Results!$F:$F,0),MATCH(AE$5,CPAT_Results!$1:$1,0)) -> 0
B14: egy.air.ada.u24|EG1 | C14: EG1 | D14: Averted deaths by age group: under 24 years (including neonatal) | E14: deaths | F14: CPAT_Results (EG1) | H14: egy.air.ada.u24 | L14: =INDEX(CPAT_Results!$A:$AD,MATCH($H14&"_"&$C14,CPAT_Results!$F:$F,0),MATCH(L$5,CPAT_Results!$1:$1,0)) -> 0 | M14: =INDEX(CPAT_Results!$A:$AD,MATCH($H14&"_"&$C14,CPAT_Results!$F:$F,0),MATCH(M$5,CPAT_Results!$1:$1,0)) -> 0 | N14: =INDEX(CPAT_Results!$A:$AD,MATCH($H14&"_"&$C14,CPAT_Results!$F:$F,0),MATCH(N$5,CPAT_Results!$1:$1,0)) -> 0 | O14: =INDEX(CPAT_Results!$A:$AD,MATCH($H14&"_"&$C14,CPAT_Results!$F:$F,0),MATCH(O$5,CPAT_Results!$1:$1,0)) -> 0 | P14: =INDEX(CPAT_Results!$A:$AD,MATCH($H14&"_"&$C14,CPAT_Results!$F:$F,0),MATCH(P$5,CPAT_Results!$1:$1,0)) -> 132 | Q14: =INDEX(CPAT_Results!$A:$AD,MATCH($H14&"_"&$C14,CPAT_Results!$F:$F,0),MATCH(Q$5,CPAT_Results!$1:$1,0)) -> 110 | R14: =INDEX(CPAT_Results!$A:$AD,MATCH($H14&"_"&$C14,CPAT_Results!$F:$F,0),MATCH(R$5,CPAT_Results!$1:$1,0)) -> 102 | S14: =INDEX(CPAT_Results!$A:$AD,MATCH($H14&"_"&$C14,CPAT_Results!$F:$F,0),MATCH(S$5,CPAT_Results!$1:$1,0)) -> 93 | ... AE14: =INDEX(CPAT_Results!$A:$AD,MATCH($H14&"_"&$C14,CPAT_Results!$F:$F,0),MATCH(AE$5,CPAT_Results!$1:$1,0)) -> 0
B15: egy.air.ada.u24|EG2 | C15: EG2 | D15: Averted deaths by age group: under 24 years (including neonatal) | E15: deaths | F15: CPAT_Results (EG2) | H15: egy.air.ada.u24 | L15: =INDEX(CPAT_Results!$A:$AD,MATCH($H15&"_"&$C15,CPAT_Results!$F:$F,0),MATCH(L$5,CPAT_Results!$1:$1,0)) -> 0 | M15: =INDEX(CPAT_Results!$A:$AD,MATCH($H15&"_"&$C15,CPAT_Results!$F:$F,0),MATCH(M$5,CPAT_Results!$1:$1,0)) -> 0 | N15: =INDEX(CPAT_Results!$A:$AD,MATCH($H15&"_"&$C15,CPAT_Results!$F:$F,0),MATCH(N$5,CPAT_Results!$1:$1,0)) -> 0 | O15: =INDEX(CPAT_Results!$A:$AD,MATCH($H15&"_"&$C15,CPAT_Results!$F:$F,0),MATCH(O$5,CPAT_Results!$1:$1,0)) -> 0 | P15: =INDEX(CPAT_Results!$A:$AD,MATCH($H15&"_"&$C15,CPAT_Results!$F:$F,0),MATCH(P$5,CPAT_Results!$1:$1,0)) -> 0 | Q15: =INDEX(CPAT_Results!$A:$AD,MATCH($H15&"_"&$C15,CPAT_Results!$F:$F,0),MATCH(Q$5,CPAT_Results!$1:$1,0)) -> 0 | R15: =INDEX(CPAT_Results!$A:$AD,MATCH($H15&"_"&$C15,CPAT_Results!$F:$F,0),MATCH(R$5,CPAT_Results!$1:$1,0)) -> 0 | S15: =INDEX(CPAT_Results!$A:$AD,MATCH($H15&"_"&$C15,CPAT_Results!$F:$F,0),MATCH(S$5,CPAT_Results!$1:$1,0)) -> 4 | ... AE15: =INDEX(CPAT_Results!$A:$AD,MATCH($H15&"_"&$C15,CPAT_Results!$F:$F,0),MATCH(AE$5,CPAT_Results!$1:$1,0)) -> 0
B16: egy.air.ada.u24|EG3 | C16: EG3 | D16: Averted deaths by age group: under 24 years (including neonatal) | E16: deaths | F16: CPAT_Results (EG3) | H16: egy.air.ada.u24 | L16: =INDEX(CPAT_Results!$A:$AD,MATCH($H16&"_"&$C16,CPAT_Results!$F:$F,0),MATCH(L$5,CPAT_Results!$1:$1,0)) -> 0 | M16: =INDEX(CPAT_Results!$A:$AD,MATCH($H16&"_"&$C16,CPAT_Results!$F:$F,0),MATCH(M$5,CPAT_Results!$1:$1,0)) -> 0 | N16: =INDEX(CPAT_Results!$A:$AD,MATCH($H16&"_"&$C16,CPAT_Results!$F:$F,0),MATCH(N$5,CPAT_Results!$1:$1,0)) -> 0 | O16: =INDEX(CPAT_Results!$A:$AD,MATCH($H16&"_"&$C16,CPAT_Results!$F:$F,0),MATCH(O$5,CPAT_Results!$1:$1,0)) -> 0 | P16: =INDEX(CPAT_Results!$A:$AD,MATCH($H16&"_"&$C16,CPAT_Results!$F:$F,0),MATCH(P$5,CPAT_Results!$1:$1,0)) -> 36 | Q16: =INDEX(CPAT_Results!$A:$AD,MATCH($H16&"_"&$C16,CPAT_Results!$F:$F,0),MATCH(Q$5,CPAT_Results!$1:$1,0)) -> 13 | R16: =INDEX(CPAT_Results!$A:$AD,MATCH($H16&"_"&$C16,CPAT_Results!$F:$F,0),MATCH(R$5,CPAT_Results!$1:$1,0)) -> 17 | S16: =INDEX(CPAT_Results!$A:$AD,MATCH($H16&"_"&$C16,CPAT_Results!$F:$F,0),MATCH(S$5,CPAT_Results!$1:$1,0)) -> 28 | ... AE16: =INDEX(CPAT_Results!$A:$AD,MATCH($H16&"_"&$C16,CPAT_Results!$F:$F,0),MATCH(AE$5,CPAT_Results!$1:$1,0)) -> 0
B17: egy.air.ada.u24|EG4 | C17: EG4 | D17: Averted deaths by age group: under 24 years (including neonatal) | E17: deaths | F17: CPAT_Results (EG4) | H17: egy.air.ada.u24 | L17: =INDEX(CPAT_Results!$A:$AD,MATCH($H17&"_"&$C17,CPAT_Results!$F:$F,0),MATCH(L$5,CPAT_Results!$1:$1,0)) -> 0 | M17: =INDEX(CPAT_Results!$A:$AD,MATCH($H17&"_"&$C17,CPAT_Results!$F:$F,0),MATCH(M$5,CPAT_Results!$1:$1,0)) -> 0 | N17: =INDEX(CPAT_Results!$A:$AD,MATCH($H17&"_"&$C17,CPAT_Results!$F:$F,0),MATCH(N$5,CPAT_Results!$1:$1,0)) -> 0 | O17: =INDEX(CPAT_Results!$A:$AD,MATCH($H17&"_"&$C17,CPAT_Results!$F:$F,0),MATCH(O$5,CPAT_Results!$1:$1,0)) -> 0 | P17: =INDEX(CPAT_Results!$A:$AD,MATCH($H17&"_"&$C17,CPAT_Results!$F:$F,0),MATCH(P$5,CPAT_Results!$1:$1,0)) -> 0 | Q17: =INDEX(CPAT_Results!$A:$AD,MATCH($H17&"_"&$C17,CPAT_Results!$F:$F,0),MATCH(Q$5,CPAT_Results!$1:$1,0)) -> 0 | R17: =INDEX(CPAT_Results!$A:$AD,MATCH($H17&"_"&$C17,CPAT_Results!$F:$F,0),MATCH(R$5,CPAT_Results!$1:$1,0)) -> 0 | S17: =INDEX(CPAT_Results!$A:$AD,MATCH($H17&"_"&$C17,CPAT_Results!$F:$F,0),MATCH(S$5,CPAT_Results!$1:$1,0)) -> 1 | ... AE17: =INDEX(CPAT_Results!$A:$AD,MATCH($H17&"_"&$C17,CPAT_Results!$F:$F,0),MATCH(AE$5,CPAT_Results!$1:$1,0)) -> 0
... B133: egy.mit.wel.air.pct|EG4 | C133: EG4 | D133: Air pollution co-benefits (% GDP) | E133: MtCO2 | F133: CPAT_Results (EG4) | H133: egy.mit.wel.air.pct | L133: =INDEX(CPAT_Results!$A:$AD,MATCH($H133&"_"&$C133,CPAT_Results!$F:$F,0),MATCH(L$5,CPAT_Results!$1:$1,0)) -> 0 | M133: =INDEX(CPAT_Results!$A:$AD,MATCH($H133&"_"&$C133,CPAT_Results!$F:$F,0),MATCH(M$5,CPAT_Results!$1:$1,0)) -> 0 | N133: =INDEX(CPAT_Results!$A:$AD,MATCH($H133&"_"&$C133,CPAT_Results!$F:$F,0),MATCH(N$5,CPAT_Results!$1:$1,0)) -> 0 | O133: =INDEX(CPAT_Results!$A:$AD,MATCH($H133&"_"&$C133,CPAT_Results!$F:$F,0),MATCH(O$5,CPAT_Results!$1:$1,0)) -> 0 | P133: =INDEX(CPAT_Results!$A:$AD,MATCH($H133&"_"&$C133,CPAT_Results!$F:$F,0),MATCH(P$5,CPAT_Results!$1:$1,0)) -> 0 | Q133: =INDEX(CPAT_Results!$A:$AD,MATCH($H133&"_"&$C133,CPAT_Results!$F:$F,0),MATCH(Q$5,CPAT_Results!$1:$1,0)) -> 0 | R133: =INDEX(CPAT_Results!$A:$AD,MATCH($H133&"_"&$C133,CPAT_Results!$F:$F,0),MATCH(R$5,CPAT_Results!$1:$1,0)) -> 0 | S133: =INDEX(CPAT_Results!$A:$AD,MATCH($H133&"_"&$C133,CPAT_Results!$F:$F,0),MATCH(S$5,CPAT_Results!$1:$1,0)) -> 0 | ... AE133: =INDEX(CPAT_Results!$A:$AD,MATCH($H133&"_"&$C133,CPAT_Results!$F:$F,0),MATCH(AE$5,CPAT_Results!$1:$1,0)) -> 0
B135: Note: different data vintage from the CPAT values stored in the kernel (IPPU_Industry section A, CPAT_1_0pre_456 xlsb): 2030 baseline IPPU 85.97 vs 87.67, industrial energy CO2 88.97 vs 75.38 MtCO2. Task M uses deltas (policy - baseline) of a run only; levels of the two sources are never mixed.

Sheet CPAT_Results
A1: Include | B1: Country | C1: Scenario | D1: CPATIndicator | E1: CPATCode | F1: MTCode | G1: Tab | H1: Variable | I1: Unit | J1: SubScenario | K1: =CPATStartYear -> 2022 | L1: =K1+1 -> 2023 | M1: =L1+1 -> 2024 | N1: =M1+1 -> 2025 | O1: =N1+1 -> 2026 | P1: =O1+1 -> 2027 | Q1: =P1+1 -> 2028 | R1: =Q1+1 -> 2029 | S1: =R1+1 -> 2030 | ... AD1: =AC1+1 -> 2041
B2: Egypt | C2: EG1 | D2: Emissions coverage | E2: egy.mit.co2cov.2 | F2: egy.mit.co2cov.2_EG1 | G2: mit | H2: co2cov | I2: pc | J2: 2 | K2: 0 | L2: 0 | M2: 0 | N2: 0 | O2: 0.98816 | P2: 0.98744 | Q2: 0.98752 | R2: 0.98751 | S2: 0.98761 | T2: 0.9877 | U2: 0.98781 | V2: 0.98793 | W2: 0.98805 | X2: 0.98819 | Y2: 0.98832 | Z2: 0.98847 | AA2: 0.98863 | AB2: 0.9888 | AC2: 0.989 | AD2: 0.98917
B3: Egypt | C3: EG1 | D3: Carbon tax trajectory | E3: egy.mit.cptraj.2 | F3: egy.mit.cptraj.2_EG1 | G3: mit | H3: cptraj | I3: usdtco2 | J3: 2 | K3: 0 | L3: 0 | M3: 0 | N3: 0 | O3: 20 | P3: 20 | Q3: 20 | R3: 20 | S3: 20 | T3: 20 | U3: 20 | V3: 20 | W3: 20 | X3: 20 | Y3: 20 | Z3: 20 | AA3: 20 | AB3: 20 | AC3: 20 | AD3: 20
B4: Egypt | C4: EG1 | D4: Effective carbon tax trajectory | E4: egy.mit.eff.cptraj.2 | F4: egy.mit.eff.cptraj.2_EG1 | G4: mit | H4: effcptraj | I4: usdtco2 | J4: 2 | K4: 0 | L4: 0 | M4: 0 | N4: 0 | O4: 19.763 | P4: 19.749 | Q4: 19.75 | R4: 19.75 | S4: 19.752 | T4: 19.754 | U4: 19.756 | V4: 19.759 | W4: 19.761 | X4: 19.764 | Y4: 19.766 | Z4: 19.769 | AA4: 19.773 | AB4: 19.776 | AC4: 19.78 | AD4: 19.783
B5: Egypt | C5: EG1 | D5: ETS Trajector\y | E5: egy.mit.etstraj.2 | F5: egy.mit.etstraj.2_EG1 | G5: mit | H5: etstraj | I5: usdtco2 | J5: 2 | K5: 0 | L5: 0 | M5: 0 | N5: 0 | O5: 0 | P5: 0 | Q5: 0 | R5: 0 | S5: 0 | T5: 0 | U5: 0 | V5: 0 | W5: 0 | X5: 0 | Y5: 0 | Z5: 0 | AA5: 0 | AB5: 0 | AC5: 0 | AD5: 0
B6: Egypt | C6: EG1 | D6: Emissions covered by sector: power sector | E6: egy.mit.co2cov.pow.cont.2 | F6: egy.mit.co2cov.pow.cont.2_EG1 | G6: mit | H6: co2cov | I6: pc | J6: 2 | K6: 0 | L6: 0 | M6: 0 | N6: 0 | O6: 0.41588 | P6: 0.37477 | Q6: 0.37159 | R6: 0.36198 | S6: 0.35448 | T6: 0.34343 | U6: 0.33368 | V6: 0.32426 | W6: 0.31631 | X6: 0.30948 | Y6: 0.30392 | Z6: 0.29978 | AA6: 0.29711 | AB6: 0.29604 | AC6: 0.29677 | AD6: 0.29717
B7: Egypt | C7: EG1 | D7: Emissions covered, transport sector | E7: egy.mit.co2cov.tra.cont.2 | F7: egy.mit.co2cov.tra.cont.2_EG1 | G7: mit | H7: co2cov | I7: pc | J7: 2 | K7: 0 | L7: 0 | M7: 0 | N7: 0 | O7: 0.20507 | P7: 0.22498 | Q7: 0.23287 | R7: 0.24405 | S7: 0.2569 | T7: 0.27288 | U7: 0.28846 | V7: 0.30382 | W7: 0.31817 | X7: 0.33153 | Y7: 0.34377 | Z7: 0.35488 | AA7: 0.36487 | AB7: 0.37363 | AC7: 0.38103 | AD7: 0.38809
B8: Egypt | C8: EG1 | D8: Emissions covered, residential sector | E8: egy.mit.co2cov.res.cont.2 | F8: egy.mit.co2cov.res.cont.2_EG1 | G8: mit | H8: co2cov | I8: pc | J8: 2 | K8: 0 | L8: 0 | M8: 0 | N8: 0 | O8: 0.0811 | P8: 0.08261 | Q8: 0.07978 | R8: 0.07799 | S8: 0.07586 | T8: 0.07395 | U8: 0.0719 | V8: 0.06986 | W8: 0.06776 | X8: 0.06566 | Y8: 0.06356 | Z8: 0.0615 | AA8: 0.05942 | AB8: 0.05732 | AC8: 0.05519 | AD8: 0.05322
B9: Egypt | C9: EG1 | D9: Emissions covered, industry | E9: egy.mit.co2cov.ind.cont.2 | F9: egy.mit.co2cov.ind.cont.2_EG1 | G9: mit | H9: co2cov | I9: pc | J9: 2 | K9: 0 | L9: 0 | M9: 0 | N9: 0 | O9: 0.28621 | P9: 0.30519 | Q9: 0.3034 | R9: 0.30359 | S9: 0.30046 | T9: 0.29754 | U9: 0.29387 | V9: 0.29008 | W9: 0.28591 | X9: 0.28161 | Y9: 0.27716 | Z9: 0.27239 | AA9: 0.26731 | AB9: 0.2619 | AC9: 0.25609 | AD9: 0.25077
B10: Egypt | C10: EG1 | D10: Emissions covered, other energy use | E10: egy.mit.co2cov.oth.cont.2 | F10: egy.mit.co2cov.oth.cont.2_EG1 | G10: mit | H10: co2cov | I10: pc | J10: 2 | K10: 0 | L10: 0 | M10: 0 | N10: 0 | O10: 0 | P10: 0 | Q10: 0 | R10: 0 | S10: 0 | T10: 0 | U10: 0 | V10: 0 | W10: 0 | X10: 0 | Y10: 0 | Z10: 0 | AA10: 0 | AB10: 0 | AC10: 0 | AD10: 0
B11: Egypt | C11: EG1 | D11: Effect on GDP: Baseline GDP growth | E11: egy.mit.gdp.pre.pct.2 | F11: egy.mit.gdp.pre.pct.2_EG1 | G11: mit | H11: gdp | I11: pc | J11: 2 | K11: 0.06651 | L11: 0.0376 | M11: 0.02399 | N11: 0.04392 | O11: 0.0424 | P11: 0.04829 | Q11: 0.05535 | R11: 0.05227 | S11: 0.04842 | T11: 0.04789 | U11: 0.04736 | V11: 0.04682 | W11: 0.04629 | X11: 0.04576 | Y11: 0.04523 | Z11: 0.0447 | AA11: 0.04417 | AB11: 0.04364 | AC11: 0.0431 | AD11: 0.04257
B12: Egypt | C12: EG1 | D12: Effect on GDP: - Carbon tax | E12: egy.mit.gdp.exc.pct.2 | F12: egy.mit.gdp.exc.pct.2_EG1 | G12: mit | H12: gdp | I12: pc | J12: 2 | K12: 0 | L12: 0 | M12: 0 | N12: 0 | O12: -0.00455 | P12: -0.00726 | Q12: -0.00692 | R12: -0.00701 | S12: -0.00637 | T12: -0.00572 | U12: -0.0055 | V12: -0.00507 | W12: -0.00456 | X12: -0.00415 | Y12: -0.00396 | Z12: -0.00402 | AA12: -0.00409 | AB12: -0.00415 | AC12: -0.00403 | AD12: -0.00384
B13: Egypt | C13: EG1 | D13: Effect on GDP: Personal income tax | E13: egy.mit.gdp.pit.pct.2 | F13: egy.mit.gdp.pit.pct.2_EG1 | G13: mit | H13: gdp | I13: pc | J13: 2 | K13: 0 | L13: 0 | M13: 0 | N13: 0 | O13: 0.00092 | P13: 0.00107 | Q13: 0.00103 | R13: 0.00092 | S13: 0.00088 | T13: 0.00091 | U13: 0.00091 | V13: 0.00098 | W13: 0.00098 | X13: 0.00096 | Y13: 0.00095 | Z13: 0.00096 | AA13: 0.00099 | AB13: 0.00101 | AC13: 0.001 | AD13: 0.00098
... B21: Egypt | C21: EG1 | D21: Total revenues, % of GDP (policy) | E21: egy.mit.rev.new.pct.2 | F21: egy.mit.rev.new.pct.2_EG1 | G21: mit | H21: rev | I21: pc | J21: 2 | K21: -0.05845 | L21: -0.04678 | M21: -0.06658 | N21: -0.06182 | O21: -0.0499 | P21: -0.04387 | Q21: -0.04215 | R21: -0.04043 | S21: -0.03916 | T21: -0.03754 | U21: -0.03619 | V21: -0.03474 | W21: -0.03327 | X21: -0.03172 | Y21: -0.03002 | Z21: -0.02825 | AA21: -0.02636 | AB21: -0.02438 | AC21: -0.02263 | AD21: -0.02263
B22: Egypt | C22: EG1 | D22: Base erosion, % of GDP | E22: egy.mit.ers | F22: egy.mit.ers_EG1 | J22: 2 | K22: 0 | L22: 2.844543e-05 | M22: 2.4134132e-05 | N22: 2.2817555e-05 | O22: 0.0053636661 | P22: 0.0054115216 | Q22: 0.0047133669 | R22: 0.0045573619 | S22: 0.0044597548 | T22: 0.004534663 | U22: 0.0045964129 | V22: 0.0046718475 | W22: 0.0047194276 | X22: 0.0047563481 | Y22: 0.0047806517 | Z22: 0.0047817783 | AA22: 0.0047717964 | AB22: 0.0047494631 | AC22: 0.0047072887 | AD22: 0.0046640048
B23: Egypt | C23: EG1 | D23: Revenues - Carbon tax, % of GDP | E23: egy.mit.rcp | F23: egy.mit.rcp_EG1 | J23: 2 | K23: 0 | L23: 0 | M23: 0 | N23: 0 | O23: 0.0070282371 | P23: 0.0066914376 | Q23: 0.006691428 | R23: 0.0066205231 | S23: 0.0065941239 | T23: 0.0065572299 | U23: 0.0065423109 | V23: 0.0065358456 | W23: 0.0065449547 | X23: 0.0065665537 | Y23: 0.0065990759 | Z23: 0.0066460374 | AA23: 0.0067053353 | AB23: 0.0067782859 | AC23: 0.0068676131 | AD23: 0.0069502042
B24: Egypt | C24: EG1 | D24: Power sector carbon tax revenues | E24: egy.mit.rcp.pow | F24: egy.mit.rcp.pow_EG1 | J24: 2 | K24: 0 | L24: 0 | M24: 0 | N24: 0 | O24: 0.0029270922 | P24: 0.0025119838 | Q24: 0.0024906595 | R24: 0.0024005138 | S24: 0.002341282 | T24: 0.0022554069 | U24: 0.0021862333 | V24: 0.0021222911 | W24: 0.002073028 | X24: 0.0020347992 | Y24: 0.0020079946 | Z24: 0.0019946306 | AA24: 0.0019943886 | AB24: 0.0020086829 | AC24: 0.0020400658 | AD24: 0.0020672587
B25: Egypt | C25: EG1 | D25: Transport sector carbon tax revenues | E25: egy.mit.rcp.trs | F25: egy.mit.rcp.trs_EG1 | J25: 2 | K25: 0 | L25: 0 | M25: 0 | N25: 0 | O25: 0.0015159442 | P25: 0.0015801373 | Q25: 0.0016324432 | R25: 0.0016895292 | S25: 0.0017672912 | T25: 0.0018621026 | U25: 0.0019595348 | V25: 0.0020577283 | W25: 0.0021541125 | X25: 0.0022485125 | Y25: 0.0023399117 | Z25: 0.0024298037 | AA25: 0.0025177046 | AB25: 0.0026036397 | AC25: 0.0026877358 | AD25: 0.0027682159
B26: Egypt | C26: EG1 | D26: Buildings sector carbon tax revenues | E26: egy.mit.rcp.bld | F26: egy.mit.rcp.bld_EG1 | J26: 2 | K26: 0 | L26: 0 | M26: 0 | N26: 0 | O26: 0.00057080737 | P26: 0.00055370628 | Q26: 0.00053472521 | R26: 0.00051719763 | S26: 0.00050105953 | T26: 0.00048566665 | U26: 0.00047108621 | V26: 0.00045721944 | W26: 0.00044407029 | X26: 0.00043170054 | Y26: 0.00041997014 | Z26: 0.00040920311 | AA26: 0.00039886654 | AB26: 0.00038893228 | AC26: 0.0003793921 | AD26: 0.00037022679
B27: Egypt | C27: EG1 | D27: Industry sector carbon tax revenues | E27: egy.mit.rcp.ind | F27: egy.mit.rcp.ind_EG1 | J27: 2 | K27: 0 | L27: 0 | M27: 0 | N27: 0 | O27: 0.0020143933 | P27: 0.0020456102 | Q27: 0.0020336001 | R27: 0.0020132825 | S27: 0.0019844911 | T27: 0.0019540536 | U27: 0.0019254565 | V27: 0.0018986068 | W27: 0.0018737439 | X27: 0.0018515414 | Y27: 0.0018311995 | Z27: 0.0018123999 | AA27: 0.0017943756 | AB27: 0.0017770311 | AC27: 0.0017604194 | AD27: 0.0017445028
B28: Egypt | C28: EG1 | D28: Baseline ln(GDP per capita) | E28: egy.mit.ln.gdppc | F28: egy.mit.ln.gdppc_EG1 | G28: mit | H28: lngdppc | I28: unitless | J28: 1 | K28: 6.3 | L28: 6.34 | M28: 6.37 | N28: 6.41 | O28: 6.45 | P28: 6.5 | Q28: 6.55 | R28: 6.6 | S28: 6.65 | T28: 6.7 | U28: 6.74 | V28: 6.79 | W28: 6.83 | X28: 6.88 | Y28: 6.92 | Z28: 6.97 | AA28: 7.01 | AB28: 7.05 | AC28: 7.09 | AD28: 7.14
B29: Egypt | C29: EG1 | D29: Baseline GDP | E29: egy.mit.gdp.pre.lvl.1 | F29: egy.mit.gdp.pre.lvl.1_EG1 | G29: mit | H29: gdp | I29: usdbn | J29: 1 | K29: 546.97092 | L29: 567.53857 | M29: 581.15269 | N29: 606.67916 | O29: 632.40058 | P29: 662.94058 | Q29: 699.63644 | R29: 736.20368 | S29: 771.84975 | T29: 808.8116 | U29: 847.11364 | V29: 886.77935 | W29: 927.83114 | X29: 970.29029 | Y29: 1014.1768 | Z29: 1059.5094 | AA29: 1106.3053 | AB29: 1154.5801 | AC29: 1204.3479 | AD29: 1255.6209
B30: Egypt | C30: EG1 | D30: Post-policy GDP | E30: egy.mit.gdp.pst.lvl.2 | F30: egy.mit.gdp.pst.lvl.2_EG1 | G30: mit | H30: gdp | I30: usdbn | J30: 2 | K30: 546.97092 | L30: 567.53857 | M30: 581.15269 | N30: 606.67916 | O30: 632.40064 | P30: 663.30583 | Q30: 699.12177 | R30: 735.89129 | S30: 771.11883 | T30: 808.62015 | U30: 847.83187 | V30: 888.25231 | W30: 930.31798 | X30: 974.4035 | Y30: 1019.5241 | Z30: 1065.9639 | AA30: 1113.3315 | AB30: 1162.1247 | AC30: 1212.4927 | AD30: 1264.3711
B31: Egypt | C31: EG1 | D31: Population | E31: egy.mit.pop.mn | F31: egy.mit.pop.mn_EG1 | G31: mit | H31: pop | I31: mn | J31: 1 | K31: 103.6 | L31: 105.2 | M31: 106.6 | N31: 107.9 | O31: 110.058 | P31: 112.25916 | Q31: 114.50434 | R31: 116.79443 | S31: 120.29826 | T31: 125.11019 | U31: 130.1146 | V31: 135.31918 | W31: 140.73195 | X31: 146.36123 | Y31: 152.21568 | Z31: 158.3043 | AA31: 164.63647 | AB31: 171.22193 | AC31: 178.07081 | AD31: 185.19364
B32: Egypt | C32: EG1 | D32: Total GHG emissions, exc. LULUCF (baseline) | E32: egy.mit.ghg.tot.exc.1 | F32: egy.mit.ghg.tot.exc.1_EG1 | G32: mit | H32: emis | I32: mtco2e | J32: 1 | K32: 400.912 | L32: 412.105 | M32: 450.924 | N32: 467.515 | O32: 473.648 | P32: 484.763 | Q32: 501.104 | R32: 518.139 | S32: 535.623 | T32: 555.043 | U32: 576.999 | V32: 601.287 | W32: 626.831 | X32: 653.747 | Y32: 682.01 | Z32: 711.827 | AA32: 743.304 | AB32: 776.605 | AC32: 811.925 | AD32: 848.157
B33: Egypt | C33: EG1 | D33: Total GHG emissions, inc. LULUCF (baseline) | E33: egy.mit.ghg.tot.inc.1 | F33: egy.mit.ghg.tot.inc.1_EG1 | G33: mit | H33: emis | I33: mtco2e | J33: 1 | K33: 400.912 | L33: 412.105 | M33: 450.924 | N33: 467.515 | O33: 473.648 | P33: 484.763 | Q33: 501.104 | R33: 518.139 | S33: 535.623 | T33: 555.043 | U33: 576.999 | V33: 601.287 | W33: 626.831 | X33: 653.747 | Y33: 682.01 | Z33: 711.827 | AA33: 743.304 | AB33: 776.605 | AC33: 811.925 | AD33: 848.157
B34: Egypt | C34: EG1 | D34: Energy-related GHG emissions (baseline) | E34: egy.mit.ghg.enr.tot.1 | F34: egy.mit.ghg.enr.tot.1_EG1 | G34: mit | H34: emis | I34: mtco2e | J34: 1 | K34: 213.939 | L34: 210.133 | M34: 236.548 | N34: 245.532 | O34: 247.516 | P34: 253.847 | Q34: 264.069 | R34: 274.969 | S34: 286.428 | T34: 299.23 | U34: 312.897 | V34: 327.613 | W34: 343.276 | X34: 359.992 | Y34: 377.725 | Z34: 396.674 | AA34: 416.933 | AB34: 438.654 | AC34: 462.022 | AD34: 485.918
B35: Egypt | C35: EG1 | D35: Industrial processes GHG emissions (baseline) | E35: egy.mit.ghg.ipr.tot.1 | F35: egy.mit.ghg.ipr.tot.1_EG1 | G35: mit | H35: emis | I35: mtco2e | J35: 1 | K35: 52.2 | L35: 56.903 | M35: 67.059 | N35: 72.5 | O35: 74.569 | P35: 76.99 | Q35: 79.929 | R35: 82.77 | S35: 85.454 | T35: 88.177 | U35: 90.929 | V35: 93.73 | W35: 96.58 | X35: 99.478 | Y35: 102.424 | Z35: 105.418 | AA35: 108.459 | AB35: 111.547 | AC35: 114.681 | AD35: 117.86
B36: Egypt | C36: EG1 | D36: Agriculture, GHG emissions (baseline) | E36: egy.mit.ghg.agr.tot.1 | F36: egy.mit.ghg.agr.tot.1_EG1 | G36: mit | H36: emis | I36: mtco2e | J36: 1 | K36: 41.563 | L36: 43.505 | M36: 44.234 | N36: 44.885 | O36: 45.614 | P36: 46.396 | Q36: 47.424 | R36: 48.524 | S36: 49.628 | T36: 50.838 | U36: 52.455 | V36: 54.397 | W36: 56.407 | X36: 58.486 | Y36: 60.638 | Z36: 62.864 | AA36: 65.166 | AB36: 67.548 | AC36: 70.012 | AD36: 72.56
B37: Egypt | C37: EG1 | D37: Waste GHG emissions (baseline) | E37: egy.mit.ghg.wst.tot.1 | F37: egy.mit.ghg.wst.tot.1_EG1 | G37: mit | H37: emis | I37: mtco2e | J37: 1 | K37: 93.209 | L37: 101.564 | M37: 103.083 | N37: 104.597 | O37: 105.948 | P37: 107.531 | Q37: 109.682 | R37: 111.875 | S37: 114.113 | T37: 116.798 | U37: 120.718 | V37: 125.546 | W37: 130.568 | X37: 135.791 | Y37: 141.223 | Z37: 146.872 | AA37: 152.746 | AB37: 158.856 | AC37: 165.21 | AD37: 171.819
B38: Egypt | C38: EG1 | D38: LULUCF, GHG emissions (baseline) | E38: egy.mit.ghg.lucf.tot.1 | F38: egy.mit.ghg.lucf.tot.1_EG1 | G38: mit | H38: emis | I38: mtco2e | J38: 1 | K38: 0 | L38: 0 | M38: 0 | N38: 0 | O38: 0 | P38: 0 | Q38: 0 | R38: 0 | S38: 0 | T38: 0 | U38: 0 | V38: 0 | W38: 0 | X38: 0 | Y38: 0 | Z38: 0 | AA38: 0 | AB38: 0 | AC38: 0 | AD38: 0
B39: Egypt | C39: EG1 | D39: Total CO2 emissions - baseline | E39: egy.mit.co2.tot.1 | F39: egy.mit.co2.tot.1_EG1 | G39: mit | H39: emis | I39: mtco2 | J39: 1 | K39: 307.637 | L39: 315.625 | M39: 350.605 | N39: 364.723 | O39: 369.176 | P39: 378.155 | Q39: 391.945 | R39: 406.364 | S39: 421.246 | T39: 437.519 | U39: 455.457 | V39: 475.305 | W39: 496.254 | X39: 518.414 | Y39: 541.754 | Z39: 566.478 | AA39: 592.682 | AB39: 620.525 | AC39: 650.194 | AD39: 680.584
... B73: Egypt | C73: EG1 | D73: Energy related CO2 emissions - Other (policy) | E73: egy.mit.co2.oth.2 | F73: egy.mit.co2.oth.2_EG1 | G73: mit | H73: emis | I73: mtco2 | J73: 2 | K73: 0.294 | L73: 0.268 | M73: 0.317 | N73: 0.417 | O73: 0.316 | P73: 0.376 | Q73: 0.398 | R73: 0.409 | S73: 0.411 | T73: 0.41 | U73: 0.409 | V73: 0.408 | W73: 0.406 | X73: 0.405 | Y73: 0.404 | Z73: 0.403 | AA73: 0.401 | AB73: 0.4 | AC73: 0.399 | AD73: 0.398
B74: Egypt | C74: EG1 | D74: Change in CO2 emissions - (policy vs. baseline) | E74: egy.mit.co2.tot.red.pct | F74: egy.mit.co2.tot.red.pct_EG1 | G74: mit | H74: co2red | I74: mtco2 | J74: t | K74: 0 | L74: 0 | M74: 0 | N74: 0 | O74: -0.086 | P74: -0.098 | Q74: -0.089 | R74: -0.088 | S74: -0.087 | T74: -0.089 | U74: -0.09 | V74: -0.091 | W74: -0.091 | X74: -0.09 | Y74: -0.089 | Z74: -0.088 | AA74: -0.086 | AB74: -0.084 | AC74: -0.082 | AD74: -0.079
B75: Egypt | C75: EG1 | D75: Total GHG emissions, excl LULUCF - baseline | E75: egy.mit.ghg.tot.exc.fuel.1 | F75: egy.mit.ghg.tot.exc.fuel.1_EG1 | G75: mit | H75: emis | I75: mtco2e | J75: 1 | K75: 400.912 | L75: 412.105 | M75: 450.924 | N75: 467.515 | O75: 473.648 | P75: 484.763 | Q75: 501.104 | R75: 518.139 | S75: 535.623 | T75: 555.043 | U75: 576.999 | V75: 601.287 | W75: 626.831 | X75: 653.747 | Y75: 682.01 | Z75: 711.827 | AA75: 743.304 | AB75: 776.605 | AC75: 811.925 | AD75: 848.157
B76: Egypt | C76: EG1 | D76: Carbon dioxide (CO2) - baseline | E76: egy.mit.co2.tot.1 | F76: egy.mit.co2.tot.1_EG1 | G76: mit | H76: emis | I76: mtco2 | J76: 1 | K76: 307.637 | L76: 315.625 | M76: 350.605 | N76: 364.723 | O76: 369.176 | P76: 378.155 | Q76: 391.945 | R76: 406.364 | S76: 421.246 | T76: 437.519 | U76: 455.457 | V76: 475.305 | W76: 496.254 | X76: 518.414 | Y76: 541.754 | Z76: 566.478 | AA76: 592.682 | AB76: 620.525 | AC76: 650.194 | AD76: 680.584
B77: Egypt | C77: EG1 | D77: Methane (CH4) - baseline | E77: egy.mit.ch4.tot.1 | F77: egy.mit.ch4.tot.1_EG1 | G77: mit | H77: emis | I77: mtco2e | J77: 1 | K77: 53.088 | L77: 55.678 | M77: 56.592 | N77: 57.34 | O77: 58.083 | P77: 59.234 | Q77: 60.428 | R77: 61.667 | S77: 62.922 | T77: 64.748 | U77: 67.185 | V77: 69.717 | W77: 72.347 | X77: 75.078 | Y77: 77.915 | Z77: 80.859 | AA77: 83.917 | AB77: 87.093 | AC77: 90.39 | AD77: 93.815
B78: Egypt | C78: EG1 | D78: Nitrous oxide (N2O) - baseline | E78: egy.mit.nox.tot.1 | F78: egy.mit.nox.tot.1_EG1 | G78: mit | H78: emis | I78: mtco2e | J78: 1 | K78: 28.488 | L78: 28.577 | M78: 29.32 | N78: 29.875 | O78: 30.368 | P78: 30.834 | Q78: 31.558 | R78: 32.325 | S78: 33.096 | T78: 33.832 | U78: 34.822 | V78: 36.127 | W78: 37.48 | X78: 38.883 | Y78: 40.336 | Z78: 41.842 | AA78: 43.404 | AB78: 45.023 | AC78: 46.703 | AD78: 48.438
B79: Egypt | C79: EG1 | D79: F-gases (PFCs, HFCs, SF6, NF3) - baseline | E79: egy.mit.fga.tot.1 | F79: egy.mit.fga.tot.1_EG1 | G79: mit | H79: emis | I79: mtco2e | J79: 1 | K79: 11.699 | L79: 12.225 | M79: 14.407 | N79: 15.576 | O79: 16.02 | P79: 16.54 | Q79: 17.172 | R79: 17.782 | S79: 18.359 | T79: 18.944 | U79: 19.535 | V79: 20.137 | W79: 20.749 | X79: 21.372 | Y79: 22.005 | Z79: 22.648 | AA79: 23.301 | AB79: 23.965 | AC79: 24.638 | AD79: 25.321
B80: Egypt | C80: EG1 | D80: Total GHG emissions, excl LULUCF - policy | E80: egy.mit.ghg.tot.exc.fuel.2 | F80: egy.mit.ghg.tot.exc.fuel.2_EG1 | G80: mit | H80: emis | I80: mtco2e | J80: 2 | K80: 400.912 | L80: 411.973 | M80: 450.796 | N80: 467.39 | O80: 438.859 | P80: 444.819 | Q80: 463.596 | R80: 479.444 | S80: 496.028 | T80: 513.03 | U80: 532.997 | V80: 555.064 | W80: 578.658 | X80: 603.788 | Y80: 630.452 | Z80: 658.918 | AA80: 689.165 | AB80: 721.379 | AC80: 755.868 | AD80: 791.334
B81: Egypt | C81: EG1 | D81: Carbon dioxide (CO2) - policy | E81: egy.mit.co2.tot.2 | F81: egy.mit.co2.tot.2_EG1 | G81: mit | H81: emis | I81: mtco2 | J81: 2 | K81: 307.637 | L81: 315.493 | M81: 350.477 | N81: 364.598 | O81: 337.551 | P81: 341.053 | Q81: 357.197 | R81: 370.437 | S81: 384.488 | T81: 398.444 | U81: 414.47 | V81: 432.162 | W81: 451.21 | X81: 471.606 | Y81: 493.346 | Z81: 516.702 | AA81: 541.651 | AB81: 568.378 | AC81: 597.177 | AD81: 626.75
B82: Egypt | C82: EG1 | D82: Methane (CH4) - policy | E82: egy.mit.ch4.tot.2 | F82: egy.mit.ch4.tot.2_EG1 | G82: mit | H82: emis | I82: mtco2e | J82: 2 | K82: 53.088 | L82: 55.678 | M82: 56.592 | N82: 57.34 | O82: 58.042 | P82: 59.191 | Q82: 60.39 | R82: 61.624 | S82: 62.88 | T82: 64.702 | U82: 67.139 | V82: 69.674 | W82: 72.306 | X82: 75.04 | Y82: 77.882 | Z82: 80.831 | AA82: 83.893 | AB82: 87.071 | AC82: 90.371 | AD82: 93.798
B83: Egypt | C83: EG1 | D83: Nitrous oxide (N2O) - policy | E83: egy.mit.nox.tot.2 | F83: egy.mit.nox.tot.2_EG1 | G83: mit | H83: emis | I83: mtco2e | J83: 2 | K83: 28.488 | L83: 28.577 | M83: 29.321 | N83: 29.876 | O83: 30.038 | P83: 30.493 | Q83: 31.235 | R83: 31.991 | S83: 32.755 | T83: 33.472 | U83: 34.45 | V83: 35.746 | W83: 37.09 | X83: 38.487 | Y83: 39.939 | Z83: 41.445 | AA83: 43.006 | AB83: 44.624 | AC83: 46.303 | AD83: 48.039
B84: Egypt | C84: EG1 | D84: F-gases (PFCs, HFCs, SF6, NF3) - policy | E84: egy.mit.fga.tot.2 | F84: egy.mit.fga.tot.2_EG1 | G84: mit | H84: emis | I84: mtco2e | J84: 2 | K84: 11.699 | L84: 12.225 | M84: 14.407 | N84: 15.576 | O84: 13.228 | P84: 14.082 | Q84: 14.774 | R84: 15.391 | S84: 15.906 | T84: 16.412 | U84: 16.937 | V84: 17.483 | W84: 18.053 | X84: 18.655 | Y84: 19.285 | Z84: 19.94 | AA84: 20.614 | AB84: 21.305 | AC84: 22.016 | AD84: 22.746
B85: Egypt | C85: EG1 | D85: Total methane, incl. LULUCF (baseline) | E85: egy.mit.ghg.tot.inc.ch4.1 | F85: egy.mit.ghg.tot.inc.ch4.1_EG1 | G85: mit | H85: emis | I85: mtco2e | J85: 1 | K85: 53.088 | L85: 55.678 | M85: 56.592 | N85: 57.34 | O85: 58.083 | P85: 59.234 | Q85: 60.428 | R85: 61.667 | S85: 62.922 | T85: 64.748 | U85: 67.185 | V85: 69.717 | W85: 72.347 | X85: 75.078 | Y85: 77.915 | Z85: 80.859 | AA85: 83.917 | AB85: 87.093 | AC85: 90.39 | AD85: 93.815
B86: Egypt | C86: EG1 | D86: Total methane, excl. LULUCF (baseline) | E86: egy.mit.ghg.tot.exc.ch4.1 | F86: egy.mit.ghg.tot.exc.ch4.1_EG1 | G86: mit | H86: emis | I86: mtco2e | J86: 1 | K86: 53.088 | L86: 55.678 | M86: 56.592 | N86: 57.34 | O86: 58.083 | P86: 59.234 | Q86: 60.428 | R86: 61.667 | S86: 62.922 | T86: 64.748 | U86: 67.185 | V86: 69.717 | W86: 72.347 | X86: 75.078 | Y86: 77.915 | Z86: 80.859 | AA86: 83.917 | AB86: 87.093 | AC86: 90.39 | AD86: 93.815
... B105: Egypt | C105: EG1 | D105: Change in GHG emissions exc LULUCF - (policy vs. baseline) | E105: egy.mit.ghg.tot.inc.red.pct | F105: egy.mit.ghg.tot.inc.red.pct_EG1 | G105: mit | H105: ghgchange | I105: pc | J105: 2 | K105: 0 | L105: 0 | M105: 0 | N105: 0 | O105: -0.073 | P105: -0.082 | Q105: -0.075 | R105: -0.075 | S105: -0.074 | T105: -0.076 | U105: -0.076 | V105: -0.077 | W105: -0.077 | X105: -0.076 | Y105: -0.076 | Z105: -0.074 | AA105: -0.073 | AB105: -0.071 | AC105: -0.069 | AD105: -0.067
B106: Egypt | C106: EG1 | D106: NDC option | E106: egy.mit.ndc.option | F106: egy.mit.ndc.option_EG1 | G106: mit | H106: ndcoption | I106: text | J106: 1 | K106: Latest*
B107: Egypt | D107: NDC target year | E107: egy.mit.ndc.targetyear | F107: egy.mit.ndc.targetyear_EG1 | G107: mit | H107: ndctargetyear | I107: text | J107: 1 | K107: 1
B108: Egypt | C108: EG1 | D108: NDC, description - long | E108: egy.mit.ndc.desc.lng | F108: egy.mit.ndc.desc.lng_EG1 | G108: mit | H108: ndcdesclong | I108: text | J108: 1 | K108: #VALUE!
B109: Egypt | C109: EG1 | D109: NDC, description - short | E109: egy.mit.ndc.desc.sht | F109: egy.mit.ndc.desc.sht_EG1 | G109: mit | H109: ndcdescshort | I109: text | J109: 1 | K109: #VALUE!
B110: Egypt | C110: EG1 | D110: NDC target: unconditional (2018=100) | E110: egy.mit.undc.index | F110: egy.mit.undc.index_EG1 | G110: mit | H110: ndcunct | I110: index | J110: 1 | K110: #VALUE! | L110: #VALUE! | M110: #VALUE! | N110: #VALUE! | O110: #VALUE! | P110: #VALUE! | Q110: #VALUE! | R110: #VALUE! | S110: #VALUE! | T110: #VALUE! | U110: #VALUE! | V110: #VALUE! | W110: #VALUE! | X110: #VALUE! | Y110: #VALUE! | Z110: #VALUE! | AA110: #VALUE! | AB110: #VALUE! | AC110: #VALUE! | AD110: #VALUE!
B111: Egypt | C111: EG1 | D111: NDC target: conditional (2018=100) | E111: egy.mit.cndc.index | F111: egy.mit.cndc.index_EG1 | G111: mit | H111: ndccont | I111: index | J111: 1 | K111: N/A | L111: N/A | M111: N/A | N111: N/A | O111: N/A | P111: N/A | Q111: N/A | R111: N/A | S111: N/A | T111: N/A | U111: N/A | V111: N/A | W111: N/A | X111: N/A | Y111: N/A | Z111: N/A | AA111: N/A | AB111: N/A | AC111: N/A | AD111: N/A
B112: Egypt | C112: EG1 | D112: Unconditional NDC, target level (mtCO2e) | E112: egy.mit.undc.trg.ton | F112: egy.mit.undc.trg.ton_EG1 | G112: mit | H112: ndcunclevel | I112: ton | J112: 1 | K112: #VALUE! | L112: #VALUE! | M112: #VALUE! | N112: #VALUE! | O112: #VALUE! | P112: #VALUE! | Q112: #VALUE! | R112: #VALUE! | S112: #VALUE! | T112: #VALUE! | U112: #VALUE! | V112: #VALUE! | W112: #VALUE! | X112: #VALUE! | Y112: #VALUE! | Z112: #VALUE! | AA112: #VALUE! | AB112: #VALUE! | AC112: #VALUE! | AD112: #VALUE!
B113: Egypt | C113: EG1 | D113: Conditional NDC, target level (mtCO2e) | E113: egy.mit.cndc.trg.ton | F113: egy.mit.cndc.trg.ton_EG1 | G113: mit | H113: ndcconlevel | I113: ton | J113: 1 | K113: N/A | L113: N/A | M113: N/A | N113: N/A | O113: N/A | P113: N/A | Q113: N/A | R113: N/A | S113: N/A | T113: N/A | U113: N/A | V113: N/A | W113: N/A | X113: N/A | Y113: N/A | Z113: N/A | AA113: N/A | AB113: N/A | AC113: N/A | AD113: N/A
B114: Egypt | C114: EG1 | D114: Unconditional NDC, reduction against the modelled baseline (% by 2030) | E114: egy.mit.undc.2030.pct | F114: egy.mit.undc.2030.pct_EG1 | G114: mit | H114: undc | I114: pct | J114: 1 | K114: #VALUE!
B115: Egypt | C115: EG1 | D115: Conditional NDC, reduction against the modelled baseline (% by 2030) | E115: egy.mit.cndc.2030.pct | F115: egy.mit.cndc.2030.pct_EG1 | G115: mit | H115: cndc | I115: pct | J115: 1 | K115: #VALUE!
B116: Egypt | C116: EG1 | D116: Average NDC, reduction against the modelled baseline (% by 2030) | E116: egy.mit.andc.2030.pct | F116: egy.mit.andc.2030.pct_EG1 | G116: mit | H116: andc | I116: pct | J116: 1 | K116: #VALUE!
B117: Egypt | C117: EG1 | D117: CO2 emissions intensity of output,cement (tCO2 per $m GVA) | E117: egy.mit.emin.cem | F117: egy.mit.emin.cem_EG1 | G117: mit | K117: 377.96 | L117: 205.55 | M117: 583.5 | N117: 0.03
B118: Egypt | C118: EG1 | D118: CO2 emissions intensity of output, iron/steel (tCO2 per $m GVA) | E118: egy.mit.emin.irn | F118: egy.mit.emin.irn_EG1 | G118: mit | K118: 635.9 | L118: 492.6 | M118: 1128.51 | N118: 0.01
B119: Egypt | C119: EG1 | D119: CO2 emissions intensity of output, mining (tCO2 per $m GVA) | E119: egy.mit.emin.mch | F119: egy.mit.emin.mch_EG1 | G119: mit | K119: 0 | L119: 54.95 | M119: 54.95 | N119: 0.03
B120: Egypt | C120: EG1 | D120: CO2 emissions intensity of output, manufactures (tCO2 per $m GVA) | E120: egy.mit.emin.man | F120: egy.mit.emin.man_EG1 | G120: mit | K120: 159.22 | L120: 26.04 | M120: 185.25 | N120: 0.12
B121: Egypt | C121: EG1 | D121: CO2 emissions intensity of output, other metals (tCO2 per $m GVA) | E121: egy.mit.emin.oth | F121: egy.mit.emin.oth_EG1 | G121: mit | K121: 0 | L121: 2.34 | M121: 2.34 | N121: 0.01
B122: Egypt | C122: EG1 | D122: CO2 emissions intensity of output, food (tCO2 per $m GVA) | E122: egy.mit.emin.foo | F122: egy.mit.emin.foo_EG1 | G122: mit | K122: 9.78 | L122: 21.23 | M122: 31.01 | N122: 0.26
B123: Egypt | C123: EG1 | D123: CO2 emissions intensity of output, services (tCO2 per $m GVA) | E123: egy.mit.emin.srv | F123: egy.mit.emin.srv_EG1 | G123: mit | K123: 0 | L123: 46.09 | M123: 46.09 | N123: 0.36
B124: Egypt | C124: EG1 | D124: CO2 emissions intensity of output, machinery (tCO2 per $m GVA) | E124: egy.mit.emin.mac | F124: egy.mit.emin.mac_EG1 | G124: mit | K124: 0 | L124: 48.78 | M124: 48.78 | N124: 0.05
B125: Egypt | C125: EG1 | D125: CO2 emissions intensity of output, construction (tCO2 per $m GVA) | E125: egy.mit.emin.cst | F125: egy.mit.emin.cst_EG1 | G125: mit | K125: 0 | L125: 0 | M125: 0 | N125: 0.06
B126: Egypt | C126: EG1 | D126: CO2 emissions and GVA, fuel refining | E126: egy.mit.emin.ftr | F126: egy.mit.emin.ftr_EG1 | G126: mit | K126: 0.07 | L126: 0.41 | M126: 820.06 | N126: 0.07 | O126: 0.41
B127: Egypt | C127: EG1 | D127: CO2 emissions and GVA, food | E127: egy.mit.emin.foo | F127: egy.mit.emin.foo_EG1 | G127: mit | K127: 0.26 | L127: 0 | M127: 31.01 | N127: 0.33 | O127: 0.41
B128: Egypt | C128: EG1 | D128: CO2 emissions and GVA, mining | E128: egy.mit.emin.mch | F128: egy.mit.emin.mch_EG1 | G128: mit | K128: 0.03 | L128: 0 | M128: 54.95 | N128: 0.36 | O128: 0.41
B129: Egypt | C129: EG1 | D129: CO2 emissions and GVA, manufactures | E129: egy.mit.emin.man | F129: egy.mit.emin.man_EG1 | G129: mit | K129: 0.12 | L129: 0.32 | M129: 185.25 | N129: 0.48 | O129: 0.73
B130: Egypt | C130: EG1 | D130: CO2 emissions and GVA, cement | E130: egy.mit.emin.cem | F130: egy.mit.emin.cem_EG1 | G130: mit | K130: 0.03 | L130: 0.16 | M130: 583.5 | N130: 0.51 | O130: 0.89
B131: Egypt | C131: EG1 | D131: CO2 emissions and GVA, iron/steel | E131: egy.mit.emin.irn | F131: egy.mit.emin.irn_EG1 | G131: mit | K131: 0.01 | L131: 0.07 | M131: 1128.51 | N131: 0.52 | O131: 0.96
B132: Egypt | C132: EG1 | D132: CO2 emissions and GVA, construction | E132: egy.mit.emin.con | F132: egy.mit.emin.con_EG1 | G132: mit | K132: 0.06 | L132: 0 | M132: 0 | N132: 0.58 | O132: 0.96
B133: Egypt | C133: EG1 | D133: CO2 emissions and GVA, machinery | E133: egy.mit.emin.mac | F133: egy.mit.emin.mac_EG1 | G133: mit | K133: 0.05 | L133: 48.78 | M133: 48.78 | N133: 0.63 | O133: 49.74
B134: Egypt | C134: EG1 | D134: CO2 emissions and GVA, other metals | E134: egy.mit.emin.oth | F134: egy.mit.emin.oth_EG1 | G134: mit | K134: 0.01 | L134: 0 | M134: 2.34 | N134: 0.64 | O134: 49.74
B135: Egypt | C135: EG1 | D135: CO2 emissions and GVA, services | E135: egy.mit.emin.srv | F135: egy.mit.emin.srv_EG1 | G135: mit | K135: 0.36 | L135: 0.04 | M135: 46.09 | N135: 1 | O135: 49.78
B136: Egypt | C136: EG1 | D136: Electricity ($/kwh) | E136: egy.mit.rp.all.ecy.wtd.1 | F136: egy.mit.rp.all.ecy.wtd.1_EG1 | G136: mit | H136: rp | I136: usdkwh | J136: 1 | K136: 0.063 | L136: 0.058 | M136: 0.049 | N136: 0.047 | O136: 0.049 | P136: 0.05 | Q136: 0.05 | R136: 0.05 | S136: 0.049 | T136: 0.049 | U136: 0.049 | V136: 0.049 | W136: 0.048 | X136: 0.048 | Y136: 0.048 | Z136: 0.047 | AA136: 0.047 | AB136: 0.047 | AC136: 0.047 | AD136: 0.046
B137: Egypt | C137: EG1 | D137: Coal ($/GJ) | E137: egy.mit.rp.all.coa.wtd.1 | F137: egy.mit.rp.all.coa.wtd.1_EG1 | G137: mit | H137: rp | I137: usdgj | J137: 1 | K137: 11.478 | L137: 8.838 | M137: 7.753 | N137: 7.06 | O137: 7.079 | P137: 7.133 | Q137: 7.107 | R137: 7.079 | S137: 7.05 | T137: 7.021 | U137: 7.021 | V137: 7.021 | W137: 7.021 | X137: 7.02 | Y137: 7.02 | Z137: 7.02 | AA137: 7.02 | AB137: 7.02 | AC137: 7.02 | AD137: 7.02
B138: Egypt | C138: EG1 | D138: Natural gas ($/GJ) | E138: egy.mit.rp.all.nga.wtd.1 | F138: egy.mit.rp.all.nga.wtd.1_EG1 | G138: mit | H138: rp | I138: usdgj | J138: 1 | K138: 3.534 | L138: 3.22 | M138: 3.181 | N138: 3.19 | O138: 3.217 | P138: 3.241 | Q138: 3.253 | R138: 3.261 | S138: 3.27 | T138: 3.279 | U138: 3.287 | V138: 3.293 | W138: 3.297 | X138: 3.299 | Y138: 3.3 | Z138: 3.298 | AA138: 3.294 | AB138: 3.287 | AC138: 3.278 | AD138: 3.269
B139: Egypt | C139: EG1 | D139: Oil ($/bbl) | E139: egy.mit.rp.all.oil.wtd.1 | F139: egy.mit.rp.all.oil.wtd.1_EG1 | G139: mit | H139: rp | I139: bbusdl | J139: 1 | K139: 33.051 | L139: 26.301 | M139: 23.176 | N139: 15 | O139: 15 | P139: 15 | Q139: 15 | R139: 15 | S139: 15 | T139: 15 | U139: 15 | V139: 15 | W139: 15 | X139: 15 | Y139: 15 | Z139: 15 | AA139: 15 | AB139: 15 | AC139: 15 | AD139: 15
B140: Egypt | C140: EG1 | D140: Gasoline ($/liter) | E140: egy.mit.rp.all.gso.wtd.1 | F140: egy.mit.rp.all.gso.wtd.1_EG1 | G140: mit | H140: rp | I140: usdl | J140: 1 | K140: 0.6 | L140: 0.411 | M140: 0.335 | N140: 0.335 | O140: 0.335 | P140: 0.335 | Q140: 0.335 | R140: 0.335 | S140: 0.335 | T140: 0.335 | U140: 0.335 | V140: 0.335 | W140: 0.335 | X140: 0.335 | Y140: 0.335 | Z140: 0.335 | AA140: 0.335 | AB140: 0.335 | AC140: 0.335 | AD140: 0.335
B141: Egypt | C141: EG1 | D141: Diesel ($/liter) | E141: egy.mit.rp.all.die.wtd.1 | F141: egy.mit.rp.all.die.wtd.1_EG1 | G141: mit | H141: rp | I141: usdl | J141: 1 | K141: 0.414 | L141: 0.281 | M141: 0.249 | N141: 0.249 | O141: 0.249 | P141: 0.249 | Q141: 0.249 | R141: 0.249 | S141: 0.249 | T141: 0.249 | U141: 0.249 | V141: 0.249 | W141: 0.249 | X141: 0.249 | Y141: 0.249 | Z141: 0.249 | AA141: 0.249 | AB141: 0.249 | AC141: 0.249 | AD141: 0.249
B142: Egypt | C142: EG1 | D142: LPG ($/liter) | E142: egy.mit.rp.all.lpg.wtd.1 | F142: egy.mit.rp.all.lpg.wtd.1_EG1 | G142: mit | H142: rp | I142: usdl | J142: 1 | K142: 0.175 | L142: 0.102 | M142: 0.088 | N142: 0.088 | O142: 0.088 | P142: 0.088 | Q142: 0.088 | R142: 0.088 | S142: 0.088 | T142: 0.088 | U142: 0.088 | V142: 0.088 | W142: 0.088 | X142: 0.088 | Y142: 0.088 | Z142: 0.088 | AA142: 0.088 | AB142: 0.088 | AC142: 0.088 | AD142: 0.088
B143: Egypt | C143: EG1 | D143: Kerosene ($/liter) | E143: egy.mit.rp.all.ker.wtd.1 | F143: egy.mit.rp.all.ker.wtd.1_EG1 | G143: mit | H143: rp | I143: usdl | J143: 1 | K143: 0.414 | L143: 0.259 | M143: 0.244 | N143: 0.244 | O143: 0.244 | P143: 0.244 | Q143: 0.244 | R143: 0.244 | S143: 0.244 | T143: 0.244 | U143: 0.244 | V143: 0.244 | W143: 0.244 | X143: 0.244 | Y143: 0.244 | Z143: 0.244 | AA143: 0.244 | AB143: 0.244 | AC143: 0.244 | AD143: 0.244
B144: Egypt | C144: EG1 | D144: Electricity ($/kwh) | E144: egy.mit.rp.all.ecy.wtd.2 | F144: egy.mit.rp.all.ecy.wtd.2_EG1 | G144: mit | H144: rp | I144: usdkwh | J144: 2 | K144: 0.063 | L144: 0.058 | M144: 0.049 | N144: 0.047 | O144: 0.057 | P144: 0.058 | Q144: 0.059 | R144: 0.058 | S144: 0.057 | T144: 0.056 | U144: 0.056 | V144: 0.056 | W144: 0.056 | X144: 0.055 | Y144: 0.055 | Z144: 0.055 | AA144: 0.054 | AB144: 0.054 | AC144: 0.054 | AD144: 0.053
B145: Egypt | C145: EG1 | D145: Coal ($/GJ) | E145: egy.mit.rp.coa.wtd.2 | F145: egy.mit.rp.coa.wtd.2_EG1 | G145: mit | H145: rp | I145: usdgj | J145: 2 | K145: 11.478 | L145: 8.838 | M145: 7.753 | N145: 7.06 | O145: 9.079 | P145: 9.134 | Q145: 9.108 | R145: 9.08 | S145: 9.05 | T145: 9.021 | U145: 9.021 | V145: 9.021 | W145: 9.021 | X145: 9.021 | Y145: 9.021 | Z145: 9.021 | AA145: 9.02 | AB145: 9.02 | AC145: 9.02 | AD145: 9.02
B146: Egypt | C146: EG1 | D146: Natural gas ($/GJ) | E146: egy.mit.rp.nga.wtd.2 | F146: egy.mit.rp.nga.wtd.2_EG1 | G146: mit | H146: rp | I146: usdgj | J146: 2 | K146: 3.534 | L146: 3.22 | M146: 3.181 | N146: 3.19 | O146: 4.333 | P146: 4.358 | Q146: 4.371 | R146: 4.38 | S146: 4.39 | T146: 4.399 | U146: 4.408 | V146: 4.415 | W146: 4.42 | X146: 4.423 | Y146: 4.424 | Z146: 4.422 | AA146: 4.418 | AB146: 4.411 | AC146: 4.401 | AD146: 4.392
B147: Egypt | C147: EG1 | D147: Oil ($/bbl) | E147: egy.mit.rp.oil.wtd.2 | F147: egy.mit.rp.oil.wtd.2_EG1 | G147: mit | H147: rp | I147: bbusdl | J147: 2 | K147: 33.051 | L147: 26.301 | M147: 23.176 | N147: 15 | O147: 23.014 | P147: 17.477 | Q147: 15.953 | R147: 15.185 | S147: 15 | T147: 15 | U147: 15 | V147: 15 | W147: 15 | X147: 15 | Y147: 15 | Z147: 15 | AA147: 15 | AB147: 15 | AC147: 15 | AD147: 15
... B159: Egypt | C159: EG1 | D159: Kerosene (% change) | E159: egy.mit.rp.all.ker.pct.2 | F159: egy.mit.rp.all.ker.pct.2_EG1 | G159: mit | H159: rp | I159: pc | J159: 2 | K159: 0 | L159: 0 | M159: 0 | N159: 0 | O159: 0.21 | P159: 0.21 | Q159: 0.21 | R159: 0.21 | S159: 0.21 | T159: 0.21 | U159: 0.21 | V159: 0.21 | W159: 0.21 | X159: 0.21 | Y159: 0.21 | Z159: 0.21 | AA159: 0.21 | AB159: 0.21 | AC159: 0.21 | AD159: 0.21
B160: Egypt | C160: EG1 | D160: Implied economy-wide CO2 elasticity | E160: egy.mit.co2.ela.eco.2 | F160: egy.mit.co2.ela.eco.2_EG1 | G160: mit | H160: co2ela | I160: unitusdless | J160: 2
B161: Egypt | C161: EG1 | D161: Implied additional carbon price to achieve NDC (US$ per ton CO2) | E161: egy.mit.ndc.ecr.2 | F161: egy.mit.ndc.ecr.2_EG1 | G161: mit | H161: ndcerc | I161: usdtco2 | J161: 2 | K161: #VALUE!
B162: Egypt | C162: EG1 | D162: Effective carbon rate - economy-wide (US$ per ton CO2) | E162: egy.mit.ecr.1 | F162: egy.mit.ecr.1_EG1 | G162: mit | H162: ecr | I162: usdtco2 | J162: 1 | K162: -151.581 | L162: -128.294 | M162: -165.888 | N162: -154.876 | O162: -161.085 | P162: -152.54 | Q162: -147.751 | R162: -144.482 | S162: -141.161 | T162: -137.051 | U162: -133.401 | V162: -129.433 | W162: -125.136 | X162: -120.459 | Y162: -115.237 | Z162: -109.639 | AA162: -103.673 | AB162: -97.374 | AC162: -91.656 | AD162: -90.676
B163: Egypt | C163: EG1 | D163: Effective carbon rate - economy-wide (US$ per ton CO2) | E163: egy.mit.ecr.2 | F163: egy.mit.ecr.2_EG1 | G163: mit | H163: ecr | I163: usdtco2 | J163: 2 | K163: -151.581 | L163: -128.298 | M163: -165.919 | N163: -154.899 | O163: -141.799 | P163: -130.887 | Q163: -125.762 | R163: -121.928 | S163: -118.587 | T163: -114.331 | U163: -110.456 | V163: -106.168 | W163: -101.525 | X163: -96.491 | Y163: -90.888 | Z163: -84.908 | AA163: -78.546 | AB163: -71.85 | AC163: -65.845 | AD163: -65.068
B164: Egypt | C164: EG1 | D164: Electricity retail price in industry, ($/kWh), baseline | E164: egy.mit.rp.ind.ecy.t.1 | F164: egy.mit.rp.ind.ecy.t.1_EG1 | G164: mit | H164: rp | I164: usdkwh | J164: 1 | K164: 0.064 | L164: 0.062 | M164: 0.052 | N164: 0.049 | O164: 0.051 | P164: 0.053 | Q164: 0.053 | R164: 0.052 | S164: 0.052 | T164: 0.052 | U164: 0.051 | V164: 0.051 | W164: 0.051 | X164: 0.051 | Y164: 0.05 | Z164: 0.05 | AA164: 0.05 | AB164: 0.049 | AC164: 0.049 | AD164: 0.049
B165: Egypt | C165: EG1 | D165: Electricity retail price in residential use, $/kWh (baseline) | E165: egy.mit.rp.res.ecy.t.1 | F165: egy.mit.rp.res.ecy.t.1_EG1 | G165: mit | H165: rp | I165: usdkwh | J165: 1 | K165: 0.061 | L165: 0.052 | M165: 0.046 | N165: 0.043 | O165: 0.045 | P165: 0.046 | Q165: 0.046 | R165: 0.046 | S165: 0.046 | T165: 0.045 | U165: 0.045 | V165: 0.045 | W165: 0.045 | X165: 0.044 | Y165: 0.044 | Z165: 0.044 | AA165: 0.044 | AB165: 0.043 | AC165: 0.043 | AD165: 0.043
B166: Egypt | C166: EG1 | D166: Coal retail price in industry, ($/GJ), baseline | E166: egy.mit.rp.ind.coa.a.1 | F166: egy.mit.rp.ind.coa.a.1_EG1 | G166: mit | H166: rp | I166: usdgj | J166: 1 | K166: 11.466 | L166: 8.83 | M166: 7.746 | N166: 7.054 | O166: 7.072 | P166: 7.127 | Q166: 7.101 | R166: 7.073 | S166: 7.043 | T166: 7.014 | U166: 7.014 | V166: 7.014 | W166: 7.014 | X166: 7.014 | Y166: 7.014 | Z166: 7.014 | AA166: 7.014 | AB166: 7.014 | AC166: 7.014 | AD166: 7.014
B167: Egypt | C167: EG1 | D167: Natural gas retail price in industry, ($/GJ), baseline | E167: egy.mit.rp.ind.nga.a.1 | F167: egy.mit.rp.ind.nga.a.1_EG1 | G167: mit | H167: rp | I167: usdgj | J167: 1 | K167: 5.336 | L167: 5.01 | M167: 5.087 | N167: 5.087 | O167: 5.087 | P167: 5.087 | Q167: 5.087 | R167: 5.087 | S167: 5.087 | T167: 5.087 | U167: 5.087 | V167: 5.087 | W167: 5.087 | X167: 5.087 | Y167: 5.087 | Z167: 5.087 | AA167: 5.087 | AB167: 5.087 | AC167: 5.087 | AD167: 5.087
B168: Egypt | C168: EG1 | D168: Coal retail price in residential use, ($/GJ), baseline | E168: egy.mit.rp.res.coa.a.1 | F168: egy.mit.rp.res.coa.a.1_EG1 | G168: mit | H168: rp | I168: usdgj | J168: 1 | K168: 23.399 | L168: 15.864 | M168: 14.744 | N168: 13.652 | O168: 13.681 | P168: 13.768 | Q168: 13.727 | R168: 13.683 | S168: 13.636 | T168: 13.59 | U168: 13.59 | V168: 13.59 | W168: 13.59 | X168: 13.59 | Y168: 13.59 | Z168: 13.59 | AA168: 13.59 | AB168: 13.59 | AC168: 13.59 | AD168: 13.59
B169: Egypt | C169: EG1 | D169: Natural gas retail price in residential use, ($/GJ), baseline | E169: egy.mit.rp.res.nga.a.1 | F169: egy.mit.rp.res.nga.a.1_EG1 | G169: mit | H169: rp | I169: usdgj | J169: 1 | K169: 4.634 | L169: 3.209 | M169: 2.331 | N169: 2.331 | O169: 2.331 | P169: 2.331 | Q169: 2.331 | R169: 2.331 | S169: 2.331 | T169: 2.331 | U169: 2.331 | V169: 2.331 | W169: 2.331 | X169: 2.331 | Y169: 2.331 | Z169: 2.331 | AA169: 2.331 | AB169: 2.331 | AC169: 2.331 | AD169: 2.331
...

Sheet Scenarios
B1: Scenarios (EGY): carbon price paths, policy bundles, active-bundle series
B2: Policy scenario 2 runs the bundle selected in Settings!B10 (one at a time). Section 4 is mirrored into Data_Prices by code. LEGACY reproduces v0.3 / CPAT default values exactly.
B3: Change only green cells. Bundles from EgyptResultsInitial.docx Table 1/2.
A5: 1 | B5: Carbon price paths ($/ton CO2 real)
B6: Path | C6: Description | D6: Source | I6: Unit | J6: Scenario | K6: 2021 | L6: 2022 | M6: 2023 | N6: 2024 | O6: 2025 | P6: 2026 | Q6: 2027 | R6: 2028 | S6: 2029 | T6: 2030 | U6: 2031 | V6: 2032 | W6: 2033 | X6: 2034 | Y6: 2035 | Z6: 2036 | AA6: 2037 | AB6: 2038 | AC6: 2039 | AD6: 2040 | AE6: 2041 | AF6: 2042 | AG6: 2043 | AH6: 2044 | AI6: 2045
B7: LEGACY_CP | C7: CPAT default carbon tax path in the legacy file | D7: CPAT 1.0pre_456 Mitigation row 8582 (cptraj.2) | I7: $/ton CO2 real | J7: EGY | L7: 0 | M7: 0 | N7: 0 | O7: 0 | P7: 0 | Q7: 12.5 | R7: 25 | S7: 37.5 | T7: 50 | U7: 62.5 | V7: 75 | W7: 87.5 | X7: 100 | Y7: 112.5 | Z7: 125 | AA7: 137.5 | AB7: 150 | AC7: 162.5 | AD7: 175 | AE7: 187.5
B8: LEGACY_ETS | C8: CPAT default auctioned ETS path in the legacy file | D8: CPAT 1.0pre_456 Mitigation row 8583 (etstraj.2) | I8: $/ton CO2 real | J8: EGY | L8: 0 | M8: 0 | N8: 0 | O8: 0 | P8: 0 | Q8: 0 | R8: 0 | S8: 0 | T8: 0 | U8: 0 | V8: 0 | W8: 0 | X8: 0 | Y8: 0 | Z8: 0 | AA8: 0 | AB8: 0 | AC8: 0 | AD8: 0 | AE8: 0
B9: ZERO | C9: No price | D9: - | I9: $/ton CO2 real | J9: EGY | K9: 0 | L9: 0 | M9: 0 | N9: 0 | O9: 0 | P9: 0 | Q9: 0 | R9: 0 | S9: 0 | T9: 0 | U9: 0 | V9: 0 | W9: 0 | X9: 0 | Y9: 0 | Z9: 0 | AA9: 0 | AB9: 0 | AC9: 0 | AD9: 0 | AE9: 0 | AF9: 0 | AG9: 0 | AH9: 0 | AI9: 0
B10: FLAT20_2028 | C10: USD20/tCO2 flat from 2028 | D10: EgyptResultsInitial 1A/2A/2B; CPAT runs EG1/EG2 | I10: $/ton CO2 real | J10: EGY | K10: 0 | L10: 0 | M10: 0 | N10: 0 | O10: 0 | P10: 0 | Q10: 0 | R10: 20 | S10: 20 | T10: 20 | U10: 20 | V10: 20 | W10: 20 | X10: 20 | Y10: 20 | Z10: 20 | AA10: 20 | AB10: 20 | AC10: 20 | AD10: 20 | AE10: 20 | AF10: 20 | AG10: 20 | AH10: 20 | AI10: 20
B11: RAMP_EG3 | C11: USD5 in 2028, +7.5/yr (USD20 in 2030, USD50 in 2034, keeps rising) | D11: CPAT run EG3 (Outputs), behind the reported 3A-3C numbers | I11: $/ton CO2 real | J11: EGY | K11: 0 | L11: 0 | M11: 0 | N11: 0 | O11: 0 | P11: 0 | Q11: 0 | R11: 5 | S11: 12.5 | T11: 20 | U11: 27.5 | V11: 35 | W11: 42.5 | X11: 50 | Y11: 57.5 | Z11: 65 | AA11: 72.5 | AB11: 80 | AC11: 87.5 | AD11: 95 | AE11: 102.5 | AF11: 110 | AG11: 117.5 | AH11: 125 | AI11: 132.5
B12: RAMP50_2034 | C12: USD5 in 2028, +7.5/yr to USD50 in 2034, flat after | D12: EgyptResultsInitial text ('USD5 to USD50 by 2034') | I12: $/ton CO2 real | J12: EGY | K12: 0 | L12: 0 | M12: 0 | N12: 0 | O12: 0 | P12: 0 | Q12: 0 | R12: 5 | S12: 12.5 | T12: 20 | U12: 27.5 | V12: 35 | W12: 42.5 | X12: 50 | Y12: 50 | Z12: 50 | AA12: 50 | AB12: 50 | AC12: 50 | AD12: 50 | AE12: 50 | AF12: 50 | AG12: 50 | AH12: 50 | AI12: 50
B13: Kernel and Data_Prices use 2022-2041 (L..AE), the CPAT data horizon. Reported EgyptResultsInitial metrics refer to 2030, when every non-legacy bundle prices USD20/tCO2. RAMP_EG3 (3A-3C default) and RAMP50_2034 differ only after 2034.
A15: 2 | B15: Policy bundles (one row per bundle)
B16: Bundle | C16: Name | D16: Energy CO2 price path | E16: ETS path | F16: Industry energy covered (share) | G16: Process emissions covered (0/1) | H16: Process price path | I16: OBR share (theta) | J16: Fund share (phi) | K16: Revenue use | L16: Energy scope in main CPAT (Task M) | M16: fc covered (0/1) | N16: fp covered (0/1) | O16: np covered (0/1) | P16: no covered (0/1)
B17: LEGACY | C17: CPAT default policy scenario (regression) | D17: LEGACY_CP | E17: LEGACY_ETS | F17: 1 | G17: 0 | H17: LEGACY_CP | I17: 0 | J17: 0 | K17: CPAT default | L17: All sectors | M17: 1 | N17: 1 | O17: 1 | P17: 1
B18: 1A | C18: Comprehensive levy + CBAM process fee | D18: FLAT20_2028 | E18: ZERO | F18: 1 | G18: 1 | H18: FLAT20_2028 | I18: 0 | J18: 0 | K18: Public investment (non-green) | L18: All sectors | M18: 1 | N18: 1 | O18: 1 | P18: 1
B19: 2A | C19: Upstream levy, public investment | D19: FLAT20_2028 | E19: ZERO | F19: 1 | G19: 0 | H19: FLAT20_2028 | I19: 0 | J19: 0 | K19: Public investment (non-green) | L19: All sectors | M19: 1 | N19: 1 | O19: 1 | P19: 1
B20: 2B | C20: Upstream levy, households | D20: FLAT20_2028 | E20: ZERO | F20: 1 | G20: 0 | H20: FLAT20_2028 | I20: 0 | J20: 0 | K20: Households (per capita) | L20: All sectors | M20: 1 | N20: 1 | O20: 1 | P20: 1
B21: 3A | C21: Downstream heavy industry, households | D21: RAMP_EG3 | E21: ZERO | F21: 1 | G21: 1 | H21: RAMP_EG3 | I21: 0 | J21: 0 | K21: Households (per capita) | L21: Industry only | M21: 1 | N21: 1 | O21: 1 | P21: 1
B22: 3B | C22: Downstream heavy industry, free allocation (benchmark) | D22: RAMP_EG3 | E22: ZERO | F22: 1 | G22: 1 | H22: RAMP_EG3 | I22: 1 | J22: 0 | K22: Firms: output-based free allocation | L22: Industry only | M22: 1 | N22: 1 | O22: 1 | P22: 1
B23: 3C | C23: Downstream heavy industry, abatement rebate | D23: RAMP_EG3 | E23: ZERO | F23: 1 | G23: 1 | H23: RAMP_EG3 | I23: 0 | J23: 1 | K23: Firms: abatement rebate fund | L23: Industry only | M23: 1 | N23: 1 | O23: 1 | P23: 1
A25: 3 | B25: Active bundle (policy scenario 2) and carbon price pass-through factors
B26: Bundle | C26: Name | D26: Energy CO2 price path | E26: ETS path | F26: Industry energy covered (share) | G26: Process emissions covered (0/1) | H26: Process price path | I26: OBR share (theta) | J26: Fund share (phi) | K26: Revenue use | L26: Energy scope in main CPAT (Task M) | M26: fc covered (0/1) | N26: fp covered (0/1) | O26: np covered (0/1) | P26: no covered (0/1)
B27: =Settings!$B$10 -> LEGACY | C27: =INDEX(C$17:C$23,MATCH($B$27,$B$17:$B$23,0)) -> CPAT default policy scenario (regression) | D27: =INDEX(D$17:D$23,MATCH($B$27,$B$17:$B$23,0)) -> LEGACY_CP | E27: =INDEX(E$17:E$23,MATCH($B$27,$B$17:$B$23,0)) -> LEGACY_ETS | F27: =INDEX(F$17:F$23,MATCH($B$27,$B$17:$B$23,0)) -> 1 | G27: =INDEX(G$17:G$23,MATCH($B$27,$B$17:$B$23,0)) -> 0 | H27: =INDEX(H$17:H$23,MATCH($B$27,$B$17:$B$23,0)) -> LEGACY_CP | I27: =INDEX(I$17:I$23,MATCH($B$27,$B$17:$B$23,0)) -> 0 | J27: =INDEX(J$17:J$23,MATCH($B$27,$B$17:$B$23,0)) -> 0 | ... P27: =INDEX(P$17:P$23,MATCH($B$27,$B$17:$B$23,0)) -> 1
B29: Fuel | C29: Pass-through factor: price units per $/ton CO2 | E29: Factor | I29: Unit | J29: Source
B30: coa | C30: CO2 content per native unit (tCO2/unit) | E30: 0.1 | I30: $/GJ per $/tCO2 | J30: Implied by CPAT: legacy nce.2 / cptraj.2 (exactly proportional)
B31: nga | C31: CO2 content per native unit (tCO2/unit) | E31: 0.0558 | I31: $/GJ per $/tCO2 | J31: Implied by CPAT: legacy nce.2 / cptraj.2 (exactly proportional)
B32: gso | C32: CO2 content per native unit (tCO2/unit) | E32: 0.0023142275 | I32: $/liter per $/tCO2 | J32: Implied by CPAT: legacy nce.2 / cptraj.2 (exactly proportional)
B33: die | C33: CO2 content per native unit (tCO2/unit) | E33: 0.0026408351 | I33: $/liter per $/tCO2 | J33: Implied by CPAT: legacy nce.2 / cptraj.2 (exactly proportional)
B34: lpg | C34: CO2 content per native unit (tCO2/unit) | E34: 0.0017684866 | I34: $/liter per $/tCO2 | J34: Implied by CPAT: legacy nce.2 / cptraj.2 (exactly proportional)
B35: ker | C35: CO2 content per native unit (tCO2/unit) | E35: 0.0025591064 | I35: $/liter per $/tCO2 | J35: Implied by CPAT: legacy nce.2 / cptraj.2 (exactly proportional)
B36: oop | C36: CO2 content per native unit (tCO2/unit) | E36: 0.469404 | I36: $/bbl per $/tCO2 | J36: Implied by CPAT: legacy nce.2 / cptraj.2 (exactly proportional)
B37: bio | C37: CO2 content per native unit (tCO2/unit) | E37: 0 | I37: $/GJ per $/tCO2 | J37: Implied by CPAT: legacy nce.2 / cptraj.2 (exactly proportional)
B38: ren | C38: CO2 content per native unit (tCO2/unit) | E38: 0 | I38: $/kwh per $/tCO2 | J38: Implied by CPAT: legacy nce.2 / cptraj.2 (exactly proportional)
A40: 4 | B40: Active-bundle series for scenario 2 (read by Data_Prices via code in column G)
B41: Variable | C41: Description | D41: Written by | E41: Unit | F41: Source | G41: Input Code | H41: Read by | J41: Scenario | K41: 2021 | L41: 2022 | M41: 2023 | N41: 2024 | O41: 2025 | P41: 2026 | Q41: 2027 | R41: 2028 | S41: 2029 | T41: 2030 | U41: 2031 | V41: 2032 | W41: 2033 | X41: 2034 | Y41: 2035 | Z41: 2036 | AA41: 2037 | AB41: 2038 | AC41: 2039 | AD41: 2040 | AE41: 2041 | AF41: 2042 | AG41: 2043 | AH41: 2044 | AI41: 2045
B42: cptraj | C42: Carbon price on energy CO2 (active bundle) | D42: Stream 2 (E) | E42: $/ton CO2 real | F42: Scenarios | G42: egy.mit.cptraj.2 | H42: kernel via nce; CBAM block o2 (fuel CO2 only from v0.7) | J42: EGY | K42: =INDEX(K$7:K$12,MATCH($D$27,$B$7:$B$12,0)) -> 0 | L42: =INDEX(L$7:L$12,MATCH($D$27,$B$7:$B$12,0)) -> 0 | M42: =INDEX(M$7:M$12,MATCH($D$27,$B$7:$B$12,0)) -> 0 | N42: =INDEX(N$7:N$12,MATCH($D$27,$B$7:$B$12,0)) -> 0 | O42: =INDEX(O$7:O$12,MATCH($D$27,$B$7:$B$12,0)) -> 0 | P42: =INDEX(P$7:P$12,MATCH($D$27,$B$7:$B$12,0)) -> 0 | Q42: =INDEX(Q$7:Q$12,MATCH($D$27,$B$7:$B$12,0)) -> 12.5 | R42: =INDEX(R$7:R$12,MATCH($D$27,$B$7:$B$12,0)) -> 25 | ... AI42: =INDEX(AI$7:AI$12,MATCH($D$27,$B$7:$B$12,0)) -> 0
B43: etstraj | C43: Auctioned ETS price (active bundle) | D43: Stream 2 (E) | E43: $/ton CO2 real | F43: Scenarios | G43: egy.mit.etstraj.2 | H43: CBAM block o3 | J43: EGY | K43: =INDEX(K$7:K$12,MATCH($E$27,$B$7:$B$12,0)) -> 0 | L43: =INDEX(L$7:L$12,MATCH($E$27,$B$7:$B$12,0)) -> 0 | M43: =INDEX(M$7:M$12,MATCH($E$27,$B$7:$B$12,0)) -> 0 | N43: =INDEX(N$7:N$12,MATCH($E$27,$B$7:$B$12,0)) -> 0 | O43: =INDEX(O$7:O$12,MATCH($E$27,$B$7:$B$12,0)) -> 0 | P43: =INDEX(P$7:P$12,MATCH($E$27,$B$7:$B$12,0)) -> 0 | Q43: =INDEX(Q$7:Q$12,MATCH($E$27,$B$7:$B$12,0)) -> 0 | R43: =INDEX(R$7:R$12,MATCH($E$27,$B$7:$B$12,0)) -> 0 | ... AI43: =INDEX(AI$7:AI$12,MATCH($E$27,$B$7:$B$12,0)) -> 0
B44: pptraj | C44: Carbon price on CBAM process emissions = process path x process flag | D44: Stream 2 (E) | E44: $/ton CO2 real | F44: Scenarios | G44: egy.mit.pptraj.2 | H44: CBAM block o63 (Task C, process price); Stream 1 L: CBAM obligations | J44: EGY | K44: =INDEX(K$7:K$12,MATCH($H$27,$B$7:$B$12,0))*$G$27 -> 0 | L44: =INDEX(L$7:L$12,MATCH($H$27,$B$7:$B$12,0))*$G$27 -> 0 | M44: =INDEX(M$7:M$12,MATCH($H$27,$B$7:$B$12,0))*$G$27 -> 0 | N44: =INDEX(N$7:N$12,MATCH($H$27,$B$7:$B$12,0))*$G$27 -> 0 | O44: =INDEX(O$7:O$12,MATCH($H$27,$B$7:$B$12,0))*$G$27 -> 0 | P44: =INDEX(P$7:P$12,MATCH($H$27,$B$7:$B$12,0))*$G$27 -> 0 | Q44: =INDEX(Q$7:Q$12,MATCH($H$27,$B$7:$B$12,0))*$G$27 -> 0 | R44: =INDEX(R$7:R$12,MATCH($H$27,$B$7:$B$12,0))*$G$27 -> 0 | ... AI44: =INDEX(AI$7:AI$12,MATCH($H$27,$B$7:$B$12,0))*$G$27 -> 0
B45: encov | C45: Share of industry energy CO2 covered by the energy price | D45: Stream 2 (E) | E45: share | F45: Scenarios | G45: egy.mit.encov.2 | H45: nce (this sheet) | J45: EGY | K45: =$F$27 -> 1 | L45: =$F$27 -> 1 | M45: =$F$27 -> 1 | N45: =$F$27 -> 1 | O45: =$F$27 -> 1 | P45: =$F$27 -> 1 | Q45: =$F$27 -> 1 | R45: =$F$27 -> 1 | ... AI45: =$F$27 -> 1
B46: obrsh | C46: Output-based rebate share theta (free allocation / benchmark) | D46: Stream 2 (E, I) | E46: share | F46: Scenarios | G46: egy.mit.obrsh.2 | H46: Stream 1 (H: output response; L: CBAM price deduction); Stream 2 (I: Rebate_Industry) | J46: EGY | K46: =$I$27 -> 0 | L46: =$I$27 -> 0 | M46: =$I$27 -> 0 | N46: =$I$27 -> 0 | O46: =$I$27 -> 0 | P46: =$I$27 -> 0 | Q46: =$I$27 -> 0 | R46: =$I$27 -> 0 | ... AI46: =$I$27 -> 0
B47: obrrb | C47: Output-based rebate = theta x cptraj (value returned per t at benchmark) | D47: Stream 2 (E, I) | E47: $/ton CO2 real | F47: Scenarios | G47: egy.mit.obrrb.2 | H47: CBAM block o6; Stream 1 (H, L); Stream 2 (I: Rebate_Industry) | J47: EGY | K47: =K46*K42 -> 0 | L47: =L46*L42 -> 0 | M47: =M46*M42 -> 0 | N47: =N46*N42 -> 0 | O47: =O46*O42 -> 0 | P47: =P46*P42 -> 0 | Q47: =Q46*Q42 -> 0 | R47: =R46*R42 -> 0 | ... AI47: =AI46*AI42 -> 0
B48: fundsh | C48: Share of revenue recycled to the industrial abatement fund phi | D48: Stream 2 (E, J) | E48: share | F48: Scenarios | G48: egy.mit.fundsh.2 | H48: CBAM block o5; Fund_Industry fund size F = phi x rev0 (Task J) | J48: EGY | K48: =$J$27 -> 0 | L48: =$J$27 -> 0 | M48: =$J$27 -> 0 | N48: =$J$27 -> 0 | O48: =$J$27 -> 0 | P48: =$J$27 -> 0 | Q48: =$J$27 -> 0 | R48: =$J$27 -> 0 | ... AI48: =$J$27 -> 0
B49: fundsp | C49: Shadow price of fund-financed abatement s (acts on intensity only): solved in Fund_Industry so that fund outlay(s) = phi x carbon revenue (Task J) | D49: Stream 2 (J) | E49: $/ton CO2 real | F49: Scenarios | G49: egy.mit.fundsp.2 | H49: CBAM block o4 -> fuel ER rows o107-o114 and process ER rows o118-o125 (price term P + s); kernel shp via Data_Prices shp.<fuel>.ind.2 (Fund_Industry shpf rows) | J49: EGY | K49: 0 | L49: =Fund_Industry!L$397 -> 0 | M49: =Fund_Industry!M$397 -> 0 | N49: =Fund_Industry!N$397 -> 0 | O49: =Fund_Industry!O$397 -> 0 | P49: =Fund_Industry!P$397 -> 0 | Q49: =Fund_Industry!Q$397 -> 0 | R49: =Fund_Industry!R$397 -> 0 | S49: =Fund_Industry!S$397 -> 0 | ... AE49: =Fund_Industry!AE$397 -> 0 | AF49: 0 | AG49: 0 | AH49: 0 | AI49: 0
B50: nce | C50: New-policy wedge, coa = cptraj x encov x factor | D50: Stream 2 (E) | E50: $/GJ | F50: Scenarios | G50: egy.mit.nce.ind.coa.a.2 | H50: kernel atp rows | J50: EGY | K50: =K42*K45*$E$30 -> 0 | L50: =L42*L45*$E$30 -> 0 | M50: =M42*M45*$E$30 -> 0 | N50: =N42*N45*$E$30 -> 0 | O50: =O42*O45*$E$30 -> 0 | P50: =P42*P45*$E$30 -> 0 | Q50: =Q42*Q45*$E$30 -> 1.25 | R50: =R42*R45*$E$30 -> 2.5 | ... AI50: =AI42*AI45*$E$30 -> 0
B51: nce | C51: New-policy wedge, nga = cptraj x encov x factor | D51: Stream 2 (E) | E51: $/GJ | F51: Scenarios | G51: egy.mit.nce.ind.nga.a.2 | H51: kernel atp rows | J51: EGY | K51: =K42*K45*$E$31 -> 0 | L51: =L42*L45*$E$31 -> 0 | M51: =M42*M45*$E$31 -> 0 | N51: =N42*N45*$E$31 -> 0 | O51: =O42*O45*$E$31 -> 0 | P51: =P42*P45*$E$31 -> 0 | Q51: =Q42*Q45*$E$31 -> 0.6975 | R51: =R42*R45*$E$31 -> 1.395 | ... AI51: =AI42*AI45*$E$31 -> 0
B52: nce | C52: New-policy wedge, gso = cptraj x encov x factor | D52: Stream 2 (E) | E52: $/liter | F52: Scenarios | G52: egy.mit.nce.ind.gso.a.2 | H52: kernel atp rows | J52: EGY | K52: =K42*K45*$E$32 -> 0 | L52: =L42*L45*$E$32 -> 0 | M52: =M42*M45*$E$32 -> 0 | N52: =N42*N45*$E$32 -> 0 | O52: =O42*O45*$E$32 -> 0 | P52: =P42*P45*$E$32 -> 0 | Q52: =Q42*Q45*$E$32 -> 0.028927843 | R52: =R42*R45*$E$32 -> 0.057855686 | ... AI52: =AI42*AI45*$E$32 -> 0
B53: nce | C53: New-policy wedge, die = cptraj x encov x factor | D53: Stream 2 (E) | E53: $/liter | F53: Scenarios | G53: egy.mit.nce.ind.die.a.2 | H53: kernel atp rows | J53: EGY | K53: =K42*K45*$E$33 -> 0 | L53: =L42*L45*$E$33 -> 0 | M53: =M42*M45*$E$33 -> 0 | N53: =N42*N45*$E$33 -> 0 | O53: =O42*O45*$E$33 -> 0 | P53: =P42*P45*$E$33 -> 0 | Q53: =Q42*Q45*$E$33 -> 0.033010439 | R53: =R42*R45*$E$33 -> 0.066020878 | ... AI53: =AI42*AI45*$E$33 -> 0
B54: nce | C54: New-policy wedge, lpg = cptraj x encov x factor | D54: Stream 2 (E) | E54: $/liter | F54: Scenarios | G54: egy.mit.nce.ind.lpg.a.2 | H54: kernel atp rows | J54: EGY | K54: =K42*K45*$E$34 -> 0 | L54: =L42*L45*$E$34 -> 0 | M54: =M42*M45*$E$34 -> 0 | N54: =N42*N45*$E$34 -> 0 | O54: =O42*O45*$E$34 -> 0 | P54: =P42*P45*$E$34 -> 0 | Q54: =Q42*Q45*$E$34 -> 0.022106083 | R54: =R42*R45*$E$34 -> 0.044212166 | ... AI54: =AI42*AI45*$E$34 -> 0
B55: nce | C55: New-policy wedge, ker = cptraj x encov x factor | D55: Stream 2 (E) | E55: $/liter | F55: Scenarios | G55: egy.mit.nce.ind.ker.a.2 | H55: kernel atp rows | J55: EGY | K55: =K42*K45*$E$35 -> 0 | L55: =L42*L45*$E$35 -> 0 | M55: =M42*M45*$E$35 -> 0 | N55: =N42*N45*$E$35 -> 0 | O55: =O42*O45*$E$35 -> 0 | P55: =P42*P45*$E$35 -> 0 | Q55: =Q42*Q45*$E$35 -> 0.03198883 | R55: =R42*R45*$E$35 -> 0.06397766 | ... AI55: =AI42*AI45*$E$35 -> 0
B56: nce | C56: New-policy wedge, oop = cptraj x encov x factor | D56: Stream 2 (E) | E56: $/bbl | F56: Scenarios | G56: egy.mit.nce.ind.oop.a.2 | H56: kernel atp rows | J56: EGY | K56: =K42*K45*$E$36 -> 0 | L56: =L42*L45*$E$36 -> 0 | M56: =M42*M45*$E$36 -> 0 | N56: =N42*N45*$E$36 -> 0 | O56: =O42*O45*$E$36 -> 0 | P56: =P42*P45*$E$36 -> 0 | Q56: =Q42*Q45*$E$36 -> 5.86755 | R56: =R42*R45*$E$36 -> 11.7351 | ... AI56: =AI42*AI45*$E$36 -> 0
B57: nce | C57: New-policy wedge, bio = cptraj x encov x factor | D57: Stream 2 (E) | E57: $/GJ | F57: Scenarios | G57: egy.mit.nce.ind.bio.a.2 | H57: kernel atp rows | J57: EGY | K57: =K42*K45*$E$37 -> 0 | L57: =L42*L45*$E$37 -> 0 | M57: =M42*M45*$E$37 -> 0 | N57: =N42*N45*$E$37 -> 0 | O57: =O42*O45*$E$37 -> 0 | P57: =P42*P45*$E$37 -> 0 | Q57: =Q42*Q45*$E$37 -> 0 | R57: =R42*R45*$E$37 -> 0 | ... AI57: =AI42*AI45*$E$37 -> 0
B58: nce | C58: New-policy wedge, ren = cptraj x encov x factor | D58: Stream 2 (E) | E58: $/kwh | F58: Scenarios | G58: egy.mit.nce.ind.ren.a.2 | H58: kernel atp rows | J58: EGY | K58: =K42*K45*$E$38 -> 0 | L58: =L42*L45*$E$38 -> 0 | M58: =M42*M45*$E$38 -> 0 | N58: =N42*N45*$E$38 -> 0 | O58: =O42*O45*$E$38 -> 0 | P58: =P42*P45*$E$38 -> 0 | Q58: =Q42*Q45*$E$38 -> 0 | R58: =R42*R45*$E$38 -> 0 | ... AI58: =AI42*AI45*$E$38 -> 0
A60: 5 | B60: Interface contract between work streams (merge rules)
B61: Stream 1 = product/CBAM side (tasks A, B, C, D, H, K, L): owns Manual inputs rows 18-47 and CBAM block rows o7-o155.
B62: Stream 2 = energy/policy side (tasks E, F, I, J): owns Scenarios, Data_Prices policy rows, kernel sector blocks, block rows o2-o6.
B63: Interface = the codes in section 4 (Data_Prices egy.mit.<var>.<s>) plus block rows o2-o6. Stream 2 writes, stream 1 reads.
B64: o2 Carbon Tax = cptraj; o3 ETS = etstraj; o4 Total Shadow Price = fundsp ($/tCO2, intensity only); o5 Revenues Fund = fundsh x Total Revenues (o155); o6 Output-based rebate = obrrb.
B65: Price seen by: efficiency / intensity (fuel and process ER) = full price (+ o4); output / usage = price - obrrb (Task H, I).
B66: Process emissions price = pptraj (Task C switches block process rows from o2 to pptraj; equal for all current bundles).
B67: Manual inputs E21 (process emissions priced) = active bundle 'Process emissions covered'; per-sector detail stays in Manual inputs (Task C).
B68: Rules: find rows by code/label, never by row number; never insert rows in the other stream's area; each stream adds its own Check section; merge = run both stream build scripts on v0.4.
B69: Stream 1 output codes (Task A, CBAM block column H, suffix = scenario): cpef / cpep.ind.<sec> (post-policy fuel / process emissions by sector); emisf / emisp / emis.cbam.tot; emrf / emrp / emr.cbam.tot; revf / revp / rev.cbam.tot (o137 / o138 / o155). o5 fund base = o155 = fuel + process revenue; main CPAT adds only revp (fuel CO2 already in nce).
B70: Task B (stream 1): EF category coverage switches M:P (c.fc, c.fp, c.np, c.no; 1 in every bundle: the report treats fc + fp as the fuel-combustion share covered by energy CO2 pricing and np + no as all process emissions). fc, fp are priced with the energy CO2 flags, np, no with the process flags (E21). Set c.fp = 0 to exclude reductant/feedstock fuel, c.no = 0 to exclude non-CO2. Outputs emisfc / emisfp / emisnp / emisno.cbam.tot (block o13-o16); fuel switches affect only CBAM-block memo revenue, not the kernel energy wedge (nce).
B71: Task C (stream 1, v0.7): CBAM process emissions (np + no) are priced at pptraj (block o63), fuel CO2 (fc + fp) at cptraj (o2); ETS (o3) applies to both via the sector ETS flags. To give process emissions their own path, set the bundle's 'Process price path' (column H); 'Process emissions covered' (G) switches it off. Reporting convention: all bundles price 20 $/t in 2030 (checked).
B72: Task K (stream 1, v0.8): CBAM metric codes (block column H, G = cbam.tot): cbcov (o39, priced share of CBAM-sector emissions), cbint (o40, tCO2e/t), cbintch (o41, intensity change vs pre-policy), cbintchx (o51, EU-export-weighted intensity change), cbcovx (o52, EU-export-weighted coverage). Fuel/process split of the change: emisfc..emisno (o13-o16) vs pre-policy o85-o103.
... B82: v0.16: P* 122 (USD2024); fuel-CO2 reallocation in the national composition (Table2 rows 59/60); EG3 full-coverage approximation via kappa (Table2 row 54); fund F = phi x post-fund block revenue (fixed point, Fund_Industry rows 427-433). Table 2 snapshot refilled.

Sheet Mitigation_Industry
B1: Fuel | C1: Sector | D1: Description | E1: Unit | F1: Source | G1: Input Code | H1: Output Code | I1: Note | J1: Helper | K1: 2021 | L1: 2022 | M1: 2023 | N1: 2024 | O1: 2025 | P1: 2026 | Q1: 2027 | R1: 2028 | S1: 2029 | T1: 2030 | U1: 2031 | V1: 2032 | W1: 2033 | X1: 2034 | Y1: 2035 | Z1: 2036 | AA1: 2037 | AB1: 2038 | AC1: 2039 | AD1: 2040 | AE1: 2041 | AF1: 2042 | AG1: 2043 | AH1: 2044 | AI1: 2045
B2: Mitigation Module - Egypt: Industry kernel
A3: 7 | B3: Industrial sector - Baseline (CBAM sectors: iron and steel, cement, non-ferrous metals, mining & chemicals)
B5: Iron and steel | C5: irn | D5: Fuel Type | E5: Unit | F5: Variable Code | G5: Input Code (data-table key) | H5: Output Code | I5: Scenario | J5: 1 | K5: 2021 | L5: 2022 | M5: 2023 | N5: 2024 | O5: 2025 | P5: 2026 | Q5: 2027 | R5: 2028 | S5: 2029 | T5: 2030 | U5: 2031 | V5: 2032 | W5: 2033 | X5: 2034 | Y5: 2035 | Z5: 2036 | AA5: 2037 | AB5: 2038 | AC5: 2039 | AD5: 2040 | AE5: 2041 | AF5: 2042 | AG5: 2043 | AH5: 2044 | AI5: 2045
B6: Pre-tax price: price before any new policy (supply cost + VAT + existing excise, subsidies and carbon prices)
B7: coa | C7: =$C$5 -> irn | D7: Coal | E7: $/GJ | F7: ptp | G7: =Settings!$B$3&".mit.pbc."&Settings!$B$4&"."&$B7&".a."&$J$5 -> egy.mit.pbc.ind.coa.a.1 | H7: =Settings!$B$3&".mit.ptp."&$C$5&"."&$B7&".e."&$J$5 -> egy.mit.ptp.irn.coa.e.1 | K7: =INDEX(Data_Prices!K:K,MATCH($G7,Data_Prices!$A:$A,0)) -> 11.182902 | L7: =INDEX(Data_Prices!L:L,MATCH($G7,Data_Prices!$A:$A,0)) -> 10.523361 | M7: =INDEX(Data_Prices!M:M,MATCH($G7,Data_Prices!$A:$A,0)) -> 10.299561 | N7: =INDEX(Data_Prices!N:N,MATCH($G7,Data_Prices!$A:$A,0)) -> 9.5775284 | O7: =INDEX(Data_Prices!O:O,MATCH($G7,Data_Prices!$A:$A,0)) -> 8.4854783 | P7: =INDEX(Data_Prices!P:P,MATCH($G7,Data_Prices!$A:$A,0)) -> 9.0871922 | Q7: =INDEX(Data_Prices!Q:Q,MATCH($G7,Data_Prices!$A:$A,0)) -> 9.2229237 | R7: =INDEX(Data_Prices!R:R,MATCH($G7,Data_Prices!$A:$A,0)) -> 9.158565 | S7: =INDEX(Data_Prices!S:S,MATCH($G7,Data_Prices!$A:$A,0)) -> 9.0895479 | T7: =INDEX(Data_Prices!T:T,MATCH($G7,Data_Prices!$A:$A,0)) -> 9.0156817 | U7: =INDEX(Data_Prices!U:U,MATCH($G7,Data_Prices!$A:$A,0)) -> 8.9443978 | V7: =INDEX(Data_Prices!V:V,MATCH($G7,Data_Prices!$A:$A,0)) -> 8.9443978 | W7: =INDEX(Data_Prices!W:W,MATCH($G7,Data_Prices!$A:$A,0)) -> 8.9443978 | X7: =INDEX(Data_Prices!X:X,MATCH($G7,Data_Prices!$A:$A,0)) -> 8.9443978 | Y7: =INDEX(Data_Prices!Y:Y,MATCH($G7,Data_Prices!$A:$A,0)) -> 8.9443978 | Z7: =INDEX(Data_Prices!Z:Z,MATCH($G7,Data_Prices!$A:$A,0)) -> 8.9443978 | AA7: =INDEX(Data_Prices!AA:AA,MATCH($G7,Data_Prices!$A:$A,0)) -> 8.9443978 | AB7: =INDEX(Data_Prices!AB:AB,MATCH($G7,Data_Prices!$A:$A,0)) -> 8.9443978 | AC7: =INDEX(Data_Prices!AC:AC,MATCH($G7,Data_Prices!$A:$A,0)) -> 8.9443978 | AD7: =INDEX(Data_Prices!AD:AD,MATCH($G7,Data_Prices!$A:$A,0)) -> 8.9443978 | AE7: =INDEX(Data_Prices!AE:AE,MATCH($G7,Data_Prices!$A:$A,0)) -> 8.9443978
B8: nga | C8: =$C$5 -> irn | D8: Natural gas | E8: $/GJ | F8: ptp | G8: =Settings!$B$3&".mit.pbc."&Settings!$B$4&"."&$B8&".a."&$J$5 -> egy.mit.pbc.ind.nga.a.1 | H8: =Settings!$B$3&".mit.ptp."&$C$5&"."&$B8&".e."&$J$5 -> egy.mit.ptp.irn.nga.e.1 | K8: =INDEX(Data_Prices!K:K,MATCH($G8,Data_Prices!$A:$A,0)) -> 6.0634636 | L8: =INDEX(Data_Prices!L:L,MATCH($G8,Data_Prices!$A:$A,0)) -> 5.4510151 | M8: =INDEX(Data_Prices!M:M,MATCH($G8,Data_Prices!$A:$A,0)) -> 5.1193563 | N8: =INDEX(Data_Prices!N:N,MATCH($G8,Data_Prices!$A:$A,0)) -> 5.0821846 | O8: =INDEX(Data_Prices!O:O,MATCH($G8,Data_Prices!$A:$A,0)) -> 5.0821846 | P8: =INDEX(Data_Prices!P:P,MATCH($G8,Data_Prices!$A:$A,0)) -> 5.0821846 | Q8: =INDEX(Data_Prices!Q:Q,MATCH($G8,Data_Prices!$A:$A,0)) -> 5.0821846 | R8: =INDEX(Data_Prices!R:R,MATCH($G8,Data_Prices!$A:$A,0)) -> 5.0821846 | S8: =INDEX(Data_Prices!S:S,MATCH($G8,Data_Prices!$A:$A,0)) -> 5.0821846 | T8: =INDEX(Data_Prices!T:T,MATCH($G8,Data_Prices!$A:$A,0)) -> 5.0821846 | U8: =INDEX(Data_Prices!U:U,MATCH($G8,Data_Prices!$A:$A,0)) -> 5.0821846 | V8: =INDEX(Data_Prices!V:V,MATCH($G8,Data_Prices!$A:$A,0)) -> 5.0821846 | W8: =INDEX(Data_Prices!W:W,MATCH($G8,Data_Prices!$A:$A,0)) -> 5.0821846 | X8: =INDEX(Data_Prices!X:X,MATCH($G8,Data_Prices!$A:$A,0)) -> 5.0821846 | Y8: =INDEX(Data_Prices!Y:Y,MATCH($G8,Data_Prices!$A:$A,0)) -> 5.0821846 | Z8: =INDEX(Data_Prices!Z:Z,MATCH($G8,Data_Prices!$A:$A,0)) -> 5.0821846 | AA8: =INDEX(Data_Prices!AA:AA,MATCH($G8,Data_Prices!$A:$A,0)) -> 5.0821846 | AB8: =INDEX(Data_Prices!AB:AB,MATCH($G8,Data_Prices!$A:$A,0)) -> 5.0821846 | AC8: =INDEX(Data_Prices!AC:AC,MATCH($G8,Data_Prices!$A:$A,0)) -> 5.0821846 | AD8: =INDEX(Data_Prices!AD:AD,MATCH($G8,Data_Prices!$A:$A,0)) -> 5.0821846 | AE8: =INDEX(Data_Prices!AE:AE,MATCH($G8,Data_Prices!$A:$A,0)) -> 5.0821846
B9: gso | C9: =$C$5 -> irn | D9: Gasoline | E9: $/liter | F9: ptp | G9: =Settings!$B$3&".mit.pbc."&Settings!$B$4&"."&$B9&".a."&$J$5 -> egy.mit.pbc.ind.gso.a.1 | H9: =Settings!$B$3&".mit.ptp."&$C$5&"."&$B9&".e."&$J$5 -> egy.mit.ptp.irn.gso.e.1 | K9: =INDEX(Data_Prices!K:K,MATCH($G9,Data_Prices!$A:$A,0)) -> 0.67114653 | L9: =INDEX(Data_Prices!L:L,MATCH($G9,Data_Prices!$A:$A,0)) -> 0.61197798 | M9: =INDEX(Data_Prices!M:M,MATCH($G9,Data_Prices!$A:$A,0)) -> 0.61180975 | N9: =INDEX(Data_Prices!N:N,MATCH($G9,Data_Prices!$A:$A,0)) -> 0.6035831 | O9: =INDEX(Data_Prices!O:O,MATCH($G9,Data_Prices!$A:$A,0)) -> 0.6035831 | P9: =INDEX(Data_Prices!P:P,MATCH($G9,Data_Prices!$A:$A,0)) -> 0.6035831 | Q9: =INDEX(Data_Prices!Q:Q,MATCH($G9,Data_Prices!$A:$A,0)) -> 0.6035831 | R9: =INDEX(Data_Prices!R:R,MATCH($G9,Data_Prices!$A:$A,0)) -> 0.6035831 | S9: =INDEX(Data_Prices!S:S,MATCH($G9,Data_Prices!$A:$A,0)) -> 0.6035831 | T9: =INDEX(Data_Prices!T:T,MATCH($G9,Data_Prices!$A:$A,0)) -> 0.6035831 | U9: =INDEX(Data_Prices!U:U,MATCH($G9,Data_Prices!$A:$A,0)) -> 0.6035831 | V9: =INDEX(Data_Prices!V:V,MATCH($G9,Data_Prices!$A:$A,0)) -> 0.6035831 | W9: =INDEX(Data_Prices!W:W,MATCH($G9,Data_Prices!$A:$A,0)) -> 0.6035831 | X9: =INDEX(Data_Prices!X:X,MATCH($G9,Data_Prices!$A:$A,0)) -> 0.6035831 | Y9: =INDEX(Data_Prices!Y:Y,MATCH($G9,Data_Prices!$A:$A,0)) -> 0.6035831 | Z9: =INDEX(Data_Prices!Z:Z,MATCH($G9,Data_Prices!$A:$A,0)) -> 0.6035831 | AA9: =INDEX(Data_Prices!AA:AA,MATCH($G9,Data_Prices!$A:$A,0)) -> 0.6035831 | AB9: =INDEX(Data_Prices!AB:AB,MATCH($G9,Data_Prices!$A:$A,0)) -> 0.6035831 | AC9: =INDEX(Data_Prices!AC:AC,MATCH($G9,Data_Prices!$A:$A,0)) -> 0.6035831 | AD9: =INDEX(Data_Prices!AD:AD,MATCH($G9,Data_Prices!$A:$A,0)) -> 0.6035831 | AE9: =INDEX(Data_Prices!AE:AE,MATCH($G9,Data_Prices!$A:$A,0)) -> 0.6035831
B10: die | C10: =$C$5 -> irn | D10: Diesel | E10: $/liter | F10: ptp | G10: =Settings!$B$3&".mit.pbc."&Settings!$B$4&"."&$B10&".a."&$J$5 -> egy.mit.pbc.ind.die.a.1 | H10: =Settings!$B$3&".mit.ptp."&$C$5&"."&$B10&".e."&$J$5 -> egy.mit.ptp.irn.die.e.1 | K10: =INDEX(Data_Prices!K:K,MATCH($G10,Data_Prices!$A:$A,0)) -> 0.55971121 | L10: =INDEX(Data_Prices!L:L,MATCH($G10,Data_Prices!$A:$A,0)) -> 0.49458873 | M10: =INDEX(Data_Prices!M:M,MATCH($G10,Data_Prices!$A:$A,0)) -> 0.50778655 | N10: =INDEX(Data_Prices!N:N,MATCH($G10,Data_Prices!$A:$A,0)) -> 0.47043643 | O10: =INDEX(Data_Prices!O:O,MATCH($G10,Data_Prices!$A:$A,0)) -> 0.47043643 | P10: =INDEX(Data_Prices!P:P,MATCH($G10,Data_Prices!$A:$A,0)) -> 0.47043643 | Q10: =INDEX(Data_Prices!Q:Q,MATCH($G10,Data_Prices!$A:$A,0)) -> 0.47043643 | R10: =INDEX(Data_Prices!R:R,MATCH($G10,Data_Prices!$A:$A,0)) -> 0.47043643 | S10: =INDEX(Data_Prices!S:S,MATCH($G10,Data_Prices!$A:$A,0)) -> 0.47043643 | T10: =INDEX(Data_Prices!T:T,MATCH($G10,Data_Prices!$A:$A,0)) -> 0.47043643 | U10: =INDEX(Data_Prices!U:U,MATCH($G10,Data_Prices!$A:$A,0)) -> 0.47043643 | V10: =INDEX(Data_Prices!V:V,MATCH($G10,Data_Prices!$A:$A,0)) -> 0.47043643 | W10: =INDEX(Data_Prices!W:W,MATCH($G10,Data_Prices!$A:$A,0)) -> 0.47043643 | X10: =INDEX(Data_Prices!X:X,MATCH($G10,Data_Prices!$A:$A,0)) -> 0.47043643 | Y10: =INDEX(Data_Prices!Y:Y,MATCH($G10,Data_Prices!$A:$A,0)) -> 0.47043643 | Z10: =INDEX(Data_Prices!Z:Z,MATCH($G10,Data_Prices!$A:$A,0)) -> 0.47043643 | AA10: =INDEX(Data_Prices!AA:AA,MATCH($G10,Data_Prices!$A:$A,0)) -> 0.47043643 | AB10: =INDEX(Data_Prices!AB:AB,MATCH($G10,Data_Prices!$A:$A,0)) -> 0.47043643 | AC10: =INDEX(Data_Prices!AC:AC,MATCH($G10,Data_Prices!$A:$A,0)) -> 0.47043643 | AD10: =INDEX(Data_Prices!AD:AD,MATCH($G10,Data_Prices!$A:$A,0)) -> 0.47043643 | AE10: =INDEX(Data_Prices!AE:AE,MATCH($G10,Data_Prices!$A:$A,0)) -> 0.47043643
B11: lpg | C11: =$C$5 -> irn | D11: LPG | E11: $/liter | F11: ptp | G11: =Settings!$B$3&".mit.pbc."&Settings!$B$4&"."&$B11&".a."&$J$5 -> egy.mit.pbc.ind.lpg.a.1 | H11: =Settings!$B$3&".mit.ptp."&$C$5&"."&$B11&".e."&$J$5 -> egy.mit.ptp.irn.lpg.e.1 | K11: =INDEX(Data_Prices!K:K,MATCH($G11,Data_Prices!$A:$A,0)) -> 0.20036669 | L11: =INDEX(Data_Prices!L:L,MATCH($G11,Data_Prices!$A:$A,0)) -> 0.15734474 | M11: =INDEX(Data_Prices!M:M,MATCH($G11,Data_Prices!$A:$A,0)) -> 0.16448404 | N11: =INDEX(Data_Prices!N:N,MATCH($G11,Data_Prices!$A:$A,0)) -> 0.15070908 | O11: =INDEX(Data_Prices!O:O,MATCH($G11,Data_Prices!$A:$A,0)) -> 0.15070908 | P11: =INDEX(Data_Prices!P:P,MATCH($G11,Data_Prices!$A:$A,0)) -> 0.15070908 | Q11: =INDEX(Data_Prices!Q:Q,MATCH($G11,Data_Prices!$A:$A,0)) -> 0.15070908 | R11: =INDEX(Data_Prices!R:R,MATCH($G11,Data_Prices!$A:$A,0)) -> 0.15070908 | S11: =INDEX(Data_Prices!S:S,MATCH($G11,Data_Prices!$A:$A,0)) -> 0.15070908 | T11: =INDEX(Data_Prices!T:T,MATCH($G11,Data_Prices!$A:$A,0)) -> 0.15070908 | U11: =INDEX(Data_Prices!U:U,MATCH($G11,Data_Prices!$A:$A,0)) -> 0.15070908 | V11: =INDEX(Data_Prices!V:V,MATCH($G11,Data_Prices!$A:$A,0)) -> 0.15070908 | W11: =INDEX(Data_Prices!W:W,MATCH($G11,Data_Prices!$A:$A,0)) -> 0.15070908 | X11: =INDEX(Data_Prices!X:X,MATCH($G11,Data_Prices!$A:$A,0)) -> 0.15070908 | Y11: =INDEX(Data_Prices!Y:Y,MATCH($G11,Data_Prices!$A:$A,0)) -> 0.15070908 | Z11: =INDEX(Data_Prices!Z:Z,MATCH($G11,Data_Prices!$A:$A,0)) -> 0.15070908 | AA11: =INDEX(Data_Prices!AA:AA,MATCH($G11,Data_Prices!$A:$A,0)) -> 0.15070908 | AB11: =INDEX(Data_Prices!AB:AB,MATCH($G11,Data_Prices!$A:$A,0)) -> 0.15070908 | AC11: =INDEX(Data_Prices!AC:AC,MATCH($G11,Data_Prices!$A:$A,0)) -> 0.15070908 | AD11: =INDEX(Data_Prices!AD:AD,MATCH($G11,Data_Prices!$A:$A,0)) -> 0.15070908 | AE11: =INDEX(Data_Prices!AE:AE,MATCH($G11,Data_Prices!$A:$A,0)) -> 0.15070908
B12: ker | C12: =$C$5 -> irn | D12: Kerosene | E12: $/liter | F12: ptp | G12: =Settings!$B$3&".mit.pbc."&Settings!$B$4&"."&$B12&".a."&$J$5 -> egy.mit.pbc.ind.ker.a.1 | H12: =Settings!$B$3&".mit.ptp."&$C$5&"."&$B12&".e."&$J$5 -> egy.mit.ptp.irn.ker.e.1 | K12: =INDEX(Data_Prices!K:K,MATCH($G12,Data_Prices!$A:$A,0)) -> 0.48429424 | L12: =INDEX(Data_Prices!L:L,MATCH($G12,Data_Prices!$A:$A,0)) -> 0.45642817 | M12: =INDEX(Data_Prices!M:M,MATCH($G12,Data_Prices!$A:$A,0)) -> 0.4316892 | N12: =INDEX(Data_Prices!N:N,MATCH($G12,Data_Prices!$A:$A,0)) -> 0.42507558 | O12: =INDEX(Data_Prices!O:O,MATCH($G12,Data_Prices!$A:$A,0)) -> 0.42507558 | P12: =INDEX(Data_Prices!P:P,MATCH($G12,Data_Prices!$A:$A,0)) -> 0.42507558 | Q12: =INDEX(Data_Prices!Q:Q,MATCH($G12,Data_Prices!$A:$A,0)) -> 0.42507558 | R12: =INDEX(Data_Prices!R:R,MATCH($G12,Data_Prices!$A:$A,0)) -> 0.42507558 | S12: =INDEX(Data_Prices!S:S,MATCH($G12,Data_Prices!$A:$A,0)) -> 0.42507558 | T12: =INDEX(Data_Prices!T:T,MATCH($G12,Data_Prices!$A:$A,0)) -> 0.42507558 | U12: =INDEX(Data_Prices!U:U,MATCH($G12,Data_Prices!$A:$A,0)) -> 0.42507558 | V12: =INDEX(Data_Prices!V:V,MATCH($G12,Data_Prices!$A:$A,0)) -> 0.42507558 | W12: =INDEX(Data_Prices!W:W,MATCH($G12,Data_Prices!$A:$A,0)) -> 0.42507558 | X12: =INDEX(Data_Prices!X:X,MATCH($G12,Data_Prices!$A:$A,0)) -> 0.42507558 | Y12: =INDEX(Data_Prices!Y:Y,MATCH($G12,Data_Prices!$A:$A,0)) -> 0.42507558 | Z12: =INDEX(Data_Prices!Z:Z,MATCH($G12,Data_Prices!$A:$A,0)) -> 0.42507558 | AA12: =INDEX(Data_Prices!AA:AA,MATCH($G12,Data_Prices!$A:$A,0)) -> 0.42507558 | AB12: =INDEX(Data_Prices!AB:AB,MATCH($G12,Data_Prices!$A:$A,0)) -> 0.42507558 | AC12: =INDEX(Data_Prices!AC:AC,MATCH($G12,Data_Prices!$A:$A,0)) -> 0.42507558 | AD12: =INDEX(Data_Prices!AD:AD,MATCH($G12,Data_Prices!$A:$A,0)) -> 0.42507558 | AE12: =INDEX(Data_Prices!AE:AE,MATCH($G12,Data_Prices!$A:$A,0)) -> 0.42507558
B13: oop | C13: =$C$5 -> irn | D13: Other oil products | E13: $/bbl | F13: ptp | G13: =Settings!$B$3&".mit.pbc."&Settings!$B$4&"."&$B13&".a."&$J$5 -> egy.mit.pbc.ind.oop.a.1 | H13: =Settings!$B$3&".mit.ptp."&$C$5&"."&$B13&".e."&$J$5 -> egy.mit.ptp.irn.oop.e.1 | K13: =INDEX(Data_Prices!K:K,MATCH($G13,Data_Prices!$A:$A,0)) -> 41.500338 | L13: =INDEX(Data_Prices!L:L,MATCH($G13,Data_Prices!$A:$A,0)) -> 34.41537 | M13: =INDEX(Data_Prices!M:M,MATCH($G13,Data_Prices!$A:$A,0)) -> 37.368961 | N13: =INDEX(Data_Prices!N:N,MATCH($G13,Data_Prices!$A:$A,0)) -> 28.982761 | O13: =INDEX(Data_Prices!O:O,MATCH($G13,Data_Prices!$A:$A,0)) -> 15 | P13: =INDEX(Data_Prices!P:P,MATCH($G13,Data_Prices!$A:$A,0)) -> 24.25863 | Q13: =INDEX(Data_Prices!Q:Q,MATCH($G13,Data_Prices!$A:$A,0)) -> 15 | R13: =INDEX(Data_Prices!R:R,MATCH($G13,Data_Prices!$A:$A,0)) -> 15 | S13: =INDEX(Data_Prices!S:S,MATCH($G13,Data_Prices!$A:$A,0)) -> 15 | T13: =INDEX(Data_Prices!T:T,MATCH($G13,Data_Prices!$A:$A,0)) -> 15 | U13: =INDEX(Data_Prices!U:U,MATCH($G13,Data_Prices!$A:$A,0)) -> 15 | V13: =INDEX(Data_Prices!V:V,MATCH($G13,Data_Prices!$A:$A,0)) -> 15 | W13: =INDEX(Data_Prices!W:W,MATCH($G13,Data_Prices!$A:$A,0)) -> 15 | X13: =INDEX(Data_Prices!X:X,MATCH($G13,Data_Prices!$A:$A,0)) -> 15 | Y13: =INDEX(Data_Prices!Y:Y,MATCH($G13,Data_Prices!$A:$A,0)) -> 15 | Z13: =INDEX(Data_Prices!Z:Z,MATCH($G13,Data_Prices!$A:$A,0)) -> 15 | AA13: =INDEX(Data_Prices!AA:AA,MATCH($G13,Data_Prices!$A:$A,0)) -> 15 | AB13: =INDEX(Data_Prices!AB:AB,MATCH($G13,Data_Prices!$A:$A,0)) -> 15 | AC13: =INDEX(Data_Prices!AC:AC,MATCH($G13,Data_Prices!$A:$A,0)) -> 15 | AD13: =INDEX(Data_Prices!AD:AD,MATCH($G13,Data_Prices!$A:$A,0)) -> 15 | AE13: =INDEX(Data_Prices!AE:AE,MATCH($G13,Data_Prices!$A:$A,0)) -> 15
B14: bio | C14: =$C$5 -> irn | D14: Biomass | E14: $/GJ | F14: ptp | G14: =Settings!$B$3&".mit.pbc."&Settings!$B$4&"."&$B14&".a."&$J$5 -> egy.mit.pbc.ind.bio.a.1 | H14: =Settings!$B$3&".mit.ptp."&$C$5&"."&$B14&".e."&$J$5 -> egy.mit.ptp.irn.bio.e.1 | K14: =INDEX(Data_Prices!K:K,MATCH($G14,Data_Prices!$A:$A,0)) -> 15.334551 | L14: =INDEX(Data_Prices!L:L,MATCH($G14,Data_Prices!$A:$A,0)) -> 14.199528 | M14: =INDEX(Data_Prices!M:M,MATCH($G14,Data_Prices!$A:$A,0)) -> 13.840442 | N14: =INDEX(Data_Prices!N:N,MATCH($G14,Data_Prices!$A:$A,0)) -> 13.567727 | O14: =INDEX(Data_Prices!O:O,MATCH($G14,Data_Prices!$A:$A,0)) -> 13.567727 | P14: =INDEX(Data_Prices!P:P,MATCH($G14,Data_Prices!$A:$A,0)) -> 13.567727 | Q14: =INDEX(Data_Prices!Q:Q,MATCH($G14,Data_Prices!$A:$A,0)) -> 13.567727 | R14: =INDEX(Data_Prices!R:R,MATCH($G14,Data_Prices!$A:$A,0)) -> 13.567727 | S14: =INDEX(Data_Prices!S:S,MATCH($G14,Data_Prices!$A:$A,0)) -> 13.567727 | T14: =INDEX(Data_Prices!T:T,MATCH($G14,Data_Prices!$A:$A,0)) -> 13.567727 | U14: =INDEX(Data_Prices!U:U,MATCH($G14,Data_Prices!$A:$A,0)) -> 13.567727 | V14: =INDEX(Data_Prices!V:V,MATCH($G14,Data_Prices!$A:$A,0)) -> 13.567727 | W14: =INDEX(Data_Prices!W:W,MATCH($G14,Data_Prices!$A:$A,0)) -> 13.567727 | X14: =INDEX(Data_Prices!X:X,MATCH($G14,Data_Prices!$A:$A,0)) -> 13.567727 | Y14: =INDEX(Data_Prices!Y:Y,MATCH($G14,Data_Prices!$A:$A,0)) -> 13.567727 | Z14: =INDEX(Data_Prices!Z:Z,MATCH($G14,Data_Prices!$A:$A,0)) -> 13.567727 | AA14: =INDEX(Data_Prices!AA:AA,MATCH($G14,Data_Prices!$A:$A,0)) -> 13.567727 | AB14: =INDEX(Data_Prices!AB:AB,MATCH($G14,Data_Prices!$A:$A,0)) -> 13.567727 | AC14: =INDEX(Data_Prices!AC:AC,MATCH($G14,Data_Prices!$A:$A,0)) -> 13.567727 | AD14: =INDEX(Data_Prices!AD:AD,MATCH($G14,Data_Prices!$A:$A,0)) -> 13.567727 | AE14: =INDEX(Data_Prices!AE:AE,MATCH($G14,Data_Prices!$A:$A,0)) -> 13.567727
B15: ren | C15: =$C$5 -> irn | D15: Self-generated renewables | E15: $/kwh | F15: ptp | G15: =Settings!$B$3&".mit.pbc."&Settings!$B$4&"."&$B15&".a."&$J$5 -> egy.mit.pbc.ind.ren.a.1 | H15: =Settings!$B$3&".mit.ptp."&$C$5&"."&$B15&".e."&$J$5 -> egy.mit.ptp.irn.ren.e.1 | K15: =INDEX(Data_Prices!K:K,MATCH($G15,Data_Prices!$A:$A,0)) -> 0 | L15: =INDEX(Data_Prices!L:L,MATCH($G15,Data_Prices!$A:$A,0)) -> 0.14404499 | M15: =INDEX(Data_Prices!M:M,MATCH($G15,Data_Prices!$A:$A,0)) -> 0.14102041 | N15: =INDEX(Data_Prices!N:N,MATCH($G15,Data_Prices!$A:$A,0)) -> 0.13511636 | O15: =INDEX(Data_Prices!O:O,MATCH($G15,Data_Prices!$A:$A,0)) -> 0.13098826 | P15: =INDEX(Data_Prices!P:P,MATCH($G15,Data_Prices!$A:$A,0)) -> 0.12790842 | Q15: =INDEX(Data_Prices!Q:Q,MATCH($G15,Data_Prices!$A:$A,0)) -> 0.12481431 | R15: =INDEX(Data_Prices!R:R,MATCH($G15,Data_Prices!$A:$A,0)) -> 0.12146026 | S15: =INDEX(Data_Prices!S:S,MATCH($G15,Data_Prices!$A:$A,0)) -> 0.11795074 | T15: =INDEX(Data_Prices!T:T,MATCH($G15,Data_Prices!$A:$A,0)) -> 0.11419916 | U15: =INDEX(Data_Prices!U:U,MATCH($G15,Data_Prices!$A:$A,0)) -> 0.1136651 | V15: =INDEX(Data_Prices!V:V,MATCH($G15,Data_Prices!$A:$A,0)) -> 0.11301693 | W15: =INDEX(Data_Prices!W:W,MATCH($G15,Data_Prices!$A:$A,0)) -> 0.11231407 | X15: =INDEX(Data_Prices!X:X,MATCH($G15,Data_Prices!$A:$A,0)) -> 0.11142204 | Y15: =INDEX(Data_Prices!Y:Y,MATCH($G15,Data_Prices!$A:$A,0)) -> 0.11043412 | Z15: =INDEX(Data_Prices!Z:Z,MATCH($G15,Data_Prices!$A:$A,0)) -> 0.10948397 | AA15: =INDEX(Data_Prices!AA:AA,MATCH($G15,Data_Prices!$A:$A,0)) -> 0.10839192 | AB15: =INDEX(Data_Prices!AB:AB,MATCH($G15,Data_Prices!$A:$A,0)) -> 0.10735443 | AC15: =INDEX(Data_Prices!AC:AC,MATCH($G15,Data_Prices!$A:$A,0)) -> 0.10516868 | AD15: =INDEX(Data_Prices!AD:AD,MATCH($G15,Data_Prices!$A:$A,0)) -> 0.10305798 | AE15: =INDEX(Data_Prices!AE:AE,MATCH($G15,Data_Prices!$A:$A,0)) -> 0.10093184
B16: Post-tax price: pre-tax + new-policy wedge x sector coverage factor (= CPAT atp row)
B17: coa | C17: =$C$5 -> irn | D17: Coal | E17: $/GJ | F17: atp | G17: =Settings!$B$3&".mit.nce."&Settings!$B$4&"."&$B17&".a."&$J$5 -> egy.mit.nce.ind.coa.a.1 | H17: =Settings!$B$3&".mit.atp."&$C$5&"."&$B17&".e."&$J$5 -> egy.mit.atp.irn.coa.e.1 | K17: =K7+INDEX(Data_Prices!K:K,MATCH($G17,Data_Prices!$A:$A,0))*K$37 -> 11.182902 | L17: =L7+INDEX(Data_Prices!L:L,MATCH($G17,Data_Prices!$A:$A,0))*L$37 -> 10.523361 | M17: =M7+INDEX(Data_Prices!M:M,MATCH($G17,Data_Prices!$A:$A,0))*M$37 -> 10.299561 | N17: =N7+INDEX(Data_Prices!N:N,MATCH($G17,Data_Prices!$A:$A,0))*N$37 -> 9.5775284 | O17: =O7+INDEX(Data_Prices!O:O,MATCH($G17,Data_Prices!$A:$A,0))*O$37 -> 8.4854783 | P17: =P7+INDEX(Data_Prices!P:P,MATCH($G17,Data_Prices!$A:$A,0))*P$37 -> 9.0871922 | Q17: =Q7+INDEX(Data_Prices!Q:Q,MATCH($G17,Data_Prices!$A:$A,0))*Q$37 -> 9.2229237 | R17: =R7+INDEX(Data_Prices!R:R,MATCH($G17,Data_Prices!$A:$A,0))*R$37 -> 9.158565 | S17: =S7+INDEX(Data_Prices!S:S,MATCH($G17,Data_Prices!$A:$A,0))*S$37 -> 9.0895479 | T17: =T7+INDEX(Data_Prices!T:T,MATCH($G17,Data_Prices!$A:$A,0))*T$37 -> 9.0156817 | U17: =U7+INDEX(Data_Prices!U:U,MATCH($G17,Data_Prices!$A:$A,0))*U$37 -> 8.9443978 | V17: =V7+INDEX(Data_Prices!V:V,MATCH($G17,Data_Prices!$A:$A,0))*V$37 -> 8.9443978 | W17: =W7+INDEX(Data_Prices!W:W,MATCH($G17,Data_Prices!$A:$A,0))*W$37 -> 8.9443978 | X17: =X7+INDEX(Data_Prices!X:X,MATCH($G17,Data_Prices!$A:$A,0))*X$37 -> 8.9443978 | Y17: =Y7+INDEX(Data_Prices!Y:Y,MATCH($G17,Data_Prices!$A:$A,0))*Y$37 -> 8.9443978 | Z17: =Z7+INDEX(Data_Prices!Z:Z,MATCH($G17,Data_Prices!$A:$A,0))*Z$37 -> 8.9443978 | AA17: =AA7+INDEX(Data_Prices!AA:AA,MATCH($G17,Data_Prices!$A:$A,0))*AA$37 -> 8.9443978 | AB17: =AB7+INDEX(Data_Prices!AB:AB,MATCH($G17,Data_Prices!$A:$A,0))*AB$37 -> 8.9443978 | AC17: =AC7+INDEX(Data_Prices!AC:AC,MATCH($G17,Data_Prices!$A:$A,0))*AC$37 -> 8.9443978 | AD17: =AD7+INDEX(Data_Prices!AD:AD,MATCH($G17,Data_Prices!$A:$A,0))*AD$37 -> 8.9443978 | AE17: =AE7+INDEX(Data_Prices!AE:AE,MATCH($G17,Data_Prices!$A:$A,0))*AE$37 -> 8.9443978
B18: nga | C18: =$C$5 -> irn | D18: Natural gas | E18: $/GJ | F18: atp | G18: =Settings!$B$3&".mit.nce."&Settings!$B$4&"."&$B18&".a."&$J$5 -> egy.mit.nce.ind.nga.a.1 | H18: =Settings!$B$3&".mit.atp."&$C$5&"."&$B18&".e."&$J$5 -> egy.mit.atp.irn.nga.e.1 | K18: =K8+INDEX(Data_Prices!K:K,MATCH($G18,Data_Prices!$A:$A,0))*K$37 -> 6.0634636 | L18: =L8+INDEX(Data_Prices!L:L,MATCH($G18,Data_Prices!$A:$A,0))*L$37 -> 5.4510151 | M18: =M8+INDEX(Data_Prices!M:M,MATCH($G18,Data_Prices!$A:$A,0))*M$37 -> 5.1193563 | N18: =N8+INDEX(Data_Prices!N:N,MATCH($G18,Data_Prices!$A:$A,0))*N$37 -> 5.0821846 | O18: =O8+INDEX(Data_Prices!O:O,MATCH($G18,Data_Prices!$A:$A,0))*O$37 -> 5.0821846 | P18: =P8+INDEX(Data_Prices!P:P,MATCH($G18,Data_Prices!$A:$A,0))*P$37 -> 5.0821846 | Q18: =Q8+INDEX(Data_Prices!Q:Q,MATCH($G18,Data_Prices!$A:$A,0))*Q$37 -> 5.0821846 | R18: =R8+INDEX(Data_Prices!R:R,MATCH($G18,Data_Prices!$A:$A,0))*R$37 -> 5.0821846 | S18: =S8+INDEX(Data_Prices!S:S,MATCH($G18,Data_Prices!$A:$A,0))*S$37 -> 5.0821846 | T18: =T8+INDEX(Data_Prices!T:T,MATCH($G18,Data_Prices!$A:$A,0))*T$37 -> 5.0821846 | U18: =U8+INDEX(Data_Prices!U:U,MATCH($G18,Data_Prices!$A:$A,0))*U$37 -> 5.0821846 | V18: =V8+INDEX(Data_Prices!V:V,MATCH($G18,Data_Prices!$A:$A,0))*V$37 -> 5.0821846 | W18: =W8+INDEX(Data_Prices!W:W,MATCH($G18,Data_Prices!$A:$A,0))*W$37 -> 5.0821846 | X18: =X8+INDEX(Data_Prices!X:X,MATCH($G18,Data_Prices!$A:$A,0))*X$37 -> 5.0821846 | Y18: =Y8+INDEX(Data_Prices!Y:Y,MATCH($G18,Data_Prices!$A:$A,0))*Y$37 -> 5.0821846 | Z18: =Z8+INDEX(Data_Prices!Z:Z,MATCH($G18,Data_Prices!$A:$A,0))*Z$37 -> 5.0821846 | AA18: =AA8+INDEX(Data_Prices!AA:AA,MATCH($G18,Data_Prices!$A:$A,0))*AA$37 -> 5.0821846 | AB18: =AB8+INDEX(Data_Prices!AB:AB,MATCH($G18,Data_Prices!$A:$A,0))*AB$37 -> 5.0821846 | AC18: =AC8+INDEX(Data_Prices!AC:AC,MATCH($G18,Data_Prices!$A:$A,0))*AC$37 -> 5.0821846 | AD18: =AD8+INDEX(Data_Prices!AD:AD,MATCH($G18,Data_Prices!$A:$A,0))*AD$37 -> 5.0821846 | AE18: =AE8+INDEX(Data_Prices!AE:AE,MATCH($G18,Data_Prices!$A:$A,0))*AE$37 -> 5.0821846
B19: gso | C19: =$C$5 -> irn | D19: Gasoline | E19: $/liter | F19: atp | G19: =Settings!$B$3&".mit.nce."&Settings!$B$4&"."&$B19&".a."&$J$5 -> egy.mit.nce.ind.gso.a.1 | H19: =Settings!$B$3&".mit.atp."&$C$5&"."&$B19&".e."&$J$5 -> egy.mit.atp.irn.gso.e.1 | K19: =K9+INDEX(Data_Prices!K:K,MATCH($G19,Data_Prices!$A:$A,0))*K$37 -> 0.67114653 | L19: =L9+INDEX(Data_Prices!L:L,MATCH($G19,Data_Prices!$A:$A,0))*L$37 -> 0.61197798 | M19: =M9+INDEX(Data_Prices!M:M,MATCH($G19,Data_Prices!$A:$A,0))*M$37 -> 0.61180975 | N19: =N9+INDEX(Data_Prices!N:N,MATCH($G19,Data_Prices!$A:$A,0))*N$37 -> 0.6035831 | O19: =O9+INDEX(Data_Prices!O:O,MATCH($G19,Data_Prices!$A:$A,0))*O$37 -> 0.6035831 | P19: =P9+INDEX(Data_Prices!P:P,MATCH($G19,Data_Prices!$A:$A,0))*P$37 -> 0.6035831 | Q19: =Q9+INDEX(Data_Prices!Q:Q,MATCH($G19,Data_Prices!$A:$A,0))*Q$37 -> 0.6035831 | R19: =R9+INDEX(Data_Prices!R:R,MATCH($G19,Data_Prices!$A:$A,0))*R$37 -> 0.6035831 | S19: =S9+INDEX(Data_Prices!S:S,MATCH($G19,Data_Prices!$A:$A,0))*S$37 -> 0.6035831 | T19: =T9+INDEX(Data_Prices!T:T,MATCH($G19,Data_Prices!$A:$A,0))*T$37 -> 0.6035831 | U19: =U9+INDEX(Data_Prices!U:U,MATCH($G19,Data_Prices!$A:$A,0))*U$37 -> 0.6035831 | V19: =V9+INDEX(Data_Prices!V:V,MATCH($G19,Data_Prices!$A:$A,0))*V$37 -> 0.6035831 | W19: =W9+INDEX(Data_Prices!W:W,MATCH($G19,Data_Prices!$A:$A,0))*W$37 -> 0.6035831 | X19: =X9+INDEX(Data_Prices!X:X,MATCH($G19,Data_Prices!$A:$A,0))*X$37 -> 0.6035831 | Y19: =Y9+INDEX(Data_Prices!Y:Y,MATCH($G19,Data_Prices!$A:$A,0))*Y$37 -> 0.6035831 | Z19: =Z9+INDEX(Data_Prices!Z:Z,MATCH($G19,Data_Prices!$A:$A,0))*Z$37 -> 0.6035831 | AA19: =AA9+INDEX(Data_Prices!AA:AA,MATCH($G19,Data_Prices!$A:$A,0))*AA$37 -> 0.6035831 | AB19: =AB9+INDEX(Data_Prices!AB:AB,MATCH($G19,Data_Prices!$A:$A,0))*AB$37 -> 0.6035831 | AC19: =AC9+INDEX(Data_Prices!AC:AC,MATCH($G19,Data_Prices!$A:$A,0))*AC$37 -> 0.6035831 | AD19: =AD9+INDEX(Data_Prices!AD:AD,MATCH($G19,Data_Prices!$A:$A,0))*AD$37 -> 0.6035831 | AE19: =AE9+INDEX(Data_Prices!AE:AE,MATCH($G19,Data_Prices!$A:$A,0))*AE$37 -> 0.6035831
B20: die | C20: =$C$5 -> irn | D20: Diesel | E20: $/liter | F20: atp | G20: =Settings!$B$3&".mit.nce."&Settings!$B$4&"."&$B20&".a."&$J$5 -> egy.mit.nce.ind.die.a.1 | H20: =Settings!$B$3&".mit.atp."&$C$5&"."&$B20&".e."&$J$5 -> egy.mit.atp.irn.die.e.1 | K20: =K10+INDEX(Data_Prices!K:K,MATCH($G20,Data_Prices!$A:$A,0))*K$37 -> 0.55971121 | L20: =L10+INDEX(Data_Prices!L:L,MATCH($G20,Data_Prices!$A:$A,0))*L$37 -> 0.49458873 | M20: =M10+INDEX(Data_Prices!M:M,MATCH($G20,Data_Prices!$A:$A,0))*M$37 -> 0.50778655 | N20: =N10+INDEX(Data_Prices!N:N,MATCH($G20,Data_Prices!$A:$A,0))*N$37 -> 0.47043643 | O20: =O10+INDEX(Data_Prices!O:O,MATCH($G20,Data_Prices!$A:$A,0))*O$37 -> 0.47043643 | P20: =P10+INDEX(Data_Prices!P:P,MATCH($G20,Data_Prices!$A:$A,0))*P$37 -> 0.47043643 | Q20: =Q10+INDEX(Data_Prices!Q:Q,MATCH($G20,Data_Prices!$A:$A,0))*Q$37 -> 0.47043643 | R20: =R10+INDEX(Data_Prices!R:R,MATCH($G20,Data_Prices!$A:$A,0))*R$37 -> 0.47043643 | S20: =S10+INDEX(Data_Prices!S:S,MATCH($G20,Data_Prices!$A:$A,0))*S$37 -> 0.47043643 | T20: =T10+INDEX(Data_Prices!T:T,MATCH($G20,Data_Prices!$A:$A,0))*T$37 -> 0.47043643 | U20: =U10+INDEX(Data_Prices!U:U,MATCH($G20,Data_Prices!$A:$A,0))*U$37 -> 0.47043643 | V20: =V10+INDEX(Data_Prices!V:V,MATCH($G20,Data_Prices!$A:$A,0))*V$37 -> 0.47043643 | W20: =W10+INDEX(Data_Prices!W:W,MATCH($G20,Data_Prices!$A:$A,0))*W$37 -> 0.47043643 | X20: =X10+INDEX(Data_Prices!X:X,MATCH($G20,Data_Prices!$A:$A,0))*X$37 -> 0.47043643 | Y20: =Y10+INDEX(Data_Prices!Y:Y,MATCH($G20,Data_Prices!$A:$A,0))*Y$37 -> 0.47043643 | Z20: =Z10+INDEX(Data_Prices!Z:Z,MATCH($G20,Data_Prices!$A:$A,0))*Z$37 -> 0.47043643 | AA20: =AA10+INDEX(Data_Prices!AA:AA,MATCH($G20,Data_Prices!$A:$A,0))*AA$37 -> 0.47043643 | AB20: =AB10+INDEX(Data_Prices!AB:AB,MATCH($G20,Data_Prices!$A:$A,0))*AB$37 -> 0.47043643 | AC20: =AC10+INDEX(Data_Prices!AC:AC,MATCH($G20,Data_Prices!$A:$A,0))*AC$37 -> 0.47043643 | AD20: =AD10+INDEX(Data_Prices!AD:AD,MATCH($G20,Data_Prices!$A:$A,0))*AD$37 -> 0.47043643 | AE20: =AE10+INDEX(Data_Prices!AE:AE,MATCH($G20,Data_Prices!$A:$A,0))*AE$37 -> 0.47043643
B21: lpg | C21: =$C$5 -> irn | D21: LPG | E21: $/liter | F21: atp | G21: =Settings!$B$3&".mit.nce."&Settings!$B$4&"."&$B21&".a."&$J$5 -> egy.mit.nce.ind.lpg.a.1 | H21: =Settings!$B$3&".mit.atp."&$C$5&"."&$B21&".e."&$J$5 -> egy.mit.atp.irn.lpg.e.1 | K21: =K11+INDEX(Data_Prices!K:K,MATCH($G21,Data_Prices!$A:$A,0))*K$37 -> 0.20036669 | L21: =L11+INDEX(Data_Prices!L:L,MATCH($G21,Data_Prices!$A:$A,0))*L$37 -> 0.15734474 | M21: =M11+INDEX(Data_Prices!M:M,MATCH($G21,Data_Prices!$A:$A,0))*M$37 -> 0.16448404 | N21: =N11+INDEX(Data_Prices!N:N,MATCH($G21,Data_Prices!$A:$A,0))*N$37 -> 0.15070908 | O21: =O11+INDEX(Data_Prices!O:O,MATCH($G21,Data_Prices!$A:$A,0))*O$37 -> 0.15070908 | P21: =P11+INDEX(Data_Prices!P:P,MATCH($G21,Data_Prices!$A:$A,0))*P$37 -> 0.15070908 | Q21: =Q11+INDEX(Data_Prices!Q:Q,MATCH($G21,Data_Prices!$A:$A,0))*Q$37 -> 0.15070908 | R21: =R11+INDEX(Data_Prices!R:R,MATCH($G21,Data_Prices!$A:$A,0))*R$37 -> 0.15070908 | S21: =S11+INDEX(Data_Prices!S:S,MATCH($G21,Data_Prices!$A:$A,0))*S$37 -> 0.15070908 | T21: =T11+INDEX(Data_Prices!T:T,MATCH($G21,Data_Prices!$A:$A,0))*T$37 -> 0.15070908 | U21: =U11+INDEX(Data_Prices!U:U,MATCH($G21,Data_Prices!$A:$A,0))*U$37 -> 0.15070908 | V21: =V11+INDEX(Data_Prices!V:V,MATCH($G21,Data_Prices!$A:$A,0))*V$37 -> 0.15070908 | W21: =W11+INDEX(Data_Prices!W:W,MATCH($G21,Data_Prices!$A:$A,0))*W$37 -> 0.15070908 | X21: =X11+INDEX(Data_Prices!X:X,MATCH($G21,Data_Prices!$A:$A,0))*X$37 -> 0.15070908 | Y21: =Y11+INDEX(Data_Prices!Y:Y,MATCH($G21,Data_Prices!$A:$A,0))*Y$37 -> 0.15070908 | Z21: =Z11+INDEX(Data_Prices!Z:Z,MATCH($G21,Data_Prices!$A:$A,0))*Z$37 -> 0.15070908 | AA21: =AA11+INDEX(Data_Prices!AA:AA,MATCH($G21,Data_Prices!$A:$A,0))*AA$37 -> 0.15070908 | AB21: =AB11+INDEX(Data_Prices!AB:AB,MATCH($G21,Data_Prices!$A:$A,0))*AB$37 -> 0.15070908 | AC21: =AC11+INDEX(Data_Prices!AC:AC,MATCH($G21,Data_Prices!$A:$A,0))*AC$37 -> 0.15070908 | AD21: =AD11+INDEX(Data_Prices!AD:AD,MATCH($G21,Data_Prices!$A:$A,0))*AD$37 -> 0.15070908 | AE21: =AE11+INDEX(Data_Prices!AE:AE,MATCH($G21,Data_Prices!$A:$A,0))*AE$37 -> 0.15070908
B22: ker | C22: =$C$5 -> irn | D22: Kerosene | E22: $/liter | F22: atp | G22: =Settings!$B$3&".mit.nce."&Settings!$B$4&"."&$B22&".a."&$J$5 -> egy.mit.nce.ind.ker.a.1 | H22: =Settings!$B$3&".mit.atp."&$C$5&"."&$B22&".e."&$J$5 -> egy.mit.atp.irn.ker.e.1 | K22: =K12+INDEX(Data_Prices!K:K,MATCH($G22,Data_Prices!$A:$A,0))*K$37 -> 0.48429424 | L22: =L12+INDEX(Data_Prices!L:L,MATCH($G22,Data_Prices!$A:$A,0))*L$37 -> 0.45642817 | M22: =M12+INDEX(Data_Prices!M:M,MATCH($G22,Data_Prices!$A:$A,0))*M$37 -> 0.4316892 | N22: =N12+INDEX(Data_Prices!N:N,MATCH($G22,Data_Prices!$A:$A,0))*N$37 -> 0.42507558 | O22: =O12+INDEX(Data_Prices!O:O,MATCH($G22,Data_Prices!$A:$A,0))*O$37 -> 0.42507558 | P22: =P12+INDEX(Data_Prices!P:P,MATCH($G22,Data_Prices!$A:$A,0))*P$37 -> 0.42507558 | Q22: =Q12+INDEX(Data_Prices!Q:Q,MATCH($G22,Data_Prices!$A:$A,0))*Q$37 -> 0.42507558 | R22: =R12+INDEX(Data_Prices!R:R,MATCH($G22,Data_Prices!$A:$A,0))*R$37 -> 0.42507558 | S22: =S12+INDEX(Data_Prices!S:S,MATCH($G22,Data_Prices!$A:$A,0))*S$37 -> 0.42507558 | T22: =T12+INDEX(Data_Prices!T:T,MATCH($G22,Data_Prices!$A:$A,0))*T$37 -> 0.42507558 | U22: =U12+INDEX(Data_Prices!U:U,MATCH($G22,Data_Prices!$A:$A,0))*U$37 -> 0.42507558 | V22: =V12+INDEX(Data_Prices!V:V,MATCH($G22,Data_Prices!$A:$A,0))*V$37 -> 0.42507558 | W22: =W12+INDEX(Data_Prices!W:W,MATCH($G22,Data_Prices!$A:$A,0))*W$37 -> 0.42507558 | X22: =X12+INDEX(Data_Prices!X:X,MATCH($G22,Data_Prices!$A:$A,0))*X$37 -> 0.42507558 | Y22: =Y12+INDEX(Data_Prices!Y:Y,MATCH($G22,Data_Prices!$A:$A,0))*Y$37 -> 0.42507558 | Z22: =Z12+INDEX(Data_Prices!Z:Z,MATCH($G22,Data_Prices!$A:$A,0))*Z$37 -> 0.42507558 | AA22: =AA12+INDEX(Data_Prices!AA:AA,MATCH($G22,Data_Prices!$A:$A,0))*AA$37 -> 0.42507558 | AB22: =AB12+INDEX(Data_Prices!AB:AB,MATCH($G22,Data_Prices!$A:$A,0))*AB$37 -> 0.42507558 | AC22: =AC12+INDEX(Data_Prices!AC:AC,MATCH($G22,Data_Prices!$A:$A,0))*AC$37 -> 0.42507558 | AD22: =AD12+INDEX(Data_Prices!AD:AD,MATCH($G22,Data_Prices!$A:$A,0))*AD$37 -> 0.42507558 | AE22: =AE12+INDEX(Data_Prices!AE:AE,MATCH($G22,Data_Prices!$A:$A,0))*AE$37 -> 0.42507558
B23: oop | C23: =$C$5 -> irn | D23: Other oil products | E23: $/bbl | F23: atp | G23: =Settings!$B$3&".mit.nce."&Settings!$B$4&"."&$B23&".a."&$J$5 -> egy.mit.nce.ind.oop.a.1 | H23: =Settings!$B$3&".mit.atp."&$C$5&"."&$B23&".e."&$J$5 -> egy.mit.atp.irn.oop.e.1 | K23: =K13+INDEX(Data_Prices!K:K,MATCH($G23,Data_Prices!$A:$A,0))*K$37 -> 41.500338 | L23: =L13+INDEX(Data_Prices!L:L,MATCH($G23,Data_Prices!$A:$A,0))*L$37 -> 34.41537 | M23: =M13+INDEX(Data_Prices!M:M,MATCH($G23,Data_Prices!$A:$A,0))*M$37 -> 37.368961 | N23: =N13+INDEX(Data_Prices!N:N,MATCH($G23,Data_Prices!$A:$A,0))*N$37 -> 28.982761 | O23: =O13+INDEX(Data_Prices!O:O,MATCH($G23,Data_Prices!$A:$A,0))*O$37 -> 15 | P23: =P13+INDEX(Data_Prices!P:P,MATCH($G23,Data_Prices!$A:$A,0))*P$37 -> 24.25863 | Q23: =Q13+INDEX(Data_Prices!Q:Q,MATCH($G23,Data_Prices!$A:$A,0))*Q$37 -> 15 | R23: =R13+INDEX(Data_Prices!R:R,MATCH($G23,Data_Prices!$A:$A,0))*R$37 -> 15 | S23: =S13+INDEX(Data_Prices!S:S,MATCH($G23,Data_Prices!$A:$A,0))*S$37 -> 15 | T23: =T13+INDEX(Data_Prices!T:T,MATCH($G23,Data_Prices!$A:$A,0))*T$37 -> 15 | U23: =U13+INDEX(Data_Prices!U:U,MATCH($G23,Data_Prices!$A:$A,0))*U$37 -> 15 | V23: =V13+INDEX(Data_Prices!V:V,MATCH($G23,Data_Prices!$A:$A,0))*V$37 -> 15 | W23: =W13+INDEX(Data_Prices!W:W,MATCH($G23,Data_Prices!$A:$A,0))*W$37 -> 15 | X23: =X13+INDEX(Data_Prices!X:X,MATCH($G23,Data_Prices!$A:$A,0))*X$37 -> 15 | Y23: =Y13+INDEX(Data_Prices!Y:Y,MATCH($G23,Data_Prices!$A:$A,0))*Y$37 -> 15 | Z23: =Z13+INDEX(Data_Prices!Z:Z,MATCH($G23,Data_Prices!$A:$A,0))*Z$37 -> 15 | AA23: =AA13+INDEX(Data_Prices!AA:AA,MATCH($G23,Data_Prices!$A:$A,0))*AA$37 -> 15 | AB23: =AB13+INDEX(Data_Prices!AB:AB,MATCH($G23,Data_Prices!$A:$A,0))*AB$37 -> 15 | AC23: =AC13+INDEX(Data_Prices!AC:AC,MATCH($G23,Data_Prices!$A:$A,0))*AC$37 -> 15 | AD23: =AD13+INDEX(Data_Prices!AD:AD,MATCH($G23,Data_Prices!$A:$A,0))*AD$37 -> 15 | AE23: =AE13+INDEX(Data_Prices!AE:AE,MATCH($G23,Data_Prices!$A:$A,0))*AE$37 -> 15
B24: bio | C24: =$C$5 -> irn | D24: Biomass | E24: $/GJ | F24: atp | G24: =Settings!$B$3&".mit.nce."&Settings!$B$4&"."&$B24&".a."&$J$5 -> egy.mit.nce.ind.bio.a.1 | H24: =Settings!$B$3&".mit.atp."&$C$5&"."&$B24&".e."&$J$5 -> egy.mit.atp.irn.bio.e.1 | K24: =K14+INDEX(Data_Prices!K:K,MATCH($G24,Data_Prices!$A:$A,0))*K$37 -> 15.334551 | L24: =L14+INDEX(Data_Prices!L:L,MATCH($G24,Data_Prices!$A:$A,0))*L$37 -> 14.199528 | M24: =M14+INDEX(Data_Prices!M:M,MATCH($G24,Data_Prices!$A:$A,0))*M$37 -> 13.840442 | N24: =N14+INDEX(Data_Prices!N:N,MATCH($G24,Data_Prices!$A:$A,0))*N$37 -> 13.567727 | O24: =O14+INDEX(Data_Prices!O:O,MATCH($G24,Data_Prices!$A:$A,0))*O$37 -> 13.567727 | P24: =P14+INDEX(Data_Prices!P:P,MATCH($G24,Data_Prices!$A:$A,0))*P$37 -> 13.567727 | Q24: =Q14+INDEX(Data_Prices!Q:Q,MATCH($G24,Data_Prices!$A:$A,0))*Q$37 -> 13.567727 | R24: =R14+INDEX(Data_Prices!R:R,MATCH($G24,Data_Prices!$A:$A,0))*R$37 -> 13.567727 | S24: =S14+INDEX(Data_Prices!S:S,MATCH($G24,Data_Prices!$A:$A,0))*S$37 -> 13.567727 | T24: =T14+INDEX(Data_Prices!T:T,MATCH($G24,Data_Prices!$A:$A,0))*T$37 -> 13.567727 | U24: =U14+INDEX(Data_Prices!U:U,MATCH($G24,Data_Prices!$A:$A,0))*U$37 -> 13.567727 | V24: =V14+INDEX(Data_Prices!V:V,MATCH($G24,Data_Prices!$A:$A,0))*V$37 -> 13.567727 | W24: =W14+INDEX(Data_Prices!W:W,MATCH($G24,Data_Prices!$A:$A,0))*W$37 -> 13.567727 | X24: =X14+INDEX(Data_Prices!X:X,MATCH($G24,Data_Prices!$A:$A,0))*X$37 -> 13.567727 | Y24: =Y14+INDEX(Data_Prices!Y:Y,MATCH($G24,Data_Prices!$A:$A,0))*Y$37 -> 13.567727 | Z24: =Z14+INDEX(Data_Prices!Z:Z,MATCH($G24,Data_Prices!$A:$A,0))*Z$37 -> 13.567727 | AA24: =AA14+INDEX(Data_Prices!AA:AA,MATCH($G24,Data_Prices!$A:$A,0))*AA$37 -> 13.567727 | AB24: =AB14+INDEX(Data_Prices!AB:AB,MATCH($G24,Data_Prices!$A:$A,0))*AB$37 -> 13.567727 | AC24: =AC14+INDEX(Data_Prices!AC:AC,MATCH($G24,Data_Prices!$A:$A,0))*AC$37 -> 13.567727 | AD24: =AD14+INDEX(Data_Prices!AD:AD,MATCH($G24,Data_Prices!$A:$A,0))*AD$37 -> 13.567727 | AE24: =AE14+INDEX(Data_Prices!AE:AE,MATCH($G24,Data_Prices!$A:$A,0))*AE$37 -> 13.567727
B25: ren | C25: =$C$5 -> irn | D25: Self-generated renewables | E25: $/kwh | F25: atp | G25: =Settings!$B$3&".mit.nce."&Settings!$B$4&"."&$B25&".a."&$J$5 -> egy.mit.nce.ind.ren.a.1 | H25: =Settings!$B$3&".mit.atp."&$C$5&"."&$B25&".e."&$J$5 -> egy.mit.atp.irn.ren.e.1 | K25: =K15+INDEX(Data_Prices!K:K,MATCH($G25,Data_Prices!$A:$A,0))*K$37 -> 0 | L25: =L15+INDEX(Data_Prices!L:L,MATCH($G25,Data_Prices!$A:$A,0))*L$37 -> 0.14404499 | M25: =M15+INDEX(Data_Prices!M:M,MATCH($G25,Data_Prices!$A:$A,0))*M$37 -> 0.14102041 | N25: =N15+INDEX(Data_Prices!N:N,MATCH($G25,Data_Prices!$A:$A,0))*N$37 -> 0.13511636 | O25: =O15+INDEX(Data_Prices!O:O,MATCH($G25,Data_Prices!$A:$A,0))*O$37 -> 0.13098826 | P25: =P15+INDEX(Data_Prices!P:P,MATCH($G25,Data_Prices!$A:$A,0))*P$37 -> 0.12790842 | Q25: =Q15+INDEX(Data_Prices!Q:Q,MATCH($G25,Data_Prices!$A:$A,0))*Q$37 -> 0.12481431 | R25: =R15+INDEX(Data_Prices!R:R,MATCH($G25,Data_Prices!$A:$A,0))*R$37 -> 0.12146026 | S25: =S15+INDEX(Data_Prices!S:S,MATCH($G25,Data_Prices!$A:$A,0))*S$37 -> 0.11795074 | T25: =T15+INDEX(Data_Prices!T:T,MATCH($G25,Data_Prices!$A:$A,0))*T$37 -> 0.11419916 | U25: =U15+INDEX(Data_Prices!U:U,MATCH($G25,Data_Prices!$A:$A,0))*U$37 -> 0.1136651 | V25: =V15+INDEX(Data_Prices!V:V,MATCH($G25,Data_Prices!$A:$A,0))*V$37 -> 0.11301693 | W25: =W15+INDEX(Data_Prices!W:W,MATCH($G25,Data_Prices!$A:$A,0))*W$37 -> 0.11231407 | X25: =X15+INDEX(Data_Prices!X:X,MATCH($G25,Data_Prices!$A:$A,0))*X$37 -> 0.11142204 | Y25: =Y15+INDEX(Data_Prices!Y:Y,MATCH($G25,Data_Prices!$A:$A,0))*Y$37 -> 0.11043412 | Z25: =Z15+INDEX(Data_Prices!Z:Z,MATCH($G25,Data_Prices!$A:$A,0))*Z$37 -> 0.10948397 | AA25: =AA15+INDEX(Data_Prices!AA:AA,MATCH($G25,Data_Prices!$A:$A,0))*AA$37 -> 0.10839192 | AB25: =AB15+INDEX(Data_Prices!AB:AB,MATCH($G25,Data_Prices!$A:$A,0))*AB$37 -> 0.10735443 | AC25: =AC15+INDEX(Data_Prices!AC:AC,MATCH($G25,Data_Prices!$A:$A,0))*AC$37 -> 0.10516868 | AD25: =AD15+INDEX(Data_Prices!AD:AD,MATCH($G25,Data_Prices!$A:$A,0))*AD$37 -> 0.10305798 | AE25: =AE15+INDEX(Data_Prices!AE:AE,MATCH($G25,Data_Prices!$A:$A,0))*AE$37 -> 0.10093184
B26: Shadow price: post-tax + shadow price of non-price policies x share acting on efficiency
B27: coa | C27: =$C$5 -> irn | D27: Coal | E27: $/GJ | F27: shp | G27: =Settings!$B$3&".mit.shp."&$B27&"."&Settings!$B$4&"."&$J$5 -> egy.mit.shp.coa.ind.1 | H27: =Settings!$B$3&".mit.shp."&$C$5&"."&$B27&".e."&$J$5 -> egy.mit.shp.irn.coa.e.1 | K27: =K17+INDEX(Data_Prices!K:K,MATCH($G27,Data_Prices!$A:$A,0))*K$38 -> 11.182902 | L27: =L17+INDEX(Data_Prices!L:L,MATCH($G27,Data_Prices!$A:$A,0))*L$38 -> 10.523361 | M27: =M17+INDEX(Data_Prices!M:M,MATCH($G27,Data_Prices!$A:$A,0))*M$38 -> 10.299561 | N27: =N17+INDEX(Data_Prices!N:N,MATCH($G27,Data_Prices!$A:$A,0))*N$38 -> 9.5775284 | O27: =O17+INDEX(Data_Prices!O:O,MATCH($G27,Data_Prices!$A:$A,0))*O$38 -> 8.4854783 | P27: =P17+INDEX(Data_Prices!P:P,MATCH($G27,Data_Prices!$A:$A,0))*P$38 -> 9.0871922 | Q27: =Q17+INDEX(Data_Prices!Q:Q,MATCH($G27,Data_Prices!$A:$A,0))*Q$38 -> 9.2229237 | R27: =R17+INDEX(Data_Prices!R:R,MATCH($G27,Data_Prices!$A:$A,0))*R$38 -> 9.158565 | S27: =S17+INDEX(Data_Prices!S:S,MATCH($G27,Data_Prices!$A:$A,0))*S$38 -> 9.0895479 | T27: =T17+INDEX(Data_Prices!T:T,MATCH($G27,Data_Prices!$A:$A,0))*T$38 -> 9.0156817 | U27: =U17+INDEX(Data_Prices!U:U,MATCH($G27,Data_Prices!$A:$A,0))*U$38 -> 8.9443978 | V27: =V17+INDEX(Data_Prices!V:V,MATCH($G27,Data_Prices!$A:$A,0))*V$38 -> 8.9443978 | W27: =W17+INDEX(Data_Prices!W:W,MATCH($G27,Data_Prices!$A:$A,0))*W$38 -> 8.9443978 | X27: =X17+INDEX(Data_Prices!X:X,MATCH($G27,Data_Prices!$A:$A,0))*X$38 -> 8.9443978 | Y27: =Y17+INDEX(Data_Prices!Y:Y,MATCH($G27,Data_Prices!$A:$A,0))*Y$38 -> 8.9443978 | Z27: =Z17+INDEX(Data_Prices!Z:Z,MATCH($G27,Data_Prices!$A:$A,0))*Z$38 -> 8.9443978 | AA27: =AA17+INDEX(Data_Prices!AA:AA,MATCH($G27,Data_Prices!$A:$A,0))*AA$38 -> 8.9443978 | AB27: =AB17+INDEX(Data_Prices!AB:AB,MATCH($G27,Data_Prices!$A:$A,0))*AB$38 -> 8.9443978 | AC27: =AC17+INDEX(Data_Prices!AC:AC,MATCH($G27,Data_Prices!$A:$A,0))*AC$38 -> 8.9443978 | AD27: =AD17+INDEX(Data_Prices!AD:AD,MATCH($G27,Data_Prices!$A:$A,0))*AD$38 -> 8.9443978 | AE27: =AE17+INDEX(Data_Prices!AE:AE,MATCH($G27,Data_Prices!$A:$A,0))*AE$38 -> 8.9443978
B28: nga | C28: =$C$5 -> irn | D28: Natural gas | E28: $/GJ | F28: shp | G28: =Settings!$B$3&".mit.shp."&$B28&"."&Settings!$B$4&"."&$J$5 -> egy.mit.shp.nga.ind.1 | H28: =Settings!$B$3&".mit.shp."&$C$5&"."&$B28&".e."&$J$5 -> egy.mit.shp.irn.nga.e.1 | K28: =K18+INDEX(Data_Prices!K:K,MATCH($G28,Data_Prices!$A:$A,0))*K$38 -> 6.0634636 | L28: =L18+INDEX(Data_Prices!L:L,MATCH($G28,Data_Prices!$A:$A,0))*L$38 -> 5.4510151 | M28: =M18+INDEX(Data_Prices!M:M,MATCH($G28,Data_Prices!$A:$A,0))*M$38 -> 5.1193563 | N28: =N18+INDEX(Data_Prices!N:N,MATCH($G28,Data_Prices!$A:$A,0))*N$38 -> 5.0821846 | O28: =O18+INDEX(Data_Prices!O:O,MATCH($G28,Data_Prices!$A:$A,0))*O$38 -> 5.0821846 | P28: =P18+INDEX(Data_Prices!P:P,MATCH($G28,Data_Prices!$A:$A,0))*P$38 -> 5.0821846 | Q28: =Q18+INDEX(Data_Prices!Q:Q,MATCH($G28,Data_Prices!$A:$A,0))*Q$38 -> 5.0821846 | R28: =R18+INDEX(Data_Prices!R:R,MATCH($G28,Data_Prices!$A:$A,0))*R$38 -> 5.0821846 | S28: =S18+INDEX(Data_Prices!S:S,MATCH($G28,Data_Prices!$A:$A,0))*S$38 -> 5.0821846 | T28: =T18+INDEX(Data_Prices!T:T,MATCH($G28,Data_Prices!$A:$A,0))*T$38 -> 5.0821846 | U28: =U18+INDEX(Data_Prices!U:U,MATCH($G28,Data_Prices!$A:$A,0))*U$38 -> 5.0821846 | V28: =V18+INDEX(Data_Prices!V:V,MATCH($G28,Data_Prices!$A:$A,0))*V$38 -> 5.0821846 | W28: =W18+INDEX(Data_Prices!W:W,MATCH($G28,Data_Prices!$A:$A,0))*W$38 -> 5.0821846 | X28: =X18+INDEX(Data_Prices!X:X,MATCH($G28,Data_Prices!$A:$A,0))*X$38 -> 5.0821846 | Y28: =Y18+INDEX(Data_Prices!Y:Y,MATCH($G28,Data_Prices!$A:$A,0))*Y$38 -> 5.0821846 | Z28: =Z18+INDEX(Data_Prices!Z:Z,MATCH($G28,Data_Prices!$A:$A,0))*Z$38 -> 5.0821846 | AA28: =AA18+INDEX(Data_Prices!AA:AA,MATCH($G28,Data_Prices!$A:$A,0))*AA$38 -> 5.0821846 | AB28: =AB18+INDEX(Data_Prices!AB:AB,MATCH($G28,Data_Prices!$A:$A,0))*AB$38 -> 5.0821846 | AC28: =AC18+INDEX(Data_Prices!AC:AC,MATCH($G28,Data_Prices!$A:$A,0))*AC$38 -> 5.0821846 | AD28: =AD18+INDEX(Data_Prices!AD:AD,MATCH($G28,Data_Prices!$A:$A,0))*AD$38 -> 5.0821846 | AE28: =AE18+INDEX(Data_Prices!AE:AE,MATCH($G28,Data_Prices!$A:$A,0))*AE$38 -> 5.0821846
B29: gso | C29: =$C$5 -> irn | D29: Gasoline | E29: $/liter | F29: shp | G29: =Settings!$B$3&".mit.shp."&$B29&"."&Settings!$B$4&"."&$J$5 -> egy.mit.shp.gso.ind.1 | H29: =Settings!$B$3&".mit.shp."&$C$5&"."&$B29&".e."&$J$5 -> egy.mit.shp.irn.gso.e.1 | K29: =K19+INDEX(Data_Prices!K:K,MATCH($G29,Data_Prices!$A:$A,0))*K$38 -> 0.67114653 | L29: =L19+INDEX(Data_Prices!L:L,MATCH($G29,Data_Prices!$A:$A,0))*L$38 -> 0.61197798 | M29: =M19+INDEX(Data_Prices!M:M,MATCH($G29,Data_Prices!$A:$A,0))*M$38 -> 0.61180975 | N29: =N19+INDEX(Data_Prices!N:N,MATCH($G29,Data_Prices!$A:$A,0))*N$38 -> 0.6035831 | O29: =O19+INDEX(Data_Prices!O:O,MATCH($G29,Data_Prices!$A:$A,0))*O$38 -> 0.6035831 | P29: =P19+INDEX(Data_Prices!P:P,MATCH($G29,Data_Prices!$A:$A,0))*P$38 -> 0.6035831 | Q29: =Q19+INDEX(Data_Prices!Q:Q,MATCH($G29,Data_Prices!$A:$A,0))*Q$38 -> 0.6035831 | R29: =R19+INDEX(Data_Prices!R:R,MATCH($G29,Data_Prices!$A:$A,0))*R$38 -> 0.6035831 | S29: =S19+INDEX(Data_Prices!S:S,MATCH($G29,Data_Prices!$A:$A,0))*S$38 -> 0.6035831 | T29: =T19+INDEX(Data_Prices!T:T,MATCH($G29,Data_Prices!$A:$A,0))*T$38 -> 0.6035831 | U29: =U19+INDEX(Data_Prices!U:U,MATCH($G29,Data_Prices!$A:$A,0))*U$38 -> 0.6035831 | V29: =V19+INDEX(Data_Prices!V:V,MATCH($G29,Data_Prices!$A:$A,0))*V$38 -> 0.6035831 | W29: =W19+INDEX(Data_Prices!W:W,MATCH($G29,Data_Prices!$A:$A,0))*W$38 -> 0.6035831 | X29: =X19+INDEX(Data_Prices!X:X,MATCH($G29,Data_Prices!$A:$A,0))*X$38 -> 0.6035831 | Y29: =Y19+INDEX(Data_Prices!Y:Y,MATCH($G29,Data_Prices!$A:$A,0))*Y$38 -> 0.6035831 | Z29: =Z19+INDEX(Data_Prices!Z:Z,MATCH($G29,Data_Prices!$A:$A,0))*Z$38 -> 0.6035831 | AA29: =AA19+INDEX(Data_Prices!AA:AA,MATCH($G29,Data_Prices!$A:$A,0))*AA$38 -> 0.6035831 | AB29: =AB19+INDEX(Data_Prices!AB:AB,MATCH($G29,Data_Prices!$A:$A,0))*AB$38 -> 0.6035831 | AC29: =AC19+INDEX(Data_Prices!AC:AC,MATCH($G29,Data_Prices!$A:$A,0))*AC$38 -> 0.6035831 | AD29: =AD19+INDEX(Data_Prices!AD:AD,MATCH($G29,Data_Prices!$A:$A,0))*AD$38 -> 0.6035831 | AE29: =AE19+INDEX(Data_Prices!AE:AE,MATCH($G29,Data_Prices!$A:$A,0))*AE$38 -> 0.6035831
B30: die | C30: =$C$5 -> irn | D30: Diesel | E30: $/liter | F30: shp | G30: =Settings!$B$3&".mit.shp."&$B30&"."&Settings!$B$4&"."&$J$5 -> egy.mit.shp.die.ind.1 | H30: =Settings!$B$3&".mit.shp."&$C$5&"."&$B30&".e."&$J$5 -> egy.mit.shp.irn.die.e.1 | K30: =K20+INDEX(Data_Prices!K:K,MATCH($G30,Data_Prices!$A:$A,0))*K$38 -> 0.55971121 | L30: =L20+INDEX(Data_Prices!L:L,MATCH($G30,Data_Prices!$A:$A,0))*L$38 -> 0.49458873 | M30: =M20+INDEX(Data_Prices!M:M,MATCH($G30,Data_Prices!$A:$A,0))*M$38 -> 0.50778655 | N30: =N20+INDEX(Data_Prices!N:N,MATCH($G30,Data_Prices!$A:$A,0))*N$38 -> 0.47043643 | O30: =O20+INDEX(Data_Prices!O:O,MATCH($G30,Data_Prices!$A:$A,0))*O$38 -> 0.47043643 | P30: =P20+INDEX(Data_Prices!P:P,MATCH($G30,Data_Prices!$A:$A,0))*P$38 -> 0.47043643 | Q30: =Q20+INDEX(Data_Prices!Q:Q,MATCH($G30,Data_Prices!$A:$A,0))*Q$38 -> 0.47043643 | R30: =R20+INDEX(Data_Prices!R:R,MATCH($G30,Data_Prices!$A:$A,0))*R$38 -> 0.47043643 | S30: =S20+INDEX(Data_Prices!S:S,MATCH($G30,Data_Prices!$A:$A,0))*S$38 -> 0.47043643 | T30: =T20+INDEX(Data_Prices!T:T,MATCH($G30,Data_Prices!$A:$A,0))*T$38 -> 0.47043643 | U30: =U20+INDEX(Data_Prices!U:U,MATCH($G30,Data_Prices!$A:$A,0))*U$38 -> 0.47043643 | V30: =V20+INDEX(Data_Prices!V:V,MATCH($G30,Data_Prices!$A:$A,0))*V$38 -> 0.47043643 | W30: =W20+INDEX(Data_Prices!W:W,MATCH($G30,Data_Prices!$A:$A,0))*W$38 -> 0.47043643 | X30: =X20+INDEX(Data_Prices!X:X,MATCH($G30,Data_Prices!$A:$A,0))*X$38 -> 0.47043643 | Y30: =Y20+INDEX(Data_Prices!Y:Y,MATCH($G30,Data_Prices!$A:$A,0))*Y$38 -> 0.47043643 | Z30: =Z20+INDEX(Data_Prices!Z:Z,MATCH($G30,Data_Prices!$A:$A,0))*Z$38 -> 0.47043643 | AA30: =AA20+INDEX(Data_Prices!AA:AA,MATCH($G30,Data_Prices!$A:$A,0))*AA$38 -> 0.47043643 | AB30: =AB20+INDEX(Data_Prices!AB:AB,MATCH($G30,Data_Prices!$A:$A,0))*AB$38 -> 0.47043643 | AC30: =AC20+INDEX(Data_Prices!AC:AC,MATCH($G30,Data_Prices!$A:$A,0))*AC$38 -> 0.47043643 | AD30: =AD20+INDEX(Data_Prices!AD:AD,MATCH($G30,Data_Prices!$A:$A,0))*AD$38 -> 0.47043643 | AE30: =AE20+INDEX(Data_Prices!AE:AE,MATCH($G30,Data_Prices!$A:$A,0))*AE$38 -> 0.47043643
B31: lpg | C31: =$C$5 -> irn | D31: LPG | E31: $/liter | F31: shp | G31: =Settings!$B$3&".mit.shp."&$B31&"."&Settings!$B$4&"."&$J$5 -> egy.mit.shp.lpg.ind.1 | H31: =Settings!$B$3&".mit.shp."&$C$5&"."&$B31&".e."&$J$5 -> egy.mit.shp.irn.lpg.e.1 | K31: =K21+INDEX(Data_Prices!K:K,MATCH($G31,Data_Prices!$A:$A,0))*K$38 -> 0.20036669 | L31: =L21+INDEX(Data_Prices!L:L,MATCH($G31,Data_Prices!$A:$A,0))*L$38 -> 0.15734474 | M31: =M21+INDEX(Data_Prices!M:M,MATCH($G31,Data_Prices!$A:$A,0))*M$38 -> 0.16448404 | N31: =N21+INDEX(Data_Prices!N:N,MATCH($G31,Data_Prices!$A:$A,0))*N$38 -> 0.15070908 | O31: =O21+INDEX(Data_Prices!O:O,MATCH($G31,Data_Prices!$A:$A,0))*O$38 -> 0.15070908 | P31: =P21+INDEX(Data_Prices!P:P,MATCH($G31,Data_Prices!$A:$A,0))*P$38 -> 0.15070908 | Q31: =Q21+INDEX(Data_Prices!Q:Q,MATCH($G31,Data_Prices!$A:$A,0))*Q$38 -> 0.15070908 | R31: =R21+INDEX(Data_Prices!R:R,MATCH($G31,Data_Prices!$A:$A,0))*R$38 -> 0.15070908 | S31: =S21+INDEX(Data_Prices!S:S,MATCH($G31,Data_Prices!$A:$A,0))*S$38 -> 0.15070908 | T31: =T21+INDEX(Data_Prices!T:T,MATCH($G31,Data_Prices!$A:$A,0))*T$38 -> 0.15070908 | U31: =U21+INDEX(Data_Prices!U:U,MATCH($G31,Data_Prices!$A:$A,0))*U$38 -> 0.15070908 | V31: =V21+INDEX(Data_Prices!V:V,MATCH($G31,Data_Prices!$A:$A,0))*V$38 -> 0.15070908 | W31: =W21+INDEX(Data_Prices!W:W,MATCH($G31,Data_Prices!$A:$A,0))*W$38 -> 0.15070908 | X31: =X21+INDEX(Data_Prices!X:X,MATCH($G31,Data_Prices!$A:$A,0))*X$38 -> 0.15070908 | Y31: =Y21+INDEX(Data_Prices!Y:Y,MATCH($G31,Data_Prices!$A:$A,0))*Y$38 -> 0.15070908 | Z31: =Z21+INDEX(Data_Prices!Z:Z,MATCH($G31,Data_Prices!$A:$A,0))*Z$38 -> 0.15070908 | AA31: =AA21+INDEX(Data_Prices!AA:AA,MATCH($G31,Data_Prices!$A:$A,0))*AA$38 -> 0.15070908 | AB31: =AB21+INDEX(Data_Prices!AB:AB,MATCH($G31,Data_Prices!$A:$A,0))*AB$38 -> 0.15070908 | AC31: =AC21+INDEX(Data_Prices!AC:AC,MATCH($G31,Data_Prices!$A:$A,0))*AC$38 -> 0.15070908 | AD31: =AD21+INDEX(Data_Prices!AD:AD,MATCH($G31,Data_Prices!$A:$A,0))*AD$38 -> 0.15070908 | AE31: =AE21+INDEX(Data_Prices!AE:AE,MATCH($G31,Data_Prices!$A:$A,0))*AE$38 -> 0.15070908
B32: ker | C32: =$C$5 -> irn | D32: Kerosene | E32: $/liter | F32: shp | G32: =Settings!$B$3&".mit.shp."&$B32&"."&Settings!$B$4&"."&$J$5 -> egy.mit.shp.ker.ind.1 | H32: =Settings!$B$3&".mit.shp."&$C$5&"."&$B32&".e."&$J$5 -> egy.mit.shp.irn.ker.e.1 | K32: =K22+INDEX(Data_Prices!K:K,MATCH($G32,Data_Prices!$A:$A,0))*K$38 -> 0.48429424 | L32: =L22+INDEX(Data_Prices!L:L,MATCH($G32,Data_Prices!$A:$A,0))*L$38 -> 0.45642817 | M32: =M22+INDEX(Data_Prices!M:M,MATCH($G32,Data_Prices!$A:$A,0))*M$38 -> 0.4316892 | N32: =N22+INDEX(Data_Prices!N:N,MATCH($G32,Data_Prices!$A:$A,0))*N$38 -> 0.42507558 | O32: =O22+INDEX(Data_Prices!O:O,MATCH($G32,Data_Prices!$A:$A,0))*O$38 -> 0.42507558 | P32: =P22+INDEX(Data_Prices!P:P,MATCH($G32,Data_Prices!$A:$A,0))*P$38 -> 0.42507558 | Q32: =Q22+INDEX(Data_Prices!Q:Q,MATCH($G32,Data_Prices!$A:$A,0))*Q$38 -> 0.42507558 | R32: =R22+INDEX(Data_Prices!R:R,MATCH($G32,Data_Prices!$A:$A,0))*R$38 -> 0.42507558 | S32: =S22+INDEX(Data_Prices!S:S,MATCH($G32,Data_Prices!$A:$A,0))*S$38 -> 0.42507558 | T32: =T22+INDEX(Data_Prices!T:T,MATCH($G32,Data_Prices!$A:$A,0))*T$38 -> 0.42507558 | U32: =U22+INDEX(Data_Prices!U:U,MATCH($G32,Data_Prices!$A:$A,0))*U$38 -> 0.42507558 | V32: =V22+INDEX(Data_Prices!V:V,MATCH($G32,Data_Prices!$A:$A,0))*V$38 -> 0.42507558 | W32: =W22+INDEX(Data_Prices!W:W,MATCH($G32,Data_Prices!$A:$A,0))*W$38 -> 0.42507558 | X32: =X22+INDEX(Data_Prices!X:X,MATCH($G32,Data_Prices!$A:$A,0))*X$38 -> 0.42507558 | Y32: =Y22+INDEX(Data_Prices!Y:Y,MATCH($G32,Data_Prices!$A:$A,0))*Y$38 -> 0.42507558 | Z32: =Z22+INDEX(Data_Prices!Z:Z,MATCH($G32,Data_Prices!$A:$A,0))*Z$38 -> 0.42507558 | AA32: =AA22+INDEX(Data_Prices!AA:AA,MATCH($G32,Data_Prices!$A:$A,0))*AA$38 -> 0.42507558 | AB32: =AB22+INDEX(Data_Prices!AB:AB,MATCH($G32,Data_Prices!$A:$A,0))*AB$38 -> 0.42507558 | AC32: =AC22+INDEX(Data_Prices!AC:AC,MATCH($G32,Data_Prices!$A:$A,0))*AC$38 -> 0.42507558 | AD32: =AD22+INDEX(Data_Prices!AD:AD,MATCH($G32,Data_Prices!$A:$A,0))*AD$38 -> 0.42507558 | AE32: =AE22+INDEX(Data_Prices!AE:AE,MATCH($G32,Data_Prices!$A:$A,0))*AE$38 -> 0.42507558
B33: oop | C33: =$C$5 -> irn | D33: Other oil products | E33: $/bbl | F33: shp | G33: =Settings!$B$3&".mit.shp."&$B33&"."&Settings!$B$4&"."&$J$5 -> egy.mit.shp.oop.ind.1 | H33: =Settings!$B$3&".mit.shp."&$C$5&"."&$B33&".e."&$J$5 -> egy.mit.shp.irn.oop.e.1 | K33: =K23+INDEX(Data_Prices!K:K,MATCH($G33,Data_Prices!$A:$A,0))*K$38 -> 41.500338 | L33: =L23+INDEX(Data_Prices!L:L,MATCH($G33,Data_Prices!$A:$A,0))*L$38 -> 34.41537 | M33: =M23+INDEX(Data_Prices!M:M,MATCH($G33,Data_Prices!$A:$A,0))*M$38 -> 37.368961 | N33: =N23+INDEX(Data_Prices!N:N,MATCH($G33,Data_Prices!$A:$A,0))*N$38 -> 28.982761 | O33: =O23+INDEX(Data_Prices!O:O,MATCH($G33,Data_Prices!$A:$A,0))*O$38 -> 15 | P33: =P23+INDEX(Data_Prices!P:P,MATCH($G33,Data_Prices!$A:$A,0))*P$38 -> 24.25863 | Q33: =Q23+INDEX(Data_Prices!Q:Q,MATCH($G33,Data_Prices!$A:$A,0))*Q$38 -> 15 | R33: =R23+INDEX(Data_Prices!R:R,MATCH($G33,Data_Prices!$A:$A,0))*R$38 -> 15 | S33: =S23+INDEX(Data_Prices!S:S,MATCH($G33,Data_Prices!$A:$A,0))*S$38 -> 15 | T33: =T23+INDEX(Data_Prices!T:T,MATCH($G33,Data_Prices!$A:$A,0))*T$38 -> 15 | U33: =U23+INDEX(Data_Prices!U:U,MATCH($G33,Data_Prices!$A:$A,0))*U$38 -> 15 | V33: =V23+INDEX(Data_Prices!V:V,MATCH($G33,Data_Prices!$A:$A,0))*V$38 -> 15 | W33: =W23+INDEX(Data_Prices!W:W,MATCH($G33,Data_Prices!$A:$A,0))*W$38 -> 15 | X33: =X23+INDEX(Data_Prices!X:X,MATCH($G33,Data_Prices!$A:$A,0))*X$38 -> 15 | Y33: =Y23+INDEX(Data_Prices!Y:Y,MATCH($G33,Data_Prices!$A:$A,0))*Y$38 -> 15 | Z33: =Z23+INDEX(Data_Prices!Z:Z,MATCH($G33,Data_Prices!$A:$A,0))*Z$38 -> 15 | AA33: =AA23+INDEX(Data_Prices!AA:AA,MATCH($G33,Data_Prices!$A:$A,0))*AA$38 -> 15 | AB33: =AB23+INDEX(Data_Prices!AB:AB,MATCH($G33,Data_Prices!$A:$A,0))*AB$38 -> 15 | AC33: =AC23+INDEX(Data_Prices!AC:AC,MATCH($G33,Data_Prices!$A:$A,0))*AC$38 -> 15 | AD33: =AD23+INDEX(Data_Prices!AD:AD,MATCH($G33,Data_Prices!$A:$A,0))*AD$38 -> 15 | AE33: =AE23+INDEX(Data_Prices!AE:AE,MATCH($G33,Data_Prices!$A:$A,0))*AE$38 -> 15
B34: bio | C34: =$C$5 -> irn | D34: Biomass | E34: $/GJ | F34: shp | G34: =Settings!$B$3&".mit.shp."&$B34&"."&Settings!$B$4&"."&$J$5 -> egy.mit.shp.bio.ind.1 | H34: =Settings!$B$3&".mit.shp."&$C$5&"."&$B34&".e."&$J$5 -> egy.mit.shp.irn.bio.e.1 | K34: =K24+INDEX(Data_Prices!K:K,MATCH($G34,Data_Prices!$A:$A,0))*K$38 -> 15.334551 | L34: =L24+INDEX(Data_Prices!L:L,MATCH($G34,Data_Prices!$A:$A,0))*L$38 -> 14.199528 | M34: =M24+INDEX(Data_Prices!M:M,MATCH($G34,Data_Prices!$A:$A,0))*M$38 -> 13.840442 | N34: =N24+INDEX(Data_Prices!N:N,MATCH($G34,Data_Prices!$A:$A,0))*N$38 -> 13.567727 | O34: =O24+INDEX(Data_Prices!O:O,MATCH($G34,Data_Prices!$A:$A,0))*O$38 -> 13.567727 | P34: =P24+INDEX(Data_Prices!P:P,MATCH($G34,Data_Prices!$A:$A,0))*P$38 -> 13.567727 | Q34: =Q24+INDEX(Data_Prices!Q:Q,MATCH($G34,Data_Prices!$A:$A,0))*Q$38 -> 13.567727 | R34: =R24+INDEX(Data_Prices!R:R,MATCH($G34,Data_Prices!$A:$A,0))*R$38 -> 13.567727 | S34: =S24+INDEX(Data_Prices!S:S,MATCH($G34,Data_Prices!$A:$A,0))*S$38 -> 13.567727 | T34: =T24+INDEX(Data_Prices!T:T,MATCH($G34,Data_Prices!$A:$A,0))*T$38 -> 13.567727 | U34: =U24+INDEX(Data_Prices!U:U,MATCH($G34,Data_Prices!$A:$A,0))*U$38 -> 13.567727 | V34: =V24+INDEX(Data_Prices!V:V,MATCH($G34,Data_Prices!$A:$A,0))*V$38 -> 13.567727 | W34: =W24+INDEX(Data_Prices!W:W,MATCH($G34,Data_Prices!$A:$A,0))*W$38 -> 13.567727 | X34: =X24+INDEX(Data_Prices!X:X,MATCH($G34,Data_Prices!$A:$A,0))*X$38 -> 13.567727 | Y34: =Y24+INDEX(Data_Prices!Y:Y,MATCH($G34,Data_Prices!$A:$A,0))*Y$38 -> 13.567727 | Z34: =Z24+INDEX(Data_Prices!Z:Z,MATCH($G34,Data_Prices!$A:$A,0))*Z$38 -> 13.567727 | AA34: =AA24+INDEX(Data_Prices!AA:AA,MATCH($G34,Data_Prices!$A:$A,0))*AA$38 -> 13.567727 | AB34: =AB24+INDEX(Data_Prices!AB:AB,MATCH($G34,Data_Prices!$A:$A,0))*AB$38 -> 13.567727 | AC34: =AC24+INDEX(Data_Prices!AC:AC,MATCH($G34,Data_Prices!$A:$A,0))*AC$38 -> 13.567727 | AD34: =AD24+INDEX(Data_Prices!AD:AD,MATCH($G34,Data_Prices!$A:$A,0))*AD$38 -> 13.567727 | AE34: =AE24+INDEX(Data_Prices!AE:AE,MATCH($G34,Data_Prices!$A:$A,0))*AE$38 -> 13.567727
B35: ren | C35: =$C$5 -> irn | D35: Self-generated renewables | E35: $/kwh | F35: shp | G35: =Settings!$B$3&".mit.shp."&$B35&"."&Settings!$B$4&"."&$J$5 -> egy.mit.shp.ren.ind.1 | H35: =Settings!$B$3&".mit.shp."&$C$5&"."&$B35&".e."&$J$5 -> egy.mit.shp.irn.ren.e.1 | K35: =K25+INDEX(Data_Prices!K:K,MATCH($G35,Data_Prices!$A:$A,0))*K$38 -> 0 | L35: =L25+INDEX(Data_Prices!L:L,MATCH($G35,Data_Prices!$A:$A,0))*L$38 -> 0.14404499 | M35: =M25+INDEX(Data_Prices!M:M,MATCH($G35,Data_Prices!$A:$A,0))*M$38 -> 0.14102041 | N35: =N25+INDEX(Data_Prices!N:N,MATCH($G35,Data_Prices!$A:$A,0))*N$38 -> 0.13511636 | O35: =O25+INDEX(Data_Prices!O:O,MATCH($G35,Data_Prices!$A:$A,0))*O$38 -> 0.13098826 | P35: =P25+INDEX(Data_Prices!P:P,MATCH($G35,Data_Prices!$A:$A,0))*P$38 -> 0.12790842 | Q35: =Q25+INDEX(Data_Prices!Q:Q,MATCH($G35,Data_Prices!$A:$A,0))*Q$38 -> 0.12481431 | R35: =R25+INDEX(Data_Prices!R:R,MATCH($G35,Data_Prices!$A:$A,0))*R$38 -> 0.12146026 | S35: =S25+INDEX(Data_Prices!S:S,MATCH($G35,Data_Prices!$A:$A,0))*S$38 -> 0.11795074 | T35: =T25+INDEX(Data_Prices!T:T,MATCH($G35,Data_Prices!$A:$A,0))*T$38 -> 0.11419916 | U35: =U25+INDEX(Data_Prices!U:U,MATCH($G35,Data_Prices!$A:$A,0))*U$38 -> 0.1136651 | V35: =V25+INDEX(Data_Prices!V:V,MATCH($G35,Data_Prices!$A:$A,0))*V$38 -> 0.11301693 | W35: =W25+INDEX(Data_Prices!W:W,MATCH($G35,Data_Prices!$A:$A,0))*W$38 -> 0.11231407 | X35: =X25+INDEX(Data_Prices!X:X,MATCH($G35,Data_Prices!$A:$A,0))*X$38 -> 0.11142204 | Y35: =Y25+INDEX(Data_Prices!Y:Y,MATCH($G35,Data_Prices!$A:$A,0))*Y$38 -> 0.11043412 | Z35: =Z25+INDEX(Data_Prices!Z:Z,MATCH($G35,Data_Prices!$A:$A,0))*Z$38 -> 0.10948397 | AA35: =AA25+INDEX(Data_Prices!AA:AA,MATCH($G35,Data_Prices!$A:$A,0))*AA$38 -> 0.10839192 | AB35: =AB25+INDEX(Data_Prices!AB:AB,MATCH($G35,Data_Prices!$A:$A,0))*AB$38 -> 0.10735443 | AC35: =AC25+INDEX(Data_Prices!AC:AC,MATCH($G35,Data_Prices!$A:$A,0))*AC$38 -> 0.10516868 | AD35: =AD25+INDEX(Data_Prices!AD:AD,MATCH($G35,Data_Prices!$A:$A,0))*AD$38 -> 0.10305798 | AE35: =AE25+INDEX(Data_Prices!AE:AE,MATCH($G35,Data_Prices!$A:$A,0))*AE$38 -> 0.10093184
B36: Sector policy and macro drivers
B37: - | C37: =$C$5 -> irn | D37: Sector coverage factor of the new-policy wedge | E37: share | F37: tcf | G37: =Settings!$B$3&".mit.tcf."&$C$5&"."&$J$5 -> egy.mit.tcf.irn.1 | K37: =INDEX(Data_Prices!K:K,MATCH($G37,Data_Prices!$A:$A,0)) -> 0 | L37: =INDEX(Data_Prices!L:L,MATCH($G37,Data_Prices!$A:$A,0)) -> 0 | M37: =INDEX(Data_Prices!M:M,MATCH($G37,Data_Prices!$A:$A,0)) -> 0 | N37: =INDEX(Data_Prices!N:N,MATCH($G37,Data_Prices!$A:$A,0)) -> 0 | O37: =INDEX(Data_Prices!O:O,MATCH($G37,Data_Prices!$A:$A,0)) -> 0 | P37: =INDEX(Data_Prices!P:P,MATCH($G37,Data_Prices!$A:$A,0)) -> 0 | Q37: =INDEX(Data_Prices!Q:Q,MATCH($G37,Data_Prices!$A:$A,0)) -> 0 | R37: =INDEX(Data_Prices!R:R,MATCH($G37,Data_Prices!$A:$A,0)) -> 0 | S37: =INDEX(Data_Prices!S:S,MATCH($G37,Data_Prices!$A:$A,0)) -> 0 | T37: =INDEX(Data_Prices!T:T,MATCH($G37,Data_Prices!$A:$A,0)) -> 0 | U37: =INDEX(Data_Prices!U:U,MATCH($G37,Data_Prices!$A:$A,0)) -> 0 | V37: =INDEX(Data_Prices!V:V,MATCH($G37,Data_Prices!$A:$A,0)) -> 0 | W37: =INDEX(Data_Prices!W:W,MATCH($G37,Data_Prices!$A:$A,0)) -> 0 | X37: =INDEX(Data_Prices!X:X,MATCH($G37,Data_Prices!$A:$A,0)) -> 0 | Y37: =INDEX(Data_Prices!Y:Y,MATCH($G37,Data_Prices!$A:$A,0)) -> 0 | Z37: =INDEX(Data_Prices!Z:Z,MATCH($G37,Data_Prices!$A:$A,0)) -> 0 | AA37: =INDEX(Data_Prices!AA:AA,MATCH($G37,Data_Prices!$A:$A,0)) -> 0 | AB37: =INDEX(Data_Prices!AB:AB,MATCH($G37,Data_Prices!$A:$A,0)) -> 0 | AC37: =INDEX(Data_Prices!AC:AC,MATCH($G37,Data_Prices!$A:$A,0)) -> 0 | AD37: =INDEX(Data_Prices!AD:AD,MATCH($G37,Data_Prices!$A:$A,0)) -> 0 | AE37: =INDEX(Data_Prices!AE:AE,MATCH($G37,Data_Prices!$A:$A,0)) -> 0
B38: - | C38: =$C$5 -> irn | D38: Share of shadow price acting on efficiency | E38: share | F38: ssc | G38: =Settings!$B$3&".mit.ssc."&$C$5&"."&$J$5 -> egy.mit.ssc.irn.1 | K38: =INDEX(Data_Prices!K:K,MATCH($G38,Data_Prices!$A:$A,0)) -> 0 | L38: =INDEX(Data_Prices!L:L,MATCH($G38,Data_Prices!$A:$A,0)) -> 0 | M38: =INDEX(Data_Prices!M:M,MATCH($G38,Data_Prices!$A:$A,0)) -> 0 | N38: =INDEX(Data_Prices!N:N,MATCH($G38,Data_Prices!$A:$A,0)) -> 0 | O38: =INDEX(Data_Prices!O:O,MATCH($G38,Data_Prices!$A:$A,0)) -> 0 | P38: =INDEX(Data_Prices!P:P,MATCH($G38,Data_Prices!$A:$A,0)) -> 0 | Q38: =INDEX(Data_Prices!Q:Q,MATCH($G38,Data_Prices!$A:$A,0)) -> 0 | R38: =INDEX(Data_Prices!R:R,MATCH($G38,Data_Prices!$A:$A,0)) -> 0 | S38: =INDEX(Data_Prices!S:S,MATCH($G38,Data_Prices!$A:$A,0)) -> 0 | T38: =INDEX(Data_Prices!T:T,MATCH($G38,Data_Prices!$A:$A,0)) -> 0 | U38: =INDEX(Data_Prices!U:U,MATCH($G38,Data_Prices!$A:$A,0)) -> 0 | V38: =INDEX(Data_Prices!V:V,MATCH($G38,Data_Prices!$A:$A,0)) -> 0 | W38: =INDEX(Data_Prices!W:W,MATCH($G38,Data_Prices!$A:$A,0)) -> 0 | X38: =INDEX(Data_Prices!X:X,MATCH($G38,Data_Prices!$A:$A,0)) -> 0 | Y38: =INDEX(Data_Prices!Y:Y,MATCH($G38,Data_Prices!$A:$A,0)) -> 0 | Z38: =INDEX(Data_Prices!Z:Z,MATCH($G38,Data_Prices!$A:$A,0)) -> 0 | AA38: =INDEX(Data_Prices!AA:AA,MATCH($G38,Data_Prices!$A:$A,0)) -> 0 | AB38: =INDEX(Data_Prices!AB:AB,MATCH($G38,Data_Prices!$A:$A,0)) -> 0 | AC38: =INDEX(Data_Prices!AC:AC,MATCH($G38,Data_Prices!$A:$A,0)) -> 0 | AD38: =INDEX(Data_Prices!AD:AD,MATCH($G38,Data_Prices!$A:$A,0)) -> 0 | AE38: =INDEX(Data_Prices!AE:AE,MATCH($G38,Data_Prices!$A:$A,0)) -> 0
B39: - | C39: =$C$5 -> irn | D39: Post-policy real GDP growth | E39: % | F39: g | G39: =Settings!$B$3&".mit.gdp.pos.pct."&$J$5 -> egy.mit.gdp.pos.pct.1 | K39: =INDEX(Data_Macro!K:K,MATCH($G39,Data_Macro!$A:$A,0)) -> 0 | L39: =INDEX(Data_Macro!L:L,MATCH($G39,Data_Macro!$A:$A,0)) -> 0.06651345 | M39: =INDEX(Data_Macro!M:M,MATCH($G39,Data_Macro!$A:$A,0)) -> 0.03760281 | N39: =INDEX(Data_Macro!N:N,MATCH($G39,Data_Macro!$A:$A,0)) -> 0.02398801 | O39: =INDEX(Data_Macro!O:O,MATCH($G39,Data_Macro!$A:$A,0)) -> 0.04392387 | P39: =INDEX(Data_Macro!P:P,MATCH($G39,Data_Macro!$A:$A,0)) -> 0.04239706 | Q39: =INDEX(Data_Macro!Q:Q,MATCH($G39,Data_Macro!$A:$A,0)) -> 0.04829218 | R39: =INDEX(Data_Macro!R:R,MATCH($G39,Data_Macro!$A:$A,0)) -> 0.05535316 | S39: =INDEX(Data_Macro!S:S,MATCH($G39,Data_Macro!$A:$A,0)) -> 0.05226606 | T39: =INDEX(Data_Macro!T:T,MATCH($G39,Data_Macro!$A:$A,0)) -> 0.04841877 | U39: =INDEX(Data_Macro!U:U,MATCH($G39,Data_Macro!$A:$A,0)) -> 0.04788736 | V39: =INDEX(Data_Macro!V:V,MATCH($G39,Data_Macro!$A:$A,0)) -> 0.04735595 | W39: =INDEX(Data_Macro!W:W,MATCH($G39,Data_Macro!$A:$A,0)) -> 0.04682454 | X39: =INDEX(Data_Macro!X:X,MATCH($G39,Data_Macro!$A:$A,0)) -> 0.04629313 | Y39: =INDEX(Data_Macro!Y:Y,MATCH($G39,Data_Macro!$A:$A,0)) -> 0.04576172 | Z39: =INDEX(Data_Macro!Z:Z,MATCH($G39,Data_Macro!$A:$A,0)) -> 0.04523031 | AA39: =INDEX(Data_Macro!AA:AA,MATCH($G39,Data_Macro!$A:$A,0)) -> 0.0446989 | AB39: =INDEX(Data_Macro!AB:AB,MATCH($G39,Data_Macro!$A:$A,0)) -> 0.04416749 | AC39: =INDEX(Data_Macro!AC:AC,MATCH($G39,Data_Macro!$A:$A,0)) -> 0.04363608 | AD39: =INDEX(Data_Macro!AD:AD,MATCH($G39,Data_Macro!$A:$A,0)) -> 0.04310467 | AE39: =INDEX(Data_Macro!AE:AE,MATCH($G39,Data_Macro!$A:$A,0)) -> 0.04257326
B40: - | C40: =$C$5 -> irn | D40: Income-elasticity discount factor | E40: ratio | F40: delta | G40: =Settings!$B$3&".mit.inc.ela.adj."&$J$5 -> egy.mit.inc.ela.adj.1 | K40: =INDEX(Data_Macro!K:K,MATCH($G40,Data_Macro!$A:$A,0)) -> 0 | L40: =INDEX(Data_Macro!L:L,MATCH($G40,Data_Macro!$A:$A,0)) -> 1.0271517 | M40: =INDEX(Data_Macro!M:M,MATCH($G40,Data_Macro!$A:$A,0)) -> 1.0271517 | N40: =INDEX(Data_Macro!N:N,MATCH($G40,Data_Macro!$A:$A,0)) -> 1.0205698 | O40: =INDEX(Data_Macro!O:O,MATCH($G40,Data_Macro!$A:$A,0)) -> 1.0173344 | P40: =INDEX(Data_Macro!P:P,MATCH($G40,Data_Macro!$A:$A,0)) -> 1.0076683 | Q40: =INDEX(Data_Macro!Q:Q,MATCH($G40,Data_Macro!$A:$A,0)) -> 1.0007443 | R40: =INDEX(Data_Macro!R:R,MATCH($G40,Data_Macro!$A:$A,0)) -> 0.99188649 | S40: =INDEX(Data_Macro!S:S,MATCH($G40,Data_Macro!$A:$A,0)) -> 0.9806554 | T40: =INDEX(Data_Macro!T:T,MATCH($G40,Data_Macro!$A:$A,0)) -> 0.9702094 | U40: =INDEX(Data_Macro!U:U,MATCH($G40,Data_Macro!$A:$A,0)) -> 0.96419266 | V40: =INDEX(Data_Macro!V:V,MATCH($G40,Data_Macro!$A:$A,0)) -> 0.96161287 | W40: =INDEX(Data_Macro!W:W,MATCH($G40,Data_Macro!$A:$A,0)) -> 0.95919845 | X40: =INDEX(Data_Macro!X:X,MATCH($G40,Data_Macro!$A:$A,0)) -> 0.95695125 | Y40: =INDEX(Data_Macro!Y:Y,MATCH($G40,Data_Macro!$A:$A,0)) -> 0.95487298 | Z40: =INDEX(Data_Macro!Z:Z,MATCH($G40,Data_Macro!$A:$A,0)) -> 0.95296514 | AA40: =INDEX(Data_Macro!AA:AA,MATCH($G40,Data_Macro!$A:$A,0)) -> 0.9512291 | AB40: =INDEX(Data_Macro!AB:AB,MATCH($G40,Data_Macro!$A:$A,0)) -> 0.94966609 | AC40: =INDEX(Data_Macro!AC:AC,MATCH($G40,Data_Macro!$A:$A,0)) -> 0.94827716 | AD40: =INDEX(Data_Macro!AD:AD,MATCH($G40,Data_Macro!$A:$A,0)) -> 0.94706328 | AE40: =INDEX(Data_Macro!AE:AE,MATCH($G40,Data_Macro!$A:$A,0)) -> 0.94602527
B41: - | C41: =$C$5 -> irn | D41: Exogenous shock on energy consumption | E41: ratio | F41: psi | G41: =Settings!$B$3&".mit.shock."&$J$5 -> egy.mit.shock.1 | K41: =INDEX(Data_Macro!K:K,MATCH($G41,Data_Macro!$A:$A,0)) -> 0 | L41: =INDEX(Data_Macro!L:L,MATCH($G41,Data_Macro!$A:$A,0)) -> 0 | M41: =INDEX(Data_Macro!M:M,MATCH($G41,Data_Macro!$A:$A,0)) -> -0.20813308 | N41: =INDEX(Data_Macro!N:N,MATCH($G41,Data_Macro!$A:$A,0)) -> 0.092371429 | O41: =INDEX(Data_Macro!O:O,MATCH($G41,Data_Macro!$A:$A,0)) -> 0 | P41: =INDEX(Data_Macro!P:P,MATCH($G41,Data_Macro!$A:$A,0)) -> 0 | Q41: =INDEX(Data_Macro!Q:Q,MATCH($G41,Data_Macro!$A:$A,0)) -> 0 | R41: =INDEX(Data_Macro!R:R,MATCH($G41,Data_Macro!$A:$A,0)) -> 0 | S41: =INDEX(Data_Macro!S:S,MATCH($G41,Data_Macro!$A:$A,0)) -> 0 | T41: =INDEX(Data_Macro!T:T,MATCH($G41,Data_Macro!$A:$A,0)) -> 0 | U41: =INDEX(Data_Macro!U:U,MATCH($G41,Data_Macro!$A:$A,0)) -> 0 | V41: =INDEX(Data_Macro!V:V,MATCH($G41,Data_Macro!$A:$A,0)) -> 0 | W41: =INDEX(Data_Macro!W:W,MATCH($G41,Data_Macro!$A:$A,0)) -> 0 | X41: =INDEX(Data_Macro!X:X,MATCH($G41,Data_Macro!$A:$A,0)) -> 0 | Y41: =INDEX(Data_Macro!Y:Y,MATCH($G41,Data_Macro!$A:$A,0)) -> 0 | Z41: =INDEX(Data_Macro!Z:Z,MATCH($G41,Data_Macro!$A:$A,0)) -> 0 | AA41: =INDEX(Data_Macro!AA:AA,MATCH($G41,Data_Macro!$A:$A,0)) -> 0 | AB41: =INDEX(Data_Macro!AB:AB,MATCH($G41,Data_Macro!$A:$A,0)) -> 0 | AC41: =INDEX(Data_Macro!AC:AC,MATCH($G41,Data_Macro!$A:$A,0)) -> 0 | AD41: =INDEX(Data_Macro!AD:AD,MATCH($G41,Data_Macro!$A:$A,0)) -> 0 | AE41: =INDEX(Data_Macro!AE:AE,MATCH($G41,Data_Macro!$A:$A,0)) -> 0
B42: Kernel parameters (looked up from Data_Elast; column = Settings elasticity group)
B43: Fuel | C43: Sector | D43: Description | E43: Income el. (eY) | F43: Usage el. (eU) | G43: Efficiency el. (eF) | H43: AEEI (a) | I43: Add. efficiency (a+) | J43: Elasticity fuel group
B44: coa | C44: =$C$5 -> irn | D44: Parameters: Coal | E44: =INDEX(Data_Elast!$D:$G,MATCH("el_inc_"&INDEX(Data_Elast!$J:$J,MATCH($B44,Data_Elast!$I:$I,0)),Data_Elast!$A:$A,0),MATCH(Settings!$B$5,Data_Elast!$D$1:$G$1,0)) -> 0.5 | F44: =INDEX(Data_Elast!$D:$G,MATCH("el_dem_"&INDEX(Data_Elast!$J:$J,MATCH($B44,Data_Elast!$I:$I,0)),Data_Elast!$A:$A,0),MATCH(Settings!$B$5,Data_Elast!$D$1:$G$1,0)) -> -0.3 | G44: =INDEX(Data_Elast!$D:$G,MATCH("el_eff_"&INDEX(Data_Elast!$J:$J,MATCH($B44,Data_Elast!$I:$I,0)),Data_Elast!$A:$A,0),MATCH(Settings!$B$5,Data_Elast!$D$1:$G$1,0)) -> -0.4 | H44: =INDEX(Data_Elast!$D:$G,MATCH("eff_imp_"&INDEX(Data_Elast!$K:$K,MATCH($B44,Data_Elast!$I:$I,0)),Data_Elast!$A:$A,0),MATCH(Settings!$B$5,Data_Elast!$D$1:$G$1,0)) -> 0.005 | I44: =Settings!$B$7 -> 0 | J44: =INDEX(Data_Elast!$J:$J,MATCH($B44,Data_Elast!$I:$I,0)) -> coa
B45: nga | C45: =$C$5 -> irn | D45: Parameters: Natural gas | E45: =INDEX(Data_Elast!$D:$G,MATCH("el_inc_"&INDEX(Data_Elast!$J:$J,MATCH($B45,Data_Elast!$I:$I,0)),Data_Elast!$A:$A,0),MATCH(Settings!$B$5,Data_Elast!$D$1:$G$1,0)) -> 1 | F45: =INDEX(Data_Elast!$D:$G,MATCH("el_dem_"&INDEX(Data_Elast!$J:$J,MATCH($B45,Data_Elast!$I:$I,0)),Data_Elast!$A:$A,0),MATCH(Settings!$B$5,Data_Elast!$D$1:$G$1,0)) -> -0.5 | G45: =INDEX(Data_Elast!$D:$G,MATCH("el_eff_"&INDEX(Data_Elast!$J:$J,MATCH($B45,Data_Elast!$I:$I,0)),Data_Elast!$A:$A,0),MATCH(Settings!$B$5,Data_Elast!$D$1:$G$1,0)) -> -0.5 | H45: =INDEX(Data_Elast!$D:$G,MATCH("eff_imp_"&INDEX(Data_Elast!$K:$K,MATCH($B45,Data_Elast!$I:$I,0)),Data_Elast!$A:$A,0),MATCH(Settings!$B$5,Data_Elast!$D$1:$G$1,0)) -> 0.01 | I45: =Settings!$B$7 -> 0 | J45: =INDEX(Data_Elast!$J:$J,MATCH($B45,Data_Elast!$I:$I,0)) -> nga
B46: gso | C46: =$C$5 -> irn | D46: Parameters: Gasoline | E46: =INDEX(Data_Elast!$D:$G,MATCH("el_inc_"&INDEX(Data_Elast!$J:$J,MATCH($B46,Data_Elast!$I:$I,0)),Data_Elast!$A:$A,0),MATCH(Settings!$B$5,Data_Elast!$D$1:$G$1,0)) -> 0.5 | F46: =INDEX(Data_Elast!$D:$G,MATCH("el_dem_"&INDEX(Data_Elast!$J:$J,MATCH($B46,Data_Elast!$I:$I,0)),Data_Elast!$A:$A,0),MATCH(Settings!$B$5,Data_Elast!$D$1:$G$1,0)) -> -0.4 | G46: =INDEX(Data_Elast!$D:$G,MATCH("el_eff_"&INDEX(Data_Elast!$J:$J,MATCH($B46,Data_Elast!$I:$I,0)),Data_Elast!$A:$A,0),MATCH(Settings!$B$5,Data_Elast!$D$1:$G$1,0)) -> -0.7 | H46: =INDEX(Data_Elast!$D:$G,MATCH("eff_imp_"&INDEX(Data_Elast!$K:$K,MATCH($B46,Data_Elast!$I:$I,0)),Data_Elast!$A:$A,0),MATCH(Settings!$B$5,Data_Elast!$D$1:$G$1,0)) -> 0.005 | I46: =Settings!$B$7 -> 0 | J46: =INDEX(Data_Elast!$J:$J,MATCH($B46,Data_Elast!$I:$I,0)) -> gso
B47: die | C47: =$C$5 -> irn | D47: Parameters: Diesel | E47: =INDEX(Data_Elast!$D:$G,MATCH("el_inc_"&INDEX(Data_Elast!$J:$J,MATCH($B47,Data_Elast!$I:$I,0)),Data_Elast!$A:$A,0),MATCH(Settings!$B$5,Data_Elast!$D$1:$G$1,0)) -> 0.5 | F47: =INDEX(Data_Elast!$D:$G,MATCH("el_dem_"&INDEX(Data_Elast!$J:$J,MATCH($B47,Data_Elast!$I:$I,0)),Data_Elast!$A:$A,0),MATCH(Settings!$B$5,Data_Elast!$D$1:$G$1,0)) -> -0.7 | G47: =INDEX(Data_Elast!$D:$G,MATCH("el_eff_"&INDEX(Data_Elast!$J:$J,MATCH($B47,Data_Elast!$I:$I,0)),Data_Elast!$A:$A,0),MATCH(Settings!$B$5,Data_Elast!$D$1:$G$1,0)) -> -1.2 | H47: =INDEX(Data_Elast!$D:$G,MATCH("eff_imp_"&INDEX(Data_Elast!$K:$K,MATCH($B47,Data_Elast!$I:$I,0)),Data_Elast!$A:$A,0),MATCH(Settings!$B$5,Data_Elast!$D$1:$G$1,0)) -> 0.005 | I47: =Settings!$B$7 -> 0 | J47: =INDEX(Data_Elast!$J:$J,MATCH($B47,Data_Elast!$I:$I,0)) -> die
B48: lpg | C48: =$C$5 -> irn | D48: Parameters: LPG | E48: =INDEX(Data_Elast!$D:$G,MATCH("el_inc_"&INDEX(Data_Elast!$J:$J,MATCH($B48,Data_Elast!$I:$I,0)),Data_Elast!$A:$A,0),MATCH(Settings!$B$5,Data_Elast!$D$1:$G$1,0)) -> 0.8 | F48: =INDEX(Data_Elast!$D:$G,MATCH("el_dem_"&INDEX(Data_Elast!$J:$J,MATCH($B48,Data_Elast!$I:$I,0)),Data_Elast!$A:$A,0),MATCH(Settings!$B$5,Data_Elast!$D$1:$G$1,0)) -> -0.4 | G48: =INDEX(Data_Elast!$D:$G,MATCH("el_eff_"&INDEX(Data_Elast!$J:$J,MATCH($B48,Data_Elast!$I:$I,0)),Data_Elast!$A:$A,0),MATCH(Settings!$B$5,Data_Elast!$D$1:$G$1,0)) -> -0.4 | H48: =INDEX(Data_Elast!$D:$G,MATCH("eff_imp_"&INDEX(Data_Elast!$K:$K,MATCH($B48,Data_Elast!$I:$I,0)),Data_Elast!$A:$A,0),MATCH(Settings!$B$5,Data_Elast!$D$1:$G$1,0)) -> 0.005 | I48: =Settings!$B$7 -> 0 | J48: =INDEX(Data_Elast!$J:$J,MATCH($B48,Data_Elast!$I:$I,0)) -> oil
B49: ker | C49: =$C$5 -> irn | D49: Parameters: Kerosene | E49: =INDEX(Data_Elast!$D:$G,MATCH("el_inc_"&INDEX(Data_Elast!$J:$J,MATCH($B49,Data_Elast!$I:$I,0)),Data_Elast!$A:$A,0),MATCH(Settings!$B$5,Data_Elast!$D$1:$G$1,0)) -> 0.8 | F49: =INDEX(Data_Elast!$D:$G,MATCH("el_dem_"&INDEX(Data_Elast!$J:$J,MATCH($B49,Data_Elast!$I:$I,0)),Data_Elast!$A:$A,0),MATCH(Settings!$B$5,Data_Elast!$D$1:$G$1,0)) -> -0.4 | G49: =INDEX(Data_Elast!$D:$G,MATCH("el_eff_"&INDEX(Data_Elast!$J:$J,MATCH($B49,Data_Elast!$I:$I,0)),Data_Elast!$A:$A,0),MATCH(Settings!$B$5,Data_Elast!$D$1:$G$1,0)) -> -0.4 | H49: =INDEX(Data_Elast!$D:$G,MATCH("eff_imp_"&INDEX(Data_Elast!$K:$K,MATCH($B49,Data_Elast!$I:$I,0)),Data_Elast!$A:$A,0),MATCH(Settings!$B$5,Data_Elast!$D$1:$G$1,0)) -> 0.005 | I49: =Settings!$B$7 -> 0 | J49: =INDEX(Data_Elast!$J:$J,MATCH($B49,Data_Elast!$I:$I,0)) -> oil
B50: oop | C50: =$C$5 -> irn | D50: Parameters: Other oil products | E50: =INDEX(Data_Elast!$D:$G,MATCH("el_inc_"&INDEX(Data_Elast!$J:$J,MATCH($B50,Data_Elast!$I:$I,0)),Data_Elast!$A:$A,0),MATCH(Settings!$B$5,Data_Elast!$D$1:$G$1,0)) -> 0.8 | F50: =INDEX(Data_Elast!$D:$G,MATCH("el_dem_"&INDEX(Data_Elast!$J:$J,MATCH($B50,Data_Elast!$I:$I,0)),Data_Elast!$A:$A,0),MATCH(Settings!$B$5,Data_Elast!$D$1:$G$1,0)) -> -0.4 | G50: =INDEX(Data_Elast!$D:$G,MATCH("el_eff_"&INDEX(Data_Elast!$J:$J,MATCH($B50,Data_Elast!$I:$I,0)),Data_Elast!$A:$A,0),MATCH(Settings!$B$5,Data_Elast!$D$1:$G$1,0)) -> -0.4 | H50: =INDEX(Data_Elast!$D:$G,MATCH("eff_imp_"&INDEX(Data_Elast!$K:$K,MATCH($B50,Data_Elast!$I:$I,0)),Data_Elast!$A:$A,0),MATCH(Settings!$B$5,Data_Elast!$D$1:$G$1,0)) -> 0.005 | I50: =Settings!$B$7 -> 0 | J50: =INDEX(Data_Elast!$J:$J,MATCH($B50,Data_Elast!$I:$I,0)) -> oil
B51: bio | C51: =$C$5 -> irn | D51: Parameters: Biomass | E51: =INDEX(Data_Elast!$D:$G,MATCH("el_inc_"&INDEX(Data_Elast!$J:$J,MATCH($B51,Data_Elast!$I:$I,0)),Data_Elast!$A:$A,0),MATCH(Settings!$B$5,Data_Elast!$D$1:$G$1,0)) -> 0.1 | F51: =INDEX(Data_Elast!$D:$G,MATCH("el_dem_"&INDEX(Data_Elast!$J:$J,MATCH($B51,Data_Elast!$I:$I,0)),Data_Elast!$A:$A,0),MATCH(Settings!$B$5,Data_Elast!$D$1:$G$1,0)) -> -0.3 | G51: =INDEX(Data_Elast!$D:$G,MATCH("el_eff_"&INDEX(Data_Elast!$J:$J,MATCH($B51,Data_Elast!$I:$I,0)),Data_Elast!$A:$A,0),MATCH(Settings!$B$5,Data_Elast!$D$1:$G$1,0)) -> -0.2 | H51: =INDEX(Data_Elast!$D:$G,MATCH("eff_imp_"&INDEX(Data_Elast!$K:$K,MATCH($B51,Data_Elast!$I:$I,0)),Data_Elast!$A:$A,0),MATCH(Settings!$B$5,Data_Elast!$D$1:$G$1,0)) -> 0.005 | I51: =Settings!$B$7 -> 0 | J51: =INDEX(Data_Elast!$J:$J,MATCH($B51,Data_Elast!$I:$I,0)) -> bio
B52: ren | C52: =$C$5 -> irn | D52: Parameters: Self-generated renewables | E52: =INDEX(Data_Elast!$D:$G,MATCH("el_inc_"&INDEX(Data_Elast!$J:$J,MATCH($B52,Data_Elast!$I:$I,0)),Data_Elast!$A:$A,0),MATCH(Settings!$B$5,Data_Elast!$D$1:$G$1,0)) -> 0.8 | F52: =INDEX(Data_Elast!$D:$G,MATCH("el_dem_"&INDEX(Data_Elast!$J:$J,MATCH($B52,Data_Elast!$I:$I,0)),Data_Elast!$A:$A,0),MATCH(Settings!$B$5,Data_Elast!$D$1:$G$1,0)) -> -0.5 | G52: =INDEX(Data_Elast!$D:$G,MATCH("el_eff_"&INDEX(Data_Elast!$J:$J,MATCH($B52,Data_Elast!$I:$I,0)),Data_Elast!$A:$A,0),MATCH(Settings!$B$5,Data_Elast!$D$1:$G$1,0)) -> -0.4 | H52: =INDEX(Data_Elast!$D:$G,MATCH("eff_imp_"&INDEX(Data_Elast!$K:$K,MATCH($B52,Data_Elast!$I:$I,0)),Data_Elast!$A:$A,0),MATCH(Settings!$B$5,Data_Elast!$D$1:$G$1,0)) -> 0.005 | I52: =Settings!$B$7 -> 0 | J52: =INDEX(Data_Elast!$J:$J,MATCH($B52,Data_Elast!$I:$I,0)) -> ren
B53: Energy use: base year from Data_Energy, later years from the kernel (= CPAT ener rows)
B54: coa | C54: =$C$5 -> irn | D54: Coal | E54: ktoe | F54: ener | G54: =Settings!$B$3&".mit.enc."&$B54 -> egy.mit.enc.coa | H54: =Settings!$B$3&".mit.ener."&$C$5&"."&$B54&".e."&$J$5 -> egy.mit.ener.irn.coa.e.1 | I54: usage term reads net price Rebate_Industry row 84 (atpn, Task I); efficiency term shp | L54: =INDEX(Data_Energy!$D$3:$U$22,MATCH($B54,Data_Energy!$C$3:$C$22,0),MATCH($C54,Data_Energy!$D$2:$U$2,0)) -> 232.65735 | M54: =L54*(1+M$39)^($E44*M$40)*(1+M$41)*IF(Rebate_Industry!L$84<=0,1,Rebate_Industry!M$84/Rebate_Industry!L$84)^$F44*(IF(L27<=0,1,M27/L27)^$G44/(1+$H44+$I44))^(1+$F44) -> 189.45266 | N54: =M54*(1+N$39)^($E44*N$40)*(1+N$41)*IF(Rebate_Industry!M$84<=0,1,Rebate_Industry!N$84/Rebate_Industry!M$84)^$F44*(IF(M27<=0,1,N27/M27)^$G44/(1+$H44+$I44))^(1+$F44) -> 217.72884 | O54: =N54*(1+O$39)^($E44*O$40)*(1+O$41)*IF(Rebate_Industry!N$84<=0,1,Rebate_Industry!O$84/Rebate_Industry!N$84)^$F44*(IF(N27<=0,1,O27/N27)^$G44/(1+$H44+$I44))^(1+$F44) -> 237.89793 | P54: =O54*(1+P$39)^($E44*P$40)*(1+P$41)*IF(Rebate_Industry!O$84<=0,1,Rebate_Industry!P$84/Rebate_Industry!O$84)^$F44*(IF(O27<=0,1,P27/O27)^$G44/(1+$H44+$I44))^(1+$F44) -> 232.65007 | Q54: =P54*(1+Q$39)^($E44*Q$40)*(1+Q$41)*IF(Rebate_Industry!P$84<=0,1,Rebate_Industry!Q$84/Rebate_Industry!P$84)^$F44*(IF(P27<=0,1,Q27/P27)^$G44/(1+$H44+$I44))^(1+$F44) -> 235.34294 | R54: =Q54*(1+R$39)^($E44*R$40)*(1+R$41)*IF(Rebate_Industry!Q$84<=0,1,Rebate_Industry!R$84/Rebate_Industry!Q$84)^$F44*(IF(Q27<=0,1,R27/Q27)^$G44/(1+$H44+$I44))^(1+$F44) -> 241.85374 | S54: =R54*(1+S$39)^($E44*S$40)*(1+S$41)*IF(Rebate_Industry!R$84<=0,1,Rebate_Industry!S$84/Rebate_Industry!R$84)^$F44*(IF(R27<=0,1,S27/R27)^$G44/(1+$H44+$I44))^(1+$F44) -> 248.19369 | T54: =S54*(1+T$39)^($E44*T$40)*(1+T$41)*IF(Rebate_Industry!S$84<=0,1,Rebate_Industry!T$84/Rebate_Industry!S$84)^$F44*(IF(S27<=0,1,T27/S27)^$G44/(1+$H44+$I44))^(1+$F44) -> 254.2678 | ... AE54: =AD54*(1+AE$39)^($E44*AE$40)*(1+AE$41)*IF(Rebate_Industry!AD$84<=0,1,Rebate_Industry!AE$84/Rebate_Industry!AD$84)^$F44*(IF(AD27<=0,1,AE27/AD27)^$G44/(1+$H44+$I44))^(1+$F44) -> 310.04019
B55: nga | C55: =$C$5 -> irn | D55: Natural gas | E55: ktoe | F55: ener | G55: =Settings!$B$3&".mit.enc."&$B55 -> egy.mit.enc.nga | H55: =Settings!$B$3&".mit.ener."&$C$5&"."&$B55&".e."&$J$5 -> egy.mit.ener.irn.nga.e.1 | I55: usage term reads net price Rebate_Industry row 85 (atpn, Task I); efficiency term shp | L55: =INDEX(Data_Energy!$D$3:$U$22,MATCH($B55,Data_Energy!$C$3:$C$22,0),MATCH($C55,Data_Energy!$D$2:$U$2,0)) -> 1669.0567 | M55: =L55*(1+M$39)^($E45*M$40)*(1+M$41)*IF(Rebate_Industry!L$85<=0,1,Rebate_Industry!M$85/Rebate_Industry!L$85)^$F45*(IF(L28<=0,1,M28/L28)^$G45/(1+$H45+$I45))^(1+$F45) -> 1431.7775 | N55: =M55*(1+N$39)^($E45*N$40)*(1+N$41)*IF(Rebate_Industry!M$85<=0,1,Rebate_Industry!N$85/Rebate_Industry!M$85)^$F45*(IF(M28<=0,1,N28/M28)^$G45/(1+$H45+$I45))^(1+$F45) -> 1603.1181 | O55: =N55*(1+O$39)^($E45*O$40)*(1+O$41)*IF(Rebate_Industry!N$85<=0,1,Rebate_Industry!O$85/Rebate_Industry!N$85)^$F45*(IF(N28<=0,1,O28/N28)^$G45/(1+$H45+$I45))^(1+$F45) -> 1666.4691 | P55: =O55*(1+P$39)^($E45*P$40)*(1+P$41)*IF(Rebate_Industry!O$85<=0,1,Rebate_Industry!P$85/Rebate_Industry!O$85)^$F45*(IF(O28<=0,1,P28/O28)^$G45/(1+$H45+$I45))^(1+$F45) -> 1729.052 | Q55: =P55*(1+Q$39)^($E45*Q$40)*(1+Q$41)*IF(Rebate_Industry!P$85<=0,1,Rebate_Industry!Q$85/Rebate_Industry!P$85)^$F45*(IF(P28<=0,1,Q28/P28)^$G45/(1+$H45+$I45))^(1+$F45) -> 1803.6196 | R55: =Q55*(1+R$39)^($E45*R$40)*(1+R$41)*IF(Rebate_Industry!Q$85<=0,1,Rebate_Industry!R$85/Rebate_Industry!Q$85)^$F45*(IF(Q28<=0,1,R28/Q28)^$G45/(1+$H45+$I45))^(1+$F45) -> 1893.1814 | S55: =R55*(1+S$39)^($E45*S$40)*(1+S$41)*IF(Rebate_Industry!R$85<=0,1,Rebate_Industry!S$85/Rebate_Industry!R$85)^$F45*(IF(R28<=0,1,S28/R28)^$G45/(1+$H45+$I45))^(1+$F45) -> 1980.2914 | T55: =S55*(1+T$39)^($E45*T$40)*(1+T$41)*IF(Rebate_Industry!S$85<=0,1,Rebate_Industry!T$85/Rebate_Industry!S$85)^$F45*(IF(S28<=0,1,T28/S28)^$G45/(1+$H45+$I45))^(1+$F45) -> 2062.9631 | ... AE55: =AD55*(1+AE$39)^($E45*AE$40)*(1+AE$41)*IF(Rebate_Industry!AD$85<=0,1,Rebate_Industry!AE$85/Rebate_Industry!AD$85)^$F45*(IF(AD28<=0,1,AE28/AD28)^$G45/(1+$H45+$I45))^(1+$F45) -> 3106.9586
B56: gso | C56: =$C$5 -> irn | D56: Gasoline | E56: ktoe | F56: ener | G56: =Settings!$B$3&".mit.enc."&$B56 -> egy.mit.enc.gso | H56: =Settings!$B$3&".mit.ener."&$C$5&"."&$B56&".e."&$J$5 -> egy.mit.ener.irn.gso.e.1 | I56: usage term reads net price Rebate_Industry row 86 (atpn, Task I); efficiency term shp | L56: =INDEX(Data_Energy!$D$3:$U$22,MATCH($B56,Data_Energy!$C$3:$C$22,0),MATCH($C56,Data_Energy!$D$2:$U$2,0)) -> 0 | M56: =L56*(1+M$39)^($E46*M$40)*(1+M$41)*IF(Rebate_Industry!L$86<=0,1,Rebate_Industry!M$86/Rebate_Industry!L$86)^$F46*(IF(L29<=0,1,M29/L29)^$G46/(1+$H46+$I46))^(1+$F46) -> 0 | N56: =M56*(1+N$39)^($E46*N$40)*(1+N$41)*IF(Rebate_Industry!M$86<=0,1,Rebate_Industry!N$86/Rebate_Industry!M$86)^$F46*(IF(M29<=0,1,N29/M29)^$G46/(1+$H46+$I46))^(1+$F46) -> 0 | O56: =N56*(1+O$39)^($E46*O$40)*(1+O$41)*IF(Rebate_Industry!N$86<=0,1,Rebate_Industry!O$86/Rebate_Industry!N$86)^$F46*(IF(N29<=0,1,O29/N29)^$G46/(1+$H46+$I46))^(1+$F46) -> 0 | P56: =O56*(1+P$39)^($E46*P$40)*(1+P$41)*IF(Rebate_Industry!O$86<=0,1,Rebate_Industry!P$86/Rebate_Industry!O$86)^$F46*(IF(O29<=0,1,P29/O29)^$G46/(1+$H46+$I46))^(1+$F46) -> 0 | Q56: =P56*(1+Q$39)^($E46*Q$40)*(1+Q$41)*IF(Rebate_Industry!P$86<=0,1,Rebate_Industry!Q$86/Rebate_Industry!P$86)^$F46*(IF(P29<=0,1,Q29/P29)^$G46/(1+$H46+$I46))^(1+$F46) -> 0 | R56: =Q56*(1+R$39)^($E46*R$40)*(1+R$41)*IF(Rebate_Industry!Q$86<=0,1,Rebate_Industry!R$86/Rebate_Industry!Q$86)^$F46*(IF(Q29<=0,1,R29/Q29)^$G46/(1+$H46+$I46))^(1+$F46) -> 0 | S56: =R56*(1+S$39)^($E46*S$40)*(1+S$41)*IF(Rebate_Industry!R$86<=0,1,Rebate_Industry!S$86/Rebate_Industry!R$86)^$F46*(IF(R29<=0,1,S29/R29)^$G46/(1+$H46+$I46))^(1+$F46) -> 0 | T56: =S56*(1+T$39)^($E46*T$40)*(1+T$41)*IF(Rebate_Industry!S$86<=0,1,Rebate_Industry!T$86/Rebate_Industry!S$86)^$F46*(IF(S29<=0,1,T29/S29)^$G46/(1+$H46+$I46))^(1+$F46) -> 0 | ... AE56: =AD56*(1+AE$39)^($E46*AE$40)*(1+AE$41)*IF(Rebate_Industry!AD$86<=0,1,Rebate_Industry!AE$86/Rebate_Industry!AD$86)^$F46*(IF(AD29<=0,1,AE29/AD29)^$G46/(1+$H46+$I46))^(1+$F46) -> 0
