Workbook
Name BaseYr: Inputs!$D$37
Name BetaSet: Inputs!$D$10
Name Bf: Inputs!$D$33
Name BfScen: Inputs!$D$12
Name BT_Code: Inputs!$A$74:$A$79
Name BT_Flag: Inputs!$D$74:$D$79
Name BT_Phi: Inputs!$F$74:$F$79
Name BT_Recyc: Inputs!$H$74:$H$79
Name BT_Scen: Inputs!$B$74:$B$79
Name BT_Scope: Inputs!$C$74:$C$79
Name BT_Tau: Inputs!$G$74:$G$79
Name BT_Theta: Inputs!$E$74:$E$79
Name BT_Traj: Inputs!$I$74:$I$79
Name CBFsel: Inputs!$D$35
Name CBFyr: Inputs!$D$34
Name ChecksOverall: Checks!$D$23
Name Conv: Inputs!$D$7
Name CPO_Data: CPAT_Outputs!$E$4:$X$131
Name CPO_Keys: CPAT_Outputs!$C$4:$C$131
Name CPO_Years: CPAT_Outputs!$E$3:$X$3
Name CV_cptraj: Inputs!$C$49:$F$49
Name CV_deaths: Inputs!$C$64:$F$64
Name CV_denr: Inputs!$C$68:$F$68
Name CV_dghg: Inputs!$C$66:$F$66
Name CV_dind: Inputs!$C$69:$F$69
Name CV_dippu: Inputs!$C$67:$F$67
Name CV_drev: Inputs!$C$70:$F$70
Name CV_effcp: Inputs!$C$50:$F$50
Name CV_enr0: Inputs!$C$45:$F$45
Name CV_enr1: Inputs!$C$46:$F$46
Name CV_ghg0: Inputs!$C$41:$F$41
Name CV_ghg1: Inputs!$C$42:$F$42
Name CV_Hdr: Inputs!$C$40:$F$40
Name CV_ind0: Inputs!$C$47:$F$47
Name CV_ind1: Inputs!$C$48:$F$48
Name CV_ippu0: Inputs!$C$43:$F$43
Name CV_ippu1: Inputs!$C$44:$F$44
Name CV_kappa: Inputs!$C$65:$F$65
Name CV_mort: Inputs!$C$62:$F$62
Name CV_revctax: Inputs!$C$63:$F$63
Name CV_revnew0: Inputs!$C$51:$F$51
Name CV_revnew1: Inputs!$C$52:$F$52
Name EFSet: Inputs!$D$11
Name EpsF: Inputs!$D$20
Name EpsQ: Inputs!$D$22
Name EpsQ1: Inputs!$D$23
Name EpsQ2: Inputs!$D$24
Name EpsQ3: Inputs!$D$25
Name EpsQ4: Inputs!$D$26
Name EpsQ5: Inputs!$D$27
Name EpsQ6: Inputs!$D$28
Name EpsQ7: Inputs!$D$29
Name EpsQ8: Inputs!$D$30
Name EpsU: Inputs!$D$19
Name IppuOther: Inputs!$D$14
Name KappaMode: Inputs!$D$15
Name Mode: Inputs!$D$6
Name PEU: Inputs!$D$31
Name ProtoFail: Comparison!$D$208
Name ProtoPass: Comparison!$C$208

Sheet ReadMe
A1: AdHocCalculations - rebuild v0.5 (Egypt policy-options matrix, Table 2 of the results note)
A3: Purpose | B3: Transparent rebuild of AdHocCalculations.xlsb (PolicyMatrix tab) behind Table 2 of the Egypt results note. Every number on PolicyMatrix rows 7-12 is a formula reading Inputs / CPAT_Outputs / CBAM_Products / Results; nothing is typed.
A4: How to use | B4: Change assumptions ONLY on the Inputs tab (tan cells). Mode = REBUILD (default, coherent method) or PROTOTYPE (reproduces CPAT_Industry_Kernel_Egypt_v0.11 block exactly - verify on Comparison section 2 and Checks). Conv = CBAM convention for O (FULL default from v0.5). Yr = reporting year (2030 default).
A5: Sheets | B5: Inputs (all assumptions, switches, CPAT values for Yr, bundle table, product table, year vectors) | CPAT_Outputs (trimmed CPAT Outputs 2022-2041, 32 codes x 4 scenarios) | CBAM_Products (eight-product block per bundle, prototype v0.11 equations) | Results (engine: every metric by bundle, keyed) | PolicyMatrix (original layout, live) | Comparison (original / Table 2 / rebuilt / prototype) | Issues resolved (19 items) | Checks.
A6: Format changes vs original | B6: (1) Assumptions moved to Inputs (original had typed constants inside PolicyMatrix and a misaligned Inputs tab). (2) Columns AF-AQ redefined (yellow headers): the legacy half-elasticity block (AF-AP) is replaced by the K decomposition (AF-AM), export-weighted intensity change (AN), gross revenue (AO), rebates (AP) and O under FULL phase-in (AQ). (3) Rows 14-22 (non-modelled bundles) copied verbatim, grey, not recomputed. (4) Trajectory rows 26-29 rebuilt as contiguous years 2027-2034 in F-M, live from Inputs, plus a CBAM phase-in row. (5) Row 4 mode indicator added; C3 is a formula. (6) New sheets: CPAT_Outputs, CBAM_Products, Results, Comparison, Issues resolved, Checks. (7) GHG tab not rebuilt.
A7: Method differences vs original | B7: Single 2030 base (CPAT total GHG 594.2 Mt); coverage computed (kappa for partial industry runs); CBAM base bottom-up (62.42 Mt, eight products, Egypt CBAM EF v0.1); process response via beta and the output channel, CPAT's IPPU scaling removed; 1A on EG1; 3B from EG3 with explicit OBR output-channel correction; revenue = CPAT fuel receipts + block process revenue, net of rebates / fund; deaths rescaled by energy CO2 only; price start 2028; no untraceable constants; b_f calibrated on CPAT; O convention explicit.
A8: Method differences vs prototype v0.11 | B8: REBUILD mode adds: fuel-intensity channel xf = EXP(b_f (tau + fund)); IPCC-based process beta set (prototype set selectable); fund shadow price sigma on both channels; national totals from CPAT; OBR rebates in net revenue; kappa coverage; 3C differs from 3A. PROTOTYPE mode switches all of these off for the block.
A9: Provenance | B9: CPAT values: cpat_outputs_egypt_2022_2041.csv (CPAT Outputs sheet, Egypt EG1-EG4). Prototype: prototype_v0_11_results.json (run via Excel COM). Original: original_PolicyMatrix_cells.txt (verbatim dump). Builder: build_adhoc_rebuild_v0_5.py; verification: recalc_and_check_adhoc_v0_5.py (report recalc_and_check_adhoc_v0_5_report.txt). EFs: EmissionFactors/EGY_CBAM_EF_v0.1.xlsx. Methodology note (core equations, results, differences, open flags): MethodologyNote_v0.5.md / .docx.
A10: Colour code | B10: Tan = input; blue = key / identifier; green = computed; yellow = switch-dependent or review; grey = static copy.
A11: Version log | B11: v0.1 - first rebuild (openpyxl build, Excel COM verified). v0.2 - Egypt CBAM EF v0.1 (switch EFSet) and AN blended process ER100. v0.5 2026-10-04 - PStar = 122 USD2024 for IPCC beta sets, and KappaMode=SCALE default to approximate a full-coverage EG3 industry run pending a CPAT re-run. v0.5 - defaults Conv = FULL and ThetaOther = 1 (decisions 2026-10-04); no formula changes.

Sheet Inputs
A1: Inputs - all assumptions and switches (AdHoc Calculations rebuild v0.5)
A2: Edit only tan cells (switches) and light-green cells (inputs). Every other cell in the workbook is a formula. Defined names are listed in column E.
A4: A. Switches
A5: Switch | B5: Value (edit) | C5: Allowed values | D5: Effective (named) | E5: Name | F5: Notes
A6: Calculation mode | B6: REBUILD | C6: REBUILD, PROTOTYPE | D6: =UPPER(TRIM(B6)) -> REBUILD | E6: Mode | F6: REBUILD = coherent method (headline). PROTOTYPE = reproduce CPAT_Industry_Kernel_Egypt_v0.11 exactly (xf=1, prototype beta set, fund shadow price 0); verified cell by cell in Comparison section 2.
A7: CBAM obligation convention | B7: FULL | C7: FULL, NOPHASE, SCALED | D7: =UPPER(TRIM(B7)) -> FULL | E7: Conv | F7: FULL (default from v0.5): 2030 phase-in factor 0.485 on the obligation, full deduction of the carbon price paid. NOPHASE (memo; the default in v0.1-v0.3): full certificate price EUR/USD 100 with no phase-in, deduction of carbon price paid - the definition behind column O of the original (intensity + price credit). SCALED: phase-in on both obligation and deduction (prototype memo).
A8: Reporting year | B8: 2030 | C8: 2026 .. 2041 | D8: =B8 -> 2030 | E8: Yr | F8: All Table-2 metrics are for this year; CPAT values are looked up live for it.
A9: Fund shadow price sigma ($/tCO2) for bundle 3C | B9: 20 | C9: >= 0 | D9: =IF(Mode="PROTOTYPE",0,B9) -> 20 | E9: SigmaEff | F9: Abatement-fund payments modelled as a shadow price added to the carbon price in the fuel-intensity and process-intensity responses (TechNote: fund enters the efficiency term only). 0 in PROTOTYPE mode.
A10: Process half-elasticity (beta) set | B10: IPCC_CENTRAL | C10: IPCC_CENTRAL, IPCC_2030, IPCC_LONGRUN, PROTOTYPE | D10: =IF(Mode="PROTOTYPE","PROTOTYPE",UPPER(TRIM(B10))) -> IPCC_CENTRAL | E10: BetaSet | F10: beta_s = -LN(1-ER100_s)/100 from IPCC MACC bands (TASK-D drop-in). PROTOTYPE set forced in PROTOTYPE mode.
A11: Emission-factor set (fc, fp, np, no) | B11: EGY_EF_V01 | C11: EGY_EF_V01, PROTOTYPE | D11: =IF(Mode="PROTOTYPE","PROTOTYPE",UPPER(TRIM(B11))) -> EGY_EF_V01 | E11: EFSet | F11: EGY_EF_V01 = Egypt CBAM EF v0.1 (EmissionFactors/EGY_CBAM_EF_v0.1.xlsx; urea CBAM rule np = 0; AN integrated HNO3 N2O in no). PROTOTYPE = kernel v0.11 EFs (Inputs E, columns R:U); forced in PROTOTYPE mode.
A12: CPAT scenario used to calibrate the fuel-intensity semi-elasticity b_f | B12: EG1 | C12: EG1, EG2, EG3 | D12: =UPPER(TRIM(B12)) -> EG1 | E12: BfScen | F12: b_f = s_int * LN(ind.2/ind.1) / price (section B). EG1 is the economy-wide $20 run.
A13: OBR rebate (3B) also for non-CBAM priced industry? (0 = CBAM producers only) | B13: 1 | C13: 0, 1 | D13: =IF(Mode="PROTOTYPE",0,B13) -> 1 | E13: ThetaOther | F13: Default 1 from v0.5 (decision 2026-10-04); forced 0 in PROTOTYPE mode. Original 3B text says 'free allocation for CBAM producers'. 0 keeps revenue from non-CBAM industry (3B raises revenue); 1 rebates all covered industry (output channel removed everywhere, revenue ~0).
A14: Non-CBAM IPPU response to a fuel-only price | B14: NONE | C14: NONE, CPAT | D14: =UPPER(TRIM(B14)) -> NONE | E14: IppuOther | F14: CPAT scales all IPPU with industrial energy CO2 (MajorIssues #17). NONE removes it (process emissions respond only where priced or via output); CPAT keeps CPAT's scaling for the non-CBAM IPPU remainder.
A15: Coverage factor kappa / EG3 full-coverage approximation | B15: SCALE | C15: SCALE, AUTO, ONE | D15: =UPPER(TRIM(B15)) -> SCALE | E15: KappaMode | F15: SCALE (default): approximation of a full-coverage EG3 run (pending a CPAT re-run), scaling EG3 industry energy responses and fuel receipts by 1/kappa while coverage J uses kappa = 1. AUTO: expose CPAT's partial coverage. ONE: assume CPAT was already full coverage without scaling.
A17: B. Core parameters
A18: Parameter | B18: Value (edit) | C18: Unit | D18: Effective / derived (named) | E18: Name | F18: Source / notes
A19: Own-price elasticity of industrial output demand (eps_U) | B19: -0.5 | C19: - | D19: =B19 -> -0.5 | E19: EpsU | F19: TechNote App. A (CPAT industry fuel-demand split).
A20: Price elasticity of fuel intensity (eps_F) | B20: -0.5 | C20: - | D20: =B20 -> -0.5 | E20: EpsF | F20: TechNote App. A.
A21: Intensity share of the CPAT industrial fuel response s_int | B21: (derived) | C21: - | D21: =EpsF*(1+EpsU)/(EpsU+EpsF*(1+EpsU)) -> 0.33333333 | E21: SInt | F21: TechNote App. A: eps_F(1+eps_U)/(eps_U+eps_F(1+eps_U)); = 1/3 at -0.5/-0.5 (the '(2/3)/0.5' of K11 is the output share divided by |eps|). Output share = 1 - s_int.
A22: CBAM-product output response to cost pass-through (eps, prototype) | B22: -0.5 | C22: - | D22: =B22 -> -0.5 | E22: EpsQ | F22: Prototype v0.11 Manual inputs. Q = Q_base * (1 + dp)^eps with dp = net carbon cost / product price.
A23: Output response eps, DRI-EAF steel | B23: -0.4 | C23: - | D23: =IF(Mode="PROTOTYPE",EpsQ,B23) -> -0.4 | E23: EpsQ1 | F23: OutputElasticity_Note_v0.1 (PROTOTYPE mode: uniform EpsQ = -0.5).
A24: Output response eps, Scrap-EAF steel | B24: -0.4 | C24: - | D24: =IF(Mode="PROTOTYPE",EpsQ,B24) -> -0.4 | E24: EpsQ2 | F24: OutputElasticity_Note_v0.1 (PROTOTYPE mode: uniform EpsQ = -0.5).
A25: Output response eps, BF-BOF steel | B25: -0.4 | C25: - | D25: =IF(Mode="PROTOTYPE",EpsQ,B25) -> -0.4 | E25: EpsQ3 | F25: OutputElasticity_Note_v0.1 (PROTOTYPE mode: uniform EpsQ = -0.5).
A26: Output response eps, Clinker (cement) | B26: -0.1 | C26: - | D26: =IF(Mode="PROTOTYPE",EpsQ,B26) -> -0.1 | E26: EpsQ4 | F26: OutputElasticity_Note_v0.1 (PROTOTYPE mode: uniform EpsQ = -0.5).
A27: Output response eps, Ammonia | B27: -0.4 | C27: - | D27: =IF(Mode="PROTOTYPE",EpsQ,B27) -> -0.4 | E27: EpsQ5 | F27: OutputElasticity_Note_v0.1 (PROTOTYPE mode: uniform EpsQ = -0.5).
A28: Output response eps, Urea | B28: -0.4 | C28: - | D28: =IF(Mode="PROTOTYPE",EpsQ,B28) -> -0.4 | E28: EpsQ6 | F28: OutputElasticity_Note_v0.1 (PROTOTYPE mode: uniform EpsQ = -0.5).
A29: Output response eps, Ammonium nitrate | B29: -0.4 | C29: - | D29: =IF(Mode="PROTOTYPE",EpsQ,B29) -> -0.4 | E29: EpsQ7 | F29: OutputElasticity_Note_v0.1 (PROTOTYPE mode: uniform EpsQ = -0.5).
A30: Output response eps, Aluminium | B30: -0.5 | C30: - | D30: =IF(Mode="PROTOTYPE",EpsQ,B30) -> -0.5 | E30: EpsQ8 | F30: OutputElasticity_Note_v0.1 (PROTOTYPE mode: uniform EpsQ = -0.5).
A31: CBAM certificate price (EU ETS proxy) | B31: 100 | C31: $/tCO2 | D31: =B31 -> 100 | E31: PEU | F31: Prototype v0.11 (T79).
A32: IPCC process semi-elasticity anchor price P* (USD2024/tCO2) | B32: 122 | C32: $/tCO2 | D32: =B32 -> 122 | E32: PStar | F32: USD2019 100 deflated to USD2024 (US GDP deflator ≈ 1.22); Medium confidence. Used only for IPCC beta sets: beta = -LN(1-ER100)/P*. PROTOTYPE mode / BetaSet = PROTOTYPE keeps the old /100 divisor.
A33: Fuel-intensity semi-elasticity b_f (derived) | B33: (derived) | C33: 1/($/tCO2) | D33: =SInt*LN(INDEX(CV_ind1,MATCH(BfScen,CV_Hdr,0))/INDEX(CV_ind0,MATCH(BfScen,CV_Hdr,0)))/INDEX(CV_cptraj,MATCH(BfScen,CV_Hdr,0)) -> -0.0024955979 | E33: Bf | F33: Replaces the untraceable -0.549%/2 per $ of the original (AF7). Fuel intensity factor xf = EXP(b_f * (carbon price + fund shadow price)); EG1 gives -0.00250 (original -0.00274).
A34: CBAM phase-in factor in the reporting year (derived) | B34: (derived) | C34: - | D34: =INDEX(YV_CBF,MATCH(Yr,YV_Years,0)) -> 0.485 | E34: CBFyr | F34: From section F (EU CBAM definitive-period phase-in: 2.5% 2026 .. 100% 2034).
A35: Phase-in factor applied to the obligation under the selected convention | B35: (derived) | C35: - | D35: =IF(Conv="NOPHASE",1,CBFyr) -> 0.485 | E35: CBFsel | F35: NOPHASE -> 1; FULL / SCALED -> CBFyr.
A36: Scale applied to the carbon-price deduction under the selected convention | B36: (derived) | C36: - | D36: =IF(Conv="SCALED",CBFyr,1) -> 1 | E36: Ssel | F36: SCALED -> CBFyr; otherwise 1 (full deduction of the carbon price paid).
A37: Base year of the product activity data Q0 | B37: 2024 | C37: year | D37: =B37 -> 2024 | E37: BaseYr | F37: Prototype v0.11 Manual inputs.
A39: C. CPAT values in the reporting year (live lookups into CPAT_Outputs; nothing typed)
A40: Quantity | B40: CPAT code | C40: EG1 | D40: EG2 | E40: EG3 | F40: EG4 | G40: Unit | H40: Notes
A41: Total GHG incl. LULUCF - baseline | B41: egy.mit.ghg.tot.inc.1 | C41: =INDEX(CPO_Data,MATCH($B41&"|"&C$40,CPO_Keys,0),MATCH(Yr,CPO_Years,0)) -> 594.156 | D41: =INDEX(CPO_Data,MATCH($B41&"|"&D$40,CPO_Keys,0),MATCH(Yr,CPO_Years,0)) -> 594.156 | E41: =INDEX(CPO_Data,MATCH($B41&"|"&E$40,CPO_Keys,0),MATCH(Yr,CPO_Years,0)) -> 594.156 | F41: =INDEX(CPO_Data,MATCH($B41&"|"&F$40,CPO_Keys,0),MATCH(Yr,CPO_Years,0)) -> 594.156 | G41: MtCO2e
A42: Total GHG incl. LULUCF - policy | B42: egy.mit.ghg.tot.inc.2 | C42: =INDEX(CPO_Data,MATCH($B42&"|"&C$40,CPO_Keys,0),MATCH(Yr,CPO_Years,0)) -> 555.279 | D42: =INDEX(CPO_Data,MATCH($B42&"|"&D$40,CPO_Keys,0),MATCH(Yr,CPO_Years,0)) -> 553.154 | E42: =INDEX(CPO_Data,MATCH($B42&"|"&E$40,CPO_Keys,0),MATCH(Yr,CPO_Years,0)) -> 572.614 | F42: =INDEX(CPO_Data,MATCH($B42&"|"&F$40,CPO_Keys,0),MATCH(Yr,CPO_Years,0)) -> 584.539 | G42: MtCO2e
A43: IPPU GHG - baseline | B43: egy.mit.ghg.ipr.tot.1 | C43: =INDEX(CPO_Data,MATCH($B43&"|"&C$40,CPO_Keys,0),MATCH(Yr,CPO_Years,0)) -> 85.97 | D43: =INDEX(CPO_Data,MATCH($B43&"|"&D$40,CPO_Keys,0),MATCH(Yr,CPO_Years,0)) -> 85.97 | E43: =INDEX(CPO_Data,MATCH($B43&"|"&E$40,CPO_Keys,0),MATCH(Yr,CPO_Years,0)) -> 85.97 | F43: =INDEX(CPO_Data,MATCH($B43&"|"&F$40,CPO_Keys,0),MATCH(Yr,CPO_Years,0)) -> 85.97 | G43: MtCO2e
A44: IPPU GHG - policy | B44: egy.mit.ghg.ipr.tot.2 | C44: =INDEX(CPO_Data,MATCH($B44&"|"&C$40,CPO_Keys,0),MATCH(Yr,CPO_Years,0)) -> 74.015 | D44: =INDEX(CPO_Data,MATCH($B44&"|"&D$40,CPO_Keys,0),MATCH(Yr,CPO_Years,0)) -> 73.407 | E44: =INDEX(CPO_Data,MATCH($B44&"|"&E$40,CPO_Keys,0),MATCH(Yr,CPO_Years,0)) -> 77.708 | F44: =INDEX(CPO_Data,MATCH($B44&"|"&F$40,CPO_Keys,0),MATCH(Yr,CPO_Years,0)) -> 86.077 | G44: MtCO2e
A45: Energy CO2 - baseline | B45: egy.mit.co2.enr.tot.1 | C45: =INDEX(CPO_Data,MATCH($B45&"|"&C$40,CPO_Keys,0),MATCH(Yr,CPO_Years,0)) -> 340.66 | D45: =INDEX(CPO_Data,MATCH($B45&"|"&D$40,CPO_Keys,0),MATCH(Yr,CPO_Years,0)) -> 340.66 | E45: =INDEX(CPO_Data,MATCH($B45&"|"&E$40,CPO_Keys,0),MATCH(Yr,CPO_Years,0)) -> 340.66 | F45: =INDEX(CPO_Data,MATCH($B45&"|"&F$40,CPO_Keys,0),MATCH(Yr,CPO_Years,0)) -> 340.66 | G45: MtCO2
A46: Energy CO2 - policy | B46: egy.mit.co2.enr.tot.2 | C46: =INDEX(CPO_Data,MATCH($B46&"|"&C$40,CPO_Keys,0),MATCH(Yr,CPO_Years,0)) -> 313.865 | D46: =INDEX(CPO_Data,MATCH($B46&"|"&D$40,CPO_Keys,0),MATCH(Yr,CPO_Years,0)) -> 312.396 | E46: =INDEX(CPO_Data,MATCH($B46&"|"&E$40,CPO_Keys,0),MATCH(Yr,CPO_Years,0)) -> 327.453 | F46: =INDEX(CPO_Data,MATCH($B46&"|"&F$40,CPO_Keys,0),MATCH(Yr,CPO_Years,0)) -> 330.99 | G46: MtCO2
A47: Industry energy CO2 - baseline | B47: egy.mit.co2.ind.1 | C47: =INDEX(CPO_Data,MATCH($B47&"|"&C$40,CPO_Keys,0),MATCH(Yr,CPO_Years,0)) -> 88.973 | D47: =INDEX(CPO_Data,MATCH($B47&"|"&D$40,CPO_Keys,0),MATCH(Yr,CPO_Years,0)) -> 88.973 | E47: =INDEX(CPO_Data,MATCH($B47&"|"&E$40,CPO_Keys,0),MATCH(Yr,CPO_Years,0)) -> 88.973 | F47: =INDEX(CPO_Data,MATCH($B47&"|"&F$40,CPO_Keys,0),MATCH(Yr,CPO_Years,0)) -> 88.973 | G47: MtCO2
A48: Industry energy CO2 - policy | B48: egy.mit.co2.ind.2 | C48: =INDEX(CPO_Data,MATCH($B48&"|"&C$40,CPO_Keys,0),MATCH(Yr,CPO_Years,0)) -> 76.6 | D48: =INDEX(CPO_Data,MATCH($B48&"|"&D$40,CPO_Keys,0),MATCH(Yr,CPO_Years,0)) -> 75.971 | E48: =INDEX(CPO_Data,MATCH($B48&"|"&E$40,CPO_Keys,0),MATCH(Yr,CPO_Years,0)) -> 80.422 | F48: =INDEX(CPO_Data,MATCH($B48&"|"&F$40,CPO_Keys,0),MATCH(Yr,CPO_Years,0)) -> 89.084 | G48: MtCO2
A49: Carbon price trajectory | B49: egy.mit.cptraj.2 | C49: =INDEX(CPO_Data,MATCH($B49&"|"&C$40,CPO_Keys,0),MATCH(Yr,CPO_Years,0)) -> 20 | D49: =INDEX(CPO_Data,MATCH($B49&"|"&D$40,CPO_Keys,0),MATCH(Yr,CPO_Years,0)) -> 20 | E49: =INDEX(CPO_Data,MATCH($B49&"|"&E$40,CPO_Keys,0),MATCH(Yr,CPO_Years,0)) -> 20 | F49: =INDEX(CPO_Data,MATCH($B49&"|"&F$40,CPO_Keys,0),MATCH(Yr,CPO_Years,0)) -> 0 | G49: $/tCO2
A50: Effective (coverage-weighted) carbon price | B50: egy.mit.eff.cptraj.2 | C50: =INDEX(CPO_Data,MATCH($B50&"|"&C$40,CPO_Keys,0),MATCH(Yr,CPO_Years,0)) -> 19.8 | D50: =INDEX(CPO_Data,MATCH($B50&"|"&D$40,CPO_Keys,0),MATCH(Yr,CPO_Years,0)) -> 19.801 | E50: =INDEX(CPO_Data,MATCH($B50&"|"&E$40,CPO_Keys,0),MATCH(Yr,CPO_Years,0)) -> 2.807 | F50: =INDEX(CPO_Data,MATCH($B50&"|"&F$40,CPO_Keys,0),MATCH(Yr,CPO_Years,0)) -> 0 | G50: $/tCO2
A51: Net new revenue - baseline | B51: egy.mit.rev.new.usd.1 | C51: =INDEX(CPO_Data,MATCH($B51&"|"&C$40,CPO_Keys,0),MATCH(Yr,CPO_Years,0)) -> -47.61 | D51: =INDEX(CPO_Data,MATCH($B51&"|"&D$40,CPO_Keys,0),MATCH(Yr,CPO_Years,0)) -> -47.61 | E51: =INDEX(CPO_Data,MATCH($B51&"|"&E$40,CPO_Keys,0),MATCH(Yr,CPO_Years,0)) -> -47.61 | F51: =INDEX(CPO_Data,MATCH($B51&"|"&F$40,CPO_Keys,0),MATCH(Yr,CPO_Years,0)) -> -47.61 | G51: $bn
A52: Net new revenue - policy | B52: egy.mit.rev.new.usd.2 | C52: =INDEX(CPO_Data,MATCH($B52&"|"&C$40,CPO_Keys,0),MATCH(Yr,CPO_Years,0)) -> -37.18 | D52: =INDEX(CPO_Data,MATCH($B52&"|"&D$40,CPO_Keys,0),MATCH(Yr,CPO_Years,0)) -> -36.99 | E52: =INDEX(CPO_Data,MATCH($B52&"|"&E$40,CPO_Keys,0),MATCH(Yr,CPO_Years,0)) -> -44.92 | F52: =INDEX(CPO_Data,MATCH($B52&"|"&F$40,CPO_Keys,0),MATCH(Yr,CPO_Years,0)) -> -40.91 | G52: $bn
... A62: Air-pollution deaths - baseline total | B62: egy.air.mort | C62: =INDEX(CPO_Data,MATCH($B62&"|"&C$40,CPO_Keys,0),MATCH(Yr,CPO_Years,0)) -> 82651 | D62: =INDEX(CPO_Data,MATCH($B62&"|"&D$40,CPO_Keys,0),MATCH(Yr,CPO_Years,0)) -> 82651 | E62: =INDEX(CPO_Data,MATCH($B62&"|"&E$40,CPO_Keys,0),MATCH(Yr,CPO_Years,0)) -> 82651 | F62: =INDEX(CPO_Data,MATCH($B62&"|"&F$40,CPO_Keys,0),MATCH(Yr,CPO_Years,0)) -> 82651 | G62: deaths
A63: Carbon-tax revenue, six fuels (derived) | B63: CV_revctax | C63: =SUM(C53:C58) -> 6.23 | D63: =SUM(D53:D58) -> 6.19 | E63: =SUM(E53:E58) -> 0.93 | F63: =SUM(F53:F58) -> 0 | G63: $bn | H63: Gross carbon-tax receipts of the CPAT run (post-response). Replaces the original 'price x 2026 covered emissions' (V7).
A64: Air-pollution deaths avoided, all ages (derived) | B64: CV_deaths | C64: =SUM(C59:C61) -> 1564 | D64: =SUM(D59:D61) -> 1631 | E64: =SUM(E59:E61) -> 546 | F64: =SUM(F59:F61) -> 213 | G64: deaths | H64: CPAT's own estimate for the scenario and year.
A65: Coverage factor kappa of the CPAT run (derived) | B65: CV_kappa | C65: =IF(KappaMode="ONE",1,IFERROR(MIN(1,(C50/C49)*C45/C47),1)) -> 1 | D65: =IF(KappaMode="ONE",1,IFERROR(MIN(1,(D50/D49)*D45/D47),1)) -> 1 | E65: =IF(KappaMode="ONE",1,IFERROR(MIN(1,(E50/E49)*E45/E47),1)) -> 0.53737236 | F65: =IF(KappaMode="ONE",1,IFERROR(MIN(1,(F50/F49)*F45/F47),1)) -> 1 | G65: - | H65: Share of industrial energy CO2 actually priced in the CPAT run (eff.cptraj is coverage-weighted over energy CO2). SCALE keeps this raw kappa for 1/kappa adjustments; ONE forces 1.
A66: Delta total GHG, policy - baseline (derived) | B66: CV_dghg | C66: =C42-C41 -> -38.877 | D66: =D42-D41 -> -41.002 | E66: =E42-E41 -> -21.542 | F66: =F42-F41 -> -9.617 | G66: MtCO2e | H66: Single base: policy minus baseline in the reporting year.
A67: Delta IPPU GHG (derived) | B67: CV_dippu | C67: =C44-C43 -> -11.955 | D67: =D44-D43 -> -12.563 | E67: =E44-E43 -> -8.262 | F67: =F44-F43 -> 0.107 | G67: MtCO2e | H67: CPAT's IPPU response (scaled with industrial energy CO2; MajorIssues #17).
A68: Delta energy CO2 (derived) | B68: CV_denr | C68: =C46-C45 -> -26.795 | D68: =D46-D45 -> -28.264 | E68: =E46-E45 -> -13.207 | F68: =F46-F45 -> -9.67 | G68: MtCO2 | H68: Drives air-pollution deaths.
A69: Delta industry energy CO2 (derived) | B69: CV_dind | C69: =C48-C47 -> -12.373 | D69: =D48-D47 -> -13.002 | E69: =E48-E47 -> -8.551 | F69: =F48-F47 -> 0.111 | G69: MtCO2 | H69: Intensity share s_int, output share 1 - s_int (TechNote App. A).
A70: Delta net new revenue, policy - baseline (derived) | B70: CV_drev | C70: =C52-C51 -> 10.43 | D70: =D52-D51 -> 10.62 | E70: =E52-E51 -> 2.69 | F70: =F52-F51 -> 6.7 | G70: $bn | H70: PolicyMatrix column AR (was 10.62 for 2A = EG2 value; MajorIssues #6).
A72: D. Policy bundles (scenario mapping and instrument settings)
A73: Bundle | B73: CPAT scenario | C73: Scope (ALL/IND) | D73: Process priced (1/0) | E73: theta: OBR rebate share | F73: phi: fund share of net revenue | G73: tau: carbon price in Yr ($/t) | H73: Recycling | I73: Trajectory | J73: Notes
A74: 1A | B74: EG1 | C74: ALL | D74: 1 | E74: 0 | F74: 0 | G74: =INDEX(CV_cptraj,MATCH(B74,CV_Hdr,0)) -> 20 | H74: Public investment | I74: FLAT20 | J74: Economy-wide fuel levy (EG1) + CBAM process emissions priced. Original used EG2 values (MajorIssues #3).
A75: 2A | B75: EG1 | C75: ALL | D75: 0 | E75: 0 | F75: 0 | G75: =INDEX(CV_cptraj,MATCH(B75,CV_Hdr,0)) -> 20 | H75: Public investment | I75: FLAT20 | J75: Economy-wide fuel levy (EG1), process not priced.
A76: 2B | B76: EG2 | C76: ALL | D76: 0 | E76: 0 | F76: 0 | G76: =INDEX(CV_cptraj,MATCH(B76,CV_Hdr,0)) -> 20 | H76: Households | I76: FLAT20 | J76: As 2A with household transfers (EG2).
A77: 3A | B77: EG3 | C77: IND | D77: 1 | E77: 0 | F77: 0 | G77: =INDEX(CV_cptraj,MATCH(B77,CV_Hdr,0)) -> 20 | H77: Households | I77: RAMP | J77: Industry-only price (EG3): industrial energy CO2 + CBAM process emissions.
A78: 3B | B78: EG3 | C78: IND | D78: 1 | E78: 1 | F78: 0 | G78: =INDEX(CV_cptraj,MATCH(B78,CV_Hdr,0)) -> 20 | H78: Firms (output) | I78: RAMP | J78: 3A + output-based rebate for CBAM producers (theta = 1: benchmark = own baseline intensity). Built from EG3 with OBR logic; EG4 (feebate run) is unusable (MajorIssues #8).
A79: 3C | B79: EG3 | C79: IND | D79: 1 | E79: 0 | F79: 1 | G79: =INDEX(CV_cptraj,MATCH(B79,CV_Hdr,0)) -> 20 | H79: Firms (abatement) | I79: RAMP | J79: 3A with net revenue paid into an abatement fund (phi = 1) acting as shadow price sigma (Inputs A).
A81: E. CBAM products (activity, trade, prices from prototype v0.11 Manual inputs; emission factors Egypt CBAM EF v0.1; process half-elasticity sets from TASK-D)
A82: Product | B82: Q0 output in BaseYr (kt) | C82: g: output growth /yr | D82: X: EU exports (kt) | E82: P: price ($/t) | F82: fc: fuel combustion (tCO2/t) EF v0.1 | G82: fp: fuel-based process (tCO2/t) EF v0.1 | H82: np: non-fuel process (tCO2/t) EF v0.1 | I82: no: non-CO2 process (tCO2e/t) EF v0.1 | J82: F = fc + fp (selected EF set) | K82: G = max(np,0) + max(no,0) (selected EF set) | L82: ER100: prototype | M82: ER100: IPCC central | N82: ER100: IPCC 2030 horizon | O82: ER100: IPCC long-run | P82: ER100: selected set | Q82: beta = -LN(1-ER100)/100 | R82: fc prototype v0.11 | S82: fp prototype v0.11 | T82: np prototype v0.11 | U82: no prototype v0.11
A83: DRI-EAF steel | B83: 5100 | C83: 0.044 | D83: 580 | E83: 750 | F83: 0.17797725 | G83: 0.39301352 | H83: 0.03790102 | I83: 0 | J83: =IF(EFSet="PROTOTYPE",R83+S83,F83+G83) -> 0.57099077 | K83: =IF(EFSet="PROTOTYPE",MAX(T83,0)+MAX(U83,0),MAX(H83,0)+MAX(I83,0)) -> 0.03790102 | L83: 0.1 | M83: 0.3433 | N83: 0.1133 | O83: 0.5734 | P83: =IF(BetaSet="PROTOTYPE",L83,IF(BetaSet="IPCC_2030",N83,IF(BetaSet="IPCC_LONGRUN",O83,M83))) -> 0.3433 | Q83: =IF(BetaSet="PROTOTYPE",-LN(1-P83)/100,-LN(1-P83)/PStar) -> 0.0034469507 | R83: 0.12903 | S83: 0.561 | T83: 0.04 | U83: 0
A84: Scrap-EAF steel | B84: 4800 | C84: 0.044 | D84: 300 | E84: 680 | F84: 0.04488 | G84: 0 | H84: 0.04398115 | I84: 0 | J84: =IF(EFSet="PROTOTYPE",R84+S84,F84+G84) -> 0.04488 | K84: =IF(EFSet="PROTOTYPE",MAX(T84,0)+MAX(U84,0),MAX(H84,0)+MAX(I84,0)) -> 0.04398115 | L84: 0.02 | M84: 0.181 | N84: 0.0951 | O84: 0.2669 | P84: =IF(BetaSet="PROTOTYPE",L84,IF(BetaSet="IPCC_2030",N84,IF(BetaSet="IPCC_LONGRUN",O84,M84))) -> 0.181 | Q84: =IF(BetaSet="PROTOTYPE",-LN(1-P84)/100,-LN(1-P84)/PStar) -> 0.0016366491 | R84: 0.14025 | S84: 0 | T84: 0.015 | U84: 0
A85: BF-BOF steel | B85: 0 | C85: 0 | D85: 0 | E85: 620 | F85: 0.1683 | G85: 1.2566803 | H85: 0.05276542 | I85: 0 | J85: =IF(EFSet="PROTOTYPE",R85+S85,F85+G85) -> 1.4249803 | K85: =IF(EFSet="PROTOTYPE",MAX(T85,0)+MAX(U85,0),MAX(H85,0)+MAX(I85,0)) -> 0.05276542 | L85: 0.05 | M85: 0.2803 | N85: 0.1016 | O85: 0.4589 | P85: =IF(BetaSet="PROTOTYPE",L85,IF(BetaSet="IPCC_2030",N85,IF(BetaSet="IPCC_LONGRUN",O85,M85))) -> 0.2803 | Q85: =IF(BetaSet="PROTOTYPE",-LN(1-P85)/100,-LN(1-P85)/PStar) -> 0.0026960723 | R85: 0.3844 | S85: 1.5376 | T85: 0.25 | U85: 0
A86: Clinker | B86: 50000 | C86: 0.033 | D86: 800 | E86: 110 | F86: 0.3135685 | G86: 0 | H86: 0.53702616 | I86: 0 | J86: =IF(EFSet="PROTOTYPE",R86+S86,F86+G86) -> 0.3135685 | K86: =IF(EFSet="PROTOTYPE",MAX(T86,0)+MAX(U86,0),MAX(H86,0)+MAX(I86,0)) -> 0.53702616 | L86: 0.08 | M86: 0.3352 | N86: 0.1925 | O86: 0.4779 | P86: =IF(BetaSet="PROTOTYPE",L86,IF(BetaSet="IPCC_2030",N86,IF(BetaSet="IPCC_LONGRUN",O86,M86))) -> 0.3352 | Q86: =IF(BetaSet="PROTOTYPE",-LN(1-P86)/100,-LN(1-P86)/PStar) -> 0.0033464675 | R86: 0.2883 | S86: 0 | T86: 0.526 | U86: 0
A87: Ammonia | B87: 1785 | C87: 0.022 | D87: 120 | E87: 450 | F87: 0.71247 | G87: 1.26225 | H87: 0 | I87: 0 | J87: =IF(EFSet="PROTOTYPE",R87+S87,F87+G87) -> 1.97472 | K87: =IF(EFSet="PROTOTYPE",MAX(T87,0)+MAX(U87,0),MAX(H87,0)+MAX(I87,0)) -> 0 | L87: 0.18 | M87: 0.2974 | N87: 0.1499 | O87: 0.4449 | P87: =IF(BetaSet="PROTOTYPE",L87,IF(BetaSet="IPCC_2030",N87,IF(BetaSet="IPCC_LONGRUN",O87,M87))) -> 0.2974 | Q87: =IF(BetaSet="PROTOTYPE",-LN(1-P87)/100,-LN(1-P87)/PStar) -> 0.0028931766 | R87: 0.3927 | S87: 1.4586 | T87: 0 | U87: 0
A88: Urea | B88: 2800 | C88: 0.022 | D88: 1600 | E88: 380 | F88: 0.1122 | G88: 0 | H88: 0 | I88: 0 | J88: =IF(EFSet="PROTOTYPE",R88+S88,F88+G88) -> 0.1122 | K88: =IF(EFSet="PROTOTYPE",MAX(T88,0)+MAX(U88,0),MAX(H88,0)+MAX(I88,0)) -> 0 | L88: 0 | M88: 0.1158 | N88: 0.0479 | O88: 0.1838 | P88: =IF(BetaSet="PROTOTYPE",L88,IF(BetaSet="IPCC_2030",N88,IF(BetaSet="IPCC_LONGRUN",O88,M88))) -> 0.1158 | Q88: =IF(BetaSet="PROTOTYPE",-LN(1-P88)/100,-LN(1-P88)/PStar) -> 0.0010087869 | R88: 0.1122 | S88: 0 | T88: -0.733 | U88: 0
A89: Ammonium nitrate | B89: 600 | C89: 0.022 | D89: 80 | E89: 320 | F89: 0.1122 | G89: 0 | H89: 0 | I89: 0.9944125 | J89: =IF(EFSet="PROTOTYPE",R89+S89,F89+G89) -> 0.1122 | K89: =IF(EFSet="PROTOTYPE",MAX(T89,0)+MAX(U89,0),MAX(H89,0)+MAX(I89,0)) -> 0.9944125 | L89: 0.65 | M89: 0.6179 | N89: 0.5539 | O89: 0.6818 | P89: =IF(BetaSet="PROTOTYPE",L89,IF(BetaSet="IPCC_2030",N89,IF(BetaSet="IPCC_LONGRUN",O89,M89))) -> 0.6179 | Q89: =IF(BetaSet="PROTOTYPE",-LN(1-P89)/100,-LN(1-P89)/PStar) -> 0.0078858436 | R89: 0.1122 | S89: 0 | T89: 0 | U89: 0.97
A90: Aluminium | B90: 300 | C90: 0.055 | D90: 167 | E90: 2400 | F90: 0.12342 | G90: 0 | H90: 1.623493 | I90: 0.774 | J90: =IF(EFSet="PROTOTYPE",R90+S90,F90+G90) -> 0.12342 | K90: =IF(EFSet="PROTOTYPE",MAX(T90,0)+MAX(U90,0),MAX(H90,0)+MAX(I90,0)) -> 2.397493 | L90: 0.08 | M90: 0.2164 | N90: 0.0691 | O90: 0.3638 | P90: =IF(BetaSet="PROTOTYPE",L90,IF(BetaSet="IPCC_2030",N90,IF(BetaSet="IPCC_LONGRUN",O90,M90))) -> 0.2164 | Q90: =IF(BetaSet="PROTOTYPE",-LN(1-P90)/100,-LN(1-P90)/PStar) -> 0.0019988245 | R90: 0.156 | S90: 0 | T90: 1.5 | U90: 0.85
A91: ER100 = emission-intensity reduction at $100/tCO2. Prototype values are the v0.11 placeholders; IPCC sets are the TASK-D drop-in (AR6 WGIII Ch.11 / IEA sectoral MACC bands); AN = N2O-weighted blend of the unabated (0.721) and abated (0.329) rows at the EF workbook's 50 % HNO3 N2O abatement share. EF v0.1 = EGY_CBAM_EF_v0.1.xlsx Products!D:G (CBAM conventions; urea np = 0 under the CBAM rule; AN 'no' = integrated HNO3 N2O, kernel convention). For IPCC sets beta = -LN(1-ER100)/PStar (PStar default 122 USD2024/t); the PROTOTYPE set keeps -LN(1-ER100)/100. Prototype v0.11 EFs (R:U, grey) are used when EFSet = PROTOTYPE (urea np -0.733 enters G as 0).
A93: F. Year vectors 2022-2041
A94: Vector | B94: 2022 | C94: 2023 | D94: 2024 | E94: 2025 | F94: 2026 | G94: 2027 | H94: 2028 | I94: 2029 | J94: 2030 | K94: 2031 | L94: 2032 | M94: 2033 | N94: 2034 | O94: 2035 | P94: 2036 | Q94: 2037 | R94: 2038 | S94: 2039 | T94: 2040 | U94: 2041
A95: CBAM phase-in factor CBF (EU definitive period) | B95: 0 | C95: 0 | D95: 0 | E95: 0 | F95: 0.025 | G95: 0.05 | H95: 0.1 | I95: 0.225 | J95: 0.485 | K95: 0.61 | L95: 0.735 | M95: 0.86 | N95: 1 | O95: 1 | P95: 1 | Q95: 1 | R95: 1 | S95: 1 | T95: 1 | U95: 1
A96: Price trajectory 1 'flat' ($20 from 2028; label check only) | B96: 0 | C96: 0 | D96: 0 | E96: 0 | F96: 0 | G96: 0 | H96: 20 | I96: 20 | J96: 20 | K96: 20 | L96: 20 | M96: 20 | N96: 20 | O96: 20 | P96: 20 | Q96: 20 | R96: 20 | S96: 20 | T96: 20 | U96: 20
A97: Price trajectory 2 'rising' = CPAT EG3 cptraj.2 (live) | B97: =INDEX(CPO_Data,MATCH("egy.mit.cptraj.2|EG3",CPO_Keys,0),MATCH(B$94,CPO_Years,0)) -> 0 | C97: =INDEX(CPO_Data,MATCH("egy.mit.cptraj.2|EG3",CPO_Keys,0),MATCH(C$94,CPO_Years,0)) -> 0 | D97: =INDEX(CPO_Data,MATCH("egy.mit.cptraj.2|EG3",CPO_Keys,0),MATCH(D$94,CPO_Years,0)) -> 0 | E97: =INDEX(CPO_Data,MATCH("egy.mit.cptraj.2|EG3",CPO_Keys,0),MATCH(E$94,CPO_Years,0)) -> 0 | F97: =INDEX(CPO_Data,MATCH("egy.mit.cptraj.2|EG3",CPO_Keys,0),MATCH(F$94,CPO_Years,0)) -> 0 | G97: =INDEX(CPO_Data,MATCH("egy.mit.cptraj.2|EG3",CPO_Keys,0),MATCH(G$94,CPO_Years,0)) -> 0 | H97: =INDEX(CPO_Data,MATCH("egy.mit.cptraj.2|EG3",CPO_Keys,0),MATCH(H$94,CPO_Years,0)) -> 5 | I97: =INDEX(CPO_Data,MATCH("egy.mit.cptraj.2|EG3",CPO_Keys,0),MATCH(I$94,CPO_Years,0)) -> 12.5 | ... U97: =INDEX(CPO_Data,MATCH("egy.mit.cptraj.2|EG3",CPO_Keys,0),MATCH(U$94,CPO_Years,0)) -> 102.5
A98: Memo: CPAT EG1 cptraj.2 (live; should equal trajectory 1) | B98: =INDEX(CPO_Data,MATCH("egy.mit.cptraj.2|EG1",CPO_Keys,0),MATCH(B$94,CPO_Years,0)) -> 0 | C98: =INDEX(CPO_Data,MATCH("egy.mit.cptraj.2|EG1",CPO_Keys,0),MATCH(C$94,CPO_Years,0)) -> 0 | D98: =INDEX(CPO_Data,MATCH("egy.mit.cptraj.2|EG1",CPO_Keys,0),MATCH(D$94,CPO_Years,0)) -> 0 | E98: =INDEX(CPO_Data,MATCH("egy.mit.cptraj.2|EG1",CPO_Keys,0),MATCH(E$94,CPO_Years,0)) -> 0 | F98: =INDEX(CPO_Data,MATCH("egy.mit.cptraj.2|EG1",CPO_Keys,0),MATCH(F$94,CPO_Years,0)) -> 0 | G98: =INDEX(CPO_Data,MATCH("egy.mit.cptraj.2|EG1",CPO_Keys,0),MATCH(G$94,CPO_Years,0)) -> 0 | H98: =INDEX(CPO_Data,MATCH("egy.mit.cptraj.2|EG1",CPO_Keys,0),MATCH(H$94,CPO_Years,0)) -> 20 | I98: =INDEX(CPO_Data,MATCH("egy.mit.cptraj.2|EG1",CPO_Keys,0),MATCH(I$94,CPO_Years,0)) -> 20 | ... U98: =INDEX(CPO_Data,MATCH("egy.mit.cptraj.2|EG1",CPO_Keys,0),MATCH(U$94,CPO_Years,0)) -> 20

Sheet CPAT_Outputs
A1: CPAT_Outputs - trimmed CPAT 'Outputs' sheet (Egypt, scenarios EG1..EG4, 2022-2041)
A2: Provenance: CPAT Outputs sheet read via Excel COM (cpat_outputs_egypt_2022_2041.csv in this folder). Values are static data; the rest of the workbook reads them via INDEX/MATCH on the key column C (= code|scenario) and the year header. Mt for emissions, $bn for revenues, $/tCO2 for prices, deaths for air pollution.
A3: CPAT code | B3: Scenario | C3: Key (code|scenario) | D3: Label | E3: 2022 | F3: 2023 | G3: 2024 | H3: 2025 | I3: 2026 | J3: 2027 | K3: 2028 | L3: 2029 | M3: 2030 | N3: 2031 | O3: 2032 | P3: 2033 | Q3: 2034 | R3: 2035 | S3: 2036 | T3: 2037 | U3: 2038 | V3: 2039 | W3: 2040 | X3: 2041
A4: egy.mit.ghg.tot.inc.1 | B4: EG1 | C4: egy.mit.ghg.tot.inc.1|EG1 | D4: Total GHG emissions, inc. LULUCF (baseline) | E4: 400.912 | F4: 417.878 | G4: 450.28 | H4: 474.668 | I4: 488.837 | J4: 507.334 | K4: 531.747 | L4: 560.636 | M4: 594.156 | N4: 637.812 | O4: 701.794 | P4: 772.315 | Q4: 835.748 | R4: 906.166 | S4: 983.294 | T4: 1067.761 | U4: 1160.053 | V4: 1260.639 | W4: 1370.044 | X4: 1487.858
A5: egy.mit.ghg.tot.inc.1 | B5: EG2 | C5: egy.mit.ghg.tot.inc.1|EG2 | D5: Total GHG emissions, inc. LULUCF (baseline) | E5: 400.912 | F5: 417.878 | G5: 450.28 | H5: 474.668 | I5: 488.837 | J5: 507.334 | K5: 531.747 | L5: 560.636 | M5: 594.156 | N5: 637.812 | O5: 701.794 | P5: 772.315 | Q5: 835.748 | R5: 906.166 | S5: 983.294 | T5: 1067.761 | U5: 1160.053 | V5: 1260.639 | W5: 1370.044 | X5: 1487.858
A6: egy.mit.ghg.tot.inc.1 | B6: EG3 | C6: egy.mit.ghg.tot.inc.1|EG3 | D6: Total GHG emissions, inc. LULUCF (baseline) | E6: 400.912 | F6: 417.878 | G6: 450.28 | H6: 474.668 | I6: 488.837 | J6: 507.334 | K6: 531.747 | L6: 560.636 | M6: 594.156 | N6: 637.812 | O6: 701.794 | P6: 772.315 | Q6: 835.748 | R6: 906.166 | S6: 983.294 | T6: 1067.761 | U6: 1160.053 | V6: 1260.639 | W6: 1370.044 | X6: 1487.858
A7: egy.mit.ghg.tot.inc.1 | B7: EG4 | C7: egy.mit.ghg.tot.inc.1|EG4 | D7: Total GHG emissions, inc. LULUCF (baseline) | E7: 400.912 | F7: 417.878 | G7: 450.28 | H7: 474.668 | I7: 488.837 | J7: 507.334 | K7: 531.747 | L7: 560.636 | M7: 594.156 | N7: 637.812 | O7: 701.794 | P7: 772.315 | Q7: 835.748 | R7: 906.166 | S7: 983.294 | T7: 1067.761 | U7: 1160.053 | V7: 1260.639 | W7: 1370.044 | X7: 1487.858
A8: egy.mit.ghg.tot.inc.2 | B8: EG1 | C8: egy.mit.ghg.tot.inc.2|EG1 | D8: Total GHG emissions, inc. LULUCF (policy) | E8: 400.912 | F8: 417.779 | G8: 450.165 | H8: 474.557 | I8: 488.728 | J8: 507.156 | K8: 497.15 | L8: 517.963 | M8: 555.279 | N8: 598.301 | O8: 667.417 | P8: 723.178 | Q8: 784.768 | R8: 853.19 | S8: 928.765 | T8: 1012.007 | U8: 1103.439 | V8: 1203.523 | W8: 1312.661 | X8: 1430.405
A9: egy.mit.ghg.tot.inc.2 | B9: EG2 | C9: egy.mit.ghg.tot.inc.2|EG2 | D9: Total GHG emissions, inc. LULUCF (policy) | E9: 400.912 | F9: 417.779 | G9: 450.165 | H9: 474.557 | I9: 488.728 | J9: 507.156 | K9: 497.15 | L9: 516.832 | M9: 553.154 | N9: 594.932 | O9: 662.986 | P9: 718.691 | Q9: 779.162 | R9: 846.238 | S9: 920.219 | T9: 1001.454 | U9: 1090.415 | V9: 1187.592 | W9: 1293.482 | X9: 1407.72
A10: egy.mit.ghg.tot.inc.2 | B10: EG3 | C10: egy.mit.ghg.tot.inc.2|EG3 | D10: Total GHG emissions, inc. LULUCF (policy) | E10: 400.912 | F10: 417.874 | G10: 450.275 | H10: 474.663 | I10: 488.833 | J10: 507.294 | K10: 525.956 | L10: 546.53 | M10: 572.614 | N10: 607.838 | O10: 668.18 | P10: 713.418 | Q10: 765.05 | R10: 823.144 | S10: 887.994 | T10: 959.818 | U10: 1039.175 | V10: 1126.569 | W10: 1222.516 | X10: 1326.681
A11: egy.mit.ghg.tot.inc.2 | B11: EG4 | C11: egy.mit.ghg.tot.inc.2|EG4 | D11: Total GHG emissions, inc. LULUCF (policy) | E11: 400.912 | F11: 417.878 | G11: 450.28 | H11: 474.668 | I11: 488.837 | J11: 507.334 | K11: 531.747 | L11: 554.161 | M11: 584.539 | N11: 625.259 | O11: 679.525 | P11: 752.918 | Q11: 812.118 | R11: 877.489 | S11: 949.235 | T11: 1028.243 | U11: 1115.514 | V11: 1212.299 | W11: 1320.263 | X11: 1435.074
A12: egy.mit.ghg.ipr.tot.1 | B12: EG1 | C12: egy.mit.ghg.ipr.tot.1|EG1 | D12: Industrial processes GHG emissions (baseline) | E12: 52.2 | F12: 56.903 | G12: 67.485 | H12: 72.938 | I12: 75.02 | J12: 77.455 | K12: 80.412 | L12: 83.271 | M12: 85.97 | N12: 88.71 | O12: 91.479 | P12: 94.297 | Q12: 97.164 | R12: 100.08 | S12: 103.044 | T12: 106.056 | U12: 109.115 | V12: 112.221 | W12: 115.374 | X12: 118.573
A13: egy.mit.ghg.ipr.tot.1 | B13: EG2 | C13: egy.mit.ghg.ipr.tot.1|EG2 | D13: Industrial processes GHG emissions (baseline) | E13: 52.2 | F13: 56.903 | G13: 67.485 | H13: 72.938 | I13: 75.02 | J13: 77.455 | K13: 80.412 | L13: 83.271 | M13: 85.97 | N13: 88.71 | O13: 91.479 | P13: 94.297 | Q13: 97.164 | R13: 100.08 | S13: 103.044 | T13: 106.056 | U13: 109.115 | V13: 112.221 | W13: 115.374 | X13: 118.573
A14: egy.mit.ghg.ipr.tot.1 | B14: EG3 | C14: egy.mit.ghg.ipr.tot.1|EG3 | D14: Industrial processes GHG emissions (baseline) | E14: 52.2 | F14: 56.903 | G14: 67.485 | H14: 72.938 | I14: 75.02 | J14: 77.455 | K14: 80.412 | L14: 83.271 | M14: 85.97 | N14: 88.71 | O14: 91.479 | P14: 94.297 | Q14: 97.164 | R14: 100.08 | S14: 103.044 | T14: 106.056 | U14: 109.115 | V14: 112.221 | W14: 115.374 | X14: 118.573
... A131: egy.air.cad.net | B131: EG4 | C131: egy.air.cad.net|EG4 | D131: Cumulative averted deaths - net | E131: 0 | F131: 0 | G131: 0 | H131: 0 | I131: 0 | J131: 0 | K131: 0 | L131: 112 | M131: 326 | N131: 663 | O131: 2939 | P131: 5359 | Q131: 7484 | R131: 9984 | S131: 12409 | T131: 14737 | U131: 17281 | V131: 19710 | W131: 22213 | X131: 0

Sheet CBAM_Products
A1: CBAM_Products - product-level engine, one block per bundle (eight CBAM goods)
A2: Each block: row 1 scalars (from Inputs), rows 2-9 products, row 10 totals. Units: Q kt, emissions MtCO2(e), revenues and rebates $m, prices $/t, obligations $/t of product. Formulas are the prototype's (cost pass-through dp -> output Q = Qb(1+dp)^eps; process intensity via beta; CBAM obligation per tonne obl = MAX(0, CBF*P_EU*EI - S*MAX(0,d)) with d = carbon price paid net of rebate per tonne) plus the fuel-intensity factor xf (REBUILD only; = 1 in PROTOTYPE mode).
A4: Bundle 1A - Economy-wide fuel levy (EG1) + CBAM process emissions priced. Original used EG2 values (MajorIssues #3).
A5: Bundle | B5: tau: carbon price | C5: tau_p: process price | D5: obrrb: OBR rebate rate | E5: fundsp: fund shadow price | F5: incl_f | G5: incl_p | H5: xf: fuel-intensity factor | I5: CBF (selected conv.) | J5: P_EU | K5: S (selected conv.) | L5: CBF (FULL) | M5: CBF (NOPHASE) | N5: Year | O5: CPAT scenario | P5: b_f | Q5: beta set | R5: Mode
A6: 1A | B6: =INDEX(BT_Tau,MATCH($A$6,BT_Code,0)) -> 20 | C6: =B6*INDEX(BT_Flag,MATCH($A$6,BT_Code,0)) -> 20 | D6: =INDEX(BT_Theta,MATCH($A$6,BT_Code,0))*B6 -> 0 | E6: =INDEX(BT_Phi,MATCH($A$6,BT_Code,0))*SigmaEff -> 0 | F6: 1 | G6: =INDEX(BT_Flag,MATCH($A$6,BT_Code,0)) -> 1 | H6: =IF(Mode="PROTOTYPE",1,EXP(Bf*(F6*B6+E6))) -> 0.95131318 | I6: =CBFsel -> 0.485 | J6: =PEU -> 100 | K6: =Ssel -> 1 | L6: =CBFyr -> 0.485 | M6: 1 | N6: =Yr -> 2030 | O6: =INDEX(BT_Scen,MATCH($A$6,BT_Code,0)) -> EG1 | P6: =Bf -> -0.0024955979 | Q6: =BetaSet -> IPCC_CENTRAL | R6: =Mode -> REBUILD
A7: Product | B7: Q0 (kt) | C7: g | D7: X exports (kt) | E7: P ($/t) | F7: F (tCO2/t) | G7: G (tCO2e/t) | H7: beta | I7: Qb: baseline output | J7: kf: fuel cost $/t | K7: kp: process cost $/t | L7: m: rebate $/t | M7: dp: cost/price | N7: Q: output | O7: Ef: fuel emis. | P7: Ep: process emis. | Q7: ER_f: fuel-int. resp. | R7: ER_p: process-int. resp. | S7: post fuel | T7: post process | U7: post total | V7: emrq_i: output ch. | W7: emrq_proc_i | X7: J_i: process>0 | Y7: revf_i $m | Z7: revp_i $m | AA7: rev_i $m | AB7: rebate_i $m | AC7: EI: tCO2/t | AD7: d: net price paid $/t | AE7: obl (sel.) $/t | AF7: obl (FULL) $/t | AG7: obl (NOPHASE) $/t | AH7: cbobl_i $m | AI7: cbobl0_i $m | AJ7: w_den sel | AK7: w_den FULL | AL7: w_den NOPHASE | AM7: w_num sel | AN7: w_num FULL | AO7: w_num NOPHASE | AP7: X*post/Q | AQ7: X*(Ef+Ep)/Q | AR7: X*covered/Q | AS7: covered_i | AT7: Ebase_i | AU7: Efbase_i | AV7: Epbase_i
A8: =Inputs!$A$83 -> DRI-EAF steel | B8: =Inputs!$B$83 -> 5100 | C8: =Inputs!$C$83 -> 0.044 | D8: =Inputs!$D$83 -> 580 | E8: =Inputs!$E$83 -> 750 | F8: =Inputs!$J$83 -> 0.57099077 | G8: =Inputs!$K$83 -> 0.03790102 | H8: =Inputs!$Q$83 -> 0.0034469507 | I8: =B8*(1+C8)^($N$6-BaseYr) -> 6603.4846 | J8: =$F$6*$B$6*F8 -> 11.419815 | K8: =$G$6*$C$6*G8 -> 0.7580204 | L8: =MIN($D$6,$B$6)*$F$6*F8+MIN($D$6,$C$6)*$G$6*G8 -> 0 | M8: =IF(E8>0,(J8+K8-L8)/E8,0) -> 0.016237114 | N8: =I8*(1+M8)^EpsQ1 -> 6561.0772 | O8: =N8*F8/1000 -> 3.7463145 | P8: =N8*G8/1000 -> 0.24867152 | Q8: =O8*($H$6-1) -> -0.18239616 | R8: =-P8*(1-EXP(-H8*($G$6*$C$6+$E$6))) -> -0.016565601 | S8: =O8+Q8 -> 3.5639184 | T8: =P8+R8 -> 0.23210592 | U8: =S8+T8 -> 3.7960243 | V8: =(O8+P8)*(1-(1+M8)^(-EpsQ1)) -> -0.025821511 | W8: =P8*(1-(1+M8)^(-EpsQ1)) -> -0.0016072833 | X8: =IF(G8>0,1,0) -> 1 | Y8: =S8*$F$6*$B$6 -> 71.278367 | Z8: =(P8*X8+R8)*$G$6*$C$6 -> 4.6421183 | AA8: =Y8+Z8 -> 75.920486 | AB8: =L8*N8/1000 -> 0 | AC8: =IF(N8>0,U8*1000/N8,0) -> 0.57856723 | AD8: =IF(N8>0,AA8*1000/N8-L8,0) -> 11.571345 | AE8: =MAX(0,$I$6*$J$6*AC8-$K$6*MAX(0,AD8)) -> 16.489166 | AF8: =MAX(0,$L$6*$J$6*AC8-MAX(0,AD8)) -> 16.489166 | AG8: =MAX(0,$M$6*$J$6*AC8-MAX(0,AD8)) -> 46.285379 | AH8: =IF(B8>0,D8*N8/B8*AE8/1000,0) -> 12.303585 | AI8: =D8*(1+C8)^($N$6-BaseYr)*$I$6*$J$6*(F8+G8)/1000 -> 22.177513 | AJ8: =D8*$I$6*$J$6*(F8+G8) -> 17128.126 | AK8: =D8*$L$6*$J$6*(F8+G8) -> 17128.126 | AL8: =D8*$M$6*$J$6*(F8+G8) -> 35315.724 | AM8: =D8*AE8 -> 9563.7164 | AN8: =D8*AF8 -> 9563.7164 | AO8: =D8*AG8 -> 26845.52 | AP8: =IF(N8>0,D8*U8/N8,0) -> 0.335569 | AQ8: =IF(N8>0,D8*(O8+P8)/N8,0) -> 0.35315724 | AR8: =IF(N8>0,D8*AS8/N8,0) -> 0.35315724 | AS8: =O8*IF($F$6>0,1,0)+P8*X8*IF($G$6>0,1,0) -> 3.994986 | AT8: =I8*(F8+G8)/1000 -> 4.0208075 | AU8: =I8*F8/1000 -> 3.7705287 | AV8: =I8*G8/1000 -> 0.2502788
A9: =Inputs!$A$84 -> Scrap-EAF steel | B9: =Inputs!$B$84 -> 4800 | C9: =Inputs!$C$84 -> 0.044 | D9: =Inputs!$D$84 -> 300 | E9: =Inputs!$E$84 -> 680 | F9: =Inputs!$J$84 -> 0.04488 | G9: =Inputs!$K$84 -> 0.04398115 | H9: =Inputs!$Q$84 -> 0.0016366491 | I9: =B9*(1+C9)^($N$6-BaseYr) -> 6215.0443 | J9: =$F$6*$B$6*F9 -> 0.8976 | K9: =$G$6*$C$6*G9 -> 0.879623 | L9: =MIN($D$6,$B$6)*$F$6*F9+MIN($D$6,$C$6)*$G$6*G9 -> 0 | M9: =IF(E9>0,(J9+K9-L9)/E9,0) -> 0.0026135632 | N9: =I9*(1+M9)^EpsQ2 -> 6208.5588 | O9: =N9*F9/1000 -> 0.27864012 | P9: =N9*G9/1000 -> 0.27305956 | Q9: =O9*($H$6-1) -> -0.013566103 | R9: =-P9*(1-EXP(-H9*($G$6*$C$6+$E$6))) -> -0.0087933523 | S9: =O9+Q9 -> 0.26507402 | T9: =P9+R9 -> 0.2642662 | U9: =S9+T9 -> 0.52934022 | V9: =(O9+P9)*(1-(1+M9)^(-EpsQ2)) -> -0.0005763092 | W9: =P9*(1-(1+M9)^(-EpsQ2)) -> -0.00028523986 | X9: =IF(G9>0,1,0) -> 1 | Y9: =S9*$F$6*$B$6 -> 5.3014803 | Z9: =(P9*X9+R9)*$G$6*$C$6 -> 5.2853241 | AA9: =Y9+Z9 -> 10.586804 | AB9: =L9*N9/1000 -> 0 | AC9: =IF(N9>0,U9*1000/N9,0) -> 0.085259758 | AD9: =IF(N9>0,AA9*1000/N9-L9,0) -> 1.7051952 | AE9: =MAX(0,$I$6*$J$6*AC9-$K$6*MAX(0,AD9)) -> 2.4299031 | AF9: =MAX(0,$L$6*$J$6*AC9-MAX(0,AD9)) -> 2.4299031 | AG9: =MAX(0,$M$6*$J$6*AC9-MAX(0,AD9)) -> 6.8207806 | AH9: =IF(B9>0,D9*N9/B9*AE9/1000,0) -> 0.94288727 | AI9: =D9*(1+C9)^($N$6-BaseYr)*$I$6*$J$6*(F9+G9)/1000 -> 1.6740866 | AJ9: =D9*$I$6*$J$6*(F9+G9) -> 1292.9297 | AK9: =D9*$L$6*$J$6*(F9+G9) -> 1292.9297 | AL9: =D9*$M$6*$J$6*(F9+G9) -> 2665.8345 | AM9: =D9*AE9 -> 728.97093 | AN9: =D9*AF9 -> 728.97093 | AO9: =D9*AG9 -> 2046.2342 | AP9: =IF(N9>0,D9*U9/N9,0) -> 0.025577927 | AQ9: =IF(N9>0,D9*(O9+P9)/N9,0) -> 0.026658345 | AR9: =IF(N9>0,D9*AS9/N9,0) -> 0.026658345 | AS9: =O9*IF($F$6>0,1,0)+P9*X9*IF($G$6>0,1,0) -> 0.55169968 | AT9: =I9*(F9+G9)/1000 -> 0.55227598 | AU9: =I9*F9/1000 -> 0.27893119 | AV9: =I9*G9/1000 -> 0.2733448
A10: =Inputs!$A$85 -> BF-BOF steel | B10: =Inputs!$B$85 -> 0 | C10: =Inputs!$C$85 -> 0 | D10: =Inputs!$D$85 -> 0 | E10: =Inputs!$E$85 -> 620 | F10: =Inputs!$J$85 -> 1.4249803 | G10: =Inputs!$K$85 -> 0.05276542 | H10: =Inputs!$Q$85 -> 0.0026960723 | I10: =B10*(1+C10)^($N$6-BaseYr) -> 0 | J10: =$F$6*$B$6*F10 -> 28.499605 | K10: =$G$6*$C$6*G10 -> 1.0553084 | L10: =MIN($D$6,$B$6)*$F$6*F10+MIN($D$6,$C$6)*$G$6*G10 -> 0 | M10: =IF(E10>0,(J10+K10-L10)/E10,0) -> 0.047669216 | N10: =I10*(1+M10)^EpsQ3 -> 0 | O10: =N10*F10/1000 -> 0 | P10: =N10*G10/1000 -> 0 | Q10: =O10*($H$6-1) -> 0 | R10: =-P10*(1-EXP(-H10*($G$6*$C$6+$E$6))) -> 0 | S10: =O10+Q10 -> 0 | T10: =P10+R10 -> 0 | U10: =S10+T10 -> 0 | V10: =(O10+P10)*(1-(1+M10)^(-EpsQ3)) -> 0 | W10: =P10*(1-(1+M10)^(-EpsQ3)) -> 0 | X10: =IF(G10>0,1,0) -> 1 | Y10: =S10*$F$6*$B$6 -> 0 | Z10: =(P10*X10+R10)*$G$6*$C$6 -> 0 | AA10: =Y10+Z10 -> 0 | AB10: =L10*N10/1000 -> 0 | AC10: =IF(N10>0,U10*1000/N10,0) -> 0 | AD10: =IF(N10>0,AA10*1000/N10-L10,0) -> 0 | AE10: =MAX(0,$I$6*$J$6*AC10-$K$6*MAX(0,AD10)) -> 0 | AF10: =MAX(0,$L$6*$J$6*AC10-MAX(0,AD10)) -> 0 | AG10: =MAX(0,$M$6*$J$6*AC10-MAX(0,AD10)) -> 0 | AH10: =IF(B10>0,D10*N10/B10*AE10/1000,0) -> 0 | AI10: =D10*(1+C10)^($N$6-BaseYr)*$I$6*$J$6*(F10+G10)/1000 -> 0 | AJ10: =D10*$I$6*$J$6*(F10+G10) -> 0 | AK10: =D10*$L$6*$J$6*(F10+G10) -> 0 | AL10: =D10*$M$6*$J$6*(F10+G10) -> 0 | AM10: =D10*AE10 -> 0 | AN10: =D10*AF10 -> 0 | AO10: =D10*AG10 -> 0 | AP10: =IF(N10>0,D10*U10/N10,0) -> 0 | AQ10: =IF(N10>0,D10*(O10+P10)/N10,0) -> 0 | AR10: =IF(N10>0,D10*AS10/N10,0) -> 0 | AS10: =O10*IF($F$6>0,1,0)+P10*X10*IF($G$6>0,1,0) -> 0 | AT10: =I10*(F10+G10)/1000 -> 0 | AU10: =I10*F10/1000 -> 0 | AV10: =I10*G10/1000 -> 0
A11: =Inputs!$A$86 -> Clinker | B11: =Inputs!$B$86 -> 50000 | C11: =Inputs!$C$86 -> 0.033 | D11: =Inputs!$D$86 -> 800 | E11: =Inputs!$E$86 -> 110 | F11: =Inputs!$J$86 -> 0.3135685 | G11: =Inputs!$K$86 -> 0.53702616 | H11: =Inputs!$Q$86 -> 0.0033464675 | I11: =B11*(1+C11)^($N$6-BaseYr) -> 60753.588 | J11: =$F$6*$B$6*F11 -> 6.27137 | K11: =$G$6*$C$6*G11 -> 10.740523 | L11: =MIN($D$6,$B$6)*$F$6*F11+MIN($D$6,$C$6)*$G$6*G11 -> 0 | M11: =IF(E11>0,(J11+K11-L11)/E11,0) -> 0.15465357 | N11: =I11*(1+M11)^EpsQ4 -> 59886.201 | O11: =N11*F11/1000 -> 18.778426 | P11: =N11*G11/1000 -> 32.160457 | Q11: =O11*($H$6-1) -> -0.91426194 | R11: =-P11*(1-EXP(-H11*($G$6*$C$6+$E$6))) -> -2.0820269 | S11: =O11+Q11 -> 17.864164 | T11: =P11+R11 -> 30.07843 | U11: =S11+T11 -> 47.942594 | V11: =(O11+P11)*(1-(1+M11)^(-EpsQ4)) -> -0.73779503 | W11: =P11*(1-(1+M11)^(-EpsQ4)) -> -0.46580969 | X11: =IF(G11>0,1,0) -> 1 | Y11: =S11*$F$6*$B$6 -> 357.28329 | Z11: =(P11*X11+R11)*$G$6*$C$6 -> 601.56859 | AA11: =Y11+Z11 -> 958.85188 | AB11: =L11*N11/1000 -> 0 | AC11: =IF(N11>0,U11*1000/N11,0) -> 0.80056162 | AD11: =IF(N11>0,AA11*1000/N11-L11,0) -> 16.011232 | AE11: =MAX(0,$I$6*$J$6*AC11-$K$6*MAX(0,AD11)) -> 22.816006 | AF11: =MAX(0,$L$6*$J$6*AC11-MAX(0,AD11)) -> 22.816006 | AG11: =MAX(0,$M$6*$J$6*AC11-MAX(0,AD11)) -> 64.044929 | AH11: =IF(B11>0,D11*N11/B11*AE11/1000,0) -> 21.861823 | AI11: =D11*(1+C11)^($N$6-BaseYr)*$I$6*$J$6*(F11+G11)/1000 -> 40.101102 | AJ11: =D11*$I$6*$J$6*(F11+G11) -> 33003.073 | AK11: =D11*$L$6*$J$6*(F11+G11) -> 33003.073 | AL11: =D11*$M$6*$J$6*(F11+G11) -> 68047.573 | AM11: =D11*AE11 -> 18252.805 | AN11: =D11*AF11 -> 18252.805 | AO11: =D11*AG11 -> 51235.943 | AP11: =IF(N11>0,D11*U11/N11,0) -> 0.64044929 | AQ11: =IF(N11>0,D11*(O11+P11)/N11,0) -> 0.68047573 | AR11: =IF(N11>0,D11*AS11/N11,0) -> 0.68047573 | AS11: =O11*IF($F$6>0,1,0)+P11*X11*IF($G$6>0,1,0) -> 50.938883 | AT11: =I11*(F11+G11)/1000 -> 51.676678 | AU11: =I11*F11/1000 -> 19.050412 | AV11: =I11*G11/1000 -> 32.626266
A12: =Inputs!$A$87 -> Ammonia | B12: =Inputs!$B$87 -> 1785 | C12: =Inputs!$C$87 -> 0.022 | D12: =Inputs!$D$87 -> 120 | E12: =Inputs!$E$87 -> 450 | F12: =Inputs!$J$87 -> 1.97472 | G12: =Inputs!$K$87 -> 0 | H12: =Inputs!$Q$87 -> 0.0028931766 | I12: =B12*(1+C12)^($N$6-BaseYr) -> 2033.9656 | J12: =$F$6*$B$6*F12 -> 39.4944 | K12: =$G$6*$C$6*G12 -> 0 | L12: =MIN($D$6,$B$6)*$F$6*F12+MIN($D$6,$C$6)*$G$6*G12 -> 0 | M12: =IF(E12>0,(J12+K12-L12)/E12,0) -> 0.087765333 | N12: =I12*(1+M12)^EpsQ5 -> 1966.661 | O12: =N12*F12/1000 -> 3.8836048 | P12: =N12*G12/1000 -> 0 | Q12: =O12*($H$6-1) -> -0.18908039 | R12: =-P12*(1-EXP(-H12*($G$6*$C$6+$E$6))) -> 0 | S12: =O12+Q12 -> 3.6945245 | T12: =P12+R12 -> 0 | U12: =S12+T12 -> 3.6945245 | V12: =(O12+P12)*(1-(1+M12)^(-EpsQ5)) -> -0.13290763 | W12: =P12*(1-(1+M12)^(-EpsQ5)) -> 0 | X12: =IF(G12>0,1,0) -> 0 | Y12: =S12*$F$6*$B$6 -> 73.890489 | Z12: =(P12*X12+R12)*$G$6*$C$6 -> 0 | AA12: =Y12+Z12 -> 73.890489 | AB12: =L12*N12/1000 -> 0 | AC12: =IF(N12>0,U12*1000/N12,0) -> 1.8785772 | AD12: =IF(N12>0,AA12*1000/N12-L12,0) -> 37.571543 | AE12: =MAX(0,$I$6*$J$6*AC12-$K$6*MAX(0,AD12)) -> 53.539449 | AF12: =MAX(0,$L$6*$J$6*AC12-MAX(0,AD12)) -> 53.539449 | AG12: =MAX(0,$M$6*$J$6*AC12-MAX(0,AD12)) -> 150.28617 | AH12: =IF(B12>0,D12*N12/B12*AE12/1000,0) -> 7.0785847 | AI12: =D12*(1+C12)^($N$6-BaseYr)*$I$6*$J$6*(F12+G12)/1000 -> 13.095856 | AJ12: =D12*$I$6*$J$6*(F12+G12) -> 11492.87 | AK12: =D12*$L$6*$J$6*(F12+G12) -> 11492.87 | AL12: =D12*$M$6*$J$6*(F12+G12) -> 23696.64 | AM12: =D12*AE12 -> 6424.7339 | AN12: =D12*AF12 -> 6424.7339 | AO12: =D12*AG12 -> 18034.341 | AP12: =IF(N12>0,D12*U12/N12,0) -> 0.22542926 | AQ12: =IF(N12>0,D12*(O12+P12)/N12,0) -> 0.2369664 | AR12: =IF(N12>0,D12*AS12/N12,0) -> 0.2369664 | AS12: =O12*IF($F$6>0,1,0)+P12*X12*IF($G$6>0,1,0) -> 3.8836048 | AT12: =I12*(F12+G12)/1000 -> 4.0165125 | AU12: =I12*F12/1000 -> 4.0165125 | AV12: =I12*G12/1000 -> 0
A13: =Inputs!$A$88 -> Urea | B13: =Inputs!$B$88 -> 2800 | C13: =Inputs!$C$88 -> 0.022 | D13: =Inputs!$D$88 -> 1600 | E13: =Inputs!$E$88 -> 380 | F13: =Inputs!$J$88 -> 0.1122 | G13: =Inputs!$K$88 -> 0 | H13: =Inputs!$Q$88 -> 0.0010087869 | I13: =B13*(1+C13)^($N$6-BaseYr) -> 3190.5342 | J13: =$F$6*$B$6*F13 -> 2.244 | K13: =$G$6*$C$6*G13 -> 0 | L13: =MIN($D$6,$B$6)*$F$6*F13+MIN($D$6,$C$6)*$G$6*G13 -> 0 | M13: =IF(E13>0,(J13+K13-L13)/E13,0) -> 0.0059052632 | N13: =I13*(1+M13)^EpsQ6 -> 3183.0288 | O13: =N13*F13/1000 -> 0.35713584 | P13: =N13*G13/1000 -> 0 | Q13: =O13*($H$6-1) -> -0.01738781 | R13: =-P13*(1-EXP(-H13*($G$6*$C$6+$E$6))) -> 0 | S13: =O13+Q13 -> 0.33974803 | T13: =P13+R13 -> 0 | U13: =S13+T13 -> 0.33974803 | V13: =(O13+P13)*(1-(1+M13)^(-EpsQ6)) -> -0.00084210264 | W13: =P13*(1-(1+M13)^(-EpsQ6)) -> 0 | X13: =IF(G13>0,1,0) -> 0 | Y13: =S13*$F$6*$B$6 -> 6.7949605 | Z13: =(P13*X13+R13)*$G$6*$C$6 -> 0 | AA13: =Y13+Z13 -> 6.7949605 | AB13: =L13*N13/1000 -> 0 | AC13: =IF(N13>0,U13*1000/N13,0) -> 0.10673734 | AD13: =IF(N13>0,AA13*1000/N13-L13,0) -> 2.1347468 | AE13: =MAX(0,$I$6*$J$6*AC13-$K$6*MAX(0,AD13)) -> 3.0420141 | AF13: =MAX(0,$L$6*$J$6*AC13-MAX(0,AD13)) -> 3.0420141 | AG13: =MAX(0,$M$6*$J$6*AC13-MAX(0,AD13)) -> 8.5389871 | AH13: =IF(B13>0,D13*N13/B13*AE13/1000,0) -> 5.5330393 | AI13: =D13*(1+C13)^($N$6-BaseYr)*$I$6*$J$6*(F13+G13)/1000 -> 9.9211029 | AJ13: =D13*$I$6*$J$6*(F13+G13) -> 8706.72 | AK13: =D13*$L$6*$J$6*(F13+G13) -> 8706.72 | AL13: =D13*$M$6*$J$6*(F13+G13) -> 17952 | AM13: =D13*AE13 -> 4867.2226 | AN13: =D13*AF13 -> 4867.2226 | AO13: =D13*AG13 -> 13662.379 | AP13: =IF(N13>0,D13*U13/N13,0) -> 0.17077974 | AQ13: =IF(N13>0,D13*(O13+P13)/N13,0) -> 0.17952 | AR13: =IF(N13>0,D13*AS13/N13,0) -> 0.17952 | AS13: =O13*IF($F$6>0,1,0)+P13*X13*IF($G$6>0,1,0) -> 0.35713584 | AT13: =I13*(F13+G13)/1000 -> 0.35797794 | AU13: =I13*F13/1000 -> 0.35797794 | AV13: =I13*G13/1000 -> 0
A14: =Inputs!$A$89 -> Ammonium nitrate | B14: =Inputs!$B$89 -> 600 | C14: =Inputs!$C$89 -> 0.022 | D14: =Inputs!$D$89 -> 80 | E14: =Inputs!$E$89 -> 320 | F14: =Inputs!$J$89 -> 0.1122 | G14: =Inputs!$K$89 -> 0.9944125 | H14: =Inputs!$Q$89 -> 0.0078858436 | I14: =B14*(1+C14)^($N$6-BaseYr) -> 683.6859 | J14: =$F$6*$B$6*F14 -> 2.244 | K14: =$G$6*$C$6*G14 -> 19.88825 | L14: =MIN($D$6,$B$6)*$F$6*F14+MIN($D$6,$C$6)*$G$6*G14 -> 0 | M14: =IF(E14>0,(J14+K14-L14)/E14,0) -> 0.069163281 | N14: =I14*(1+M14)^EpsQ7 -> 665.63939 | O14: =N14*F14/1000 -> 0.074684739 | P14: =N14*G14/1000 -> 0.66192013 | Q14: =O14*($H$6-1) -> -0.0036361628 | R14: =-P14*(1-EXP(-H14*($G$6*$C$6+$E$6))) -> -0.09657973 | S14: =O14+Q14 -> 0.071048576 | T14: =P14+R14 -> 0.5653404 | U14: =S14+T14 -> 0.63638897 | V14: =(O14+P14)*(1-(1+M14)^(-EpsQ7)) -> -0.019970502 | W14: =P14*(1-(1+M14)^(-EpsQ7)) -> -0.017945682 | X14: =IF(G14>0,1,0) -> 1 | Y14: =S14*$F$6*$B$6 -> 1.4209715 | Z14: =(P14*X14+R14)*$G$6*$C$6 -> 11.306808 | AA14: =Y14+Z14 -> 12.727779 | AB14: =L14*N14/1000 -> 0 | AC14: =IF(N14>0,U14*1000/N14,0) -> 0.95605667 | AD14: =IF(N14>0,AA14*1000/N14-L14,0) -> 19.121133 | AE14: =MAX(0,$I$6*$J$6*AC14-$K$6*MAX(0,AD14)) -> 27.247615 | AF14: =MAX(0,$L$6*$J$6*AC14-MAX(0,AD14)) -> 27.247615 | AG14: =MAX(0,$M$6*$J$6*AC14-MAX(0,AD14)) -> 76.484533 | AH14: =IF(B14>0,D14*N14/B14*AE14/1000,0) -> 2.4182781 | AI14: =D14*(1+C14)^($N$6-BaseYr)*$I$6*$J$6*(F14+G14)/1000 -> 4.8925207 | AJ14: =D14*$I$6*$J$6*(F14+G14) -> 4293.6565 | AK14: =D14*$L$6*$J$6*(F14+G14) -> 4293.6565 | AL14: =D14*$M$6*$J$6*(F14+G14) -> 8852.9 | AM14: =D14*AE14 -> 2179.8092 | AN14: =D14*AF14 -> 2179.8092 | AO14: =D14*AG14 -> 6118.7627 | AP14: =IF(N14>0,D14*U14/N14,0) -> 0.076484533 | AQ14: =IF(N14>0,D14*(O14+P14)/N14,0) -> 0.088529 | AR14: =IF(N14>0,D14*AS14/N14,0) -> 0.088529 | AS14: =O14*IF($F$6>0,1,0)+P14*X14*IF($G$6>0,1,0) -> 0.73660486 | AT14: =I14*(F14+G14)/1000 -> 0.75657537 | AU14: =I14*F14/1000 -> 0.076709558 | AV14: =I14*G14/1000 -> 0.67986581
A15: =Inputs!$A$90 -> Aluminium | B15: =Inputs!$B$90 -> 300 | C15: =Inputs!$C$90 -> 0.055 | D15: =Inputs!$D$90 -> 167 | E15: =Inputs!$E$90 -> 2400 | F15: =Inputs!$J$90 -> 0.12342 | G15: =Inputs!$K$90 -> 2.397493 | H15: =Inputs!$Q$90 -> 0.0019988245 | I15: =B15*(1+C15)^($N$6-BaseYr) -> 413.65284 | J15: =$F$6*$B$6*F15 -> 2.4684 | K15: =$G$6*$C$6*G15 -> 47.949861 | L15: =MIN($D$6,$B$6)*$F$6*F15+MIN($D$6,$C$6)*$G$6*G15 -> 0 | M15: =IF(E15>0,(J15+K15-L15)/E15,0) -> 0.021007609 | N15: =I15*(1+M15)^EpsQ8 -> 409.37519 | O15: =N15*F15/1000 -> 0.050525086 | P15: =N15*G15/1000 -> 0.98147418 | Q15: =O15*($H$6-1) -> -0.002459906 | R15: =-P15*(1-EXP(-H15*($G$6*$C$6+$E$6))) -> -0.038461984 | S15: =O15+Q15 -> 0.04806518 | T15: =P15+R15 -> 0.94301219 | U15: =S15+T15 -> 0.99107738 | V15: =(O15+P15)*(1-(1+M15)^(-EpsQ8)) -> -0.010783578 | W15: =P15*(1-(1+M15)^(-EpsQ8)) -> -0.010255631 | X15: =IF(G15>0,1,0) -> 1 | Y15: =S15*$F$6*$B$6 -> 0.96130361 | Z15: =(P15*X15+R15)*$G$6*$C$6 -> 18.860244 | AA15: =Y15+Z15 -> 19.821548 | AB15: =L15*N15/1000 -> 0 | AC15: =IF(N15>0,U15*1000/N15,0) -> 2.4209512 | AD15: =IF(N15>0,AA15*1000/N15-L15,0) -> 48.419024 | AE15: =MAX(0,$I$6*$J$6*AC15-$K$6*MAX(0,AD15)) -> 68.99711 | AF15: =MAX(0,$L$6*$J$6*AC15-MAX(0,AD15)) -> 68.99711 | AG15: =MAX(0,$M$6*$J$6*AC15-MAX(0,AD15)) -> 193.6761 | AH15: =IF(B15>0,D15*N15/B15*AE15/1000,0) -> 15.723443 | AI15: =D15*(1+C15)^($N$6-BaseYr)*$I$6*$J$6*(F15+G15)/1000 -> 28.153399 | AJ15: =D15*$I$6*$J$6*(F15+G15) -> 20418.135 | AK15: =D15*$L$6*$J$6*(F15+G15) -> 20418.135 | AL15: =D15*$M$6*$J$6*(F15+G15) -> 42099.248 | AM15: =D15*AE15 -> 11522.517 | AN15: =D15*AF15 -> 11522.517 | AO15: =D15*AG15 -> 32343.908 | AP15: =IF(N15>0,D15*U15/N15,0) -> 0.40429885 | AQ15: =IF(N15>0,D15*(O15+P15)/N15,0) -> 0.42099248 | AR15: =IF(N15>0,D15*AS15/N15,0) -> 0.42099248 | AS15: =O15*IF($F$6>0,1,0)+P15*X15*IF($G$6>0,1,0) -> 1.0319993 | AT15: =I15*(F15+G15)/1000 -> 1.0427828 | AU15: =I15*F15/1000 -> 0.051053034 | AV15: =I15*G15/1000 -> 0.99172981
A16: Total | I16: =SUM(I8:I15) -> 79893.956 | N16: =SUM(N8:N15) -> 78880.541 | O16: =SUM(O8:O15) -> 27.169331 | P16: =SUM(P8:P15) -> 34.325582 | Q16: =SUM(Q8:Q15) -> -1.3227885 | R16: =SUM(R8:R15) -> -2.2424276 | S16: =SUM(S8:S15) -> 25.846543 | T16: =SUM(T8:T15) -> 32.083154 | U16: =SUM(U8:U15) -> 57.929697 | ... W16: =SUM(W8:W15) -> -0.49590352 | Y16: =SUM(Y8:Y15) -> 516.93086 | Z16: =SUM(Z8:Z15) -> 641.66309 | AA16: =SUM(AA8:AA15) -> 1158.5939 | AB16: =SUM(AB8:AB15) -> 0 | AH16: =SUM(AH8:AH15) -> 65.861639 | AI16: =SUM(AI8:AI15) -> 120.01558 | AJ16: =SUM(AJ8:AJ15) -> 96335.511 | AK16: =SUM(AK8:AK15) -> 96335.511 | AL16: =SUM(AL8:AL15) -> 198629.92 | AM16: =SUM(AM8:AM15) -> 53539.775 | AN16: =SUM(AN8:AN15) -> 53539.775 | AO16: =SUM(AO8:AO15) -> 150287.09 | ... AV16: =SUM(AV8:AV15) -> 34.821485
A20: Bundle 2A - Economy-wide fuel levy (EG1), process not priced.
A21: Bundle | B21: tau: carbon price | C21: tau_p: process price | D21: obrrb: OBR rebate rate | E21: fundsp: fund shadow price | F21: incl_f | G21: incl_p | H21: xf: fuel-intensity factor | I21: CBF (selected conv.) | J21: P_EU | K21: S (selected conv.) | L21: CBF (FULL) | M21: CBF (NOPHASE) | N21: Year | O21: CPAT scenario | P21: b_f | Q21: beta set | R21: Mode
A22: 2A | B22: =INDEX(BT_Tau,MATCH($A$22,BT_Code,0)) -> 20 | C22: =B22*INDEX(BT_Flag,MATCH($A$22,BT_Code,0)) -> 0 | D22: =INDEX(BT_Theta,MATCH($A$22,BT_Code,0))*B22 -> 0 | E22: =INDEX(BT_Phi,MATCH($A$22,BT_Code,0))*SigmaEff -> 0 | F22: 1 | G22: =INDEX(BT_Flag,MATCH($A$22,BT_Code,0)) -> 0 | H22: =IF(Mode="PROTOTYPE",1,EXP(Bf*(F22*B22+E22))) -> 0.95131318 | I22: =CBFsel -> 0.485 | J22: =PEU -> 100 | K22: =Ssel -> 1 | L22: =CBFyr -> 0.485 | M22: 1 | N22: =Yr -> 2030 | O22: =INDEX(BT_Scen,MATCH($A$22,BT_Code,0)) -> EG1 | P22: =Bf -> -0.0024955979 | Q22: =BetaSet -> IPCC_CENTRAL | R22: =Mode -> REBUILD
A23: Product | B23: Q0 (kt) | C23: g | D23: X exports (kt) | E23: P ($/t) | F23: F (tCO2/t) | G23: G (tCO2e/t) | H23: beta | I23: Qb: baseline output | J23: kf: fuel cost $/t | K23: kp: process cost $/t | L23: m: rebate $/t | M23: dp: cost/price | N23: Q: output | O23: Ef: fuel emis. | P23: Ep: process emis. | Q23: ER_f: fuel-int. resp. | R23: ER_p: process-int. resp. | S23: post fuel | T23: post process | U23: post total | V23: emrq_i: output ch. | W23: emrq_proc_i | X23: J_i: process>0 | Y23: revf_i $m | Z23: revp_i $m | AA23: rev_i $m | AB23: rebate_i $m | AC23: EI: tCO2/t | AD23: d: net price paid $/t | AE23: obl (sel.) $/t | AF23: obl (FULL) $/t | AG23: obl (NOPHASE) $/t | AH23: cbobl_i $m | AI23: cbobl0_i $m | AJ23: w_den sel | AK23: w_den FULL | AL23: w_den NOPHASE | AM23: w_num sel | AN23: w_num FULL | AO23: w_num NOPHASE | AP23: X*post/Q | AQ23: X*(Ef+Ep)/Q | AR23: X*covered/Q | AS23: covered_i | AT23: Ebase_i | AU23: Efbase_i | AV23: Epbase_i
A24: =Inputs!$A$83 -> DRI-EAF steel | B24: =Inputs!$B$83 -> 5100 | C24: =Inputs!$C$83 -> 0.044 | D24: =Inputs!$D$83 -> 580 | E24: =Inputs!$E$83 -> 750 | F24: =Inputs!$J$83 -> 0.57099077 | G24: =Inputs!$K$83 -> 0.03790102 | H24: =Inputs!$Q$83 -> 0.0034469507 | I24: =B24*(1+C24)^($N$22-BaseYr) -> 6603.4846 | J24: =$F$22*$B$22*F24 -> 11.419815 | K24: =$G$22*$C$22*G24 -> 0 | L24: =MIN($D$22,$B$22)*$F$22*F24+MIN($D$22,$C$22)*$G$22*G24 -> 0 | M24: =IF(E24>0,(J24+K24-L24)/E24,0) -> 0.015226421 | N24: =I24*(1+M24)^EpsQ1 -> 6563.6891 | O24: =N24*F24/1000 -> 3.7478059 | P24: =N24*G24/1000 -> 0.24877051 | Q24: =O24*($H$22-1) -> -0.18246877 | R24: =-P24*(1-EXP(-H24*($G$22*$C$22+$E$22))) -> 0 | S24: =O24+Q24 -> 3.5653371 | T24: =P24+R24 -> 0.24877051 | U24: =S24+T24 -> 3.8141077 | V24: =(O24+P24)*(1-(1+M24)^(-EpsQ1)) -> -0.024231126 | W24: =P24*(1-(1+M24)^(-EpsQ1)) -> -0.0015082883 | X24: =IF(G24>0,1,0) -> 1 | Y24: =S24*$F$22*$B$22 -> 71.306743 | Z24: =(P24*X24+R24)*$G$22*$C$22 -> 0 | AA24: =Y24+Z24 -> 71.306743 | AB24: =L24*N24/1000 -> 0 | AC24: =IF(N24>0,U24*1000/N24,0) -> 0.58109206 | AD24: =IF(N24>0,AA24*1000/N24-L24,0) -> 10.863821 | AE24: =MAX(0,$I$22*$J$22*AC24-$K$22*MAX(0,AD24)) -> 17.319144 | AF24: =MAX(0,$L$22*$J$22*AC24-MAX(0,AD24)) -> 17.319144 | AG24: =MAX(0,$M$22*$J$22*AC24-MAX(0,AD24)) -> 47.245385 | AH24: =IF(B24>0,D24*N24/B24*AE24/1000,0) -> 12.928027 | AI24: =D24*(1+C24)^($N$22-BaseYr)*$I$22*$J$22*(F24+G24)/1000 -> 22.177513 | AJ24: =D24*$I$22*$J$22*(F24+G24) -> 17128.126 | AK24: =D24*$L$22*$J$22*(F24+G24) -> 17128.126 | AL24: =D24*$M$22*$J$22*(F24+G24) -> 35315.724 | AM24: =D24*AE24 -> 10045.104 | AN24: =D24*AF24 -> 10045.104 | AO24: =D24*AG24 -> 27402.324 | AP24: =IF(N24>0,D24*U24/N24,0) -> 0.3370334 | AQ24: =IF(N24>0,D24*(O24+P24)/N24,0) -> 0.35315724 | AR24: =IF(N24>0,D24*AS24/N24,0) -> 0.33117465 | AS24: =O24*IF($F$22>0,1,0)+P24*X24*IF($G$22>0,1,0) -> 3.7478059 | AT24: =I24*(F24+G24)/1000 -> 4.0208075 | AU24: =I24*F24/1000 -> 3.7705287 | AV24: =I24*G24/1000 -> 0.2502788
A25: =Inputs!$A$84 -> Scrap-EAF steel | B25: =Inputs!$B$84 -> 4800 | C25: =Inputs!$C$84 -> 0.044 | D25: =Inputs!$D$84 -> 300 | E25: =Inputs!$E$84 -> 680 | F25: =Inputs!$J$84 -> 0.04488 | G25: =Inputs!$K$84 -> 0.04398115 | H25: =Inputs!$Q$84 -> 0.0016366491 | I25: =B25*(1+C25)^($N$22-BaseYr) -> 6215.0443 | J25: =$F$22*$B$22*F25 -> 0.8976 | K25: =$G$22*$C$22*G25 -> 0 | L25: =MIN($D$22,$B$22)*$F$22*F25+MIN($D$22,$C$22)*$G$22*G25 -> 0 | M25: =IF(E25>0,(J25+K25-L25)/E25,0) -> 0.00132 | N25: =I25*(1+M25)^EpsQ2 -> 6211.7658 | O25: =N25*F25/1000 -> 0.27878405 | P25: =N25*G25/1000 -> 0.2732006 | Q25: =O25*($H$22-1) -> -0.01357311 | R25: =-P25*(1-EXP(-H25*($G$22*$C$22+$E$22))) -> 0 | S25: =O25+Q25 -> 0.26521094 | T25: =P25+R25 -> 0.2732006 | U25: =S25+T25 -> 0.53841154 | V25: =(O25+P25)*(1-(1+M25)^(-EpsQ2)) -> -0.00029133256 | W25: =P25*(1-(1+M25)^(-EpsQ2)) -> -0.00014419284 | X25: =IF(G25>0,1,0) -> 1 | Y25: =S25*$F$22*$B$22 -> 5.3042188 | Z25: =(P25*X25+R25)*$G$22*$C$22 -> 0 | AA25: =Y25+Z25 -> 5.3042188 | AB25: =L25*N25/1000 -> 0 | AC25: =IF(N25>0,U25*1000/N25,0) -> 0.086676085 | AD25: =IF(N25>0,AA25*1000/N25-L25,0) -> 0.85389871 | AE25: =MAX(0,$I$22*$J$22*AC25-$K$22*MAX(0,AD25)) -> 3.3498914 | AF25: =MAX(0,$L$22*$J$22*AC25-MAX(0,AD25)) -> 3.3498914 | AG25: =MAX(0,$M$22*$J$22*AC25-MAX(0,AD25)) -> 7.8137098 | AH25: =IF(B25>0,D25*N25/B25*AE25/1000,0) -> 1.3005463 | AI25: =D25*(1+C25)^($N$22-BaseYr)*$I$22*$J$22*(F25+G25)/1000 -> 1.6740866 | AJ25: =D25*$I$22*$J$22*(F25+G25) -> 1292.9297 | AK25: =D25*$L$22*$J$22*(F25+G25) -> 1292.9297 | AL25: =D25*$M$22*$J$22*(F25+G25) -> 2665.8345 | AM25: =D25*AE25 -> 1004.9674 | AN25: =D25*AF25 -> 1004.9674 | AO25: =D25*AG25 -> 2344.1129 | AP25: =IF(N25>0,D25*U25/N25,0) -> 0.026002826 | AQ25: =IF(N25>0,D25*(O25+P25)/N25,0) -> 0.026658345 | AR25: =IF(N25>0,D25*AS25/N25,0) -> 0.013464 | AS25: =O25*IF($F$22>0,1,0)+P25*X25*IF($G$22>0,1,0) -> 0.27878405 | AT25: =I25*(F25+G25)/1000 -> 0.55227598 | AU25: =I25*F25/1000 -> 0.27893119 | AV25: =I25*G25/1000 -> 0.2733448
A26: =Inputs!$A$85 -> BF-BOF steel | B26: =Inputs!$B$85 -> 0 | C26: =Inputs!$C$85 -> 0 | D26: =Inputs!$D$85 -> 0 | E26: =Inputs!$E$85 -> 620 | F26: =Inputs!$J$85 -> 1.4249803 | G26: =Inputs!$K$85 -> 0.05276542 | H26: =Inputs!$Q$85 -> 0.0026960723 | I26: =B26*(1+C26)^($N$22-BaseYr) -> 0 | J26: =$F$22*$B$22*F26 -> 28.499605 | K26: =$G$22*$C$22*G26 -> 0 | L26: =MIN($D$22,$B$22)*$F$22*F26+MIN($D$22,$C$22)*$G$22*G26 -> 0 | M26: =IF(E26>0,(J26+K26-L26)/E26,0) -> 0.045967105 | N26: =I26*(1+M26)^EpsQ3 -> 0 | O26: =N26*F26/1000 -> 0 | P26: =N26*G26/1000 -> 0 | Q26: =O26*($H$22-1) -> 0 | R26: =-P26*(1-EXP(-H26*($G$22*$C$22+$E$22))) -> 0 | S26: =O26+Q26 -> 0 | T26: =P26+R26 -> 0 | U26: =S26+T26 -> 0 | V26: =(O26+P26)*(1-(1+M26)^(-EpsQ3)) -> 0 | W26: =P26*(1-(1+M26)^(-EpsQ3)) -> 0 | X26: =IF(G26>0,1,0) -> 1 | Y26: =S26*$F$22*$B$22 -> 0 | Z26: =(P26*X26+R26)*$G$22*$C$22 -> 0 | AA26: =Y26+Z26 -> 0 | AB26: =L26*N26/1000 -> 0 | AC26: =IF(N26>0,U26*1000/N26,0) -> 0 | AD26: =IF(N26>0,AA26*1000/N26-L26,0) -> 0 | AE26: =MAX(0,$I$22*$J$22*AC26-$K$22*MAX(0,AD26)) -> 0 | AF26: =MAX(0,$L$22*$J$22*AC26-MAX(0,AD26)) -> 0 | AG26: =MAX(0,$M$22*$J$22*AC26-MAX(0,AD26)) -> 0 | AH26: =IF(B26>0,D26*N26/B26*AE26/1000,0) -> 0 | AI26: =D26*(1+C26)^($N$22-BaseYr)*$I$22*$J$22*(F26+G26)/1000 -> 0 | AJ26: =D26*$I$22*$J$22*(F26+G26) -> 0 | AK26: =D26*$L$22*$J$22*(F26+G26) -> 0 | AL26: =D26*$M$22*$J$22*(F26+G26) -> 0 | AM26: =D26*AE26 -> 0 | AN26: =D26*AF26 -> 0 | AO26: =D26*AG26 -> 0 | AP26: =IF(N26>0,D26*U26/N26,0) -> 0 | AQ26: =IF(N26>0,D26*(O26+P26)/N26,0) -> 0 | AR26: =IF(N26>0,D26*AS26/N26,0) -> 0 | AS26: =O26*IF($F$22>0,1,0)+P26*X26*IF($G$22>0,1,0) -> 0 | AT26: =I26*(F26+G26)/1000 -> 0 | AU26: =I26*F26/1000 -> 0 | AV26: =I26*G26/1000 -> 0
A27: =Inputs!$A$86 -> Clinker | B27: =Inputs!$B$86 -> 50000 | C27: =Inputs!$C$86 -> 0.033 | D27: =Inputs!$D$86 -> 800 | E27: =Inputs!$E$86 -> 110 | F27: =Inputs!$J$86 -> 0.3135685 | G27: =Inputs!$K$86 -> 0.53702616 | H27: =Inputs!$Q$86 -> 0.0033464675 | I27: =B27*(1+C27)^($N$22-BaseYr) -> 60753.588 | J27: =$F$22*$B$22*F27 -> 6.27137 | K27: =$G$22*$C$22*G27 -> 0 | L27: =MIN($D$22,$B$22)*$F$22*F27+MIN($D$22,$C$22)*$G$22*G27 -> 0 | M27: =IF(E27>0,(J27+K27-L27)/E27,0) -> 0.057012455 | N27: =I27*(1+M27)^EpsQ4 -> 60417.663 | O27: =N27*F27/1000 -> 18.945076 | P27: =N27*G27/1000 -> 32.445866 | Q27: =O27*($H$22-1) -> -0.92237559 | R27: =-P27*(1-EXP(-H27*($G$22*$C$22+$E$22))) -> 0 | S27: =O27+Q27 -> 18.0227 | T27: =P27+R27 -> 32.445866 | U27: =S27+T27 -> 50.468566 | V27: =(O27+P27)*(1-(1+M27)^(-EpsQ4)) -> -0.28573615 | W27: =P27*(1-(1+M27)^(-EpsQ4)) -> -0.1804006 | X27: =IF(G27>0,1,0) -> 1 | Y27: =S27*$F$22*$B$22 -> 360.45401 | Z27: =(P27*X27+R27)*$G$22*$C$22 -> 0 | AA27: =Y27+Z27 -> 360.45401 | AB27: =L27*N27/1000 -> 0 | AC27: =IF(N27>0,U27*1000/N27,0) -> 0.83532801 | AD27: =IF(N27>0,AA27*1000/N27-L27,0) -> 5.9660369 | AE27: =MAX(0,$I$22*$J$22*AC27-$K$22*MAX(0,AD27)) -> 34.547371 | AF27: =MAX(0,$L$22*$J$22*AC27-MAX(0,AD27)) -> 34.547371 | AG27: =MAX(0,$M$22*$J$22*AC27-MAX(0,AD27)) -> 77.566764 | AH27: =IF(B27>0,D27*N27/B27*AE27/1000,0) -> 33.396343 | AI27: =D27*(1+C27)^($N$22-BaseYr)*$I$22*$J$22*(F27+G27)/1000 -> 40.101102 | AJ27: =D27*$I$22*$J$22*(F27+G27) -> 33003.073 | AK27: =D27*$L$22*$J$22*(F27+G27) -> 33003.073 | AL27: =D27*$M$22*$J$22*(F27+G27) -> 68047.573 | AM27: =D27*AE27 -> 27637.897 | AN27: =D27*AF27 -> 27637.897 | AO27: =D27*AG27 -> 62053.411 | AP27: =IF(N27>0,D27*U27/N27,0) -> 0.6682624 | AQ27: =IF(N27>0,D27*(O27+P27)/N27,0) -> 0.68047573 | AR27: =IF(N27>0,D27*AS27/N27,0) -> 0.2508548 | AS27: =O27*IF($F$22>0,1,0)+P27*X27*IF($G$22>0,1,0) -> 18.945076 | AT27: =I27*(F27+G27)/1000 -> 51.676678 | AU27: =I27*F27/1000 -> 19.050412 | AV27: =I27*G27/1000 -> 32.626266
A28: =Inputs!$A$87 -> Ammonia | B28: =Inputs!$B$87 -> 1785 | C28: =Inputs!$C$87 -> 0.022 | D28: =Inputs!$D$87 -> 120 | E28: =Inputs!$E$87 -> 450 | F28: =Inputs!$J$87 -> 1.97472 | G28: =Inputs!$K$87 -> 0 | H28: =Inputs!$Q$87 -> 0.0028931766 | I28: =B28*(1+C28)^($N$22-BaseYr) -> 2033.9656 | J28: =$F$22*$B$22*F28 -> 39.4944 | K28: =$G$22*$C$22*G28 -> 0 | L28: =MIN($D$22,$B$22)*$F$22*F28+MIN($D$22,$C$22)*$G$22*G28 -> 0 | M28: =IF(E28>0,(J28+K28-L28)/E28,0) -> 0.087765333 | N28: =I28*(1+M28)^EpsQ5 -> 1966.661 | O28: =N28*F28/1000 -> 3.8836048 | P28: =N28*G28/1000 -> 0 | Q28: =O28*($H$22-1) -> -0.18908039 | R28: =-P28*(1-EXP(-H28*($G$22*$C$22+$E$22))) -> 0 | S28: =O28+Q28 -> 3.6945245 | T28: =P28+R28 -> 0 | U28: =S28+T28 -> 3.6945245 | V28: =(O28+P28)*(1-(1+M28)^(-EpsQ5)) -> -0.13290763 | W28: =P28*(1-(1+M28)^(-EpsQ5)) -> 0 | X28: =IF(G28>0,1,0) -> 0 | Y28: =S28*$F$22*$B$22 -> 73.890489 | Z28: =(P28*X28+R28)*$G$22*$C$22 -> 0 | AA28: =Y28+Z28 -> 73.890489 | AB28: =L28*N28/1000 -> 0 | AC28: =IF(N28>0,U28*1000/N28,0) -> 1.8785772 | AD28: =IF(N28>0,AA28*1000/N28-L28,0) -> 37.571543 | AE28: =MAX(0,$I$22*$J$22*AC28-$K$22*MAX(0,AD28)) -> 53.539449 | AF28: =MAX(0,$L$22*$J$22*AC28-MAX(0,AD28)) -> 53.539449 | AG28: =MAX(0,$M$22*$J$22*AC28-MAX(0,AD28)) -> 150.28617 | AH28: =IF(B28>0,D28*N28/B28*AE28/1000,0) -> 7.0785847 | AI28: =D28*(1+C28)^($N$22-BaseYr)*$I$22*$J$22*(F28+G28)/1000 -> 13.095856 | AJ28: =D28*$I$22*$J$22*(F28+G28) -> 11492.87 | AK28: =D28*$L$22*$J$22*(F28+G28) -> 11492.87 | AL28: =D28*$M$22*$J$22*(F28+G28) -> 23696.64 | AM28: =D28*AE28 -> 6424.7339 | AN28: =D28*AF28 -> 6424.7339 | AO28: =D28*AG28 -> 18034.341 | AP28: =IF(N28>0,D28*U28/N28,0) -> 0.22542926 | AQ28: =IF(N28>0,D28*(O28+P28)/N28,0) -> 0.2369664 | AR28: =IF(N28>0,D28*AS28/N28,0) -> 0.2369664 | AS28: =O28*IF($F$22>0,1,0)+P28*X28*IF($G$22>0,1,0) -> 3.8836048 | AT28: =I28*(F28+G28)/1000 -> 4.0165125 | AU28: =I28*F28/1000 -> 4.0165125 | AV28: =I28*G28/1000 -> 0
A29: =Inputs!$A$88 -> Urea | B29: =Inputs!$B$88 -> 2800 | C29: =Inputs!$C$88 -> 0.022 | D29: =Inputs!$D$88 -> 1600 | E29: =Inputs!$E$88 -> 380 | F29: =Inputs!$J$88 -> 0.1122 | G29: =Inputs!$K$88 -> 0 | H29: =Inputs!$Q$88 -> 0.0010087869 | I29: =B29*(1+C29)^($N$22-BaseYr) -> 3190.5342 | J29: =$F$22*$B$22*F29 -> 2.244 | K29: =$G$22*$C$22*G29 -> 0 | L29: =MIN($D$22,$B$22)*$F$22*F29+MIN($D$22,$C$22)*$G$22*G29 -> 0 | M29: =IF(E29>0,(J29+K29-L29)/E29,0) -> 0.0059052632 | N29: =I29*(1+M29)^EpsQ6 -> 3183.0288 | O29: =N29*F29/1000 -> 0.35713584 | P29: =N29*G29/1000 -> 0 | Q29: =O29*($H$22-1) -> -0.01738781 | R29: =-P29*(1-EXP(-H29*($G$22*$C$22+$E$22))) -> 0 | S29: =O29+Q29 -> 0.33974803 | T29: =P29+R29 -> 0 | U29: =S29+T29 -> 0.33974803 | V29: =(O29+P29)*(1-(1+M29)^(-EpsQ6)) -> -0.00084210264 | W29: =P29*(1-(1+M29)^(-EpsQ6)) -> 0 | X29: =IF(G29>0,1,0) -> 0 | Y29: =S29*$F$22*$B$22 -> 6.7949605 | Z29: =(P29*X29+R29)*$G$22*$C$22 -> 0 | AA29: =Y29+Z29 -> 6.7949605 | AB29: =L29*N29/1000 -> 0 | AC29: =IF(N29>0,U29*1000/N29,0) -> 0.10673734 | AD29: =IF(N29>0,AA29*1000/N29-L29,0) -> 2.1347468 | AE29: =MAX(0,$I$22*$J$22*AC29-$K$22*MAX(0,AD29)) -> 3.0420141 | AF29: =MAX(0,$L$22*$J$22*AC29-MAX(0,AD29)) -> 3.0420141 | AG29: =MAX(0,$M$22*$J$22*AC29-MAX(0,AD29)) -> 8.5389871 | AH29: =IF(B29>0,D29*N29/B29*AE29/1000,0) -> 5.5330393 | AI29: =D29*(1+C29)^($N$22-BaseYr)*$I$22*$J$22*(F29+G29)/1000 -> 9.9211029 | AJ29: =D29*$I$22*$J$22*(F29+G29) -> 8706.72 | AK29: =D29*$L$22*$J$22*(F29+G29) -> 8706.72 | AL29: =D29*$M$22*$J$22*(F29+G29) -> 17952 | AM29: =D29*AE29 -> 4867.2226 | AN29: =D29*AF29 -> 4867.2226 | AO29: =D29*AG29 -> 13662.379 | AP29: =IF(N29>0,D29*U29/N29,0) -> 0.17077974 | AQ29: =IF(N29>0,D29*(O29+P29)/N29,0) -> 0.17952 | AR29: =IF(N29>0,D29*AS29/N29,0) -> 0.17952 | AS29: =O29*IF($F$22>0,1,0)+P29*X29*IF($G$22>0,1,0) -> 0.35713584 | AT29: =I29*(F29+G29)/1000 -> 0.35797794 | AU29: =I29*F29/1000 -> 0.35797794 | AV29: =I29*G29/1000 -> 0
A30: =Inputs!$A$89 -> Ammonium nitrate | B30: =Inputs!$B$89 -> 600 | C30: =Inputs!$C$89 -> 0.022 | D30: =Inputs!$D$89 -> 80 | E30: =Inputs!$E$89 -> 320 | F30: =Inputs!$J$89 -> 0.1122 | G30: =Inputs!$K$89 -> 0.9944125 | H30: =Inputs!$Q$89 -> 0.0078858436 | I30: =B30*(1+C30)^($N$22-BaseYr) -> 683.6859 | J30: =$F$22*$B$22*F30 -> 2.244 | K30: =$G$22*$C$22*G30 -> 0 | L30: =MIN($D$22,$B$22)*$F$22*F30+MIN($D$22,$C$22)*$G$22*G30 -> 0 | M30: =IF(E30>0,(J30+K30-L30)/E30,0) -> 0.0070125 | N30: =I30*(1+M30)^EpsQ7 -> 681.77753 | O30: =N30*F30/1000 -> 0.076495438 | P30: =N30*G30/1000 -> 0.67796809 | Q30: =O30*($H$22-1) -> -0.00372432 | R30: =-P30*(1-EXP(-H30*($G$22*$C$22+$E$22))) -> 0 | S30: =O30+Q30 -> 0.072771118 | T30: =P30+R30 -> 0.67796809 | U30: =S30+T30 -> 0.75073921 | V30: =(O30+P30)*(1-(1+M30)^(-EpsQ7)) -> -0.0021118347 | W30: =P30*(1-(1+M30)^(-EpsQ7)) -> -0.0018977147 | X30: =IF(G30>0,1,0) -> 1 | Y30: =S30*$F$22*$B$22 -> 1.4554224 | Z30: =(P30*X30+R30)*$G$22*$C$22 -> 0 | AA30: =Y30+Z30 -> 1.4554224 | AB30: =L30*N30/1000 -> 0 | AC30: =IF(N30>0,U30*1000/N30,0) -> 1.1011498 | AD30: =IF(N30>0,AA30*1000/N30-L30,0) -> 2.1347468 | AE30: =MAX(0,$I$22*$J$22*AC30-$K$22*MAX(0,AD30)) -> 51.27102 | AF30: =MAX(0,$L$22*$J$22*AC30-MAX(0,AD30)) -> 51.27102 | AG30: =MAX(0,$M$22*$J$22*AC30-MAX(0,AD30)) -> 107.98024 | AH30: =IF(B30>0,D30*N30/B30*AE30/1000,0) -> 4.6607239 | AI30: =D30*(1+C30)^($N$22-BaseYr)*$I$22*$J$22*(F30+G30)/1000 -> 4.8925207 | AJ30: =D30*$I$22*$J$22*(F30+G30) -> 4293.6565 | AK30: =D30*$L$22*$J$22*(F30+G30) -> 4293.6565 | AL30: =D30*$M$22*$J$22*(F30+G30) -> 8852.9 | AM30: =D30*AE30 -> 4101.6816 | AN30: =D30*AF30 -> 4101.6816 | AO30: =D30*AG30 -> 8638.419 | AP30: =IF(N30>0,D30*U30/N30,0) -> 0.088091987 | AQ30: =IF(N30>0,D30*(O30+P30)/N30,0) -> 0.088529 | AR30: =IF(N30>0,D30*AS30/N30,0) -> 0.008976 | AS30: =O30*IF($F$22>0,1,0)+P30*X30*IF($G$22>0,1,0) -> 0.076495438 | AT30: =I30*(F30+G30)/1000 -> 0.75657537 | AU30: =I30*F30/1000 -> 0.076709558 | AV30: =I30*G30/1000 -> 0.67986581
A31: =Inputs!$A$90 -> Aluminium | B31: =Inputs!$B$90 -> 300 | C31: =Inputs!$C$90 -> 0.055 | D31: =Inputs!$D$90 -> 167 | E31: =Inputs!$E$90 -> 2400 | F31: =Inputs!$J$90 -> 0.12342 | G31: =Inputs!$K$90 -> 2.397493 | H31: =Inputs!$Q$90 -> 0.0019988245 | I31: =B31*(1+C31)^($N$22-BaseYr) -> 413.65284 | J31: =$F$22*$B$22*F31 -> 2.4684 | K31: =$G$22*$C$22*G31 -> 0 | L31: =MIN($D$22,$B$22)*$F$22*F31+MIN($D$22,$C$22)*$G$22*G31 -> 0 | M31: =IF(E31>0,(J31+K31-L31)/E31,0) -> 0.0010285 | N31: =I31*(1+M31)^EpsQ8 -> 413.44029 | O31: =N31*F31/1000 -> 0.0510268 | P31: =N31*G31/1000 -> 0.99122021 | Q31: =O31*($H$22-1) -> -0.0024843328 | R31: =-P31*(1-EXP(-H31*($G$22*$C$22+$E$22))) -> 0 | S31: =O31+Q31 -> 0.048542467 | T31: =P31+R31 -> 0.99122021 | U31: =S31+T31 -> 1.0397627 | V31: =(O31+P31)*(1-(1+M31)^(-EpsQ8)) -> -0.00053583778 | W31: =P31*(1-(1+M31)^(-EpsQ8)) -> -0.00050960399 | X31: =IF(G31>0,1,0) -> 1 | Y31: =S31*$F$22*$B$22 -> 0.97084934 | Z31: =(P31*X31+R31)*$G$22*$C$22 -> 0 | AA31: =Y31+Z31 -> 0.97084934 | AB31: =L31*N31/1000 -> 0 | AC31: =IF(N31>0,U31*1000/N31,0) -> 2.5149041 | AD31: =IF(N31>0,AA31*1000/N31-L31,0) -> 2.3482214 | AE31: =MAX(0,$I$22*$J$22*AC31-$K$22*MAX(0,AD31)) -> 119.62463 | AF31: =MAX(0,$L$22*$J$22*AC31-MAX(0,AD31)) -> 119.62463 | AG31: =MAX(0,$M$22*$J$22*AC31-MAX(0,AD31)) -> 249.14219 | AH31: =IF(B31>0,D31*N31/B31*AE31/1000,0) -> 27.53142 | AI31: =D31*(1+C31)^($N$22-BaseYr)*$I$22*$J$22*(F31+G31)/1000 -> 28.153399 | AJ31: =D31*$I$22*$J$22*(F31+G31) -> 20418.135 | AK31: =D31*$L$22*$J$22*(F31+G31) -> 20418.135 | AL31: =D31*$M$22*$J$22*(F31+G31) -> 42099.248 | AM31: =D31*AE31 -> 19977.313 | AN31: =D31*AF31 -> 19977.313 | AO31: =D31*AG31 -> 41606.746 | AP31: =IF(N31>0,D31*U31/N31,0) -> 0.41998899 | AQ31: =IF(N31>0,D31*(O31+P31)/N31,0) -> 0.42099248 | AR31: =IF(N31>0,D31*AS31/N31,0) -> 0.02061114 | AS31: =O31*IF($F$22>0,1,0)+P31*X31*IF($G$22>0,1,0) -> 0.0510268 | AT31: =I31*(F31+G31)/1000 -> 1.0427828 | AU31: =I31*F31/1000 -> 0.051053034 | AV31: =I31*G31/1000 -> 0.99172981
A32: Total | I32: =SUM(I24:I31) -> 79893.956 | N32: =SUM(N24:N31) -> 79438.026 | O32: =SUM(O24:O31) -> 27.339929 | P32: =SUM(P24:P31) -> 34.637025 | Q32: =SUM(Q24:Q31) -> -1.3310943 | R32: =SUM(R24:R31) -> 0 | S32: =SUM(S24:S31) -> 26.008835 | T32: =SUM(T24:T31) -> 34.637025 | U32: =SUM(U24:U31) -> 60.64586 | ... W32: =SUM(W24:W31) -> -0.1844604 | Y32: =SUM(Y24:Y31) -> 520.17669 | Z32: =SUM(Z24:Z31) -> 0 | AA32: =SUM(AA24:AA31) -> 520.17669 | AB32: =SUM(AB24:AB31) -> 0 | AH32: =SUM(AH24:AH31) -> 92.428684 | AI32: =SUM(AI24:AI31) -> 120.01558 | AJ32: =SUM(AJ24:AJ31) -> 96335.511 | AK32: =SUM(AK24:AK31) -> 96335.511 | AL32: =SUM(AL24:AL31) -> 198629.92 | AM32: =SUM(AM24:AM31) -> 74058.919 | AN32: =SUM(AN24:AN31) -> 74058.919 | AO32: =SUM(AO24:AO31) -> 173741.73 | ... AV32: =SUM(AV24:AV31) -> 34.821485
A36: Bundle 2B - As 2A with household transfers (EG2).
A37: Bundle | B37: tau: carbon price | C37: tau_p: process price | D37: obrrb: OBR rebate rate | E37: fundsp: fund shadow price | F37: incl_f | G37: incl_p | H37: xf: fuel-intensity factor | I37: CBF (selected conv.) | J37: P_EU | K37: S (selected conv.) | L37: CBF (FULL) | M37: CBF (NOPHASE) | N37: Year | O37: CPAT scenario | P37: b_f | Q37: beta set | R37: Mode
A38: 2B | B38: =INDEX(BT_Tau,MATCH($A$38,BT_Code,0)) -> 20 | C38: =B38*INDEX(BT_Flag,MATCH($A$38,BT_Code,0)) -> 0 | D38: =INDEX(BT_Theta,MATCH($A$38,BT_Code,0))*B38 -> 0 | E38: =INDEX(BT_Phi,MATCH($A$38,BT_Code,0))*SigmaEff -> 0 | F38: 1 | G38: =INDEX(BT_Flag,MATCH($A$38,BT_Code,0)) -> 0 | H38: =IF(Mode="PROTOTYPE",1,EXP(Bf*(F38*B38+E38))) -> 0.95131318 | I38: =CBFsel -> 0.485 | J38: =PEU -> 100 | K38: =Ssel -> 1 | L38: =CBFyr -> 0.485 | M38: 1 | N38: =Yr -> 2030 | O38: =INDEX(BT_Scen,MATCH($A$38,BT_Code,0)) -> EG2 | P38: =Bf -> -0.0024955979 | Q38: =BetaSet -> IPCC_CENTRAL | R38: =Mode -> REBUILD
A39: Product | B39: Q0 (kt) | C39: g | D39: X exports (kt) | E39: P ($/t) | F39: F (tCO2/t) | G39: G (tCO2e/t) | H39: beta | I39: Qb: baseline output | J39: kf: fuel cost $/t | K39: kp: process cost $/t | L39: m: rebate $/t | M39: dp: cost/price | N39: Q: output | O39: Ef: fuel emis. | P39: Ep: process emis. | Q39: ER_f: fuel-int. resp. | R39: ER_p: process-int. resp. | S39: post fuel | T39: post process | U39: post total | V39: emrq_i: output ch. | W39: emrq_proc_i | X39: J_i: process>0 | Y39: revf_i $m | Z39: revp_i $m | AA39: rev_i $m | AB39: rebate_i $m | AC39: EI: tCO2/t | AD39: d: net price paid $/t | AE39: obl (sel.) $/t | AF39: obl (FULL) $/t | AG39: obl (NOPHASE) $/t | AH39: cbobl_i $m | AI39: cbobl0_i $m | AJ39: w_den sel | AK39: w_den FULL | AL39: w_den NOPHASE | AM39: w_num sel | AN39: w_num FULL | AO39: w_num NOPHASE | AP39: X*post/Q | AQ39: X*(Ef+Ep)/Q | AR39: X*covered/Q | AS39: covered_i | AT39: Ebase_i | AU39: Efbase_i | AV39: Epbase_i
A40: =Inputs!$A$83 -> DRI-EAF steel | B40: =Inputs!$B$83 -> 5100 | C40: =Inputs!$C$83 -> 0.044 | D40: =Inputs!$D$83 -> 580 | E40: =Inputs!$E$83 -> 750 | F40: =Inputs!$J$83 -> 0.57099077 | G40: =Inputs!$K$83 -> 0.03790102 | H40: =Inputs!$Q$83 -> 0.0034469507 | I40: =B40*(1+C40)^($N$38-BaseYr) -> 6603.4846 | J40: =$F$38*$B$38*F40 -> 11.419815 | K40: =$G$38*$C$38*G40 -> 0 | L40: =MIN($D$38,$B$38)*$F$38*F40+MIN($D$38,$C$38)*$G$38*G40 -> 0 | M40: =IF(E40>0,(J40+K40-L40)/E40,0) -> 0.015226421 | N40: =I40*(1+M40)^EpsQ1 -> 6563.6891 | O40: =N40*F40/1000 -> 3.7478059 | P40: =N40*G40/1000 -> 0.24877051 | Q40: =O40*($H$38-1) -> -0.18246877 | R40: =-P40*(1-EXP(-H40*($G$38*$C$38+$E$38))) -> 0 | S40: =O40+Q40 -> 3.5653371 | T40: =P40+R40 -> 0.24877051 | U40: =S40+T40 -> 3.8141077 | V40: =(O40+P40)*(1-(1+M40)^(-EpsQ1)) -> -0.024231126 | W40: =P40*(1-(1+M40)^(-EpsQ1)) -> -0.0015082883 | X40: =IF(G40>0,1,0) -> 1 | Y40: =S40*$F$38*$B$38 -> 71.306743 | Z40: =(P40*X40+R40)*$G$38*$C$38 -> 0 | AA40: =Y40+Z40 -> 71.306743 | AB40: =L40*N40/1000 -> 0 | AC40: =IF(N40>0,U40*1000/N40,0) -> 0.58109206 | AD40: =IF(N40>0,AA40*1000/N40-L40,0) -> 10.863821 | AE40: =MAX(0,$I$38*$J$38*AC40-$K$38*MAX(0,AD40)) -> 17.319144 | AF40: =MAX(0,$L$38*$J$38*AC40-MAX(0,AD40)) -> 17.319144 | AG40: =MAX(0,$M$38*$J$38*AC40-MAX(0,AD40)) -> 47.245385 | AH40: =IF(B40>0,D40*N40/B40*AE40/1000,0) -> 12.928027 | AI40: =D40*(1+C40)^($N$38-BaseYr)*$I$38*$J$38*(F40+G40)/1000 -> 22.177513 | AJ40: =D40*$I$38*$J$38*(F40+G40) -> 17128.126 | AK40: =D40*$L$38*$J$38*(F40+G40) -> 17128.126 | AL40: =D40*$M$38*$J$38*(F40+G40) -> 35315.724 | AM40: =D40*AE40 -> 10045.104 | AN40: =D40*AF40 -> 10045.104 | AO40: =D40*AG40 -> 27402.324 | AP40: =IF(N40>0,D40*U40/N40,0) -> 0.3370334 | AQ40: =IF(N40>0,D40*(O40+P40)/N40,0) -> 0.35315724 | AR40: =IF(N40>0,D40*AS40/N40,0) -> 0.33117465 | AS40: =O40*IF($F$38>0,1,0)+P40*X40*IF($G$38>0,1,0) -> 3.7478059 | AT40: =I40*(F40+G40)/1000 -> 4.0208075 | AU40: =I40*F40/1000 -> 3.7705287 | AV40: =I40*G40/1000 -> 0.2502788
A41: =Inputs!$A$84 -> Scrap-EAF steel | B41: =Inputs!$B$84 -> 4800 | C41: =Inputs!$C$84 -> 0.044 | D41: =Inputs!$D$84 -> 300 | E41: =Inputs!$E$84 -> 680 | F41: =Inputs!$J$84 -> 0.04488 | G41: =Inputs!$K$84 -> 0.04398115 | H41: =Inputs!$Q$84 -> 0.0016366491 | I41: =B41*(1+C41)^($N$38-BaseYr) -> 6215.0443 | J41: =$F$38*$B$38*F41 -> 0.8976 | K41: =$G$38*$C$38*G41 -> 0 | L41: =MIN($D$38,$B$38)*$F$38*F41+MIN($D$38,$C$38)*$G$38*G41 -> 0 | M41: =IF(E41>0,(J41+K41-L41)/E41,0) -> 0.00132 | N41: =I41*(1+M41)^EpsQ2 -> 6211.7658 | O41: =N41*F41/1000 -> 0.27878405 | P41: =N41*G41/1000 -> 0.2732006 | Q41: =O41*($H$38-1) -> -0.01357311 | R41: =-P41*(1-EXP(-H41*($G$38*$C$38+$E$38))) -> 0 | S41: =O41+Q41 -> 0.26521094 | T41: =P41+R41 -> 0.2732006 | U41: =S41+T41 -> 0.53841154 | V41: =(O41+P41)*(1-(1+M41)^(-EpsQ2)) -> -0.00029133256 | W41: =P41*(1-(1+M41)^(-EpsQ2)) -> -0.00014419284 | X41: =IF(G41>0,1,0) -> 1 | Y41: =S41*$F$38*$B$38 -> 5.3042188 | Z41: =(P41*X41+R41)*$G$38*$C$38 -> 0 | AA41: =Y41+Z41 -> 5.3042188 | AB41: =L41*N41/1000 -> 0 | AC41: =IF(N41>0,U41*1000/N41,0) -> 0.086676085 | AD41: =IF(N41>0,AA41*1000/N41-L41,0) -> 0.85389871 | AE41: =MAX(0,$I$38*$J$38*AC41-$K$38*MAX(0,AD41)) -> 3.3498914 | AF41: =MAX(0,$L$38*$J$38*AC41-MAX(0,AD41)) -> 3.3498914 | AG41: =MAX(0,$M$38*$J$38*AC41-MAX(0,AD41)) -> 7.8137098 | AH41: =IF(B41>0,D41*N41/B41*AE41/1000,0) -> 1.3005463 | AI41: =D41*(1+C41)^($N$38-BaseYr)*$I$38*$J$38*(F41+G41)/1000 -> 1.6740866 | AJ41: =D41*$I$38*$J$38*(F41+G41) -> 1292.9297 | AK41: =D41*$L$38*$J$38*(F41+G41) -> 1292.9297 | AL41: =D41*$M$38*$J$38*(F41+G41) -> 2665.8345 | AM41: =D41*AE41 -> 1004.9674 | AN41: =D41*AF41 -> 1004.9674 | AO41: =D41*AG41 -> 2344.1129 | AP41: =IF(N41>0,D41*U41/N41,0) -> 0.026002826 | AQ41: =IF(N41>0,D41*(O41+P41)/N41,0) -> 0.026658345 | AR41: =IF(N41>0,D41*AS41/N41,0) -> 0.013464 | AS41: =O41*IF($F$38>0,1,0)+P41*X41*IF($G$38>0,1,0) -> 0.27878405 | AT41: =I41*(F41+G41)/1000 -> 0.55227598 | AU41: =I41*F41/1000 -> 0.27893119 | AV41: =I41*G41/1000 -> 0.2733448
A42: =Inputs!$A$85 -> BF-BOF steel | B42: =Inputs!$B$85 -> 0 | C42: =Inputs!$C$85 -> 0 | D42: =Inputs!$D$85 -> 0 | E42: =Inputs!$E$85 -> 620 | F42: =Inputs!$J$85 -> 1.4249803 | G42: =Inputs!$K$85 -> 0.05276542 | H42: =Inputs!$Q$85 -> 0.0026960723 | I42: =B42*(1+C42)^($N$38-BaseYr) -> 0 | J42: =$F$38*$B$38*F42 -> 28.499605 | K42: =$G$38*$C$38*G42 -> 0 | L42: =MIN($D$38,$B$38)*$F$38*F42+MIN($D$38,$C$38)*$G$38*G42 -> 0 | M42: =IF(E42>0,(J42+K42-L42)/E42,0) -> 0.045967105 | N42: =I42*(1+M42)^EpsQ3 -> 0 | O42: =N42*F42/1000 -> 0 | P42: =N42*G42/1000 -> 0 | Q42: =O42*($H$38-1) -> 0 | R42: =-P42*(1-EXP(-H42*($G$38*$C$38+$E$38))) -> 0 | S42: =O42+Q42 -> 0 | T42: =P42+R42 -> 0 | U42: =S42+T42 -> 0 | V42: =(O42+P42)*(1-(1+M42)^(-EpsQ3)) -> 0 | W42: =P42*(1-(1+M42)^(-EpsQ3)) -> 0 | X42: =IF(G42>0,1,0) -> 1 | Y42: =S42*$F$38*$B$38 -> 0 | Z42: =(P42*X42+R42)*$G$38*$C$38 -> 0 | AA42: =Y42+Z42 -> 0 | AB42: =L42*N42/1000 -> 0 | AC42: =IF(N42>0,U42*1000/N42,0) -> 0 | AD42: =IF(N42>0,AA42*1000/N42-L42,0) -> 0 | AE42: =MAX(0,$I$38*$J$38*AC42-$K$38*MAX(0,AD42)) -> 0 | AF42: =MAX(0,$L$38*$J$38*AC42-MAX(0,AD42)) -> 0 | AG42: =MAX(0,$M$38*$J$38*AC42-MAX(0,AD42)) -> 0 | AH42: =IF(B42>0,D42*N42/B42*AE42/1000,0) -> 0 | AI42: =D42*(1+C42)^($N$38-BaseYr)*$I$38*$J$38*(F42+G42)/1000 -> 0 | AJ42: =D42*$I$38*$J$38*(F42+G42) -> 0 | AK42: =D42*$L$38*$J$38*(F42+G42) -> 0 | AL42: =D42*$M$38*$J$38*(F42+G42) -> 0 | AM42: =D42*AE42 -> 0 | AN42: =D42*AF42 -> 0 | AO42: =D42*AG42 -> 0 | AP42: =IF(N42>0,D42*U42/N42,0) -> 0 | AQ42: =IF(N42>0,D42*(O42+P42)/N42,0) -> 0 | AR42: =IF(N42>0,D42*AS42/N42,0) -> 0 | AS42: =O42*IF($F$38>0,1,0)+P42*X42*IF($G$38>0,1,0) -> 0 | AT42: =I42*(F42+G42)/1000 -> 0 | AU42: =I42*F42/1000 -> 0 | AV42: =I42*G42/1000 -> 0
A43: =Inputs!$A$86 -> Clinker | B43: =Inputs!$B$86 -> 50000 | C43: =Inputs!$C$86 -> 0.033 | D43: =Inputs!$D$86 -> 800 | E43: =Inputs!$E$86 -> 110 | F43: =Inputs!$J$86 -> 0.3135685 | G43: =Inputs!$K$86 -> 0.53702616 | H43: =Inputs!$Q$86 -> 0.0033464675 | I43: =B43*(1+C43)^($N$38-BaseYr) -> 60753.588 | J43: =$F$38*$B$38*F43 -> 6.27137 | K43: =$G$38*$C$38*G43 -> 0 | L43: =MIN($D$38,$B$38)*$F$38*F43+MIN($D$38,$C$38)*$G$38*G43 -> 0 | M43: =IF(E43>0,(J43+K43-L43)/E43,0) -> 0.057012455 | N43: =I43*(1+M43)^EpsQ4 -> 60417.663 | O43: =N43*F43/1000 -> 18.945076 | P43: =N43*G43/1000 -> 32.445866 | Q43: =O43*($H$38-1) -> -0.92237559 | R43: =-P43*(1-EXP(-H43*($G$38*$C$38+$E$38))) -> 0 | S43: =O43+Q43 -> 18.0227 | T43: =P43+R43 -> 32.445866 | U43: =S43+T43 -> 50.468566 | V43: =(O43+P43)*(1-(1+M43)^(-EpsQ4)) -> -0.28573615 | W43: =P43*(1-(1+M43)^(-EpsQ4)) -> -0.1804006 | X43: =IF(G43>0,1,0) -> 1 | Y43: =S43*$F$38*$B$38 -> 360.45401 | Z43: =(P43*X43+R43)*$G$38*$C$38 -> 0 | AA43: =Y43+Z43 -> 360.45401 | AB43: =L43*N43/1000 -> 0 | AC43: =IF(N43>0,U43*1000/N43,0) -> 0.83532801 | AD43: =IF(N43>0,AA43*1000/N43-L43,0) -> 5.9660369 | AE43: =MAX(0,$I$38*$J$38*AC43-$K$38*MAX(0,AD43)) -> 34.547371 | AF43: =MAX(0,$L$38*$J$38*AC43-MAX(0,AD43)) -> 34.547371 | AG43: =MAX(0,$M$38*$J$38*AC43-MAX(0,AD43)) -> 77.566764 | AH43: =IF(B43>0,D43*N43/B43*AE43/1000,0) -> 33.396343 | AI43: =D43*(1+C43)^($N$38-BaseYr)*$I$38*$J$38*(F43+G43)/1000 -> 40.101102 | AJ43: =D43*$I$38*$J$38*(F43+G43) -> 33003.073 | AK43: =D43*$L$38*$J$38*(F43+G43) -> 33003.073 | AL43: =D43*$M$38*$J$38*(F43+G43) -> 68047.573 | AM43: =D43*AE43 -> 27637.897 | AN43: =D43*AF43 -> 27637.897 | AO43: =D43*AG43 -> 62053.411 | AP43: =IF(N43>0,D43*U43/N43,0) -> 0.6682624 | AQ43: =IF(N43>0,D43*(O43+P43)/N43,0) -> 0.68047573 | AR43: =IF(N43>0,D43*AS43/N43,0) -> 0.2508548 | AS43: =O43*IF($F$38>0,1,0)+P43*X43*IF($G$38>0,1,0) -> 18.945076 | AT43: =I43*(F43+G43)/1000 -> 51.676678 | AU43: =I43*F43/1000 -> 19.050412 | AV43: =I43*G43/1000 -> 32.626266
A44: =Inputs!$A$87 -> Ammonia | B44: =Inputs!$B$87 -> 1785 | C44: =Inputs!$C$87 -> 0.022 | D44: =Inputs!$D$87 -> 120 | E44: =Inputs!$E$87 -> 450 | F44: =Inputs!$J$87 -> 1.97472 | G44: =Inputs!$K$87 -> 0 | H44: =Inputs!$Q$87 -> 0.0028931766 | I44: =B44*(1+C44)^($N$38-BaseYr) -> 2033.9656 | J44: =$F$38*$B$38*F44 -> 39.4944 | K44: =$G$38*$C$38*G44 -> 0 | L44: =MIN($D$38,$B$38)*$F$38*F44+MIN($D$38,$C$38)*$G$38*G44 -> 0 | M44: =IF(E44>0,(J44+K44-L44)/E44,0) -> 0.087765333 | N44: =I44*(1+M44)^EpsQ5 -> 1966.661 | O44: =N44*F44/1000 -> 3.8836048 | P44: =N44*G44/1000 -> 0 | Q44: =O44*($H$38-1) -> -0.18908039 | R44: =-P44*(1-EXP(-H44*($G$38*$C$38+$E$38))) -> 0 | S44: =O44+Q44 -> 3.6945245 | T44: =P44+R44 -> 0 | U44: =S44+T44 -> 3.6945245 | V44: =(O44+P44)*(1-(1+M44)^(-EpsQ5)) -> -0.13290763 | W44: =P44*(1-(1+M44)^(-EpsQ5)) -> 0 | X44: =IF(G44>0,1,0) -> 0 | Y44: =S44*$F$38*$B$38 -> 73.890489 | Z44: =(P44*X44+R44)*$G$38*$C$38 -> 0 | AA44: =Y44+Z44 -> 73.890489 | AB44: =L44*N44/1000 -> 0 | AC44: =IF(N44>0,U44*1000/N44,0) -> 1.8785772 | AD44: =IF(N44>0,AA44*1000/N44-L44,0) -> 37.571543 | AE44: =MAX(0,$I$38*$J$38*AC44-$K$38*MAX(0,AD44)) -> 53.539449 | AF44: =MAX(0,$L$38*$J$38*AC44-MAX(0,AD44)) -> 53.539449 | AG44: =MAX(0,$M$38*$J$38*AC44-MAX(0,AD44)) -> 150.28617 | AH44: =IF(B44>0,D44*N44/B44*AE44/1000,0) -> 7.0785847 | AI44: =D44*(1+C44)^($N$38-BaseYr)*$I$38*$J$38*(F44+G44)/1000 -> 13.095856 | AJ44: =D44*$I$38*$J$38*(F44+G44) -> 11492.87 | AK44: =D44*$L$38*$J$38*(F44+G44) -> 11492.87 | AL44: =D44*$M$38*$J$38*(F44+G44) -> 23696.64 | AM44: =D44*AE44 -> 6424.7339 | AN44: =D44*AF44 -> 6424.7339 | AO44: =D44*AG44 -> 18034.341 | AP44: =IF(N44>0,D44*U44/N44,0) -> 0.22542926 | AQ44: =IF(N44>0,D44*(O44+P44)/N44,0) -> 0.2369664 | AR44: =IF(N44>0,D44*AS44/N44,0) -> 0.2369664 | AS44: =O44*IF($F$38>0,1,0)+P44*X44*IF($G$38>0,1,0) -> 3.8836048 | AT44: =I44*(F44+G44)/1000 -> 4.0165125 | AU44: =I44*F44/1000 -> 4.0165125 | AV44: =I44*G44/1000 -> 0
A45: =Inputs!$A$88 -> Urea | B45: =Inputs!$B$88 -> 2800 | C45: =Inputs!$C$88 -> 0.022 | D45: =Inputs!$D$88 -> 1600 | E45: =Inputs!$E$88 -> 380 | F45: =Inputs!$J$88 -> 0.1122 | G45: =Inputs!$K$88 -> 0 | H45: =Inputs!$Q$88 -> 0.0010087869 | I45: =B45*(1+C45)^($N$38-BaseYr) -> 3190.5342 | J45: =$F$38*$B$38*F45 -> 2.244 | K45: =$G$38*$C$38*G45 -> 0 | L45: =MIN($D$38,$B$38)*$F$38*F45+MIN($D$38,$C$38)*$G$38*G45 -> 0 | M45: =IF(E45>0,(J45+K45-L45)/E45,0) -> 0.0059052632 | N45: =I45*(1+M45)^EpsQ6 -> 3183.0288 | O45: =N45*F45/1000 -> 0.35713584 | P45: =N45*G45/1000 -> 0 | Q45: =O45*($H$38-1) -> -0.01738781 | R45: =-P45*(1-EXP(-H45*($G$38*$C$38+$E$38))) -> 0 | S45: =O45+Q45 -> 0.33974803 | T45: =P45+R45 -> 0 | U45: =S45+T45 -> 0.33974803 | V45: =(O45+P45)*(1-(1+M45)^(-EpsQ6)) -> -0.00084210264 | W45: =P45*(1-(1+M45)^(-EpsQ6)) -> 0 | X45: =IF(G45>0,1,0) -> 0 | Y45: =S45*$F$38*$B$38 -> 6.7949605 | Z45: =(P45*X45+R45)*$G$38*$C$38 -> 0 | AA45: =Y45+Z45 -> 6.7949605 | AB45: =L45*N45/1000 -> 0 | AC45: =IF(N45>0,U45*1000/N45,0) -> 0.10673734 | AD45: =IF(N45>0,AA45*1000/N45-L45,0) -> 2.1347468 | AE45: =MAX(0,$I$38*$J$38*AC45-$K$38*MAX(0,AD45)) -> 3.0420141 | AF45: =MAX(0,$L$38*$J$38*AC45-MAX(0,AD45)) -> 3.0420141 | AG45: =MAX(0,$M$38*$J$38*AC45-MAX(0,AD45)) -> 8.5389871 | AH45: =IF(B45>0,D45*N45/B45*AE45/1000,0) -> 5.5330393 | AI45: =D45*(1+C45)^($N$38-BaseYr)*$I$38*$J$38*(F45+G45)/1000 -> 9.9211029 | AJ45: =D45*$I$38*$J$38*(F45+G45) -> 8706.72 | AK45: =D45*$L$38*$J$38*(F45+G45) -> 8706.72 | AL45: =D45*$M$38*$J$38*(F45+G45) -> 17952 | AM45: =D45*AE45 -> 4867.2226 | AN45: =D45*AF45 -> 4867.2226 | AO45: =D45*AG45 -> 13662.379 | AP45: =IF(N45>0,D45*U45/N45,0) -> 0.17077974 | AQ45: =IF(N45>0,D45*(O45+P45)/N45,0) -> 0.17952 | AR45: =IF(N45>0,D45*AS45/N45,0) -> 0.17952 | AS45: =O45*IF($F$38>0,1,0)+P45*X45*IF($G$38>0,1,0) -> 0.35713584 | AT45: =I45*(F45+G45)/1000 -> 0.35797794 | AU45: =I45*F45/1000 -> 0.35797794 | AV45: =I45*G45/1000 -> 0
A46: =Inputs!$A$89 -> Ammonium nitrate | B46: =Inputs!$B$89 -> 600 | C46: =Inputs!$C$89 -> 0.022 | D46: =Inputs!$D$89 -> 80 | E46: =Inputs!$E$89 -> 320 | F46: =Inputs!$J$89 -> 0.1122 | G46: =Inputs!$K$89 -> 0.9944125 | H46: =Inputs!$Q$89 -> 0.0078858436 | I46: =B46*(1+C46)^($N$38-BaseYr) -> 683.6859 | J46: =$F$38*$B$38*F46 -> 2.244 | K46: =$G$38*$C$38*G46 -> 0 | L46: =MIN($D$38,$B$38)*$F$38*F46+MIN($D$38,$C$38)*$G$38*G46 -> 0 | M46: =IF(E46>0,(J46+K46-L46)/E46,0) -> 0.0070125 | N46: =I46*(1+M46)^EpsQ7 -> 681.77753 | O46: =N46*F46/1000 -> 0.076495438 | P46: =N46*G46/1000 -> 0.67796809 | Q46: =O46*($H$38-1) -> -0.00372432 | R46: =-P46*(1-EXP(-H46*($G$38*$C$38+$E$38))) -> 0 | S46: =O46+Q46 -> 0.072771118 | T46: =P46+R46 -> 0.67796809 | U46: =S46+T46 -> 0.75073921 | V46: =(O46+P46)*(1-(1+M46)^(-EpsQ7)) -> -0.0021118347 | W46: =P46*(1-(1+M46)^(-EpsQ7)) -> -0.0018977147 | X46: =IF(G46>0,1,0) -> 1 | Y46: =S46*$F$38*$B$38 -> 1.4554224 | Z46: =(P46*X46+R46)*$G$38*$C$38 -> 0 | AA46: =Y46+Z46 -> 1.4554224 | AB46: =L46*N46/1000 -> 0 | AC46: =IF(N46>0,U46*1000/N46,0) -> 1.1011498 | AD46: =IF(N46>0,AA46*1000/N46-L46,0) -> 2.1347468 | AE46: =MAX(0,$I$38*$J$38*AC46-$K$38*MAX(0,AD46)) -> 51.27102 | AF46: =MAX(0,$L$38*$J$38*AC46-MAX(0,AD46)) -> 51.27102 | AG46: =MAX(0,$M$38*$J$38*AC46-MAX(0,AD46)) -> 107.98024 | AH46: =IF(B46>0,D46*N46/B46*AE46/1000,0) -> 4.6607239 | AI46: =D46*(1+C46)^($N$38-BaseYr)*$I$38*$J$38*(F46+G46)/1000 -> 4.8925207 | AJ46: =D46*$I$38*$J$38*(F46+G46) -> 4293.6565 | AK46: =D46*$L$38*$J$38*(F46+G46) -> 4293.6565 | AL46: =D46*$M$38*$J$38*(F46+G46) -> 8852.9 | AM46: =D46*AE46 -> 4101.6816 | AN46: =D46*AF46 -> 4101.6816 | AO46: =D46*AG46 -> 8638.419 | AP46: =IF(N46>0,D46*U46/N46,0) -> 0.088091987 | AQ46: =IF(N46>0,D46*(O46+P46)/N46,0) -> 0.088529 | AR46: =IF(N46>0,D46*AS46/N46,0) -> 0.008976 | AS46: =O46*IF($F$38>0,1,0)+P46*X46*IF($G$38>0,1,0) -> 0.076495438 | AT46: =I46*(F46+G46)/1000 -> 0.75657537 | AU46: =I46*F46/1000 -> 0.076709558 | AV46: =I46*G46/1000 -> 0.67986581
A47: =Inputs!$A$90 -> Aluminium | B47: =Inputs!$B$90 -> 300 | C47: =Inputs!$C$90 -> 0.055 | D47: =Inputs!$D$90 -> 167 | E47: =Inputs!$E$90 -> 2400 | F47: =Inputs!$J$90 -> 0.12342 | G47: =Inputs!$K$90 -> 2.397493 | H47: =Inputs!$Q$90 -> 0.0019988245 | I47: =B47*(1+C47)^($N$38-BaseYr) -> 413.65284 | J47: =$F$38*$B$38*F47 -> 2.4684 | K47: =$G$38*$C$38*G47 -> 0 | L47: =MIN($D$38,$B$38)*$F$38*F47+MIN($D$38,$C$38)*$G$38*G47 -> 0 | M47: =IF(E47>0,(J47+K47-L47)/E47,0) -> 0.0010285 | N47: =I47*(1+M47)^EpsQ8 -> 413.44029 | O47: =N47*F47/1000 -> 0.0510268 | P47: =N47*G47/1000 -> 0.99122021 | Q47: =O47*($H$38-1) -> -0.0024843328 | R47: =-P47*(1-EXP(-H47*($G$38*$C$38+$E$38))) -> 0 | S47: =O47+Q47 -> 0.048542467 | T47: =P47+R47 -> 0.99122021 | U47: =S47+T47 -> 1.0397627 | V47: =(O47+P47)*(1-(1+M47)^(-EpsQ8)) -> -0.00053583778 | W47: =P47*(1-(1+M47)^(-EpsQ8)) -> -0.00050960399 | X47: =IF(G47>0,1,0) -> 1 | Y47: =S47*$F$38*$B$38 -> 0.97084934 | Z47: =(P47*X47+R47)*$G$38*$C$38 -> 0 | AA47: =Y47+Z47 -> 0.97084934 | AB47: =L47*N47/1000 -> 0 | AC47: =IF(N47>0,U47*1000/N47,0) -> 2.5149041 | AD47: =IF(N47>0,AA47*1000/N47-L47,0) -> 2.3482214 | AE47: =MAX(0,$I$38*$J$38*AC47-$K$38*MAX(0,AD47)) -> 119.62463 | AF47: =MAX(0,$L$38*$J$38*AC47-MAX(0,AD47)) -> 119.62463 | AG47: =MAX(0,$M$38*$J$38*AC47-MAX(0,AD47)) -> 249.14219 | AH47: =IF(B47>0,D47*N47/B47*AE47/1000,0) -> 27.53142 | AI47: =D47*(1+C47)^($N$38-BaseYr)*$I$38*$J$38*(F47+G47)/1000 -> 28.153399 | AJ47: =D47*$I$38*$J$38*(F47+G47) -> 20418.135 | AK47: =D47*$L$38*$J$38*(F47+G47) -> 20418.135 | AL47: =D47*$M$38*$J$38*(F47+G47) -> 42099.248 | AM47: =D47*AE47 -> 19977.313 | AN47: =D47*AF47 -> 19977.313 | AO47: =D47*AG47 -> 41606.746 | AP47: =IF(N47>0,D47*U47/N47,0) -> 0.41998899 | AQ47: =IF(N47>0,D47*(O47+P47)/N47,0) -> 0.42099248 | AR47: =IF(N47>0,D47*AS47/N47,0) -> 0.02061114 | AS47: =O47*IF($F$38>0,1,0)+P47*X47*IF($G$38>0,1,0) -> 0.0510268 | AT47: =I47*(F47+G47)/1000 -> 1.0427828 | AU47: =I47*F47/1000 -> 0.051053034 | AV47: =I47*G47/1000 -> 0.99172981
A48: Total | I48: =SUM(I40:I47) -> 79893.956 | N48: =SUM(N40:N47) -> 79438.026 | O48: =SUM(O40:O47) -> 27.339929 | P48: =SUM(P40:P47) -> 34.637025 | Q48: =SUM(Q40:Q47) -> -1.3310943 | R48: =SUM(R40:R47) -> 0 | S48: =SUM(S40:S47) -> 26.008835 | T48: =SUM(T40:T47) -> 34.637025 | U48: =SUM(U40:U47) -> 60.64586 | ... W48: =SUM(W40:W47) -> -0.1844604 | Y48: =SUM(Y40:Y47) -> 520.17669 | Z48: =SUM(Z40:Z47) -> 0 | AA48: =SUM(AA40:AA47) -> 520.17669 | AB48: =SUM(AB40:AB47) -> 0 | AH48: =SUM(AH40:AH47) -> 92.428684 | AI48: =SUM(AI40:AI47) -> 120.01558 | AJ48: =SUM(AJ40:AJ47) -> 96335.511 | AK48: =SUM(AK40:AK47) -> 96335.511 | AL48: =SUM(AL40:AL47) -> 198629.92 | AM48: =SUM(AM40:AM47) -> 74058.919 | AN48: =SUM(AN40:AN47) -> 74058.919 | AO48: =SUM(AO40:AO47) -> 173741.73 | ... AV48: =SUM(AV40:AV47) -> 34.821485
A52: Bundle 3A - Industry-only price (EG3): industrial energy CO2 + CBAM process emissions.
A53: Bundle | B53: tau: carbon price | C53: tau_p: process price | D53: obrrb: OBR rebate rate | E53: fundsp: fund shadow price | F53: incl_f | G53: incl_p | H53: xf: fuel-intensity factor | I53: CBF (selected conv.) | J53: P_EU | K53: S (selected conv.) | L53: CBF (FULL) | M53: CBF (NOPHASE) | N53: Year | O53: CPAT scenario | P53: b_f | Q53: beta set | R53: Mode
A54: 3A | B54: =INDEX(BT_Tau,MATCH($A$54,BT_Code,0)) -> 20 | C54: =B54*INDEX(BT_Flag,MATCH($A$54,BT_Code,0)) -> 20 | D54: =INDEX(BT_Theta,MATCH($A$54,BT_Code,0))*B54 -> 0 | E54: =INDEX(BT_Phi,MATCH($A$54,BT_Code,0))*SigmaEff -> 0 | F54: 1 | G54: =INDEX(BT_Flag,MATCH($A$54,BT_Code,0)) -> 1 | H54: =IF(Mode="PROTOTYPE",1,EXP(Bf*(F54*B54+E54))) -> 0.95131318 | I54: =CBFsel -> 0.485 | J54: =PEU -> 100 | K54: =Ssel -> 1 | L54: =CBFyr -> 0.485 | M54: 1 | N54: =Yr -> 2030 | O54: =INDEX(BT_Scen,MATCH($A$54,BT_Code,0)) -> EG3 | P54: =Bf -> -0.0024955979 | Q54: =BetaSet -> IPCC_CENTRAL | R54: =Mode -> REBUILD
A55: Product | B55: Q0 (kt) | C55: g | D55: X exports (kt) | E55: P ($/t) | F55: F (tCO2/t) | G55: G (tCO2e/t) | H55: beta | I55: Qb: baseline output | J55: kf: fuel cost $/t | K55: kp: process cost $/t | L55: m: rebate $/t | M55: dp: cost/price | N55: Q: output | O55: Ef: fuel emis. | P55: Ep: process emis. | Q55: ER_f: fuel-int. resp. | R55: ER_p: process-int. resp. | S55: post fuel | T55: post process | U55: post total | V55: emrq_i: output ch. | W55: emrq_proc_i | X55: J_i: process>0 | Y55: revf_i $m | Z55: revp_i $m | AA55: rev_i $m | AB55: rebate_i $m | AC55: EI: tCO2/t | AD55: d: net price paid $/t | AE55: obl (sel.) $/t | AF55: obl (FULL) $/t | AG55: obl (NOPHASE) $/t | AH55: cbobl_i $m | AI55: cbobl0_i $m | AJ55: w_den sel | AK55: w_den FULL | AL55: w_den NOPHASE | AM55: w_num sel | AN55: w_num FULL | AO55: w_num NOPHASE | AP55: X*post/Q | AQ55: X*(Ef+Ep)/Q | AR55: X*covered/Q | AS55: covered_i | AT55: Ebase_i | AU55: Efbase_i | AV55: Epbase_i
A56: =Inputs!$A$83 -> DRI-EAF steel | B56: =Inputs!$B$83 -> 5100 | C56: =Inputs!$C$83 -> 0.044 | D56: =Inputs!$D$83 -> 580 | E56: =Inputs!$E$83 -> 750 | F56: =Inputs!$J$83 -> 0.57099077 | G56: =Inputs!$K$83 -> 0.03790102 | H56: =Inputs!$Q$83 -> 0.0034469507 | I56: =B56*(1+C56)^($N$54-BaseYr) -> 6603.4846 | J56: =$F$54*$B$54*F56 -> 11.419815 | K56: =$G$54*$C$54*G56 -> 0.7580204 | L56: =MIN($D$54,$B$54)*$F$54*F56+MIN($D$54,$C$54)*$G$54*G56 -> 0 | M56: =IF(E56>0,(J56+K56-L56)/E56,0) -> 0.016237114 | N56: =I56*(1+M56)^EpsQ1 -> 6561.0772 | O56: =N56*F56/1000 -> 3.7463145 | P56: =N56*G56/1000 -> 0.24867152 | Q56: =O56*($H$54-1) -> -0.18239616 | R56: =-P56*(1-EXP(-H56*($G$54*$C$54+$E$54))) -> -0.016565601 | S56: =O56+Q56 -> 3.5639184 | T56: =P56+R56 -> 0.23210592 | U56: =S56+T56 -> 3.7960243 | V56: =(O56+P56)*(1-(1+M56)^(-EpsQ1)) -> -0.025821511 | W56: =P56*(1-(1+M56)^(-EpsQ1)) -> -0.0016072833 | X56: =IF(G56>0,1,0) -> 1 | Y56: =S56*$F$54*$B$54 -> 71.278367 | Z56: =(P56*X56+R56)*$G$54*$C$54 -> 4.6421183 | AA56: =Y56+Z56 -> 75.920486 | AB56: =L56*N56/1000 -> 0 | AC56: =IF(N56>0,U56*1000/N56,0) -> 0.57856723 | AD56: =IF(N56>0,AA56*1000/N56-L56,0) -> 11.571345 | AE56: =MAX(0,$I$54*$J$54*AC56-$K$54*MAX(0,AD56)) -> 16.489166 | AF56: =MAX(0,$L$54*$J$54*AC56-MAX(0,AD56)) -> 16.489166 | AG56: =MAX(0,$M$54*$J$54*AC56-MAX(0,AD56)) -> 46.285379 | AH56: =IF(B56>0,D56*N56/B56*AE56/1000,0) -> 12.303585 | AI56: =D56*(1+C56)^($N$54-BaseYr)*$I$54*$J$54*(F56+G56)/1000 -> 22.177513 | AJ56: =D56*$I$54*$J$54*(F56+G56) -> 17128.126 | AK56: =D56*$L$54*$J$54*(F56+G56) -> 17128.126 | AL56: =D56*$M$54*$J$54*(F56+G56) -> 35315.724 | AM56: =D56*AE56 -> 9563.7164 | AN56: =D56*AF56 -> 9563.7164 | AO56: =D56*AG56 -> 26845.52 | AP56: =IF(N56>0,D56*U56/N56,0) -> 0.335569 | AQ56: =IF(N56>0,D56*(O56+P56)/N56,0) -> 0.35315724 | AR56: =IF(N56>0,D56*AS56/N56,0) -> 0.35315724 | AS56: =O56*IF($F$54>0,1,0)+P56*X56*IF($G$54>0,1,0) -> 3.994986 | AT56: =I56*(F56+G56)/1000 -> 4.0208075 | AU56: =I56*F56/1000 -> 3.7705287 | AV56: =I56*G56/1000 -> 0.2502788
A57: =Inputs!$A$84 -> Scrap-EAF steel | B57: =Inputs!$B$84 -> 4800 | C57: =Inputs!$C$84 -> 0.044 | D57: =Inputs!$D$84 -> 300 | E57: =Inputs!$E$84 -> 680 | F57: =Inputs!$J$84 -> 0.04488 | G57: =Inputs!$K$84 -> 0.04398115 | H57: =Inputs!$Q$84 -> 0.0016366491 | I57: =B57*(1+C57)^($N$54-BaseYr) -> 6215.0443 | J57: =$F$54*$B$54*F57 -> 0.8976 | K57: =$G$54*$C$54*G57 -> 0.879623 | L57: =MIN($D$54,$B$54)*$F$54*F57+MIN($D$54,$C$54)*$G$54*G57 -> 0 | M57: =IF(E57>0,(J57+K57-L57)/E57,0) -> 0.0026135632 | N57: =I57*(1+M57)^EpsQ2 -> 6208.5588 | O57: =N57*F57/1000 -> 0.27864012 | P57: =N57*G57/1000 -> 0.27305956 | Q57: =O57*($H$54-1) -> -0.013566103 | R57: =-P57*(1-EXP(-H57*($G$54*$C$54+$E$54))) -> -0.0087933523 | S57: =O57+Q57 -> 0.26507402 | T57: =P57+R57 -> 0.2642662 | U57: =S57+T57 -> 0.52934022 | V57: =(O57+P57)*(1-(1+M57)^(-EpsQ2)) -> -0.0005763092 | W57: =P57*(1-(1+M57)^(-EpsQ2)) -> -0.00028523986 | X57: =IF(G57>0,1,0) -> 1 | Y57: =S57*$F$54*$B$54 -> 5.3014803 | Z57: =(P57*X57+R57)*$G$54*$C$54 -> 5.2853241 | AA57: =Y57+Z57 -> 10.586804 | AB57: =L57*N57/1000 -> 0 | AC57: =IF(N57>0,U57*1000/N57,0) -> 0.085259758 | AD57: =IF(N57>0,AA57*1000/N57-L57,0) -> 1.7051952 | AE57: =MAX(0,$I$54*$J$54*AC57-$K$54*MAX(0,AD57)) -> 2.4299031 | AF57: =MAX(0,$L$54*$J$54*AC57-MAX(0,AD57)) -> 2.4299031 | AG57: =MAX(0,$M$54*$J$54*AC57-MAX(0,AD57)) -> 6.8207806 | AH57: =IF(B57>0,D57*N57/B57*AE57/1000,0) -> 0.94288727 | AI57: =D57*(1+C57)^($N$54-BaseYr)*$I$54*$J$54*(F57+G57)/1000 -> 1.6740866 | AJ57: =D57*$I$54*$J$54*(F57+G57) -> 1292.9297 | AK57: =D57*$L$54*$J$54*(F57+G57) -> 1292.9297 | AL57: =D57*$M$54*$J$54*(F57+G57) -> 2665.8345 | AM57: =D57*AE57 -> 728.97093 | AN57: =D57*AF57 -> 728.97093 | AO57: =D57*AG57 -> 2046.2342 | AP57: =IF(N57>0,D57*U57/N57,0) -> 0.025577927 | AQ57: =IF(N57>0,D57*(O57+P57)/N57,0) -> 0.026658345 | AR57: =IF(N57>0,D57*AS57/N57,0) -> 0.026658345 | AS57: =O57*IF($F$54>0,1,0)+P57*X57*IF($G$54>0,1,0) -> 0.55169968 | AT57: =I57*(F57+G57)/1000 -> 0.55227598 | AU57: =I57*F57/1000 -> 0.27893119 | AV57: =I57*G57/1000 -> 0.2733448
A58: =Inputs!$A$85 -> BF-BOF steel | B58: =Inputs!$B$85 -> 0 | C58: =Inputs!$C$85 -> 0 | D58: =Inputs!$D$85 -> 0 | E58: =Inputs!$E$85 -> 620 | F58: =Inputs!$J$85 -> 1.4249803 | G58: =Inputs!$K$85 -> 0.05276542 | H58: =Inputs!$Q$85 -> 0.0026960723 | I58: =B58*(1+C58)^($N$54-BaseYr) -> 0 | J58: =$F$54*$B$54*F58 -> 28.499605 | K58: =$G$54*$C$54*G58 -> 1.0553084 | L58: =MIN($D$54,$B$54)*$F$54*F58+MIN($D$54,$C$54)*$G$54*G58 -> 0 | M58: =IF(E58>0,(J58+K58-L58)/E58,0) -> 0.047669216 | N58: =I58*(1+M58)^EpsQ3 -> 0 | O58: =N58*F58/1000 -> 0 | P58: =N58*G58/1000 -> 0 | Q58: =O58*($H$54-1) -> 0 | R58: =-P58*(1-EXP(-H58*($G$54*$C$54+$E$54))) -> 0 | S58: =O58+Q58 -> 0 | T58: =P58+R58 -> 0 | U58: =S58+T58 -> 0 | V58: =(O58+P58)*(1-(1+M58)^(-EpsQ3)) -> 0 | W58: =P58*(1-(1+M58)^(-EpsQ3)) -> 0 | X58: =IF(G58>0,1,0) -> 1 | Y58: =S58*$F$54*$B$54 -> 0 | Z58: =(P58*X58+R58)*$G$54*$C$54 -> 0 | AA58: =Y58+Z58 -> 0 | AB58: =L58*N58/1000 -> 0 | AC58: =IF(N58>0,U58*1000/N58,0) -> 0 | AD58: =IF(N58>0,AA58*1000/N58-L58,0) -> 0 | AE58: =MAX(0,$I$54*$J$54*AC58-$K$54*MAX(0,AD58)) -> 0 | AF58: =MAX(0,$L$54*$J$54*AC58-MAX(0,AD58)) -> 0 | AG58: =MAX(0,$M$54*$J$54*AC58-MAX(0,AD58)) -> 0 | AH58: =IF(B58>0,D58*N58/B58*AE58/1000,0) -> 0 | AI58: =D58*(1+C58)^($N$54-BaseYr)*$I$54*$J$54*(F58+G58)/1000 -> 0 | AJ58: =D58*$I$54*$J$54*(F58+G58) -> 0 | AK58: =D58*$L$54*$J$54*(F58+G58) -> 0 | AL58: =D58*$M$54*$J$54*(F58+G58) -> 0 | AM58: =D58*AE58 -> 0 | AN58: =D58*AF58 -> 0 | AO58: =D58*AG58 -> 0 | AP58: =IF(N58>0,D58*U58/N58,0) -> 0 | AQ58: =IF(N58>0,D58*(O58+P58)/N58,0) -> 0 | AR58: =IF(N58>0,D58*AS58/N58,0) -> 0 | AS58: =O58*IF($F$54>0,1,0)+P58*X58*IF($G$54>0,1,0) -> 0 | AT58: =I58*(F58+G58)/1000 -> 0 | AU58: =I58*F58/1000 -> 0 | AV58: =I58*G58/1000 -> 0
A59: =Inputs!$A$86 -> Clinker | B59: =Inputs!$B$86 -> 50000 | C59: =Inputs!$C$86 -> 0.033 | D59: =Inputs!$D$86 -> 800 | E59: =Inputs!$E$86 -> 110 | F59: =Inputs!$J$86 -> 0.3135685 | G59: =Inputs!$K$86 -> 0.53702616 | H59: =Inputs!$Q$86 -> 0.0033464675 | I59: =B59*(1+C59)^($N$54-BaseYr) -> 60753.588 | J59: =$F$54*$B$54*F59 -> 6.27137 | K59: =$G$54*$C$54*G59 -> 10.740523 | L59: =MIN($D$54,$B$54)*$F$54*F59+MIN($D$54,$C$54)*$G$54*G59 -> 0 | M59: =IF(E59>0,(J59+K59-L59)/E59,0) -> 0.15465357 | N59: =I59*(1+M59)^EpsQ4 -> 59886.201 | O59: =N59*F59/1000 -> 18.778426 | P59: =N59*G59/1000 -> 32.160457 | Q59: =O59*($H$54-1) -> -0.91426194 | R59: =-P59*(1-EXP(-H59*($G$54*$C$54+$E$54))) -> -2.0820269 | S59: =O59+Q59 -> 17.864164 | T59: =P59+R59 -> 30.07843 | U59: =S59+T59 -> 47.942594 | V59: =(O59+P59)*(1-(1+M59)^(-EpsQ4)) -> -0.73779503 | W59: =P59*(1-(1+M59)^(-EpsQ4)) -> -0.46580969 | X59: =IF(G59>0,1,0) -> 1 | Y59: =S59*$F$54*$B$54 -> 357.28329 | Z59: =(P59*X59+R59)*$G$54*$C$54 -> 601.56859 | AA59: =Y59+Z59 -> 958.85188 | AB59: =L59*N59/1000 -> 0 | AC59: =IF(N59>0,U59*1000/N59,0) -> 0.80056162 | AD59: =IF(N59>0,AA59*1000/N59-L59,0) -> 16.011232 | AE59: =MAX(0,$I$54*$J$54*AC59-$K$54*MAX(0,AD59)) -> 22.816006 | AF59: =MAX(0,$L$54*$J$54*AC59-MAX(0,AD59)) -> 22.816006 | AG59: =MAX(0,$M$54*$J$54*AC59-MAX(0,AD59)) -> 64.044929 | AH59: =IF(B59>0,D59*N59/B59*AE59/1000,0) -> 21.861823 | AI59: =D59*(1+C59)^($N$54-BaseYr)*$I$54*$J$54*(F59+G59)/1000 -> 40.101102 | AJ59: =D59*$I$54*$J$54*(F59+G59) -> 33003.073 | AK59: =D59*$L$54*$J$54*(F59+G59) -> 33003.073 | AL59: =D59*$M$54*$J$54*(F59+G59) -> 68047.573 | AM59: =D59*AE59 -> 18252.805 | AN59: =D59*AF59 -> 18252.805 | AO59: =D59*AG59 -> 51235.943 | AP59: =IF(N59>0,D59*U59/N59,0) -> 0.64044929 | AQ59: =IF(N59>0,D59*(O59+P59)/N59,0) -> 0.68047573 | AR59: =IF(N59>0,D59*AS59/N59,0) -> 0.68047573 | AS59: =O59*IF($F$54>0,1,0)+P59*X59*IF($G$54>0,1,0) -> 50.938883 | AT59: =I59*(F59+G59)/1000 -> 51.676678 | AU59: =I59*F59/1000 -> 19.050412 | AV59: =I59*G59/1000 -> 32.626266
A60: =Inputs!$A$87 -> Ammonia | B60: =Inputs!$B$87 -> 1785 | C60: =Inputs!$C$87 -> 0.022 | D60: =Inputs!$D$87 -> 120 | E60: =Inputs!$E$87 -> 450 | F60: =Inputs!$J$87 -> 1.97472 | G60: =Inputs!$K$87 -> 0 | H60: =Inputs!$Q$87 -> 0.0028931766 | I60: =B60*(1+C60)^($N$54-BaseYr) -> 2033.9656 | J60: =$F$54*$B$54*F60 -> 39.4944 | K60: =$G$54*$C$54*G60 -> 0 | L60: =MIN($D$54,$B$54)*$F$54*F60+MIN($D$54,$C$54)*$G$54*G60 -> 0 | M60: =IF(E60>0,(J60+K60-L60)/E60,0) -> 0.087765333 | N60: =I60*(1+M60)^EpsQ5 -> 1966.661 | O60: =N60*F60/1000 -> 3.8836048 | P60: =N60*G60/1000 -> 0 | Q60: =O60*($H$54-1) -> -0.18908039 | R60: =-P60*(1-EXP(-H60*($G$54*$C$54+$E$54))) -> 0 | S60: =O60+Q60 -> 3.6945245 | T60: =P60+R60 -> 0 | U60: =S60+T60 -> 3.6945245 | V60: =(O60+P60)*(1-(1+M60)^(-EpsQ5)) -> -0.13290763 | W60: =P60*(1-(1+M60)^(-EpsQ5)) -> 0 | X60: =IF(G60>0,1,0) -> 0 | Y60: =S60*$F$54*$B$54 -> 73.890489 | Z60: =(P60*X60+R60)*$G$54*$C$54 -> 0 | AA60: =Y60+Z60 -> 73.890489 | AB60: =L60*N60/1000 -> 0 | AC60: =IF(N60>0,U60*1000/N60,0) -> 1.8785772 | AD60: =IF(N60>0,AA60*1000/N60-L60,0) -> 37.571543 | AE60: =MAX(0,$I$54*$J$54*AC60-$K$54*MAX(0,AD60)) -> 53.539449 | AF60: =MAX(0,$L$54*$J$54*AC60-MAX(0,AD60)) -> 53.539449 | AG60: =MAX(0,$M$54*$J$54*AC60-MAX(0,AD60)) -> 150.28617 | AH60: =IF(B60>0,D60*N60/B60*AE60/1000,0) -> 7.0785847 | AI60: =D60*(1+C60)^($N$54-BaseYr)*$I$54*$J$54*(F60+G60)/1000 -> 13.095856 | AJ60: =D60*$I$54*$J$54*(F60+G60) -> 11492.87 | AK60: =D60*$L$54*$J$54*(F60+G60) -> 11492.87 | AL60: =D60*$M$54*$J$54*(F60+G60) -> 23696.64 | AM60: =D60*AE60 -> 6424.7339 | AN60: =D60*AF60 -> 6424.7339 | AO60: =D60*AG60 -> 18034.341 | AP60: =IF(N60>0,D60*U60/N60,0) -> 0.22542926 | AQ60: =IF(N60>0,D60*(O60+P60)/N60,0) -> 0.2369664 | AR60: =IF(N60>0,D60*AS60/N60,0) -> 0.2369664 | AS60: =O60*IF($F$54>0,1,0)+P60*X60*IF($G$54>0,1,0) -> 3.8836048 | AT60: =I60*(F60+G60)/1000 -> 4.0165125 | AU60: =I60*F60/1000 -> 4.0165125 | AV60: =I60*G60/1000 -> 0
A61: =Inputs!$A$88 -> Urea | B61: =Inputs!$B$88 -> 2800 | C61: =Inputs!$C$88 -> 0.022 | D61: =Inputs!$D$88 -> 1600 | E61: =Inputs!$E$88 -> 380 | F61: =Inputs!$J$88 -> 0.1122 | G61: =Inputs!$K$88 -> 0 | H61: =Inputs!$Q$88 -> 0.0010087869 | I61: =B61*(1+C61)^($N$54-BaseYr) -> 3190.5342 | J61: =$F$54*$B$54*F61 -> 2.244 | K61: =$G$54*$C$54*G61 -> 0 | L61: =MIN($D$54,$B$54)*$F$54*F61+MIN($D$54,$C$54)*$G$54*G61 -> 0 | M61: =IF(E61>0,(J61+K61-L61)/E61,0) -> 0.0059052632 | N61: =I61*(1+M61)^EpsQ6 -> 3183.0288 | O61: =N61*F61/1000 -> 0.35713584 | P61: =N61*G61/1000 -> 0 | Q61: =O61*($H$54-1) -> -0.01738781 | R61: =-P61*(1-EXP(-H61*($G$54*$C$54+$E$54))) -> 0 | S61: =O61+Q61 -> 0.33974803 | T61: =P61+R61 -> 0 | U61: =S61+T61 -> 0.33974803 | V61: =(O61+P61)*(1-(1+M61)^(-EpsQ6)) -> -0.00084210264 | W61: =P61*(1-(1+M61)^(-EpsQ6)) -> 0 | X61: =IF(G61>0,1,0) -> 0 | Y61: =S61*$F$54*$B$54 -> 6.7949605 | Z61: =(P61*X61+R61)*$G$54*$C$54 -> 0 | AA61: =Y61+Z61 -> 6.7949605 | AB61: =L61*N61/1000 -> 0 | AC61: =IF(N61>0,U61*1000/N61,0) -> 0.10673734 | AD61: =IF(N61>0,AA61*1000/N61-L61,0) -> 2.1347468 | AE61: =MAX(0,$I$54*$J$54*AC61-$K$54*MAX(0,AD61)) -> 3.0420141 | AF61: =MAX(0,$L$54*$J$54*AC61-MAX(0,AD61)) -> 3.0420141 | AG61: =MAX(0,$M$54*$J$54*AC61-MAX(0,AD61)) -> 8.5389871 | AH61: =IF(B61>0,D61*N61/B61*AE61/1000,0) -> 5.5330393 | AI61: =D61*(1+C61)^($N$54-BaseYr)*$I$54*$J$54*(F61+G61)/1000 -> 9.9211029 | AJ61: =D61*$I$54*$J$54*(F61+G61) -> 8706.72 | AK61: =D61*$L$54*$J$54*(F61+G61) -> 8706.72 | AL61: =D61*$M$54*$J$54*(F61+G61) -> 17952 | AM61: =D61*AE61 -> 4867.2226 | AN61: =D61*AF61 -> 4867.2226 | AO61: =D61*AG61 -> 13662.379 | AP61: =IF(N61>0,D61*U61/N61,0) -> 0.17077974 | AQ61: =IF(N61>0,D61*(O61+P61)/N61,0) -> 0.17952 | AR61: =IF(N61>0,D61*AS61/N61,0) -> 0.17952 | AS61: =O61*IF($F$54>0,1,0)+P61*X61*IF($G$54>0,1,0) -> 0.35713584 | AT61: =I61*(F61+G61)/1000 -> 0.35797794 | AU61: =I61*F61/1000 -> 0.35797794 | AV61: =I61*G61/1000 -> 0
A62: =Inputs!$A$89 -> Ammonium nitrate | B62: =Inputs!$B$89 -> 600 | C62: =Inputs!$C$89 -> 0.022 | D62: =Inputs!$D$89 -> 80 | E62: =Inputs!$E$89 -> 320 | F62: =Inputs!$J$89 -> 0.1122 | G62: =Inputs!$K$89 -> 0.9944125 | H62: =Inputs!$Q$89 -> 0.0078858436 | I62: =B62*(1+C62)^($N$54-BaseYr) -> 683.6859 | J62: =$F$54*$B$54*F62 -> 2.244 | K62: =$G$54*$C$54*G62 -> 19.88825 | L62: =MIN($D$54,$B$54)*$F$54*F62+MIN($D$54,$C$54)*$G$54*G62 -> 0 | M62: =IF(E62>0,(J62+K62-L62)/E62,0) -> 0.069163281 | N62: =I62*(1+M62)^EpsQ7 -> 665.63939 | O62: =N62*F62/1000 -> 0.074684739 | P62: =N62*G62/1000 -> 0.66192013 | Q62: =O62*($H$54-1) -> -0.0036361628 | R62: =-P62*(1-EXP(-H62*($G$54*$C$54+$E$54))) -> -0.09657973 | S62: =O62+Q62 -> 0.071048576 | T62: =P62+R62 -> 0.5653404 | U62: =S62+T62 -> 0.63638897 | V62: =(O62+P62)*(1-(1+M62)^(-EpsQ7)) -> -0.019970502 | W62: =P62*(1-(1+M62)^(-EpsQ7)) -> -0.017945682 | X62: =IF(G62>0,1,0) -> 1 | Y62: =S62*$F$54*$B$54 -> 1.4209715 | Z62: =(P62*X62+R62)*$G$54*$C$54 -> 11.306808 | AA62: =Y62+Z62 -> 12.727779 | AB62: =L62*N62/1000 -> 0 | AC62: =IF(N62>0,U62*1000/N62,0) -> 0.95605667 | AD62: =IF(N62>0,AA62*1000/N62-L62,0) -> 19.121133 | AE62: =MAX(0,$I$54*$J$54*AC62-$K$54*MAX(0,AD62)) -> 27.247615 | AF62: =MAX(0,$L$54*$J$54*AC62-MAX(0,AD62)) -> 27.247615 | AG62: =MAX(0,$M$54*$J$54*AC62-MAX(0,AD62)) -> 76.484533 | AH62: =IF(B62>0,D62*N62/B62*AE62/1000,0) -> 2.4182781 | AI62: =D62*(1+C62)^($N$54-BaseYr)*$I$54*$J$54*(F62+G62)/1000 -> 4.8925207 | AJ62: =D62*$I$54*$J$54*(F62+G62) -> 4293.6565 | AK62: =D62*$L$54*$J$54*(F62+G62) -> 4293.6565 | AL62: =D62*$M$54*$J$54*(F62+G62) -> 8852.9 | AM62: =D62*AE62 -> 2179.8092 | AN62: =D62*AF62 -> 2179.8092 | AO62: =D62*AG62 -> 6118.7627 | AP62: =IF(N62>0,D62*U62/N62,0) -> 0.076484533 | AQ62: =IF(N62>0,D62*(O62+P62)/N62,0) -> 0.088529 | AR62: =IF(N62>0,D62*AS62/N62,0) -> 0.088529 | AS62: =O62*IF($F$54>0,1,0)+P62*X62*IF($G$54>0,1,0) -> 0.73660486 | AT62: =I62*(F62+G62)/1000 -> 0.75657537 | AU62: =I62*F62/1000 -> 0.076709558 | AV62: =I62*G62/1000 -> 0.67986581
A63: =Inputs!$A$90 -> Aluminium | B63: =Inputs!$B$90 -> 300 | C63: =Inputs!$C$90 -> 0.055 | D63: =Inputs!$D$90 -> 167 | E63: =Inputs!$E$90 -> 2400 | F63: =Inputs!$J$90 -> 0.12342 | G63: =Inputs!$K$90 -> 2.397493 | H63: =Inputs!$Q$90 -> 0.0019988245 | I63: =B63*(1+C63)^($N$54-BaseYr) -> 413.65284 | J63: =$F$54*$B$54*F63 -> 2.4684 | K63: =$G$54*$C$54*G63 -> 47.949861 | L63: =MIN($D$54,$B$54)*$F$54*F63+MIN($D$54,$C$54)*$G$54*G63 -> 0 | M63: =IF(E63>0,(J63+K63-L63)/E63,0) -> 0.021007609 | N63: =I63*(1+M63)^EpsQ8 -> 409.37519 | O63: =N63*F63/1000 -> 0.050525086 | P63: =N63*G63/1000 -> 0.98147418 | Q63: =O63*($H$54-1) -> -0.002459906 | R63: =-P63*(1-EXP(-H63*($G$54*$C$54+$E$54))) -> -0.038461984 | S63: =O63+Q63 -> 0.04806518 | T63: =P63+R63 -> 0.94301219 | U63: =S63+T63 -> 0.99107738 | V63: =(O63+P63)*(1-(1+M63)^(-EpsQ8)) -> -0.010783578 | W63: =P63*(1-(1+M63)^(-EpsQ8)) -> -0.010255631 | X63: =IF(G63>0,1,0) -> 1 | Y63: =S63*$F$54*$B$54 -> 0.96130361 | Z63: =(P63*X63+R63)*$G$54*$C$54 -> 18.860244 | AA63: =Y63+Z63 -> 19.821548 | AB63: =L63*N63/1000 -> 0 | AC63: =IF(N63>0,U63*1000/N63,0) -> 2.4209512 | AD63: =IF(N63>0,AA63*1000/N63-L63,0) -> 48.419024 | AE63: =MAX(0,$I$54*$J$54*AC63-$K$54*MAX(0,AD63)) -> 68.99711 | AF63: =MAX(0,$L$54*$J$54*AC63-MAX(0,AD63)) -> 68.99711 | AG63: =MAX(0,$M$54*$J$54*AC63-MAX(0,AD63)) -> 193.6761 | AH63: =IF(B63>0,D63*N63/B63*AE63/1000,0) -> 15.723443 | AI63: =D63*(1+C63)^($N$54-BaseYr)*$I$54*$J$54*(F63+G63)/1000 -> 28.153399 | AJ63: =D63*$I$54*$J$54*(F63+G63) -> 20418.135 | AK63: =D63*$L$54*$J$54*(F63+G63) -> 20418.135 | AL63: =D63*$M$54*$J$54*(F63+G63) -> 42099.248 | AM63: =D63*AE63 -> 11522.517 | AN63: =D63*AF63 -> 11522.517 | AO63: =D63*AG63 -> 32343.908 | AP63: =IF(N63>0,D63*U63/N63,0) -> 0.40429885 | AQ63: =IF(N63>0,D63*(O63+P63)/N63,0) -> 0.42099248 | AR63: =IF(N63>0,D63*AS63/N63,0) -> 0.42099248 | AS63: =O63*IF($F$54>0,1,0)+P63*X63*IF($G$54>0,1,0) -> 1.0319993 | AT63: =I63*(F63+G63)/1000 -> 1.0427828 | AU63: =I63*F63/1000 -> 0.051053034 | AV63: =I63*G63/1000 -> 0.99172981
A64: Total | I64: =SUM(I56:I63) -> 79893.956 | N64: =SUM(N56:N63) -> 78880.541 | O64: =SUM(O56:O63) -> 27.169331 | P64: =SUM(P56:P63) -> 34.325582 | Q64: =SUM(Q56:Q63) -> -1.3227885 | R64: =SUM(R56:R63) -> -2.2424276 | S64: =SUM(S56:S63) -> 25.846543 | T64: =SUM(T56:T63) -> 32.083154 | U64: =SUM(U56:U63) -> 57.929697 | ... W64: =SUM(W56:W63) -> -0.49590352 | Y64: =SUM(Y56:Y63) -> 516.93086 | Z64: =SUM(Z56:Z63) -> 641.66309 | AA64: =SUM(AA56:AA63) -> 1158.5939 | AB64: =SUM(AB56:AB63) -> 0 | AH64: =SUM(AH56:AH63) -> 65.861639 | AI64: =SUM(AI56:AI63) -> 120.01558 | AJ64: =SUM(AJ56:AJ63) -> 96335.511 | AK64: =SUM(AK56:AK63) -> 96335.511 | AL64: =SUM(AL56:AL63) -> 198629.92 | AM64: =SUM(AM56:AM63) -> 53539.775 | AN64: =SUM(AN56:AN63) -> 53539.775 | AO64: =SUM(AO56:AO63) -> 150287.09 | ... AV64: =SUM(AV56:AV63) -> 34.821485
A68: Bundle 3B - 3A + output-based rebate for CBAM producers (theta = 1: benchmark = own baseline intensity). Built from EG3 with OBR logic; EG4 (feebate run) is unusable (MajorIssues #8).
A69: Bundle | B69: tau: carbon price | C69: tau_p: process price | D69: obrrb: OBR rebate rate | E69: fundsp: fund shadow price | F69: incl_f | G69: incl_p | H69: xf: fuel-intensity factor | I69: CBF (selected conv.) | J69: P_EU | K69: S (selected conv.) | L69: CBF (FULL) | M69: CBF (NOPHASE) | N69: Year | O69: CPAT scenario | P69: b_f | Q69: beta set | R69: Mode
A70: 3B | B70: =INDEX(BT_Tau,MATCH($A$70,BT_Code,0)) -> 20 | C70: =B70*INDEX(BT_Flag,MATCH($A$70,BT_Code,0)) -> 20 | D70: =INDEX(BT_Theta,MATCH($A$70,BT_Code,0))*B70 -> 20 | E70: =INDEX(BT_Phi,MATCH($A$70,BT_Code,0))*SigmaEff -> 0 | F70: 1 | G70: =INDEX(BT_Flag,MATCH($A$70,BT_Code,0)) -> 1 | H70: =IF(Mode="PROTOTYPE",1,EXP(Bf*(F70*B70+E70))) -> 0.95131318 | I70: =CBFsel -> 0.485 | J70: =PEU -> 100 | K70: =Ssel -> 1 | L70: =CBFyr -> 0.485 | M70: 1 | N70: =Yr -> 2030 | O70: =INDEX(BT_Scen,MATCH($A$70,BT_Code,0)) -> EG3 | P70: =Bf -> -0.0024955979 | Q70: =BetaSet -> IPCC_CENTRAL | R70: =Mode -> REBUILD
A71: Product | B71: Q0 (kt) | C71: g | D71: X exports (kt) | E71: P ($/t) | F71: F (tCO2/t) | G71: G (tCO2e/t) | H71: beta | I71: Qb: baseline output | J71: kf: fuel cost $/t | K71: kp: process cost $/t | L71: m: rebate $/t | M71: dp: cost/price | N71: Q: output | O71: Ef: fuel emis. | P71: Ep: process emis. | Q71: ER_f: fuel-int. resp. | R71: ER_p: process-int. resp. | S71: post fuel | T71: post process | U71: post total | V71: emrq_i: output ch. | W71: emrq_proc_i | X71: J_i: process>0 | Y71: revf_i $m | Z71: revp_i $m | AA71: rev_i $m | AB71: rebate_i $m | AC71: EI: tCO2/t | AD71: d: net price paid $/t | AE71: obl (sel.) $/t | AF71: obl (FULL) $/t | AG71: obl (NOPHASE) $/t | AH71: cbobl_i $m | AI71: cbobl0_i $m | AJ71: w_den sel | AK71: w_den FULL | AL71: w_den NOPHASE | AM71: w_num sel | AN71: w_num FULL | AO71: w_num NOPHASE | AP71: X*post/Q | AQ71: X*(Ef+Ep)/Q | AR71: X*covered/Q | AS71: covered_i | AT71: Ebase_i | AU71: Efbase_i | AV71: Epbase_i
A72: =Inputs!$A$83 -> DRI-EAF steel | B72: =Inputs!$B$83 -> 5100 | C72: =Inputs!$C$83 -> 0.044 | D72: =Inputs!$D$83 -> 580 | E72: =Inputs!$E$83 -> 750 | F72: =Inputs!$J$83 -> 0.57099077 | G72: =Inputs!$K$83 -> 0.03790102 | H72: =Inputs!$Q$83 -> 0.0034469507 | I72: =B72*(1+C72)^($N$70-BaseYr) -> 6603.4846 | J72: =$F$70*$B$70*F72 -> 11.419815 | K72: =$G$70*$C$70*G72 -> 0.7580204 | L72: =MIN($D$70,$B$70)*$F$70*F72+MIN($D$70,$C$70)*$G$70*G72 -> 12.177836 | M72: =IF(E72>0,(J72+K72-L72)/E72,0) -> 0 | N72: =I72*(1+M72)^EpsQ1 -> 6603.4846 | O72: =N72*F72/1000 -> 3.7705287 | P72: =N72*G72/1000 -> 0.2502788 | Q72: =O72*($H$70-1) -> -0.18357507 | R72: =-P72*(1-EXP(-H72*($G$70*$C$70+$E$70))) -> -0.016672672 | S72: =O72+Q72 -> 3.5869537 | T72: =P72+R72 -> 0.23360613 | U72: =S72+T72 -> 3.8205598 | V72: =(O72+P72)*(1-(1+M72)^(-EpsQ1)) -> 0 | W72: =P72*(1-(1+M72)^(-EpsQ1)) -> 0 | X72: =IF(G72>0,1,0) -> 1 | Y72: =S72*$F$70*$B$70 -> 71.739073 | Z72: =(P72*X72+R72)*$G$70*$C$70 -> 4.6721226 | AA72: =Y72+Z72 -> 76.411196 | AB72: =L72*N72/1000 -> 80.416151 | AC72: =IF(N72>0,U72*1000/N72,0) -> 0.57856723 | AD72: =IF(N72>0,AA72*1000/N72-L72,0) -> -0.60649114 | AE72: =MAX(0,$I$70*$J$70*AC72-$K$70*MAX(0,AD72)) -> 28.060511 | AF72: =MAX(0,$L$70*$J$70*AC72-MAX(0,AD72)) -> 28.060511 | AG72: =MAX(0,$M$70*$J$70*AC72-MAX(0,AD72)) -> 57.856723 | AH72: =IF(B72>0,D72*N72/B72*AE72/1000,0) -> 21.073009 | AI72: =D72*(1+C72)^($N$70-BaseYr)*$I$70*$J$70*(F72+G72)/1000 -> 22.177513 | AJ72: =D72*$I$70*$J$70*(F72+G72) -> 17128.126 | AK72: =D72*$L$70*$J$70*(F72+G72) -> 17128.126 | AL72: =D72*$M$70*$J$70*(F72+G72) -> 35315.724 | AM72: =D72*AE72 -> 16275.096 | AN72: =D72*AF72 -> 16275.096 | AO72: =D72*AG72 -> 33556.9 | AP72: =IF(N72>0,D72*U72/N72,0) -> 0.335569 | AQ72: =IF(N72>0,D72*(O72+P72)/N72,0) -> 0.35315724 | AR72: =IF(N72>0,D72*AS72/N72,0) -> 0.35315724 | AS72: =O72*IF($F$70>0,1,0)+P72*X72*IF($G$70>0,1,0) -> 4.0208075 | AT72: =I72*(F72+G72)/1000 -> 4.0208075 | AU72: =I72*F72/1000 -> 3.7705287 | AV72: =I72*G72/1000 -> 0.2502788
A73: =Inputs!$A$84 -> Scrap-EAF steel | B73: =Inputs!$B$84 -> 4800 | C73: =Inputs!$C$84 -> 0.044 | D73: =Inputs!$D$84 -> 300 | E73: =Inputs!$E$84 -> 680 | F73: =Inputs!$J$84 -> 0.04488 | G73: =Inputs!$K$84 -> 0.04398115 | H73: =Inputs!$Q$84 -> 0.0016366491 | I73: =B73*(1+C73)^($N$70-BaseYr) -> 6215.0443 | J73: =$F$70*$B$70*F73 -> 0.8976 | K73: =$G$70*$C$70*G73 -> 0.879623 | L73: =MIN($D$70,$B$70)*$F$70*F73+MIN($D$70,$C$70)*$G$70*G73 -> 1.777223 | M73: =IF(E73>0,(J73+K73-L73)/E73,0) -> 0 | N73: =I73*(1+M73)^EpsQ2 -> 6215.0443 | O73: =N73*F73/1000 -> 0.27893119 | P73: =N73*G73/1000 -> 0.2733448 | Q73: =O73*($H$70-1) -> -0.013580274 | R73: =-P73*(1-EXP(-H73*($G$70*$C$70+$E$70))) -> -0.0088025379 | S73: =O73+Q73 -> 0.26535091 | T73: =P73+R73 -> 0.26454226 | U73: =S73+T73 -> 0.52989317 | V73: =(O73+P73)*(1-(1+M73)^(-EpsQ2)) -> 0 | W73: =P73*(1-(1+M73)^(-EpsQ2)) -> 0 | X73: =IF(G73>0,1,0) -> 1 | Y73: =S73*$F$70*$B$70 -> 5.3070183 | Z73: =(P73*X73+R73)*$G$70*$C$70 -> 5.2908452 | AA73: =Y73+Z73 -> 10.597863 | AB73: =L73*N73/1000 -> 11.04552 | AC73: =IF(N73>0,U73*1000/N73,0) -> 0.085259758 | AD73: =IF(N73>0,AA73*1000/N73-L73,0) -> -0.072027843 | AE73: =MAX(0,$I$70*$J$70*AC73-$K$70*MAX(0,AD73)) -> 4.1350983 | AF73: =MAX(0,$L$70*$J$70*AC73-MAX(0,AD73)) -> 4.1350983 | AG73: =MAX(0,$M$70*$J$70*AC73-MAX(0,AD73)) -> 8.5259758 | AH73: =IF(B73>0,D73*N73/B73*AE73/1000,0) -> 1.6062387 | AI73: =D73*(1+C73)^($N$70-BaseYr)*$I$70*$J$70*(F73+G73)/1000 -> 1.6740866 | AJ73: =D73*$I$70*$J$70*(F73+G73) -> 1292.9297 | AK73: =D73*$L$70*$J$70*(F73+G73) -> 1292.9297 | AL73: =D73*$M$70*$J$70*(F73+G73) -> 2665.8345 | AM73: =D73*AE73 -> 1240.5295 | AN73: =D73*AF73 -> 1240.5295 | AO73: =D73*AG73 -> 2557.7927 | AP73: =IF(N73>0,D73*U73/N73,0) -> 0.025577927 | AQ73: =IF(N73>0,D73*(O73+P73)/N73,0) -> 0.026658345 | AR73: =IF(N73>0,D73*AS73/N73,0) -> 0.026658345 | AS73: =O73*IF($F$70>0,1,0)+P73*X73*IF($G$70>0,1,0) -> 0.55227598 | AT73: =I73*(F73+G73)/1000 -> 0.55227598 | AU73: =I73*F73/1000 -> 0.27893119 | AV73: =I73*G73/1000 -> 0.2733448
A74: =Inputs!$A$85 -> BF-BOF steel | B74: =Inputs!$B$85 -> 0 | C74: =Inputs!$C$85 -> 0 | D74: =Inputs!$D$85 -> 0 | E74: =Inputs!$E$85 -> 620 | F74: =Inputs!$J$85 -> 1.4249803 | G74: =Inputs!$K$85 -> 0.05276542 | H74: =Inputs!$Q$85 -> 0.0026960723 | I74: =B74*(1+C74)^($N$70-BaseYr) -> 0 | J74: =$F$70*$B$70*F74 -> 28.499605 | K74: =$G$70*$C$70*G74 -> 1.0553084 | L74: =MIN($D$70,$B$70)*$F$70*F74+MIN($D$70,$C$70)*$G$70*G74 -> 29.554914 | M74: =IF(E74>0,(J74+K74-L74)/E74,0) -> 0 | N74: =I74*(1+M74)^EpsQ3 -> 0 | O74: =N74*F74/1000 -> 0 | P74: =N74*G74/1000 -> 0 | Q74: =O74*($H$70-1) -> 0 | R74: =-P74*(1-EXP(-H74*($G$70*$C$70+$E$70))) -> 0 | S74: =O74+Q74 -> 0 | T74: =P74+R74 -> 0 | U74: =S74+T74 -> 0 | V74: =(O74+P74)*(1-(1+M74)^(-EpsQ3)) -> 0 | W74: =P74*(1-(1+M74)^(-EpsQ3)) -> 0 | X74: =IF(G74>0,1,0) -> 1 | Y74: =S74*$F$70*$B$70 -> 0 | Z74: =(P74*X74+R74)*$G$70*$C$70 -> 0 | AA74: =Y74+Z74 -> 0 | AB74: =L74*N74/1000 -> 0 | AC74: =IF(N74>0,U74*1000/N74,0) -> 0 | AD74: =IF(N74>0,AA74*1000/N74-L74,0) -> 0 | AE74: =MAX(0,$I$70*$J$70*AC74-$K$70*MAX(0,AD74)) -> 0 | AF74: =MAX(0,$L$70*$J$70*AC74-MAX(0,AD74)) -> 0 | AG74: =MAX(0,$M$70*$J$70*AC74-MAX(0,AD74)) -> 0 | AH74: =IF(B74>0,D74*N74/B74*AE74/1000,0) -> 0 | AI74: =D74*(1+C74)^($N$70-BaseYr)*$I$70*$J$70*(F74+G74)/1000 -> 0 | AJ74: =D74*$I$70*$J$70*(F74+G74) -> 0 | AK74: =D74*$L$70*$J$70*(F74+G74) -> 0 | AL74: =D74*$M$70*$J$70*(F74+G74) -> 0 | AM74: =D74*AE74 -> 0 | AN74: =D74*AF74 -> 0 | AO74: =D74*AG74 -> 0 | AP74: =IF(N74>0,D74*U74/N74,0) -> 0 | AQ74: =IF(N74>0,D74*(O74+P74)/N74,0) -> 0 | AR74: =IF(N74>0,D74*AS74/N74,0) -> 0 | AS74: =O74*IF($F$70>0,1,0)+P74*X74*IF($G$70>0,1,0) -> 0 | AT74: =I74*(F74+G74)/1000 -> 0 | AU74: =I74*F74/1000 -> 0 | AV74: =I74*G74/1000 -> 0
A75: =Inputs!$A$86 -> Clinker | B75: =Inputs!$B$86 -> 50000 | C75: =Inputs!$C$86 -> 0.033 | D75: =Inputs!$D$86 -> 800 | E75: =Inputs!$E$86 -> 110 | F75: =Inputs!$J$86 -> 0.3135685 | G75: =Inputs!$K$86 -> 0.53702616 | H75: =Inputs!$Q$86 -> 0.0033464675 | I75: =B75*(1+C75)^($N$70-BaseYr) -> 60753.588 | J75: =$F$70*$B$70*F75 -> 6.27137 | K75: =$G$70*$C$70*G75 -> 10.740523 | L75: =MIN($D$70,$B$70)*$F$70*F75+MIN($D$70,$C$70)*$G$70*G75 -> 17.011893 | M75: =IF(E75>0,(J75+K75-L75)/E75,0) -> 0 | N75: =I75*(1+M75)^EpsQ4 -> 60753.588 | O75: =N75*F75/1000 -> 19.050412 | P75: =N75*G75/1000 -> 32.626266 | Q75: =O75*($H$70-1) -> -0.92750404 | R75: =-P75*(1-EXP(-H75*($G$70*$C$70+$E$70))) -> -2.1121829 | S75: =O75+Q75 -> 18.122907 | T75: =P75+R75 -> 30.514083 | U75: =S75+T75 -> 48.636991 | V75: =(O75+P75)*(1-(1+M75)^(-EpsQ4)) -> 0 | W75: =P75*(1-(1+M75)^(-EpsQ4)) -> 0 | X75: =IF(G75>0,1,0) -> 1 | Y75: =S75*$F$70*$B$70 -> 362.45815 | Z75: =(P75*X75+R75)*$G$70*$C$70 -> 610.28167 | AA75: =Y75+Z75 -> 972.73982 | AB75: =L75*N75/1000 -> 1033.5336 | AC75: =IF(N75>0,U75*1000/N75,0) -> 0.80056162 | AD75: =IF(N75>0,AA75*1000/N75-L75,0) -> -1.0006609 | AE75: =MAX(0,$I$70*$J$70*AC75-$K$70*MAX(0,AD75)) -> 38.827238 | AF75: =MAX(0,$L$70*$J$70*AC75-MAX(0,AD75)) -> 38.827238 | AG75: =MAX(0,$M$70*$J$70*AC75-MAX(0,AD75)) -> 80.056162 | AH75: =IF(B75>0,D75*N75/B75*AE75/1000,0) -> 37.742305 | AI75: =D75*(1+C75)^($N$70-BaseYr)*$I$70*$J$70*(F75+G75)/1000 -> 40.101102 | AJ75: =D75*$I$70*$J$70*(F75+G75) -> 33003.073 | AK75: =D75*$L$70*$J$70*(F75+G75) -> 33003.073 | AL75: =D75*$M$70*$J$70*(F75+G75) -> 68047.573 | AM75: =D75*AE75 -> 31061.791 | AN75: =D75*AF75 -> 31061.791 | AO75: =D75*AG75 -> 64044.929 | AP75: =IF(N75>0,D75*U75/N75,0) -> 0.64044929 | AQ75: =IF(N75>0,D75*(O75+P75)/N75,0) -> 0.68047573 | AR75: =IF(N75>0,D75*AS75/N75,0) -> 0.68047573 | AS75: =O75*IF($F$70>0,1,0)+P75*X75*IF($G$70>0,1,0) -> 51.676678 | AT75: =I75*(F75+G75)/1000 -> 51.676678 | AU75: =I75*F75/1000 -> 19.050412 | AV75: =I75*G75/1000 -> 32.626266
A76: =Inputs!$A$87 -> Ammonia | B76: =Inputs!$B$87 -> 1785 | C76: =Inputs!$C$87 -> 0.022 | D76: =Inputs!$D$87 -> 120 | E76: =Inputs!$E$87 -> 450 | F76: =Inputs!$J$87 -> 1.97472 | G76: =Inputs!$K$87 -> 0 | H76: =Inputs!$Q$87 -> 0.0028931766 | I76: =B76*(1+C76)^($N$70-BaseYr) -> 2033.9656 | J76: =$F$70*$B$70*F76 -> 39.4944 | K76: =$G$70*$C$70*G76 -> 0 | L76: =MIN($D$70,$B$70)*$F$70*F76+MIN($D$70,$C$70)*$G$70*G76 -> 39.4944 | M76: =IF(E76>0,(J76+K76-L76)/E76,0) -> 0 | N76: =I76*(1+M76)^EpsQ5 -> 2033.9656 | O76: =N76*F76/1000 -> 4.0165125 | P76: =N76*G76/1000 -> 0 | Q76: =O76*($H$70-1) -> -0.19555124 | R76: =-P76*(1-EXP(-H76*($G$70*$C$70+$E$70))) -> 0 | S76: =O76+Q76 -> 3.8209612 | T76: =P76+R76 -> 0 | U76: =S76+T76 -> 3.8209612 | V76: =(O76+P76)*(1-(1+M76)^(-EpsQ5)) -> 0 | W76: =P76*(1-(1+M76)^(-EpsQ5)) -> 0 | X76: =IF(G76>0,1,0) -> 0 | Y76: =S76*$F$70*$B$70 -> 76.419225 | Z76: =(P76*X76+R76)*$G$70*$C$70 -> 0 | AA76: =Y76+Z76 -> 76.419225 | AB76: =L76*N76/1000 -> 80.330249 | AC76: =IF(N76>0,U76*1000/N76,0) -> 1.8785772 | AD76: =IF(N76>0,AA76*1000/N76-L76,0) -> -1.9228569 | AE76: =MAX(0,$I$70*$J$70*AC76-$K$70*MAX(0,AD76)) -> 91.110992 | AF76: =MAX(0,$L$70*$J$70*AC76-MAX(0,AD76)) -> 91.110992 | AG76: =MAX(0,$M$70*$J$70*AC76-MAX(0,AD76)) -> 187.85772 | AH76: =IF(B76>0,D76*N76/B76*AE76/1000,0) -> 12.45826 | AI76: =D76*(1+C76)^($N$70-BaseYr)*$I$70*$J$70*(F76+G76)/1000 -> 13.095856 | AJ76: =D76*$I$70*$J$70*(F76+G76) -> 11492.87 | AK76: =D76*$L$70*$J$70*(F76+G76) -> 11492.87 | AL76: =D76*$M$70*$J$70*(F76+G76) -> 23696.64 | AM76: =D76*AE76 -> 10933.319 | AN76: =D76*AF76 -> 10933.319 | AO76: =D76*AG76 -> 22542.926 | AP76: =IF(N76>0,D76*U76/N76,0) -> 0.22542926 | AQ76: =IF(N76>0,D76*(O76+P76)/N76,0) -> 0.2369664 | AR76: =IF(N76>0,D76*AS76/N76,0) -> 0.2369664 | AS76: =O76*IF($F$70>0,1,0)+P76*X76*IF($G$70>0,1,0) -> 4.0165125 | AT76: =I76*(F76+G76)/1000 -> 4.0165125 | AU76: =I76*F76/1000 -> 4.0165125 | AV76: =I76*G76/1000 -> 0
A77: =Inputs!$A$88 -> Urea | B77: =Inputs!$B$88 -> 2800 | C77: =Inputs!$C$88 -> 0.022 | D77: =Inputs!$D$88 -> 1600 | E77: =Inputs!$E$88 -> 380 | F77: =Inputs!$J$88 -> 0.1122 | G77: =Inputs!$K$88 -> 0 | H77: =Inputs!$Q$88 -> 0.0010087869 | I77: =B77*(1+C77)^($N$70-BaseYr) -> 3190.5342 | J77: =$F$70*$B$70*F77 -> 2.244 | K77: =$G$70*$C$70*G77 -> 0 | L77: =MIN($D$70,$B$70)*$F$70*F77+MIN($D$70,$C$70)*$G$70*G77 -> 2.244 | M77: =IF(E77>0,(J77+K77-L77)/E77,0) -> 0 | N77: =I77*(1+M77)^EpsQ6 -> 3190.5342 | O77: =N77*F77/1000 -> 0.35797794 | P77: =N77*G77/1000 -> 0 | Q77: =O77*($H$70-1) -> -0.017428809 | R77: =-P77*(1-EXP(-H77*($G$70*$C$70+$E$70))) -> 0 | S77: =O77+Q77 -> 0.34054913 | T77: =P77+R77 -> 0 | U77: =S77+T77 -> 0.34054913 | V77: =(O77+P77)*(1-(1+M77)^(-EpsQ6)) -> 0 | W77: =P77*(1-(1+M77)^(-EpsQ6)) -> 0 | X77: =IF(G77>0,1,0) -> 0 | Y77: =S77*$F$70*$B$70 -> 6.8109826 | Z77: =(P77*X77+R77)*$G$70*$C$70 -> 0 | AA77: =Y77+Z77 -> 6.8109826 | AB77: =L77*N77/1000 -> 7.1595588 | AC77: =IF(N77>0,U77*1000/N77,0) -> 0.10673734 | AD77: =IF(N77>0,AA77*1000/N77-L77,0) -> -0.10925323 | AE77: =MAX(0,$I$70*$J$70*AC77-$K$70*MAX(0,AD77)) -> 5.1767609 | AF77: =MAX(0,$L$70*$J$70*AC77-MAX(0,AD77)) -> 5.1767609 | AG77: =MAX(0,$M$70*$J$70*AC77-MAX(0,AD77)) -> 10.673734 | AH77: =IF(B77>0,D77*N77/B77*AE77/1000,0) -> 9.4380759 | AI77: =D77*(1+C77)^($N$70-BaseYr)*$I$70*$J$70*(F77+G77)/1000 -> 9.9211029 | AJ77: =D77*$I$70*$J$70*(F77+G77) -> 8706.72 | AK77: =D77*$L$70*$J$70*(F77+G77) -> 8706.72 | AL77: =D77*$M$70*$J$70*(F77+G77) -> 17952 | AM77: =D77*AE77 -> 8282.8175 | AN77: =D77*AF77 -> 8282.8175 | AO77: =D77*AG77 -> 17077.974 | AP77: =IF(N77>0,D77*U77/N77,0) -> 0.17077974 | AQ77: =IF(N77>0,D77*(O77+P77)/N77,0) -> 0.17952 | AR77: =IF(N77>0,D77*AS77/N77,0) -> 0.17952 | AS77: =O77*IF($F$70>0,1,0)+P77*X77*IF($G$70>0,1,0) -> 0.35797794 | AT77: =I77*(F77+G77)/1000 -> 0.35797794 | AU77: =I77*F77/1000 -> 0.35797794 | AV77: =I77*G77/1000 -> 0
A78: =Inputs!$A$89 -> Ammonium nitrate | B78: =Inputs!$B$89 -> 600 | C78: =Inputs!$C$89 -> 0.022 | D78: =Inputs!$D$89 -> 80 | E78: =Inputs!$E$89 -> 320 | F78: =Inputs!$J$89 -> 0.1122 | G78: =Inputs!$K$89 -> 0.9944125 | H78: =Inputs!$Q$89 -> 0.0078858436 | I78: =B78*(1+C78)^($N$70-BaseYr) -> 683.6859 | J78: =$F$70*$B$70*F78 -> 2.244 | K78: =$G$70*$C$70*G78 -> 19.88825 | L78: =MIN($D$70,$B$70)*$F$70*F78+MIN($D$70,$C$70)*$G$70*G78 -> 22.13225 | M78: =IF(E78>0,(J78+K78-L78)/E78,0) -> 0 | N78: =I78*(1+M78)^EpsQ7 -> 683.6859 | O78: =N78*F78/1000 -> 0.076709558 | P78: =N78*G78/1000 -> 0.67986581 | Q78: =O78*($H$70-1) -> -0.0037347448 | R78: =-P78*(1-EXP(-H78*($G$70*$C$70+$E$70))) -> -0.099198157 | S78: =O78+Q78 -> 0.072974814 | T78: =P78+R78 -> 0.58066765 | U78: =S78+T78 -> 0.65364246 | V78: =(O78+P78)*(1-(1+M78)^(-EpsQ7)) -> 0 | W78: =P78*(1-(1+M78)^(-EpsQ7)) -> 0 | X78: =IF(G78>0,1,0) -> 1 | Y78: =S78*$F$70*$B$70 -> 1.4594963 | Z78: =(P78*X78+R78)*$G$70*$C$70 -> 11.613353 | AA78: =Y78+Z78 -> 13.072849 | AB78: =L78*N78/1000 -> 15.131507 | AC78: =IF(N78>0,U78*1000/N78,0) -> 0.95605667 | AD78: =IF(N78>0,AA78*1000/N78-L78,0) -> -3.0111167 | AE78: =MAX(0,$I$70*$J$70*AC78-$K$70*MAX(0,AD78)) -> 46.368748 | AF78: =MAX(0,$L$70*$J$70*AC78-MAX(0,AD78)) -> 46.368748 | AG78: =MAX(0,$M$70*$J$70*AC78-MAX(0,AD78)) -> 95.605667 | AH78: =IF(B78>0,D78*N78/B78*AE78/1000,0) -> 4.2268879 | AI78: =D78*(1+C78)^($N$70-BaseYr)*$I$70*$J$70*(F78+G78)/1000 -> 4.8925207 | AJ78: =D78*$I$70*$J$70*(F78+G78) -> 4293.6565 | AK78: =D78*$L$70*$J$70*(F78+G78) -> 4293.6565 | AL78: =D78*$M$70*$J$70*(F78+G78) -> 8852.9 | AM78: =D78*AE78 -> 3709.4999 | AN78: =D78*AF78 -> 3709.4999 | AO78: =D78*AG78 -> 7648.4533 | AP78: =IF(N78>0,D78*U78/N78,0) -> 0.076484533 | AQ78: =IF(N78>0,D78*(O78+P78)/N78,0) -> 0.088529 | AR78: =IF(N78>0,D78*AS78/N78,0) -> 0.088529 | AS78: =O78*IF($F$70>0,1,0)+P78*X78*IF($G$70>0,1,0) -> 0.75657537 | AT78: =I78*(F78+G78)/1000 -> 0.75657537 | AU78: =I78*F78/1000 -> 0.076709558 | AV78: =I78*G78/1000 -> 0.67986581
A79: =Inputs!$A$90 -> Aluminium | B79: =Inputs!$B$90 -> 300 | C79: =Inputs!$C$90 -> 0.055 | D79: =Inputs!$D$90 -> 167 | E79: =Inputs!$E$90 -> 2400 | F79: =Inputs!$J$90 -> 0.12342 | G79: =Inputs!$K$90 -> 2.397493 | H79: =Inputs!$Q$90 -> 0.0019988245 | I79: =B79*(1+C79)^($N$70-BaseYr) -> 413.65284 | J79: =$F$70*$B$70*F79 -> 2.4684 | K79: =$G$70*$C$70*G79 -> 47.949861 | L79: =MIN($D$70,$B$70)*$F$70*F79+MIN($D$70,$C$70)*$G$70*G79 -> 50.418261 | M79: =IF(E79>0,(J79+K79-L79)/E79,0) -> 0 | N79: =I79*(1+M79)^EpsQ8 -> 413.65284 | O79: =N79*F79/1000 -> 0.051053034 | P79: =N79*G79/1000 -> 0.99172981 | Q79: =O79*($H$70-1) -> -0.0024856101 | R79: =-P79*(1-EXP(-H79*($G$70*$C$70+$E$70))) -> -0.038863881 | S79: =O79+Q79 -> 0.048567424 | T79: =P79+R79 -> 0.95286593 | U79: =S79+T79 -> 1.0014334 | V79: =(O79+P79)*(1-(1+M79)^(-EpsQ8)) -> 0 | W79: =P79*(1-(1+M79)^(-EpsQ8)) -> 0 | X79: =IF(G79>0,1,0) -> 1 | Y79: =S79*$F$70*$B$70 -> 0.97134847 | Z79: =(P79*X79+R79)*$G$70*$C$70 -> 19.057319 | AA79: =Y79+Z79 -> 20.028667 | AB79: =L79*N79/1000 -> 20.855657 | AC79: =IF(N79>0,U79*1000/N79,0) -> 2.4209512 | AD79: =IF(N79>0,AA79*1000/N79-L79,0) -> -1.9992364 | AE79: =MAX(0,$I$70*$J$70*AC79-$K$70*MAX(0,AD79)) -> 117.41613 | AF79: =MAX(0,$L$70*$J$70*AC79-MAX(0,AD79)) -> 117.41613 | AG79: =MAX(0,$M$70*$J$70*AC79-MAX(0,AD79)) -> 242.09512 | AH79: =IF(B79>0,D79*N79/B79*AE79/1000,0) -> 27.037031 | AI79: =D79*(1+C79)^($N$70-BaseYr)*$I$70*$J$70*(F79+G79)/1000 -> 28.153399 | AJ79: =D79*$I$70*$J$70*(F79+G79) -> 20418.135 | AK79: =D79*$L$70*$J$70*(F79+G79) -> 20418.135 | AL79: =D79*$M$70*$J$70*(F79+G79) -> 42099.248 | AM79: =D79*AE79 -> 19608.494 | AN79: =D79*AF79 -> 19608.494 | AO79: =D79*AG79 -> 40429.885 | AP79: =IF(N79>0,D79*U79/N79,0) -> 0.40429885 | AQ79: =IF(N79>0,D79*(O79+P79)/N79,0) -> 0.42099248 | AR79: =IF(N79>0,D79*AS79/N79,0) -> 0.42099248 | AS79: =O79*IF($F$70>0,1,0)+P79*X79*IF($G$70>0,1,0) -> 1.0427828 | AT79: =I79*(F79+G79)/1000 -> 1.0427828 | AU79: =I79*F79/1000 -> 0.051053034 | AV79: =I79*G79/1000 -> 0.99172981
A80: Total | I80: =SUM(I72:I79) -> 79893.956 | N80: =SUM(N72:N79) -> 79893.956 | O80: =SUM(O72:O79) -> 27.602124 | P80: =SUM(P72:P79) -> 34.821485 | Q80: =SUM(Q72:Q79) -> -1.3438598 | R80: =SUM(R72:R79) -> -2.2757201 | S80: =SUM(S72:S79) -> 26.258265 | T80: =SUM(T72:T79) -> 32.545765 | U80: =SUM(U72:U79) -> 58.80403 | ... W80: =SUM(W72:W79) -> 0 | Y80: =SUM(Y72:Y79) -> 525.16529 | Z80: =SUM(Z72:Z79) -> 650.91531 | AA80: =SUM(AA72:AA79) -> 1176.0806 | AB80: =SUM(AB72:AB79) -> 1248.4722 | AH80: =SUM(AH72:AH79) -> 113.58181 | AI80: =SUM(AI72:AI79) -> 120.01558 | AJ80: =SUM(AJ72:AJ79) -> 96335.511 | AK80: =SUM(AK72:AK79) -> 96335.511 | AL80: =SUM(AL72:AL79) -> 198629.92 | AM80: =SUM(AM72:AM79) -> 91111.547 | AN80: =SUM(AN72:AN79) -> 91111.547 | AO80: =SUM(AO72:AO79) -> 187858.86 | ... AV80: =SUM(AV72:AV79) -> 34.821485
A84: Bundle 3C - 3A with net revenue paid into an abatement fund (phi = 1) acting as shadow price sigma (Inputs A).
A85: Bundle | B85: tau: carbon price | C85: tau_p: process price | D85: obrrb: OBR rebate rate | E85: fundsp: fund shadow price | F85: incl_f | G85: incl_p | H85: xf: fuel-intensity factor | I85: CBF (selected conv.) | J85: P_EU | K85: S (selected conv.) | L85: CBF (FULL) | M85: CBF (NOPHASE) | N85: Year | O85: CPAT scenario | P85: b_f | Q85: beta set | R85: Mode
A86: 3C | B86: =INDEX(BT_Tau,MATCH($A$86,BT_Code,0)) -> 20 | C86: =B86*INDEX(BT_Flag,MATCH($A$86,BT_Code,0)) -> 20 | D86: =INDEX(BT_Theta,MATCH($A$86,BT_Code,0))*B86 -> 0 | E86: =INDEX(BT_Phi,MATCH($A$86,BT_Code,0))*SigmaEff -> 20 | F86: 1 | G86: =INDEX(BT_Flag,MATCH($A$86,BT_Code,0)) -> 1 | H86: =IF(Mode="PROTOTYPE",1,EXP(Bf*(F86*B86+E86))) -> 0.90499676 | I86: =CBFsel -> 0.485 | J86: =PEU -> 100 | K86: =Ssel -> 1 | L86: =CBFyr -> 0.485 | M86: 1 | N86: =Yr -> 2030 | O86: =INDEX(BT_Scen,MATCH($A$86,BT_Code,0)) -> EG3 | P86: =Bf -> -0.0024955979 | Q86: =BetaSet -> IPCC_CENTRAL | R86: =Mode -> REBUILD
A87: Product | B87: Q0 (kt) | C87: g | D87: X exports (kt) | E87: P ($/t) | F87: F (tCO2/t) | G87: G (tCO2e/t) | H87: beta | I87: Qb: baseline output | J87: kf: fuel cost $/t | K87: kp: process cost $/t | L87: m: rebate $/t | M87: dp: cost/price | N87: Q: output | O87: Ef: fuel emis. | P87: Ep: process emis. | Q87: ER_f: fuel-int. resp. | R87: ER_p: process-int. resp. | S87: post fuel | T87: post process | U87: post total | V87: emrq_i: output ch. | W87: emrq_proc_i | X87: J_i: process>0 | Y87: revf_i $m | Z87: revp_i $m | AA87: rev_i $m | AB87: rebate_i $m | AC87: EI: tCO2/t | AD87: d: net price paid $/t | AE87: obl (sel.) $/t | AF87: obl (FULL) $/t | AG87: obl (NOPHASE) $/t | AH87: cbobl_i $m | AI87: cbobl0_i $m | AJ87: w_den sel | AK87: w_den FULL | AL87: w_den NOPHASE | AM87: w_num sel | AN87: w_num FULL | AO87: w_num NOPHASE | AP87: X*post/Q | AQ87: X*(Ef+Ep)/Q | AR87: X*covered/Q | AS87: covered_i | AT87: Ebase_i | AU87: Efbase_i | AV87: Epbase_i
A88: =Inputs!$A$83 -> DRI-EAF steel | B88: =Inputs!$B$83 -> 5100 | C88: =Inputs!$C$83 -> 0.044 | D88: =Inputs!$D$83 -> 580 | E88: =Inputs!$E$83 -> 750 | F88: =Inputs!$J$83 -> 0.57099077 | G88: =Inputs!$K$83 -> 0.03790102 | H88: =Inputs!$Q$83 -> 0.0034469507 | I88: =B88*(1+C88)^($N$86-BaseYr) -> 6603.4846 | J88: =$F$86*$B$86*F88 -> 11.419815 | K88: =$G$86*$C$86*G88 -> 0.7580204 | L88: =MIN($D$86,$B$86)*$F$86*F88+MIN($D$86,$C$86)*$G$86*G88 -> 0 | M88: =IF(E88>0,(J88+K88-L88)/E88,0) -> 0.016237114 | N88: =I88*(1+M88)^EpsQ1 -> 6561.0772 | O88: =N88*F88/1000 -> 3.7463145 | P88: =N88*G88/1000 -> 0.24867152 | Q88: =O88*($H$86-1) -> -0.35591202 | R88: =-P88*(1-EXP(-H88*($G$86*$C$86+$E$86))) -> -0.032027661 | S88: =O88+Q88 -> 3.3904025 | T88: =P88+R88 -> 0.21664386 | U88: =S88+T88 -> 3.6070464 | V88: =(O88+P88)*(1-(1+M88)^(-EpsQ1)) -> -0.025821511 | W88: =P88*(1-(1+M88)^(-EpsQ1)) -> -0.0016072833 | X88: =IF(G88>0,1,0) -> 1 | Y88: =S88*$F$86*$B$86 -> 67.80805 | Z88: =(P88*X88+R88)*$G$86*$C$86 -> 4.3328771 | AA88: =Y88+Z88 -> 72.140927 | AB88: =L88*N88/1000 -> 0 | AC88: =IF(N88>0,U88*1000/N88,0) -> 0.54976435 | AD88: =IF(N88>0,AA88*1000/N88-L88,0) -> 10.995287 | AE88: =MAX(0,$I$86*$J$86*AC88-$K$86*MAX(0,AD88)) -> 15.668284 | AF88: =MAX(0,$L$86*$J$86*AC88-MAX(0,AD88)) -> 15.668284 | AG88: =MAX(0,$M$86*$J$86*AC88-MAX(0,AD88)) -> 43.981148 | AH88: =IF(B88>0,D88*N88/B88*AE88/1000,0) -> 11.691074 | AI88: =D88*(1+C88)^($N$86-BaseYr)*$I$86*$J$86*(F88+G88)/1000 -> 22.177513 | AJ88: =D88*$I$86*$J$86*(F88+G88) -> 17128.126 | AK88: =D88*$L$86*$J$86*(F88+G88) -> 17128.126 | AL88: =D88*$M$86*$J$86*(F88+G88) -> 35315.724 | AM88: =D88*AE88 -> 9087.6047 | AN88: =D88*AF88 -> 9087.6047 | AO88: =D88*AG88 -> 25509.066 | AP88: =IF(N88>0,D88*U88/N88,0) -> 0.31886332 | AQ88: =IF(N88>0,D88*(O88+P88)/N88,0) -> 0.35315724 | AR88: =IF(N88>0,D88*AS88/N88,0) -> 0.35315724 | AS88: =O88*IF($F$86>0,1,0)+P88*X88*IF($G$86>0,1,0) -> 3.994986 | AT88: =I88*(F88+G88)/1000 -> 4.0208075 | AU88: =I88*F88/1000 -> 3.7705287 | AV88: =I88*G88/1000 -> 0.2502788
A89: =Inputs!$A$84 -> Scrap-EAF steel | B89: =Inputs!$B$84 -> 4800 | C89: =Inputs!$C$84 -> 0.044 | D89: =Inputs!$D$84 -> 300 | E89: =Inputs!$E$84 -> 680 | F89: =Inputs!$J$84 -> 0.04488 | G89: =Inputs!$K$84 -> 0.04398115 | H89: =Inputs!$Q$84 -> 0.0016366491 | I89: =B89*(1+C89)^($N$86-BaseYr) -> 6215.0443 | J89: =$F$86*$B$86*F89 -> 0.8976 | K89: =$G$86*$C$86*G89 -> 0.879623 | L89: =MIN($D$86,$B$86)*$F$86*F89+MIN($D$86,$C$86)*$G$86*G89 -> 0 | M89: =IF(E89>0,(J89+K89-L89)/E89,0) -> 0.0026135632 | N89: =I89*(1+M89)^EpsQ2 -> 6208.5588 | O89: =N89*F89/1000 -> 0.27864012 | P89: =N89*G89/1000 -> 0.27305956 | Q89: =O89*($H$86-1) -> -0.026471715 | R89: =-P89*(1-EXP(-H89*($G$86*$C$86+$E$86))) -> -0.017303532 | S89: =O89+Q89 -> 0.2521684 | T89: =P89+R89 -> 0.25575602 | U89: =S89+T89 -> 0.50792443 | V89: =(O89+P89)*(1-(1+M89)^(-EpsQ2)) -> -0.0005763092 | W89: =P89*(1-(1+M89)^(-EpsQ2)) -> -0.00028523986 | X89: =IF(G89>0,1,0) -> 1 | Y89: =S89*$F$86*$B$86 -> 5.0433681 | Z89: =(P89*X89+R89)*$G$86*$C$86 -> 5.1151205 | AA89: =Y89+Z89 -> 10.158489 | AB89: =L89*N89/1000 -> 0 | AC89: =IF(N89>0,U89*1000/N89,0) -> 0.08181036 | AD89: =IF(N89>0,AA89*1000/N89-L89,0) -> 1.6362072 | AE89: =MAX(0,$I$86*$J$86*AC89-$K$86*MAX(0,AD89)) -> 2.3315953 | AF89: =MAX(0,$L$86*$J$86*AC89-MAX(0,AD89)) -> 2.3315953 | AG89: =MAX(0,$M$86*$J$86*AC89-MAX(0,AD89)) -> 6.5448288 | AH89: =IF(B89>0,D89*N89/B89*AE89/1000,0) -> 0.90474039 | AI89: =D89*(1+C89)^($N$86-BaseYr)*$I$86*$J$86*(F89+G89)/1000 -> 1.6740866 | AJ89: =D89*$I$86*$J$86*(F89+G89) -> 1292.9297 | AK89: =D89*$L$86*$J$86*(F89+G89) -> 1292.9297 | AL89: =D89*$M$86*$J$86*(F89+G89) -> 2665.8345 | AM89: =D89*AE89 -> 699.47858 | AN89: =D89*AF89 -> 699.47858 | AO89: =D89*AG89 -> 1963.4486 | AP89: =IF(N89>0,D89*U89/N89,0) -> 0.024543108 | AQ89: =IF(N89>0,D89*(O89+P89)/N89,0) -> 0.026658345 | AR89: =IF(N89>0,D89*AS89/N89,0) -> 0.026658345 | AS89: =O89*IF($F$86>0,1,0)+P89*X89*IF($G$86>0,1,0) -> 0.55169968 | AT89: =I89*(F89+G89)/1000 -> 0.55227598 | AU89: =I89*F89/1000 -> 0.27893119 | AV89: =I89*G89/1000 -> 0.2733448
A90: =Inputs!$A$85 -> BF-BOF steel | B90: =Inputs!$B$85 -> 0 | C90: =Inputs!$C$85 -> 0 | D90: =Inputs!$D$85 -> 0 | E90: =Inputs!$E$85 -> 620 | F90: =Inputs!$J$85 -> 1.4249803 | G90: =Inputs!$K$85 -> 0.05276542 | H90: =Inputs!$Q$85 -> 0.0026960723 | I90: =B90*(1+C90)^($N$86-BaseYr) -> 0 | J90: =$F$86*$B$86*F90 -> 28.499605 | K90: =$G$86*$C$86*G90 -> 1.0553084 | L90: =MIN($D$86,$B$86)*$F$86*F90+MIN($D$86,$C$86)*$G$86*G90 -> 0 | M90: =IF(E90>0,(J90+K90-L90)/E90,0) -> 0.047669216 | N90: =I90*(1+M90)^EpsQ3 -> 0 | O90: =N90*F90/1000 -> 0 | P90: =N90*G90/1000 -> 0 | Q90: =O90*($H$86-1) -> 0 | R90: =-P90*(1-EXP(-H90*($G$86*$C$86+$E$86))) -> 0 | S90: =O90+Q90 -> 0 | T90: =P90+R90 -> 0 | U90: =S90+T90 -> 0 | V90: =(O90+P90)*(1-(1+M90)^(-EpsQ3)) -> 0 | W90: =P90*(1-(1+M90)^(-EpsQ3)) -> 0 | X90: =IF(G90>0,1,0) -> 1 | Y90: =S90*$F$86*$B$86 -> 0 | Z90: =(P90*X90+R90)*$G$86*$C$86 -> 0 | AA90: =Y90+Z90 -> 0 | AB90: =L90*N90/1000 -> 0 | AC90: =IF(N90>0,U90*1000/N90,0) -> 0 | AD90: =IF(N90>0,AA90*1000/N90-L90,0) -> 0 | AE90: =MAX(0,$I$86*$J$86*AC90-$K$86*MAX(0,AD90)) -> 0 | AF90: =MAX(0,$L$86*$J$86*AC90-MAX(0,AD90)) -> 0 | AG90: =MAX(0,$M$86*$J$86*AC90-MAX(0,AD90)) -> 0 | AH90: =IF(B90>0,D90*N90/B90*AE90/1000,0) -> 0 | AI90: =D90*(1+C90)^($N$86-BaseYr)*$I$86*$J$86*(F90+G90)/1000 -> 0 | AJ90: =D90*$I$86*$J$86*(F90+G90) -> 0 | AK90: =D90*$L$86*$J$86*(F90+G90) -> 0 | AL90: =D90*$M$86*$J$86*(F90+G90) -> 0 | AM90: =D90*AE90 -> 0 | AN90: =D90*AF90 -> 0 | AO90: =D90*AG90 -> 0 | AP90: =IF(N90>0,D90*U90/N90,0) -> 0 | AQ90: =IF(N90>0,D90*(O90+P90)/N90,0) -> 0 | AR90: =IF(N90>0,D90*AS90/N90,0) -> 0 | AS90: =O90*IF($F$86>0,1,0)+P90*X90*IF($G$86>0,1,0) -> 0 | AT90: =I90*(F90+G90)/1000 -> 0 | AU90: =I90*F90/1000 -> 0 | AV90: =I90*G90/1000 -> 0
A91: =Inputs!$A$86 -> Clinker | B91: =Inputs!$B$86 -> 50000 | C91: =Inputs!$C$86 -> 0.033 | D91: =Inputs!$D$86 -> 800 | E91: =Inputs!$E$86 -> 110 | F91: =Inputs!$J$86 -> 0.3135685 | G91: =Inputs!$K$86 -> 0.53702616 | H91: =Inputs!$Q$86 -> 0.0033464675 | I91: =B91*(1+C91)^($N$86-BaseYr) -> 60753.588 | J91: =$F$86*$B$86*F91 -> 6.27137 | K91: =$G$86*$C$86*G91 -> 10.740523 | L91: =MIN($D$86,$B$86)*$F$86*F91+MIN($D$86,$C$86)*$G$86*G91 -> 0 | M91: =IF(E91>0,(J91+K91-L91)/E91,0) -> 0.15465357 | N91: =I91*(1+M91)^EpsQ4 -> 59886.201 | O91: =N91*F91/1000 -> 18.778426 | P91: =N91*G91/1000 -> 32.160457 | Q91: =O91*($H$86-1) -> -1.7840114 | R91: =-P91*(1-EXP(-H91*($G$86*$C$86+$E$86))) -> -4.0292661 | S91: =O91+Q91 -> 16.994415 | T91: =P91+R91 -> 28.13119 | U91: =S91+T91 -> 45.125605 | V91: =(O91+P91)*(1-(1+M91)^(-EpsQ4)) -> -0.73779503 | W91: =P91*(1-(1+M91)^(-EpsQ4)) -> -0.46580969 | X91: =IF(G91>0,1,0) -> 1 | Y91: =S91*$F$86*$B$86 -> 339.8883 | Z91: =(P91*X91+R91)*$G$86*$C$86 -> 562.62381 | AA91: =Y91+Z91 -> 902.5121 | AB91: =L91*N91/1000 -> 0 | AC91: =IF(N91>0,U91*1000/N91,0) -> 0.75352259 | AD91: =IF(N91>0,AA91*1000/N91-L91,0) -> 15.070452 | AE91: =MAX(0,$I$86*$J$86*AC91-$K$86*MAX(0,AD91)) -> 21.475394 | AF91: =MAX(0,$L$86*$J$86*AC91-MAX(0,AD91)) -> 21.475394 | AG91: =MAX(0,$M$86*$J$86*AC91-MAX(0,AD91)) -> 60.281807 | AH91: =IF(B91>0,D91*N91/B91*AE91/1000,0) -> 20.577276 | AI91: =D91*(1+C91)^($N$86-BaseYr)*$I$86*$J$86*(F91+G91)/1000 -> 40.101102 | AJ91: =D91*$I$86*$J$86*(F91+G91) -> 33003.073 | AK91: =D91*$L$86*$J$86*(F91+G91) -> 33003.073 | AL91: =D91*$M$86*$J$86*(F91+G91) -> 68047.573 | AM91: =D91*AE91 -> 17180.315 | AN91: =D91*AF91 -> 17180.315 | AO91: =D91*AG91 -> 48225.446 | AP91: =IF(N91>0,D91*U91/N91,0) -> 0.60281807 | AQ91: =IF(N91>0,D91*(O91+P91)/N91,0) -> 0.68047573 | AR91: =IF(N91>0,D91*AS91/N91,0) -> 0.68047573 | AS91: =O91*IF($F$86>0,1,0)+P91*X91*IF($G$86>0,1,0) -> 50.938883 | AT91: =I91*(F91+G91)/1000 -> 51.676678 | AU91: =I91*F91/1000 -> 19.050412 | AV91: =I91*G91/1000 -> 32.626266
A92: =Inputs!$A$87 -> Ammonia | B92: =Inputs!$B$87 -> 1785 | C92: =Inputs!$C$87 -> 0.022 | D92: =Inputs!$D$87 -> 120 | E92: =Inputs!$E$87 -> 450 | F92: =Inputs!$J$87 -> 1.97472 | G92: =Inputs!$K$87 -> 0 | H92: =Inputs!$Q$87 -> 0.0028931766 | I92: =B92*(1+C92)^($N$86-BaseYr) -> 2033.9656 | J92: =$F$86*$B$86*F92 -> 39.4944 | K92: =$G$86*$C$86*G92 -> 0 | L92: =MIN($D$86,$B$86)*$F$86*F92+MIN($D$86,$C$86)*$G$86*G92 -> 0 | M92: =IF(E92>0,(J92+K92-L92)/E92,0) -> 0.087765333 | N92: =I92*(1+M92)^EpsQ5 -> 1966.661 | O92: =N92*F92/1000 -> 3.8836048 | P92: =N92*G92/1000 -> 0 | Q92: =O92*($H$86-1) -> -0.36895505 | R92: =-P92*(1-EXP(-H92*($G$86*$C$86+$E$86))) -> 0 | S92: =O92+Q92 -> 3.5146498 | T92: =P92+R92 -> 0 | U92: =S92+T92 -> 3.5146498 | V92: =(O92+P92)*(1-(1+M92)^(-EpsQ5)) -> -0.13290763 | W92: =P92*(1-(1+M92)^(-EpsQ5)) -> 0 | X92: =IF(G92>0,1,0) -> 0 | Y92: =S92*$F$86*$B$86 -> 70.292996 | Z92: =(P92*X92+R92)*$G$86*$C$86 -> 0 | AA92: =Y92+Z92 -> 70.292996 | AB92: =L92*N92/1000 -> 0 | AC92: =IF(N92>0,U92*1000/N92,0) -> 1.7871152 | AD92: =IF(N92>0,AA92*1000/N92-L92,0) -> 35.742304 | AE92: =MAX(0,$I$86*$J$86*AC92-$K$86*MAX(0,AD92)) -> 50.932783 | AF92: =MAX(0,$L$86*$J$86*AC92-MAX(0,AD92)) -> 50.932783 | AG92: =MAX(0,$M$86*$J$86*AC92-MAX(0,AD92)) -> 142.96922 | AH92: =IF(B92>0,D92*N92/B92*AE92/1000,0) -> 6.7339509 | AI92: =D92*(1+C92)^($N$86-BaseYr)*$I$86*$J$86*(F92+G92)/1000 -> 13.095856 | AJ92: =D92*$I$86*$J$86*(F92+G92) -> 11492.87 | AK92: =D92*$L$86*$J$86*(F92+G92) -> 11492.87 | AL92: =D92*$M$86*$J$86*(F92+G92) -> 23696.64 | AM92: =D92*AE92 -> 6111.934 | AN92: =D92*AF92 -> 6111.934 | AO92: =D92*AG92 -> 17156.306 | AP92: =IF(N92>0,D92*U92/N92,0) -> 0.21445382 | AQ92: =IF(N92>0,D92*(O92+P92)/N92,0) -> 0.2369664 | AR92: =IF(N92>0,D92*AS92/N92,0) -> 0.2369664 | AS92: =O92*IF($F$86>0,1,0)+P92*X92*IF($G$86>0,1,0) -> 3.8836048 | AT92: =I92*(F92+G92)/1000 -> 4.0165125 | AU92: =I92*F92/1000 -> 4.0165125 | AV92: =I92*G92/1000 -> 0
A93: =Inputs!$A$88 -> Urea | B93: =Inputs!$B$88 -> 2800 | C93: =Inputs!$C$88 -> 0.022 | D93: =Inputs!$D$88 -> 1600 | E93: =Inputs!$E$88 -> 380 | F93: =Inputs!$J$88 -> 0.1122 | G93: =Inputs!$K$88 -> 0 | H93: =Inputs!$Q$88 -> 0.0010087869 | I93: =B93*(1+C93)^($N$86-BaseYr) -> 3190.5342 | J93: =$F$86*$B$86*F93 -> 2.244 | K93: =$G$86*$C$86*G93 -> 0 | L93: =MIN($D$86,$B$86)*$F$86*F93+MIN($D$86,$C$86)*$G$86*G93 -> 0 | M93: =IF(E93>0,(J93+K93-L93)/E93,0) -> 0.0059052632 | N93: =I93*(1+M93)^EpsQ6 -> 3183.0288 | O93: =N93*F93/1000 -> 0.35713584 | P93: =N93*G93/1000 -> 0 | Q93: =O93*($H$86-1) -> -0.033929062 | R93: =-P93*(1-EXP(-H93*($G$86*$C$86+$E$86))) -> 0 | S93: =O93+Q93 -> 0.32320677 | T93: =P93+R93 -> 0 | U93: =S93+T93 -> 0.32320677 | V93: =(O93+P93)*(1-(1+M93)^(-EpsQ6)) -> -0.00084210264 | W93: =P93*(1-(1+M93)^(-EpsQ6)) -> 0 | X93: =IF(G93>0,1,0) -> 0 | Y93: =S93*$F$86*$B$86 -> 6.4641355 | Z93: =(P93*X93+R93)*$G$86*$C$86 -> 0 | AA93: =Y93+Z93 -> 6.4641355 | AB93: =L93*N93/1000 -> 0 | AC93: =IF(N93>0,U93*1000/N93,0) -> 0.10154064 | AD93: =IF(N93>0,AA93*1000/N93-L93,0) -> 2.0308127 | AE93: =MAX(0,$I$86*$J$86*AC93-$K$86*MAX(0,AD93)) -> 2.8939081 | AF93: =MAX(0,$L$86*$J$86*AC93-MAX(0,AD93)) -> 2.8939081 | AG93: =MAX(0,$M$86*$J$86*AC93-MAX(0,AD93)) -> 8.1232509 | AH93: =IF(B93>0,D93*N93/B93*AE93/1000,0) -> 5.2636532 | AI93: =D93*(1+C93)^($N$86-BaseYr)*$I$86*$J$86*(F93+G93)/1000 -> 9.9211029 | AJ93: =D93*$I$86*$J$86*(F93+G93) -> 8706.72 | AK93: =D93*$L$86*$J$86*(F93+G93) -> 8706.72 | AL93: =D93*$M$86*$J$86*(F93+G93) -> 17952 | AM93: =D93*AE93 -> 4630.253 | AN93: =D93*AF93 -> 4630.253 | AO93: =D93*AG93 -> 12997.201 | AP93: =IF(N93>0,D93*U93/N93,0) -> 0.16246502 | AQ93: =IF(N93>0,D93*(O93+P93)/N93,0) -> 0.17952 | AR93: =IF(N93>0,D93*AS93/N93,0) -> 0.17952 | AS93: =O93*IF($F$86>0,1,0)+P93*X93*IF($G$86>0,1,0) -> 0.35713584 | AT93: =I93*(F93+G93)/1000 -> 0.35797794 | AU93: =I93*F93/1000 -> 0.35797794 | AV93: =I93*G93/1000 -> 0
A94: =Inputs!$A$89 -> Ammonium nitrate | B94: =Inputs!$B$89 -> 600 | C94: =Inputs!$C$89 -> 0.022 | D94: =Inputs!$D$89 -> 80 | E94: =Inputs!$E$89 -> 320 | F94: =Inputs!$J$89 -> 0.1122 | G94: =Inputs!$K$89 -> 0.9944125 | H94: =Inputs!$Q$89 -> 0.0078858436 | I94: =B94*(1+C94)^($N$86-BaseYr) -> 683.6859 | J94: =$F$86*$B$86*F94 -> 2.244 | K94: =$G$86*$C$86*G94 -> 19.88825 | L94: =MIN($D$86,$B$86)*$F$86*F94+MIN($D$86,$C$86)*$G$86*G94 -> 0 | M94: =IF(E94>0,(J94+K94-L94)/E94,0) -> 0.069163281 | N94: =I94*(1+M94)^EpsQ7 -> 665.63939 | O94: =N94*F94/1000 -> 0.074684739 | P94: =N94*G94/1000 -> 0.66192013 | Q94: =O94*($H$86-1) -> -0.0070952923 | R94: =-P94*(1-EXP(-H94*($G$86*$C$86+$E$86))) -> -0.17906766 | S94: =O94+Q94 -> 0.067589447 | T94: =P94+R94 -> 0.48285246 | U94: =S94+T94 -> 0.55044191 | V94: =(O94+P94)*(1-(1+M94)^(-EpsQ7)) -> -0.019970502 | W94: =P94*(1-(1+M94)^(-EpsQ7)) -> -0.017945682 | X94: =IF(G94>0,1,0) -> 1 | Y94: =S94*$F$86*$B$86 -> 1.3517889 | Z94: =(P94*X94+R94)*$G$86*$C$86 -> 9.6570493 | AA94: =Y94+Z94 -> 11.008838 | AB94: =L94*N94/1000 -> 0 | AC94: =IF(N94>0,U94*1000/N94,0) -> 0.82693711 | AD94: =IF(N94>0,AA94*1000/N94-L94,0) -> 16.538742 | AE94: =MAX(0,$I$86*$J$86*AC94-$K$86*MAX(0,AD94)) -> 23.567708 | AF94: =MAX(0,$L$86*$J$86*AC94-MAX(0,AD94)) -> 23.567708 | AG94: =MAX(0,$M$86*$J$86*AC94-MAX(0,AD94)) -> 66.154969 | AH94: =IF(B94>0,D94*N94/B94*AE94/1000,0) -> 2.0916793 | AI94: =D94*(1+C94)^($N$86-BaseYr)*$I$86*$J$86*(F94+G94)/1000 -> 4.8925207 | AJ94: =D94*$I$86*$J$86*(F94+G94) -> 4293.6565 | AK94: =D94*$L$86*$J$86*(F94+G94) -> 4293.6565 | AL94: =D94*$M$86*$J$86*(F94+G94) -> 8852.9 | AM94: =D94*AE94 -> 1885.4166 | AN94: =D94*AF94 -> 1885.4166 | AO94: =D94*AG94 -> 5292.3975 | AP94: =IF(N94>0,D94*U94/N94,0) -> 0.066154969 | AQ94: =IF(N94>0,D94*(O94+P94)/N94,0) -> 0.088529 | AR94: =IF(N94>0,D94*AS94/N94,0) -> 0.088529 | AS94: =O94*IF($F$86>0,1,0)+P94*X94*IF($G$86>0,1,0) -> 0.73660486 | AT94: =I94*(F94+G94)/1000 -> 0.75657537 | AU94: =I94*F94/1000 -> 0.076709558 | AV94: =I94*G94/1000 -> 0.67986581
A95: =Inputs!$A$90 -> Aluminium | B95: =Inputs!$B$90 -> 300 | C95: =Inputs!$C$90 -> 0.055 | D95: =Inputs!$D$90 -> 167 | E95: =Inputs!$E$90 -> 2400 | F95: =Inputs!$J$90 -> 0.12342 | G95: =Inputs!$K$90 -> 2.397493 | H95: =Inputs!$Q$90 -> 0.0019988245 | I95: =B95*(1+C95)^($N$86-BaseYr) -> 413.65284 | J95: =$F$86*$B$86*F95 -> 2.4684 | K95: =$G$86*$C$86*G95 -> 47.949861 | L95: =MIN($D$86,$B$86)*$F$86*F95+MIN($D$86,$C$86)*$G$86*G95 -> 0 | M95: =IF(E95>0,(J95+K95-L95)/E95,0) -> 0.021007609 | N95: =I95*(1+M95)^EpsQ8 -> 409.37519 | O95: =N95*F95/1000 -> 0.050525086 | P95: =N95*G95/1000 -> 0.98147418 | Q95: =O95*($H$86-1) -> -0.004800047 | R95: =-P95*(1-EXP(-H95*($G$86*$C$86+$E$86))) -> -0.07541672 | S95: =O95+Q95 -> 0.045725039 | T95: =P95+R95 -> 0.90605746 | U95: =S95+T95 -> 0.9517825 | V95: =(O95+P95)*(1-(1+M95)^(-EpsQ8)) -> -0.010783578 | W95: =P95*(1-(1+M95)^(-EpsQ8)) -> -0.010255631 | X95: =IF(G95>0,1,0) -> 1 | Y95: =S95*$F$86*$B$86 -> 0.91450079 | Z95: =(P95*X95+R95)*$G$86*$C$86 -> 18.121149 | AA95: =Y95+Z95 -> 19.03565 | AB95: =L95*N95/1000 -> 0 | AC95: =IF(N95>0,U95*1000/N95,0) -> 2.3249638 | AD95: =IF(N95>0,AA95*1000/N95-L95,0) -> 46.499276 | AE95: =MAX(0,$I$86*$J$86*AC95-$K$86*MAX(0,AD95)) -> 66.261468 | AF95: =MAX(0,$L$86*$J$86*AC95-MAX(0,AD95)) -> 66.261468 | AG95: =MAX(0,$M$86*$J$86*AC95-MAX(0,AD95)) -> 185.9971 | AH95: =IF(B95>0,D95*N95/B95*AE95/1000,0) -> 15.100029 | AI95: =D95*(1+C95)^($N$86-BaseYr)*$I$86*$J$86*(F95+G95)/1000 -> 28.153399 | AJ95: =D95*$I$86*$J$86*(F95+G95) -> 20418.135 | AK95: =D95*$L$86*$J$86*(F95+G95) -> 20418.135 | AL95: =D95*$M$86*$J$86*(F95+G95) -> 42099.248 | AM95: =D95*AE95 -> 11065.665 | AN95: =D95*AF95 -> 11065.665 | AO95: =D95*AG95 -> 31061.516 | AP95: =IF(N95>0,D95*U95/N95,0) -> 0.38826895 | AQ95: =IF(N95>0,D95*(O95+P95)/N95,0) -> 0.42099248 | AR95: =IF(N95>0,D95*AS95/N95,0) -> 0.42099248 | AS95: =O95*IF($F$86>0,1,0)+P95*X95*IF($G$86>0,1,0) -> 1.0319993 | AT95: =I95*(F95+G95)/1000 -> 1.0427828 | AU95: =I95*F95/1000 -> 0.051053034 | AV95: =I95*G95/1000 -> 0.99172981
A96: Total | I96: =SUM(I88:I95) -> 79893.956 | N96: =SUM(N88:N95) -> 78880.541 | O96: =SUM(O88:O95) -> 27.169331 | P96: =SUM(P88:P95) -> 34.325582 | Q96: =SUM(Q88:Q95) -> -2.5811746 | R96: =SUM(R88:R95) -> -4.3330817 | S96: =SUM(S88:S95) -> 24.588157 | T96: =SUM(T88:T95) -> 29.9925 | U96: =SUM(U88:U95) -> 54.580657 | ... W96: =SUM(W88:W95) -> -0.49590352 | Y96: =SUM(Y88:Y95) -> 491.76314 | Z96: =SUM(Z88:Z95) -> 599.85 | AA96: =SUM(AA88:AA95) -> 1091.6131 | AB96: =SUM(AB88:AB95) -> 0 | AH96: =SUM(AH88:AH95) -> 62.362403 | AI96: =SUM(AI88:AI95) -> 120.01558 | AJ96: =SUM(AJ88:AJ95) -> 96335.511 | AK96: =SUM(AK88:AK95) -> 96335.511 | AL96: =SUM(AL88:AL95) -> 198629.92 | AM96: =SUM(AM88:AM95) -> 50660.667 | AN96: =SUM(AN88:AN95) -> 50660.667 | AO96: =SUM(AO88:AO95) -> 142205.38 | ... AV96: =SUM(AV88:AV95) -> 34.821485

Sheet Results
A1: Results - engine: block totals, block metrics, CPAT national quantities and metric composition
A2: Columns C..H = bundles. Keys (column B) are referenced by PolicyMatrix, Comparison and Checks via INDEX/MATCH. Block quantities come from CBAM_Products; national quantities from Inputs section C (CPAT). Mode / convention indicator: see row 3.
A3: ="Mode = "&Mode&" | CBAM convention = "&Conv&" | reporting year = "&Yr&" | beta set = "&BetaSet&" | sigma = "&SigmaEff&" $/t" -> Mode = REBUILD | CBAM convention = FULL | reporting year = 2030 | beta set = IPCC_CENTRAL | sigma = 20 $/t
A4: Metric | B4: Key | C4: 1A | D4: 2A | E4: 2B | F4: 3A | G4: 3B | H4: 3C | I4: Unit | J4: Definition / formula
A5: 1. Bundle settings
A6: CPAT scenario used | B6: scen | C6: =INDEX(BT_Scen,MATCH(C$4,BT_Code,0)) -> EG1 | D6: =INDEX(BT_Scen,MATCH(D$4,BT_Code,0)) -> EG1 | E6: =INDEX(BT_Scen,MATCH(E$4,BT_Code,0)) -> EG2 | F6: =INDEX(BT_Scen,MATCH(F$4,BT_Code,0)) -> EG3 | G6: =INDEX(BT_Scen,MATCH(G$4,BT_Code,0)) -> EG3 | H6: =INDEX(BT_Scen,MATCH(H$4,BT_Code,0)) -> EG3 | I6: - | J6: Inputs section D.
A7: Scope of the fuel levy | B7: scope | C7: =INDEX(BT_Scope,MATCH(C$4,BT_Code,0)) -> ALL | D7: =INDEX(BT_Scope,MATCH(D$4,BT_Code,0)) -> ALL | E7: =INDEX(BT_Scope,MATCH(E$4,BT_Code,0)) -> ALL | F7: =INDEX(BT_Scope,MATCH(F$4,BT_Code,0)) -> IND | G7: =INDEX(BT_Scope,MATCH(G$4,BT_Code,0)) -> IND | H7: =INDEX(BT_Scope,MATCH(H$4,BT_Code,0)) -> IND | I7: - | J7: ALL = economy-wide, IND = industry only.
A8: Process emissions priced (1/0) | B8: flag | C8: =INDEX(BT_Flag,MATCH(C$4,BT_Code,0)) -> 1 | D8: =INDEX(BT_Flag,MATCH(D$4,BT_Code,0)) -> 0 | E8: =INDEX(BT_Flag,MATCH(E$4,BT_Code,0)) -> 0 | F8: =INDEX(BT_Flag,MATCH(F$4,BT_Code,0)) -> 1 | G8: =INDEX(BT_Flag,MATCH(G$4,BT_Code,0)) -> 1 | H8: =INDEX(BT_Flag,MATCH(H$4,BT_Code,0)) -> 1 | I8: - | J8: Inputs section D.
A9: theta: OBR rebate share | B9: theta | C9: =INDEX(BT_Theta,MATCH(C$4,BT_Code,0)) -> 0 | D9: =INDEX(BT_Theta,MATCH(D$4,BT_Code,0)) -> 0 | E9: =INDEX(BT_Theta,MATCH(E$4,BT_Code,0)) -> 0 | F9: =INDEX(BT_Theta,MATCH(F$4,BT_Code,0)) -> 0 | G9: =INDEX(BT_Theta,MATCH(G$4,BT_Code,0)) -> 1 | H9: =INDEX(BT_Theta,MATCH(H$4,BT_Code,0)) -> 0 | I9: - | J9: 1 = output-based rebate at the firm's baseline intensity (3B).
A10: phi: fund share of net revenue | B10: phi | C10: =INDEX(BT_Phi,MATCH(C$4,BT_Code,0)) -> 0 | D10: =INDEX(BT_Phi,MATCH(D$4,BT_Code,0)) -> 0 | E10: =INDEX(BT_Phi,MATCH(E$4,BT_Code,0)) -> 0 | F10: =INDEX(BT_Phi,MATCH(F$4,BT_Code,0)) -> 0 | G10: =INDEX(BT_Phi,MATCH(G$4,BT_Code,0)) -> 0 | H10: =INDEX(BT_Phi,MATCH(H$4,BT_Code,0)) -> 1 | I10: - | J10: 1 = all net revenue to the abatement fund (3C).
A11: tau: carbon price in the reporting year | B11: tau | C11: =CBAM_Products!$B$6 -> 20 | D11: =CBAM_Products!$B$22 -> 20 | E11: =CBAM_Products!$B$38 -> 20 | F11: =CBAM_Products!$B$54 -> 20 | G11: =CBAM_Products!$B$70 -> 20 | H11: =CBAM_Products!$B$86 -> 20 | I11: $/tCO2 | J11: CPAT cptraj.2 of the scenario (block scalar B).
A12: tau_p: price on process emissions | B12: taup | C12: =CBAM_Products!$C$6 -> 20 | D12: =CBAM_Products!$C$22 -> 0 | E12: =CBAM_Products!$C$38 -> 0 | F12: =CBAM_Products!$C$54 -> 20 | G12: =CBAM_Products!$C$70 -> 20 | H12: =CBAM_Products!$C$86 -> 20 | I12: $/tCO2 | J12: tau x process flag.
A13: OBR rebate rate | B13: obrrb | C13: =CBAM_Products!$D$6 -> 0 | D13: =CBAM_Products!$D$22 -> 0 | E13: =CBAM_Products!$D$38 -> 0 | F13: =CBAM_Products!$D$54 -> 0 | G13: =CBAM_Products!$D$70 -> 20 | H13: =CBAM_Products!$D$86 -> 0 | I13: $/tCO2 | J13: theta x tau.
A14: Fund shadow price applied in the block | B14: fundsp | C14: =CBAM_Products!$E$6 -> 0 | D14: =CBAM_Products!$E$22 -> 0 | E14: =CBAM_Products!$E$38 -> 0 | F14: =CBAM_Products!$E$54 -> 0 | G14: =CBAM_Products!$E$70 -> 0 | H14: =CBAM_Products!$E$86 -> 20 | I14: $/tCO2 | J14: phi x sigma (0 in PROTOTYPE mode).
A15: xf: fuel-intensity factor | B15: xf | C15: =CBAM_Products!$H$6 -> 0.95131318 | D15: =CBAM_Products!$H$22 -> 0.95131318 | E15: =CBAM_Products!$H$38 -> 0.95131318 | F15: =CBAM_Products!$H$54 -> 0.95131318 | G15: =CBAM_Products!$H$70 -> 0.95131318 | H15: =CBAM_Products!$H$86 -> 0.90499676 | I15: - | J15: EXP(b_f (tau + fundsp)); 1 in PROTOTYPE mode.
A16: 2. CBAM block totals (eight products; Mt CO2e, $m)
A17: E_base: block emissions at baseline output and intensity | B17: Ebase | C17: =CBAM_Products!$AT$16 -> 62.42361 | D17: =CBAM_Products!$AT$32 -> 62.42361 | E17: =CBAM_Products!$AT$48 -> 62.42361 | F17: =CBAM_Products!$AT$64 -> 62.42361 | G17: =CBAM_Products!$AT$80 -> 62.42361 | H17: =CBAM_Products!$AT$96 -> 62.42361 | I17: Mt | J17: Sum Qb (F+G)/1000; 62.424 in 2030 with EF v0.1 (prototype EFs: 61.157).
A18: E_base fuel part | B18: Efbase | C18: =CBAM_Products!$AU$16 -> 27.602124 | D18: =CBAM_Products!$AU$32 -> 27.602124 | E18: =CBAM_Products!$AU$48 -> 27.602124 | F18: =CBAM_Products!$AU$64 -> 27.602124 | G18: =CBAM_Products!$AU$80 -> 27.602124 | H18: =CBAM_Products!$AU$96 -> 27.602124 | I18: Mt | J18: Sum Qb F/1000.
A19: E_base process part | B19: Epbase | C19: =CBAM_Products!$AV$16 -> 34.821485 | D19: =CBAM_Products!$AV$32 -> 34.821485 | E19: =CBAM_Products!$AV$48 -> 34.821485 | F19: =CBAM_Products!$AV$64 -> 34.821485 | G19: =CBAM_Products!$AV$80 -> 34.821485 | H19: =CBAM_Products!$AV$96 -> 34.821485 | I19: Mt | J19: Sum Qb G/1000.
A20: Baseline output | B20: Qb | C20: =CBAM_Products!$I$16 -> 79893.956 | D20: =CBAM_Products!$I$32 -> 79893.956 | E20: =CBAM_Products!$I$48 -> 79893.956 | F20: =CBAM_Products!$I$64 -> 79893.956 | G20: =CBAM_Products!$I$80 -> 79893.956 | H20: =CBAM_Products!$I$96 -> 79893.956 | I20: kt | J20: Sum Q0 (1+g)^(Yr-BaseYr).
A21: Output after response | B21: Q | C21: =CBAM_Products!$N$16 -> 78880.541 | D21: =CBAM_Products!$N$32 -> 79438.026 | E21: =CBAM_Products!$N$48 -> 79438.026 | F21: =CBAM_Products!$N$64 -> 78880.541 | G21: =CBAM_Products!$N$80 -> 79893.956 | H21: =CBAM_Products!$N$96 -> 78880.541 | I21: kt | J21: Sum Qb (1+dp)^eps.
A22: Fuel emissions at post-response output, baseline intensity | B22: Ef | C22: =CBAM_Products!$O$16 -> 27.169331 | D22: =CBAM_Products!$O$32 -> 27.339929 | E22: =CBAM_Products!$O$48 -> 27.339929 | F22: =CBAM_Products!$O$64 -> 27.169331 | G22: =CBAM_Products!$O$80 -> 27.602124 | H22: =CBAM_Products!$O$96 -> 27.169331 | I22: Mt
A23: Process emissions at post-response output, baseline intensity | B23: Ep | C23: =CBAM_Products!$P$16 -> 34.325582 | D23: =CBAM_Products!$P$32 -> 34.637025 | E23: =CBAM_Products!$P$48 -> 34.637025 | F23: =CBAM_Products!$P$64 -> 34.325582 | G23: =CBAM_Products!$P$80 -> 34.821485 | H23: =CBAM_Products!$P$96 -> 34.325582 | I23: Mt
A24: ER_f: fuel-intensity response | B24: ERf | C24: =CBAM_Products!$Q$16 -> -1.3227885 | D24: =CBAM_Products!$Q$32 -> -1.3310943 | E24: =CBAM_Products!$Q$48 -> -1.3310943 | F24: =CBAM_Products!$Q$64 -> -1.3227885 | G24: =CBAM_Products!$Q$80 -> -1.3438598 | H24: =CBAM_Products!$Q$96 -> -2.5811746 | I24: Mt | J24: Ef (xf - 1); 0 in PROTOTYPE mode.
A25: ER_p: process-intensity response | B25: ERp | C25: =CBAM_Products!$R$16 -> -2.2424276 | D25: =CBAM_Products!$R$32 -> 0 | E25: =CBAM_Products!$R$48 -> 0 | F25: =CBAM_Products!$R$64 -> -2.2424276 | G25: =CBAM_Products!$R$80 -> -2.2757201 | H25: =CBAM_Products!$R$96 -> -4.3330817 | I25: Mt | J25: -Ep (1 - EXP(-beta (tau_p + fundsp))).
A26: Post-response fuel emissions | B26: emisf | C26: =CBAM_Products!$S$16 -> 25.846543 | D26: =CBAM_Products!$S$32 -> 26.008835 | E26: =CBAM_Products!$S$48 -> 26.008835 | F26: =CBAM_Products!$S$64 -> 25.846543 | G26: =CBAM_Products!$S$80 -> 26.258265 | H26: =CBAM_Products!$S$96 -> 24.588157 | I26: Mt | J26: Ef + ER_f.
A27: Post-response process emissions | B27: emisp | C27: =CBAM_Products!$T$16 -> 32.083154 | D27: =CBAM_Products!$T$32 -> 34.637025 | E27: =CBAM_Products!$T$48 -> 34.637025 | F27: =CBAM_Products!$T$64 -> 32.083154 | G27: =CBAM_Products!$T$80 -> 32.545765 | H27: =CBAM_Products!$T$96 -> 29.9925 | I27: Mt | J27: Ep + ER_p.
A28: Post-response block emissions | B28: emis | C28: =CBAM_Products!$U$16 -> 57.929697 | D28: =CBAM_Products!$U$32 -> 60.64586 | E28: =CBAM_Products!$U$48 -> 60.64586 | F28: =CBAM_Products!$U$64 -> 57.929697 | G28: =CBAM_Products!$U$80 -> 58.80403 | H28: =CBAM_Products!$U$96 -> 54.580657 | I28: Mt | J28: emisf + emisp.
A29: emrq: output-channel reduction (fuel + process) | B29: emrq | C29: =CBAM_Products!$V$16 -> -0.92869666 | D29: =CBAM_Products!$V$32 -> -0.44665601 | E29: =CBAM_Products!$V$48 -> -0.44665601 | F29: =CBAM_Products!$V$64 -> -0.92869666 | G29: =CBAM_Products!$V$80 -> 0 | H29: =CBAM_Products!$V$96 -> -0.92869666 | I29: Mt | J29: Sum (Ef+Ep)(1-(1+dp)^-eps) (negative = reduction).
A30: emrq (process part) | B30: emrq_proc | C30: =CBAM_Products!$W$16 -> -0.49590352 | D30: =CBAM_Products!$W$32 -> -0.1844604 | E30: =CBAM_Products!$W$48 -> -0.1844604 | F30: =CBAM_Products!$W$64 -> -0.49590352 | G30: =CBAM_Products!$W$80 -> 0 | H30: =CBAM_Products!$W$96 -> -0.49590352 | I30: Mt | J30: Sum Ep (1-(1+dp)^-eps).
A31: Carbon revenue on fuel emissions | B31: revf | C31: =CBAM_Products!$Y$16 -> 516.93086 | D31: =CBAM_Products!$Y$32 -> 520.17669 | E31: =CBAM_Products!$Y$48 -> 520.17669 | F31: =CBAM_Products!$Y$64 -> 516.93086 | G31: =CBAM_Products!$Y$80 -> 525.16529 | H31: =CBAM_Products!$Y$96 -> 491.76314 | I31: $m | J31: (Ef+ER_f) tau.
A32: Carbon revenue on process emissions | B32: revp | C32: =CBAM_Products!$Z$16 -> 641.66309 | D32: =CBAM_Products!$Z$32 -> 0 | E32: =CBAM_Products!$Z$48 -> 0 | F32: =CBAM_Products!$Z$64 -> 641.66309 | G32: =CBAM_Products!$Z$80 -> 650.91531 | H32: =CBAM_Products!$Z$96 -> 599.85 | I32: $m | J32: (Ep J + ER_p) tau_p.
A33: Block carbon revenue | B33: rev | C33: =CBAM_Products!$AA$16 -> 1158.5939 | D33: =CBAM_Products!$AA$32 -> 520.17669 | E33: =CBAM_Products!$AA$48 -> 520.17669 | F33: =CBAM_Products!$AA$64 -> 1158.5939 | G33: =CBAM_Products!$AA$80 -> 1176.0806 | H33: =CBAM_Products!$AA$96 -> 1091.6131 | I33: $m | J33: revf + revp.
A34: OBR rebate paid to block producers | B34: rebate | C34: =CBAM_Products!$AB$16 -> 0 | D34: =CBAM_Products!$AB$32 -> 0 | E34: =CBAM_Products!$AB$48 -> 0 | F34: =CBAM_Products!$AB$64 -> 0 | G34: =CBAM_Products!$AB$80 -> 1248.4722 | H34: =CBAM_Products!$AB$96 -> 0 | I34: $m | J34: Sum m Q/1000.
A35: CBAM obligation on EU exports (selected convention) | B35: cbobl | C35: =CBAM_Products!$AH$16 -> 65.861639 | D35: =CBAM_Products!$AH$32 -> 92.428684 | E35: =CBAM_Products!$AH$48 -> 92.428684 | F35: =CBAM_Products!$AH$64 -> 65.861639 | G35: =CBAM_Products!$AH$80 -> 113.58181 | H35: =CBAM_Products!$AH$96 -> 62.362403 | I35: $m | J35: Sum X Q/Q0 obl/1000.
A36: CBAM obligation with no domestic policy | B36: cbobl0 | C36: =CBAM_Products!$AI$16 -> 120.01558 | D36: =CBAM_Products!$AI$32 -> 120.01558 | E36: =CBAM_Products!$AI$48 -> 120.01558 | F36: =CBAM_Products!$AI$64 -> 120.01558 | G36: =CBAM_Products!$AI$80 -> 120.01558 | H36: =CBAM_Products!$AI$96 -> 120.01558 | I36: $m | J36: Sum X (1+g)^t CBF P_EU (F+G)/1000.
A37: Block emissions covered by the carbon price | B37: covered | C37: =CBAM_Products!$AS$16 -> 61.494913 | D37: =CBAM_Products!$AS$32 -> 27.339929 | E37: =CBAM_Products!$AS$48 -> 27.339929 | F37: =CBAM_Products!$AS$64 -> 61.494913 | G37: =CBAM_Products!$AS$80 -> 62.42361 | H37: =CBAM_Products!$AS$96 -> 61.494913 | I37: Mt | J37: Fuel if incl_f, process if incl_p and G>0.
A38: emr: intensity-channel reduction (fuel + process) | B38: emr | C38: =C24+C25 -> -3.5652161 | D38: =D24+D25 -> -1.3310943 | E38: =E24+E25 -> -1.3310943 | F38: =F24+F25 -> -3.5652161 | G38: =G24+G25 -> -3.6195799 | H38: =H24+H25 -> -6.9142563 | I38: Mt | J38: ER_f + ER_p.
A39: emrt: total block reduction (output + intensity) | B39: emrt | C39: =C29+C38 -> -4.4939127 | D39: =D29+D38 -> -1.7777503 | E39: =E29+E38 -> -1.7777503 | F39: =F29+F38 -> -4.4939127 | G39: =G29+G38 -> -3.6195799 | H39: =H29+H38 -> -7.8429529 | I39: Mt | J39: emrq + emr.
A40: 3. CBAM block metrics (prototype v0.11 definitions)
A41: cbcov: CBAM coverage (share of block emissions priced) | B41: cbcov | C41: =C37/(C22+C23) -> 1 | D41: =D37/(D22+D23) -> 0.44113057 | E41: =E37/(E22+E23) -> 0.44113057 | F41: =F37/(F22+F23) -> 1 | G41: =G37/(G22+G23) -> 1 | H41: =H37/(H22+H23) -> 1 | I41: - | J41: PolicyMatrix M.
A42: cbcovx: coverage, export-weighted | B42: cbcovx | C42: =CBAM_Products!$AR$16/CBAM_Products!$AQ$16 -> 1 | D42: =CBAM_Products!$AR$32/CBAM_Products!$AQ$32 -> 0.52437568 | E42: =CBAM_Products!$AR$48/CBAM_Products!$AQ$48 -> 0.52437568 | F42: =CBAM_Products!$AR$64/CBAM_Products!$AQ$64 -> 1 | G42: =CBAM_Products!$AR$80/CBAM_Products!$AQ$80 -> 1 | H42: =CBAM_Products!$AR$96/CBAM_Products!$AQ$96 -> 1 | I42: - | J42: Memo.
A43: cbintch: emissions-intensity change of the block | B43: cbintch | C43: =C28/(C22+C23)-1 -> -0.057975788 | D43: =D28/(D22+D23)-1 -> -0.021477246 | E43: =E28/(E22+E23)-1 -> -0.021477246 | F43: =F28/(F22+F23)-1 -> -0.057975788 | G43: =G28/(G22+G23)-1 -> -0.057984149 | H43: =H28/(H22+H23)-1 -> -0.11243623 | I43: - | J43: PolicyMatrix N.
A44: cbintchx: intensity change, export-weighted | B44: cbintchx | C44: =CBAM_Products!$AP$16/CBAM_Products!$AQ$16-1 -> -0.054226768 | D44: =CBAM_Products!$AP$32/CBAM_Products!$AQ$32-1 -> -0.025530187 | E44: =CBAM_Products!$AP$48/CBAM_Products!$AQ$48-1 -> -0.025530187 | F44: =CBAM_Products!$AP$64/CBAM_Products!$AQ$64-1 -> -0.054226768 | G44: =CBAM_Products!$AP$80/CBAM_Products!$AQ$80-1 -> -0.054226768 | H44: =CBAM_Products!$AP$96/CBAM_Products!$AQ$96-1 -> -0.10508584 | I44: - | J44: PolicyMatrix AN.
A45: cbqch: output-channel reduction / E_base | B45: cbqch | C45: =C29/C17 -> -0.01487733 | D45: =D29/D17 -> -0.0071552416 | E45: =E29/E17 -> -0.0071552416 | F45: =F29/F17 -> -0.01487733 | G45: =G29/G17 -> 0 | H45: =H29/H17 -> -0.01487733 | I45: - | J45: PolicyMatrix U (industrial output change).
A46: emrt / E_base: total block emissions change | B46: emrt_pct | C46: =C39/C17 -> -0.071990594 | D46: =D39/D17 -> -0.028478813 | E46: =E39/E17 -> -0.028478813 | F46: =F39/F17 -> -0.071990594 | G46: =G39/G17 -> -0.057984149 | H46: =H39/H17 -> -0.12564081 | I46: - | J46: PolicyMatrix T.
A47: cbint: block emissions intensity after response | B47: cbint | C47: =C28*1000/C21 -> 0.73439781 | D47: =D28*1000/D21 -> 0.76343614 | E47: =E28*1000/E21 -> 0.76343614 | F47: =F28*1000/F21 -> 0.73439781 | G47: =G28*1000/G21 -> 0.73602602 | H47: =H28*1000/H21 -> 0.6919407 | I47: tCO2e/t | J47: Memo.
A48: cbobch: change in CBAM obligation (incl. export volume change) | B48: cbobch | C48: =C35/C36-1 -> -0.45122425 | D48: =D35/D36-1 -> -0.22986095 | E48: =E35/E36-1 -> -0.22986095 | F48: =F35/F36-1 -> -0.45122425 | G48: =G35/G36-1 -> -0.053607802 | H48: =H35/H36-1 -> -0.48038077 | I48: - | J48: Memo.
A49: cbobchu: change in CBAM obligation per unit exported (selected convention) | B49: cbobchu | C49: =CBAM_Products!$AM$16/CBAM_Products!$AJ$16-1 -> -0.44423635 | D49: =CBAM_Products!$AM$32/CBAM_Products!$AJ$32-1 -> -0.23123967 | E49: =CBAM_Products!$AM$48/CBAM_Products!$AJ$48-1 -> -0.23123967 | F49: =CBAM_Products!$AM$64/CBAM_Products!$AJ$64-1 -> -0.44423635 | G49: =CBAM_Products!$AM$80/CBAM_Products!$AJ$80-1 -> -0.054226768 | H49: =CBAM_Products!$AM$96/CBAM_Products!$AJ$96-1 -> -0.47412261 | I49: - | J49: PolicyMatrix O.
A50: cbobchu under FULL (2030 phase-in on obligation, full deduction) | B50: cbobchu_full | C50: =CBAM_Products!$AN$16/CBAM_Products!$AK$16-1 -> -0.44423635 | D50: =CBAM_Products!$AN$32/CBAM_Products!$AK$32-1 -> -0.23123967 | E50: =CBAM_Products!$AN$48/CBAM_Products!$AK$48-1 -> -0.23123967 | F50: =CBAM_Products!$AN$64/CBAM_Products!$AK$64-1 -> -0.44423635 | G50: =CBAM_Products!$AN$80/CBAM_Products!$AK$80-1 -> -0.054226768 | H50: =CBAM_Products!$AN$96/CBAM_Products!$AK$96-1 -> -0.47412261 | I50: - | J50: PolicyMatrix AQ.
A51: cbobchu under NOPHASE (no phase-in) | B51: cbobchu_nophase | C51: =CBAM_Products!$AO$16/CBAM_Products!$AL$16-1 -> -0.24338141 | D51: =CBAM_Products!$AO$32/CBAM_Products!$AL$32-1 -> -0.12529929 | E51: =CBAM_Products!$AO$48/CBAM_Products!$AL$48-1 -> -0.12529929 | F51: =CBAM_Products!$AO$64/CBAM_Products!$AL$64-1 -> -0.24338141 | G51: =CBAM_Products!$AO$80/CBAM_Products!$AL$80-1 -> -0.054226768 | H51: =CBAM_Products!$AO$96/CBAM_Products!$AL$96-1 -> -0.28406867 | I51: - | J51: Memo.
A52: 4. CPAT national quantities for the bundle's scenario, reporting year (Inputs section C)
A53: Total GHG incl. LULUCF - baseline | B53: ghg0 | C53: =INDEX(CV_ghg0,MATCH(C6,CV_Hdr,0)) -> 594.156 | D53: =INDEX(CV_ghg0,MATCH(D6,CV_Hdr,0)) -> 594.156 | E53: =INDEX(CV_ghg0,MATCH(E6,CV_Hdr,0)) -> 594.156 | F53: =INDEX(CV_ghg0,MATCH(F6,CV_Hdr,0)) -> 594.156 | G53: =INDEX(CV_ghg0,MATCH(G6,CV_Hdr,0)) -> 594.156 | H53: =INDEX(CV_ghg0,MATCH(H6,CV_Hdr,0)) -> 594.156 | I53: Mt | J53: CPAT code row 'CV_ghg0' for the bundle's scenario.
A54: Total GHG incl. LULUCF - policy | B54: ghg1 | C54: =INDEX(CV_ghg1,MATCH(C6,CV_Hdr,0)) -> 555.279 | D54: =INDEX(CV_ghg1,MATCH(D6,CV_Hdr,0)) -> 555.279 | E54: =INDEX(CV_ghg1,MATCH(E6,CV_Hdr,0)) -> 553.154 | F54: =INDEX(CV_ghg1,MATCH(F6,CV_Hdr,0)) -> 572.614 | G54: =INDEX(CV_ghg1,MATCH(G6,CV_Hdr,0)) -> 572.614 | H54: =INDEX(CV_ghg1,MATCH(H6,CV_Hdr,0)) -> 572.614 | I54: Mt | J54: CPAT code row 'CV_ghg1' for the bundle's scenario.
A55: IPPU GHG - baseline | B55: ippu0 | C55: =INDEX(CV_ippu0,MATCH(C6,CV_Hdr,0)) -> 85.97 | D55: =INDEX(CV_ippu0,MATCH(D6,CV_Hdr,0)) -> 85.97 | E55: =INDEX(CV_ippu0,MATCH(E6,CV_Hdr,0)) -> 85.97 | F55: =INDEX(CV_ippu0,MATCH(F6,CV_Hdr,0)) -> 85.97 | G55: =INDEX(CV_ippu0,MATCH(G6,CV_Hdr,0)) -> 85.97 | H55: =INDEX(CV_ippu0,MATCH(H6,CV_Hdr,0)) -> 85.97 | I55: Mt | J55: CPAT code row 'CV_ippu0' for the bundle's scenario.
A56: IPPU GHG - policy | B56: ippu1 | C56: =INDEX(CV_ippu1,MATCH(C6,CV_Hdr,0)) -> 74.015 | D56: =INDEX(CV_ippu1,MATCH(D6,CV_Hdr,0)) -> 74.015 | E56: =INDEX(CV_ippu1,MATCH(E6,CV_Hdr,0)) -> 73.407 | F56: =INDEX(CV_ippu1,MATCH(F6,CV_Hdr,0)) -> 77.708 | G56: =INDEX(CV_ippu1,MATCH(G6,CV_Hdr,0)) -> 77.708 | H56: =INDEX(CV_ippu1,MATCH(H6,CV_Hdr,0)) -> 77.708 | I56: Mt | J56: CPAT code row 'CV_ippu1' for the bundle's scenario.
A57: Energy CO2 - baseline | B57: enr0 | C57: =INDEX(CV_enr0,MATCH(C6,CV_Hdr,0)) -> 340.66 | D57: =INDEX(CV_enr0,MATCH(D6,CV_Hdr,0)) -> 340.66 | E57: =INDEX(CV_enr0,MATCH(E6,CV_Hdr,0)) -> 340.66 | F57: =INDEX(CV_enr0,MATCH(F6,CV_Hdr,0)) -> 340.66 | G57: =INDEX(CV_enr0,MATCH(G6,CV_Hdr,0)) -> 340.66 | H57: =INDEX(CV_enr0,MATCH(H6,CV_Hdr,0)) -> 340.66 | I57: Mt | J57: CPAT code row 'CV_enr0' for the bundle's scenario.
A58: Energy CO2 - policy | B58: enr1 | C58: =INDEX(CV_enr1,MATCH(C6,CV_Hdr,0)) -> 313.865 | D58: =INDEX(CV_enr1,MATCH(D6,CV_Hdr,0)) -> 313.865 | E58: =INDEX(CV_enr1,MATCH(E6,CV_Hdr,0)) -> 312.396 | F58: =INDEX(CV_enr1,MATCH(F6,CV_Hdr,0)) -> 327.453 | G58: =INDEX(CV_enr1,MATCH(G6,CV_Hdr,0)) -> 327.453 | H58: =INDEX(CV_enr1,MATCH(H6,CV_Hdr,0)) -> 327.453 | I58: Mt | J58: CPAT code row 'CV_enr1' for the bundle's scenario.
A59: Industry energy CO2 - baseline | B59: ind0 | C59: =INDEX(CV_ind0,MATCH(C6,CV_Hdr,0)) -> 88.973 | D59: =INDEX(CV_ind0,MATCH(D6,CV_Hdr,0)) -> 88.973 | E59: =INDEX(CV_ind0,MATCH(E6,CV_Hdr,0)) -> 88.973 | F59: =INDEX(CV_ind0,MATCH(F6,CV_Hdr,0)) -> 88.973 | G59: =INDEX(CV_ind0,MATCH(G6,CV_Hdr,0)) -> 88.973 | H59: =INDEX(CV_ind0,MATCH(H6,CV_Hdr,0)) -> 88.973 | I59: Mt | J59: CPAT code row 'CV_ind0' for the bundle's scenario.
A60: Industry energy CO2 - policy | B60: ind1 | C60: =INDEX(CV_ind1,MATCH(C6,CV_Hdr,0)) -> 76.6 | D60: =INDEX(CV_ind1,MATCH(D6,CV_Hdr,0)) -> 76.6 | E60: =INDEX(CV_ind1,MATCH(E6,CV_Hdr,0)) -> 75.971 | F60: =INDEX(CV_ind1,MATCH(F6,CV_Hdr,0)) -> 80.422 | G60: =INDEX(CV_ind1,MATCH(G6,CV_Hdr,0)) -> 80.422 | H60: =INDEX(CV_ind1,MATCH(H6,CV_Hdr,0)) -> 80.422 | I60: Mt | J60: CPAT code row 'CV_ind1' for the bundle's scenario.
A61: Delta total GHG (CPAT) | B61: dghg | C61: =INDEX(CV_dghg,MATCH(C6,CV_Hdr,0)) -> -38.877 | D61: =INDEX(CV_dghg,MATCH(D6,CV_Hdr,0)) -> -38.877 | E61: =INDEX(CV_dghg,MATCH(E6,CV_Hdr,0)) -> -41.002 | F61: =INDEX(CV_dghg,MATCH(F6,CV_Hdr,0)) -> -21.542 | G61: =INDEX(CV_dghg,MATCH(G6,CV_Hdr,0)) -> -21.542 | H61: =INDEX(CV_dghg,MATCH(H6,CV_Hdr,0)) -> -21.542 | I61: Mt | J61: CPAT code row 'CV_dghg' for the bundle's scenario.
A62: Delta IPPU (CPAT) | B62: dippu | C62: =INDEX(CV_dippu,MATCH(C6,CV_Hdr,0)) -> -11.955 | D62: =INDEX(CV_dippu,MATCH(D6,CV_Hdr,0)) -> -11.955 | E62: =INDEX(CV_dippu,MATCH(E6,CV_Hdr,0)) -> -12.563 | F62: =INDEX(CV_dippu,MATCH(F6,CV_Hdr,0)) -> -8.262 | G62: =INDEX(CV_dippu,MATCH(G6,CV_Hdr,0)) -> -8.262 | H62: =INDEX(CV_dippu,MATCH(H6,CV_Hdr,0)) -> -8.262 | I62: Mt | J62: CPAT code row 'CV_dippu' for the bundle's scenario.
A63: Delta energy CO2 (CPAT) | B63: denr | C63: =INDEX(CV_denr,MATCH(C6,CV_Hdr,0)) -> -26.795 | D63: =INDEX(CV_denr,MATCH(D6,CV_Hdr,0)) -> -26.795 | E63: =INDEX(CV_denr,MATCH(E6,CV_Hdr,0)) -> -28.264 | F63: =INDEX(CV_denr,MATCH(F6,CV_Hdr,0)) -> -13.207 | G63: =INDEX(CV_denr,MATCH(G6,CV_Hdr,0)) -> -13.207 | H63: =INDEX(CV_denr,MATCH(H6,CV_Hdr,0)) -> -13.207 | I63: Mt | J63: CPAT code row 'CV_denr' for the bundle's scenario.
A64: Delta industry energy CO2 (CPAT) | B64: dind | C64: =INDEX(CV_dind,MATCH(C6,CV_Hdr,0)) -> -12.373 | D64: =INDEX(CV_dind,MATCH(D6,CV_Hdr,0)) -> -12.373 | E64: =INDEX(CV_dind,MATCH(E6,CV_Hdr,0)) -> -13.002 | F64: =INDEX(CV_dind,MATCH(F6,CV_Hdr,0)) -> -8.551 | G64: =INDEX(CV_dind,MATCH(G6,CV_Hdr,0)) -> -8.551 | H64: =INDEX(CV_dind,MATCH(H6,CV_Hdr,0)) -> -8.551 | I64: Mt | J64: CPAT code row 'CV_dind' for the bundle's scenario.
A65: kappa: coverage factor of the CPAT run | B65: kappa | C65: =INDEX(CV_kappa,MATCH(C6,CV_Hdr,0)) -> 1 | D65: =INDEX(CV_kappa,MATCH(D6,CV_Hdr,0)) -> 1 | E65: =INDEX(CV_kappa,MATCH(E6,CV_Hdr,0)) -> 1 | F65: =INDEX(CV_kappa,MATCH(F6,CV_Hdr,0)) -> 0.53737236 | G65: =INDEX(CV_kappa,MATCH(G6,CV_Hdr,0)) -> 0.53737236 | H65: =INDEX(CV_kappa,MATCH(H6,CV_Hdr,0)) -> 0.53737236 | I65: - | J65: CPAT code row 'CV_kappa' for the bundle's scenario.
A66: Carbon-tax revenue, six fuels (CPAT) | B66: revctax | C66: =INDEX(CV_revctax,MATCH(C6,CV_Hdr,0)) -> 6.23 | D66: =INDEX(CV_revctax,MATCH(D6,CV_Hdr,0)) -> 6.23 | E66: =INDEX(CV_revctax,MATCH(E6,CV_Hdr,0)) -> 6.19 | F66: =INDEX(CV_revctax,MATCH(F6,CV_Hdr,0)) -> 0.93 | G66: =INDEX(CV_revctax,MATCH(G6,CV_Hdr,0)) -> 0.93 | H66: =INDEX(CV_revctax,MATCH(H6,CV_Hdr,0)) -> 0.93 | I66: $bn | J66: CPAT code row 'CV_revctax' for the bundle's scenario.
A67: Air-pollution deaths avoided (CPAT) | B67: deaths | C67: =INDEX(CV_deaths,MATCH(C6,CV_Hdr,0)) -> 1564 | D67: =INDEX(CV_deaths,MATCH(D6,CV_Hdr,0)) -> 1564 | E67: =INDEX(CV_deaths,MATCH(E6,CV_Hdr,0)) -> 1631 | F67: =INDEX(CV_deaths,MATCH(F6,CV_Hdr,0)) -> 546 | G67: =INDEX(CV_deaths,MATCH(G6,CV_Hdr,0)) -> 546 | H67: =INDEX(CV_deaths,MATCH(H6,CV_Hdr,0)) -> 546 | I67: deaths | J67: CPAT code row 'CV_deaths' for the bundle's scenario.
A68: Baseline air-pollution deaths (CPAT) | B68: mort | C68: =INDEX(CV_mort,MATCH(C6,CV_Hdr,0)) -> 82651 | D68: =INDEX(CV_mort,MATCH(D6,CV_Hdr,0)) -> 82651 | E68: =INDEX(CV_mort,MATCH(E6,CV_Hdr,0)) -> 82651 | F68: =INDEX(CV_mort,MATCH(F6,CV_Hdr,0)) -> 82651 | G68: =INDEX(CV_mort,MATCH(G6,CV_Hdr,0)) -> 82651 | H68: =INDEX(CV_mort,MATCH(H6,CV_Hdr,0)) -> 82651 | I68: deaths | J68: CPAT code row 'CV_mort' for the bundle's scenario.
A69: Delta net new revenue (CPAT) | B69: drev | C69: =INDEX(CV_drev,MATCH(C6,CV_Hdr,0)) -> 10.43 | D69: =INDEX(CV_drev,MATCH(D6,CV_Hdr,0)) -> 10.43 | E69: =INDEX(CV_drev,MATCH(E6,CV_Hdr,0)) -> 10.62 | F69: =INDEX(CV_drev,MATCH(F6,CV_Hdr,0)) -> 2.69 | G69: =INDEX(CV_drev,MATCH(G6,CV_Hdr,0)) -> 2.69 | H69: =INDEX(CV_drev,MATCH(H6,CV_Hdr,0)) -> 2.69 | I69: $bn | J69: CPAT code row 'CV_drev' for the bundle's scenario.
A70: 5. Composition of the Table-2 metrics (REBUILD method; PROTOTYPE mode changes only the block)
A71: SCALE active (1 = approximating full-coverage EG3) | B71: scale_active | C71: =IF(AND(KappaMode="SCALE",C65<0.999999),1,0) -> 0 | D71: =IF(AND(KappaMode="SCALE",D65<0.999999),1,0) -> 0 | E71: =IF(AND(KappaMode="SCALE",E65<0.999999),1,0) -> 0 | F71: =IF(AND(KappaMode="SCALE",F65<0.999999),1,0) -> 1 | G71: =IF(AND(KappaMode="SCALE",G65<0.999999),1,0) -> 1 | H71: =IF(AND(KappaMode="SCALE",H65<0.999999),1,0) -> 1 | I71: - | J71: Only runs with kappa < 1 are scaled; EG1/EG2 are numerically unchanged.
A72: Full-coverage scale factor for partial industry runs | B72: scale_fac | C72: =IF(C71=1,1/C65,1) -> 1 | D72: =IF(D71=1,1/D65,1) -> 1 | E72: =IF(E71=1,1/E65,1) -> 1 | F72: =IF(F71=1,1/F65,1) -> 1.860907 | G72: =IF(G71=1,1/G65,1) -> 1.860907 | H72: =IF(H71=1,1/H65,1) -> 1.860907 | I72: - | J72: SCALE approximation factor (1/kappa); 1 otherwise.
A73: Delta industry energy CO2 after SCALE adjustment | B73: dind_adj | C73: =C64*C72 -> -12.373 | D73: =D64*D72 -> -12.373 | E73: =E64*E72 -> -13.002 | F73: =F64*F72 -> -15.912616 | G73: =G64*G72 -> -15.912616 | H73: =H64*H72 -> -15.912616 | I73: Mt | J73: DeltaIndCO2_adj = DeltaIndCO2/kappa under SCALE.
A74: Delta energy CO2 after SCALE adjustment | B74: denr_adj | C74: =C63+(C72-1)*C64 -> -26.795 | D74: =D63+(D72-1)*D64 -> -26.795 | E74: =E63+(E72-1)*E64 -> -28.264 | F74: =F63+(F72-1)*F64 -> -20.568616 | G74: =G63+(G72-1)*G64 -> -20.568616 | H74: =H63+(H72-1)*H64 -> -20.568616 | I74: Mt | J74: DeltaEnergyCO2_adj = DeltaEnergyCO2 + (1/kappa - 1) DeltaIndCO2 under SCALE.
A75: Delta IPPU after SCALE adjustment | B75: dippu_adj | C75: =C62*C72 -> -11.955 | D75: =D62*D72 -> -11.955 | E75: =E62*E72 -> -12.563 | F75: =F62*F72 -> -15.374814 | G75: =G62*G72 -> -15.374814 | H75: =H62*H72 -> -15.374814 | I75: Mt | J75: DeltaIPPU_adj = DeltaIPPU/kappa under SCALE.
A76: Delta total GHG after SCALE adjustment | B76: dghg_adj | C76: =C61+(C72-1)*(C64+C62) -> -38.877 | D76: =D61+(D72-1)*(D64+D62) -> -38.877 | E76: =E61+(E72-1)*(E64+E62) -> -41.002 | F76: =F61+(F72-1)*(F64+F62) -> -36.01643 | G76: =G61+(G72-1)*(G64+G62) -> -36.01643 | H76: =H61+(H72-1)*(H64+H62) -> -36.01643 | I76: Mt | J76: DeltaGHG_adj = DeltaGHG + (1/kappa - 1)(DeltaIndCO2 + DeltaIPPU) under SCALE.
A77: Industry energy CO2 policy level after SCALE adjustment | B77: ind1_adj | C77: =C59+C73 -> 76.6 | D77: =D59+D73 -> 76.6 | E77: =E59+E73 -> 75.971 | F77: =F59+F73 -> 73.060384 | G77: =G59+G73 -> 73.060384 | H77: =H59+H73 -> 73.060384 | I77: Mt | J77: IndCO2_1_adj = IndCO2_0 + DeltaIndCO2_adj.
A78: Fuel emissions covered by the levy after SCALE adjustment | B78: Ef0_adj | C78: =IF(C7="ALL",C57,IF(C71=1,C59,C65*C59)) -> 340.66 | D78: =IF(D7="ALL",D57,IF(D71=1,D59,D65*D59)) -> 340.66 | E78: =IF(E7="ALL",E57,IF(E71=1,E59,E65*E59)) -> 340.66 | F78: =IF(F7="ALL",F57,IF(F71=1,F59,F65*F59)) -> 88.973 | G78: =IF(G7="ALL",G57,IF(G71=1,G59,G65*G59)) -> 88.973 | H78: =IF(H7="ALL",H57,IF(H71=1,H59,H65*H59)) -> 88.973 | I78: Mt | J78: Coverage J uses kappa = 1 under SCALE; otherwise EnergyCO2 (ALL) or kappa x industry CO2 (IND).
A79: Carbon-tax revenue, six fuels after SCALE adjustment | B79: revctax_adj | C79: =C66*C72 -> 6.23 | D79: =D66*D72 -> 6.23 | E79: =E66*E72 -> 6.19 | F79: =F66*F72 -> 1.7306435 | G79: =G66*G72 -> 1.7306435 | H79: =H66*H72 -> 1.7306435 | I79: $bn | J79: SCALE approximation: CPAT carbon-tax receipts on fuels are multiplied by 1/kappa.
A80: IPPU_other: response of non-CBAM IPPU | B80: ippu_other | C80: =IF(IppuOther="CPAT",(1-C19/C55)*C62,0) -> 0 | D80: =IF(IppuOther="CPAT",(1-D19/D55)*D62,0) -> 0 | E80: =IF(IppuOther="CPAT",(1-E19/E55)*E62,0) -> 0 | F80: =IF(IppuOther="CPAT",(1-F19/F55)*F62,0) -> 0 | G80: =IF(IppuOther="CPAT",(1-G19/G55)*G62,0) -> 0 | H80: =IF(IppuOther="CPAT",(1-H19/H55)*H62,0) -> 0 | I80: Mt | J80: 0 unless IppuOther = CPAT (then CPAT's scaling of the non-block IPPU remainder is kept).
A81: w: block share of the priced industrial fuel CO2 | B81: w | C81: =IF(ThetaOther=1,1,MIN(1,C18/C78)) -> 1 | D81: =IF(ThetaOther=1,1,MIN(1,D18/D78)) -> 1 | E81: =IF(ThetaOther=1,1,MIN(1,E18/E78)) -> 1 | F81: =IF(ThetaOther=1,1,MIN(1,F18/F78)) -> 1 | G81: =IF(ThetaOther=1,1,MIN(1,G18/G78)) -> 1 | H81: =IF(ThetaOther=1,1,MIN(1,H18/H78)) -> 1 | I81: - | J81: Weight of the OBR output-channel correction; under SCALE, w = E_f^base / IndCO2_0.
A82: D_obr: output-channel reduction removed by the OBR | B82: D_obr | C82: =IF(C9>0,-(1-SInt)*C81*C73,0) -> 0 | D82: =IF(D9>0,-(1-SInt)*D81*D73,0) -> 0 | E82: =IF(E9>0,-(1-SInt)*E81*E73,0) -> 0 | F82: =IF(F9>0,-(1-SInt)*F81*F73,0) -> 0 | G82: =IF(G9>0,-(1-SInt)*G81*G73,0) -> 10.608411 | H82: =IF(H9>0,-(1-SInt)*H81*H73,0) -> 0 | I82: Mt | J82: OBR neutralises the output share (1 - s_int) of the adjusted industrial fuel response for rebated producers (positive = less reduction).
A83: F_fund: extra fuel-intensity reduction bought by the fund outside the block | B83: F_fund | C83: =IF(C10>0,IF(C71=1,C77,C65*C60)*(EXP(Bf*C14)-1),0) -> 0 | D83: =IF(D10>0,IF(D71=1,D77,D65*D60)*(EXP(Bf*D14)-1),0) -> 0 | E83: =IF(E10>0,IF(E71=1,E77,E65*E60)*(EXP(Bf*E14)-1),0) -> 0 | F83: =IF(F10>0,IF(F71=1,F77,F65*F60)*(EXP(Bf*F14)-1),0) -> 0 | G83: =IF(G10>0,IF(G71=1,G77,G65*G60)*(EXP(Bf*G14)-1),0) -> 0 | H83: =IF(H10>0,IF(H71=1,H77,H65*H60)*(EXP(Bf*H14)-1),0) -> -3.5570781 | I83: Mt | J83: Adjusted IndCO2_1 (EXP(b_f sigma) - 1) under SCALE; otherwise kappa x IndCO2_1 as in v0.2. Block products already carry sigma through xf and beta.
A84: K: total emissions reduction | B84: K | C84: =C76-C75+C80+C25+C30+C82+C83 -> -29.660331 | D84: =D76-D75+D80+D25+D30+D82+D83 -> -27.10646 | E84: =E76-E75+E80+E25+E30+E82+E83 -> -28.62346 | F84: =F76-F75+F80+F25+F30+F82+F83 -> -23.379947 | G84: =G76-G75+G80+G25+G30+G82+G83 -> -12.308925 | H84: =H76-H75+H80+H25+H30+H82+H83 -> -29.027679 | I84: Mt | J84: CPAT delta GHG minus CPAT's IPPU scaling, plus block process responses (intensity + output), OBR and fund terms. PolicyMatrix K.
A85: L: total reduction, % of baseline total GHG | B85: L | C85: =C84/C53 -> -0.049920107 | D85: =D84/D53 -> -0.04562179 | E85: =E84/E53 -> -0.048174992 | F85: =F84/F53 -> -0.039349846 | G85: =G84/G53 -> -0.020716656 | H85: =H84/H53 -> -0.048855316 | I85: - | J85: Single 2030 base (CPAT baseline incl. LULUCF). PolicyMatrix L.
A86: Fuel emissions covered by the levy | B86: Ef0 | C86: =C78 -> 340.66 | D86: =D78 -> 340.66 | E86: =E78 -> 340.66 | F86: =F78 -> 88.973 | G86: =G78 -> 88.973 | H86: =H78 -> 88.973 | I86: Mt | J86: Energy CO2 (ALL), kappa x industry energy CO2 (IND/AUTO), or full industry CO2 under SCALE.
A87: J: emissions coverage, % of total GHG | B87: J | C87: =(C86+C8*C19)/C53 -> 0.63195774 | D87: =(D86+D8*D19)/D53 -> 0.57335111 | E87: =(E86+E8*E19)/E53 -> 0.57335111 | F87: =(F86+F8*F19)/F53 -> 0.20835351 | G87: =(G86+G8*G19)/G53 -> 0.20835351 | H87: =(H86+H8*H19)/H53 -> 0.20835351 | I87: - | J87: Covered fuel CO2 plus priced block process emissions over baseline total GHG. PolicyMatrix J.
A88: J as intended (kappa = 1: all industry priced) | B88: J_int | C88: =(IF(C7="ALL",C57,C59)+C8*C19)/C53 -> 0.63195774 | D88: =(IF(D7="ALL",D57,D59)+D8*D19)/D53 -> 0.57335111 | E88: =(IF(E7="ALL",E57,E59)+E8*E19)/E53 -> 0.57335111 | F88: =(IF(F7="ALL",F57,F59)+F8*F19)/F53 -> 0.20835351 | G88: =(IF(G7="ALL",G57,G59)+G8*G19)/G53 -> 0.20835351 | H88: =(IF(H7="ALL",H57,H59)+H8*H19)/H53 -> 0.20835351 | I88: - | J88: Memo: coverage if the industry run had priced all industrial energy CO2.
A89: M: CBAM coverage | B89: M | C89: =C41 -> 1 | D89: =D41 -> 0.44113057 | E89: =E41 -> 0.44113057 | F89: =F41 -> 1 | G89: =G41 -> 1 | H89: =H41 -> 1 | I89: - | J89: PolicyMatrix M.
A90: N: CBAM emissions-intensity reduction | B90: N | C90: =C43 -> -0.057975788 | D90: =D43 -> -0.021477246 | E90: =E43 -> -0.021477246 | F90: =F43 -> -0.057975788 | G90: =G43 -> -0.057984149 | H90: =H43 -> -0.11243623 | I90: - | J90: PolicyMatrix N.
A91: O: CBAM obligations reduced per unit exported (selected convention) | B91: O | C91: =C49 -> -0.44423635 | D91: =D49 -> -0.23123967 | E91: =E49 -> -0.23123967 | F91: =F49 -> -0.44423635 | G91: =G49 -> -0.054226768 | H91: =H49 -> -0.47412261 | I91: - | J91: PolicyMatrix O.
A92: O under FULL convention | B92: O_full | C92: =C50 -> -0.44423635 | D92: =D50 -> -0.23123967 | E92: =E50 -> -0.23123967 | F92: =F50 -> -0.44423635 | G92: =G50 -> -0.054226768 | H92: =H50 -> -0.47412261 | I92: - | J92: PolicyMatrix AQ.
A93: O under NOPHASE convention | B93: O_nophase | C93: =C51 -> -0.24338141 | D93: =D51 -> -0.12529929 | E93: =E51 -> -0.12529929 | F93: =F51 -> -0.24338141 | G93: =G51 -> -0.054226768 | H93: =H51 -> -0.28406867 | I93: - | J93: Memo.
A94: Gross carbon revenue | B94: P_gross | C94: =C79+C32/1000 -> 6.8716631 | D94: =D79+D32/1000 -> 6.23 | E94: =E79+E32/1000 -> 6.19 | F94: =F79+F32/1000 -> 2.3723066 | G94: =G79+G32/1000 -> 2.3815588 | H94: =H79+H32/1000 -> 2.3304935 | I94: $bn | J94: CPAT carbon-tax receipts on fuels (scaled by 1/kappa under SCALE) + block process revenue. PolicyMatrix V / AO.
A95: OBR rebate to non-CBAM priced industry | B95: rebate_other | C95: =IF(AND(C9>0,ThetaOther=1),C11*(IF(C71=1,C77,C65*C60)-C26)/1000,0) -> 0 | D95: =IF(AND(D9>0,ThetaOther=1),D11*(IF(D71=1,D77,D65*D60)-D26)/1000,0) -> 0 | E95: =IF(AND(E9>0,ThetaOther=1),E11*(IF(E71=1,E77,E65*E60)-E26)/1000,0) -> 0 | F95: =IF(AND(F9>0,ThetaOther=1),F11*(IF(F71=1,F77,F65*F60)-F26)/1000,0) -> 0 | G95: =IF(AND(G9>0,ThetaOther=1),G11*(IF(G71=1,G77,G65*G60)-G26)/1000,0) -> 0.93604239 | H95: =IF(AND(H9>0,ThetaOther=1),H11*(IF(H71=1,H77,H65*H60)-H26)/1000,0) -> 0 | I95: $bn | J95: Only if ThetaOther = 1.
A96: Total OBR rebates | B96: rebate_bn | C96: =C34/1000+C95 -> 0 | D96: =D34/1000+D95 -> 0 | E96: =E34/1000+E95 -> 0 | F96: =F34/1000+F95 -> 0 | G96: =G34/1000+G95 -> 2.1845146 | H96: =H34/1000+H95 -> 0 | I96: $bn | J96: PolicyMatrix AP.
A97: P: carbon revenues raised (net of rebates and fund) | B97: P_net | C97: =(1-C10)*(C94-C96) -> 6.8716631 | D97: =(1-D10)*(D94-D96) -> 6.23 | E97: =(1-E10)*(E94-E96) -> 6.19 | F97: =(1-F10)*(F94-F96) -> 2.3723066 | G97: =(1-G10)*(G94-G96) -> 0.19704425 | H97: =(1-H10)*(H94-H96) -> 0 | I97: $bn | J97: PolicyMatrix P.
A98: Fund budget (3C) | B98: fund_budget | C98: =C10*(C94-C34/1000) -> 0 | D98: =D10*(D94-D34/1000) -> 0 | E98: =E10*(E94-E34/1000) -> 0 | F98: =F10*(F94-F34/1000) -> 0 | G98: =G10*(G94-G34/1000) -> 0 | H98: =H10*(H94-H34/1000) -> 2.3304935 | I98: $bn | J98: phi x net revenue.
A99: Fund outlay upper bound (3C) | B99: fund_outlay | C99: =IF(C10>0,SigmaEff*ABS(C38+C83)/1000,0) -> 0 | D99: =IF(D10>0,SigmaEff*ABS(D38+D83)/1000,0) -> 0 | E99: =IF(E10>0,SigmaEff*ABS(E38+E83)/1000,0) -> 0 | F99: =IF(F10>0,SigmaEff*ABS(F38+F83)/1000,0) -> 0 | G99: =IF(G10>0,SigmaEff*ABS(G38+G83)/1000,0) -> 0 | H99: =IF(H10>0,SigmaEff*ABS(H38+H83)/1000,0) -> 0.20942669 | I99: $bn | J99: sigma x all intensity abatement (upper bound: pays sigma per tonne for all of it).
A100: Q: air-pollution deaths avoided | B100: Q_deaths | C100: =C67*IF(C7="IND",(C74+C82+C83)/C63,1) -> 1564 | D100: =D67*IF(D7="IND",(D74+D82+D83)/D63,1) -> 1564 | E100: =E67*IF(E7="IND",(E74+E82+E83)/E63,1) -> 1631 | F100: =F67*IF(F7="IND",(F74+F82+F83)/F63,1) -> 850.34181 | G100: =G67*IF(G7="IND",(G74+G82+G83)/G63,1) -> 411.77195 | H100: =H67*IF(H7="IND",(H74+H82+H83)/H63,1) -> 997.39751 | I100: deaths | J100: CPAT deaths for the scenario, scaled by DeltaEnergyCO2_adj / DeltaEnergyCO2 under SCALE, then by OBR / fund energy-CO2 corrections. PolicyMatrix Q.
...

Sheet PolicyMatrix
C1: Egypt - Policy Options Matrix (rebuild v0.5 of AdHocCalculations.xlsb) | D1: Notes:
C2: Built 2026-10-04 | D2: * relies on CPAT modeling (where feasible)
C3: ="All results for "&Yr&", at the CPAT carbon price of that year ($"&TEXT(INDEX(SumTbl,MATCH("tau",SumKeys,0),MATCH("1A",SumHdr,0)),"0")&" for 1A)." -> All results for 2030, at the CPAT carbon price of that year ($20 for 1A). | D3: ** may require different modeling or assumptions to estimate sector-specific emission intensity reductions
C4: ="Mode: "&Mode&" | CBAM convention: "&Conv&" | process beta set: "&BetaSet&" | edit only on Inputs" -> Mode: REBUILD | CBAM convention: FULL | process beta set: IPCC_CENTRAL | edit only on Inputs | E4: (+) CPAT assumptions | V4: Calculations (+) | AS4: Other/Don't Trust (+)
A5: Code | B5: CPAT Scenario code | C5: Policy Bundle | D5: Examples of jurisdictions with experience | E5: Rationale | F5: Implementation in CPAT | G5: Scenario assumptions ($20 in 2030 for all) | H5: Carbon price in 2030 | I5: Revenue recycling option | J5: Emissions coverage (% of total GHG) | K5: Estimated total emissions reductions (MtCO2) | L5: Estimated total emissions reductions (% of baseline) | M5: CBAM coverage (% of CBAM sector emissions) | N5: Emissions intensity reduction, CBAM (% of baseline) | O5: CBAM obligations reduced** | P5: Carbon revenues raised ($bn) | Q5: Air pollution deaths avoided | R5: % of total air pollution deaths | T5: Industrial Emissions Change | U5: Industrial Output Change | V5: Carbon Revenues | W5: Price | X5: Total Emissions (all GHG) | Y5: Industrial CO2 Emissions | Z5: CBAM Energy related | AA5: CBAM process emissions | AB5: Total Covered Emissions | AC5: % coverage | AD5: Total CBAM emissions | AE5: Total Covered CBAM Emissions | AF5: CPAT: change in total GHG, adjusted (Mt) | AG5: less CPAT IPPU scaling, adjusted (Mt) | AH5: Non-CBAM IPPU response (Mt) | AI5: CBAM process intensity response (Mt) | AJ5: CBAM process output response (Mt) | AK5: OBR output-channel correction (Mt) | AL5: Fund extra fuel-intensity reduction (Mt) | AM5: K decomposition check (=0) | AN5: Intensity change, export-weighted | AO5: Gross carbon revenue ($bn) | AP5: OBR rebates ($bn) | AQ5: CBAM obligations reduced, FULL phase-in | AR5: Total change in revenues (CPAT) | AS5: National emissions covered by carbon pricing (IEA) | AT5: Cobenefits (% of GDP) | AU5: Fuel subsidy expenditures saved
C6: Policy Bundle Options - Carbon Pricing (modelled) | AS6: Replaced by CPAT data | AT6: Don't trust | AU6: Don't trust
A7: 1A | B7: =INDEX(BT_Scen,MATCH($A7,BT_Code,0)) -> EG1 | C7: Carbon levy on all fossil fuel consumption (upstream carbon price) + Upstream emissions in CBAM sectors only + recycling to public investment | D7: South Africa ($18), Washington State ($65) | E7: • Economy-wide carbon price covering most GHG sectors • Generates CBAM-deductible "carbon price effectively paid" • Captures fuel-related and process emissions | F7: Energy CO2 only all sectors + CBAM process emissisons ONLY (close to 2B) | G7: $20 flat from 2028 (CPAT EG1 trajectory) | H7: =INDEX(SumTbl,MATCH("tau",SumKeys,0),MATCH($A7,SumHdr,0)) -> 20 | I7: Public investment | J7: =INDEX(SumTbl,MATCH("J",SumKeys,0),MATCH($A7,SumHdr,0)) -> 0.63195774 | K7: =INDEX(SumTbl,MATCH("K",SumKeys,0),MATCH($A7,SumHdr,0)) -> -29.660331 | L7: =INDEX(SumTbl,MATCH("L",SumKeys,0),MATCH($A7,SumHdr,0)) -> -0.049920107 | M7: =INDEX(SumTbl,MATCH("M",SumKeys,0),MATCH($A7,SumHdr,0)) -> 1 | N7: =INDEX(SumTbl,MATCH("N",SumKeys,0),MATCH($A7,SumHdr,0)) -> -0.057975788 | O7: =INDEX(SumTbl,MATCH("O",SumKeys,0),MATCH($A7,SumHdr,0)) -> -0.44423635 | P7: =INDEX(SumTbl,MATCH("P_net",SumKeys,0),MATCH($A7,SumHdr,0)) -> 6.8716631 | Q7: =INDEX(SumTbl,MATCH("Q_deaths",SumKeys,0),MATCH($A7,SumHdr,0)) -> 1564 | R7: =INDEX(SumTbl,MATCH("R",SumKeys,0),MATCH($A7,SumHdr,0)) -> 0.018922941 | T7: =INDEX(SumTbl,MATCH("T",SumKeys,0),MATCH($A7,SumHdr,0)) -> -0.071990594 | U7: =INDEX(SumTbl,MATCH("U",SumKeys,0),MATCH($A7,SumHdr,0)) -> -0.01487733 | V7: =INDEX(SumTbl,MATCH("P_gross",SumKeys,0),MATCH($A7,SumHdr,0)) -> 6.8716631 | W7: =INDEX(SumTbl,MATCH("tau",SumKeys,0),MATCH($A7,SumHdr,0)) -> 20 | X7: =INDEX(SumTbl,MATCH("ghg0",SumKeys,0),MATCH($A7,SumHdr,0)) -> 594.156 | Y7: =INDEX(SumTbl,MATCH("ind0",SumKeys,0),MATCH($A7,SumHdr,0)) -> 88.973 | Z7: =INDEX(SumTbl,MATCH("Efbase",SumKeys,0),MATCH($A7,SumHdr,0)) -> 27.602124 | AA7: =INDEX(SumTbl,MATCH("Epbase",SumKeys,0),MATCH($A7,SumHdr,0)) -> 34.821485 | AB7: =INDEX(SumTbl,MATCH("AB_cov",SumKeys,0),MATCH($A7,SumHdr,0)) -> 375.48149 | AC7: =INDEX(SumTbl,MATCH("J",SumKeys,0),MATCH($A7,SumHdr,0)) -> 0.63195774 | AD7: =INDEX(SumTbl,MATCH("Ebase",SumKeys,0),MATCH($A7,SumHdr,0)) -> 62.42361 | AE7: =INDEX(SumTbl,MATCH("AE_cov",SumKeys,0),MATCH($A7,SumHdr,0)) -> 62.42361 | AF7: =INDEX(SumTbl,MATCH("dghg_adj",SumKeys,0),MATCH($A7,SumHdr,0)) -> -38.877 | AG7: =-INDEX(SumTbl,MATCH("dippu_adj",SumKeys,0),MATCH($A7,SumHdr,0)) -> 11.955 | AH7: =INDEX(SumTbl,MATCH("ippu_other",SumKeys,0),MATCH($A7,SumHdr,0)) -> 0 | AI7: =INDEX(SumTbl,MATCH("ERp",SumKeys,0),MATCH($A7,SumHdr,0)) -> -2.2424276 | AJ7: =INDEX(SumTbl,MATCH("emrq_proc",SumKeys,0),MATCH($A7,SumHdr,0)) -> -0.49590352 | AK7: =INDEX(SumTbl,MATCH("D_obr",SumKeys,0),MATCH($A7,SumHdr,0)) -> 0 | AL7: =INDEX(SumTbl,MATCH("F_fund",SumKeys,0),MATCH($A7,SumHdr,0)) -> 0 | AM7: =INDEX(SumTbl,MATCH("K_check",SumKeys,0),MATCH($A7,SumHdr,0)) -> 0 | AN7: =INDEX(SumTbl,MATCH("cbintchx",SumKeys,0),MATCH($A7,SumHdr,0)) -> -0.054226768 | AO7: =INDEX(SumTbl,MATCH("P_gross",SumKeys,0),MATCH($A7,SumHdr,0)) -> 6.8716631 | AP7: =INDEX(SumTbl,MATCH("rebate_bn",SumKeys,0),MATCH($A7,SumHdr,0)) -> 0 | AQ7: =INDEX(SumTbl,MATCH("O_full",SumKeys,0),MATCH($A7,SumHdr,0)) -> -0.44423635 | AR7: =INDEX(SumTbl,MATCH("AR",SumKeys,0),MATCH($A7,SumHdr,0)) -> 10.43 | AS7: 0.9 | AT7: 0.0069 | AU7: 4.8484633
A8: 2A | B8: =INDEX(BT_Scen,MATCH($A8,BT_Code,0)) -> EG1 | C8: Carbon levy on all fossil fuel consumption (upstream carbon price) + recycling to public investment | D8: Canada (prior to 2025), Mexico ($4), Colombia ($8) | E8: • Applied at point of fuel entry into the economy at low administrative cost by relying on an existing excise tax administration system • Can start gradually by recalculating existing excise duty rates on carbon content • Broad coverage across all fuel-consuming sectors but can miss process emissions • Generates measurable, verifiable carbon price for CBAM credit claims, but requires further estimates of emissions covered | F8: Energy CO2 only all sectors; revenues for public investment | G8: $20 flat from 2027 | H8: =INDEX(SumTbl,MATCH("tau",SumKeys,0),MATCH($A8,SumHdr,0)) -> 20 | I8: Public investment | J8: =INDEX(SumTbl,MATCH("J",SumKeys,0),MATCH($A8,SumHdr,0)) -> 0.57335111 | K8: =INDEX(SumTbl,MATCH("K",SumKeys,0),MATCH($A8,SumHdr,0)) -> -27.10646 | L8: =INDEX(SumTbl,MATCH("L",SumKeys,0),MATCH($A8,SumHdr,0)) -> -0.04562179 | M8: =INDEX(SumTbl,MATCH("M",SumKeys,0),MATCH($A8,SumHdr,0)) -> 0.44113057 | N8: =INDEX(SumTbl,MATCH("N",SumKeys,0),MATCH($A8,SumHdr,0)) -> -0.021477246 | O8: =INDEX(SumTbl,MATCH("O",SumKeys,0),MATCH($A8,SumHdr,0)) -> -0.23123967 | P8: =INDEX(SumTbl,MATCH("P_net",SumKeys,0),MATCH($A8,SumHdr,0)) -> 6.23 | Q8: =INDEX(SumTbl,MATCH("Q_deaths",SumKeys,0),MATCH($A8,SumHdr,0)) -> 1564 | R8: =INDEX(SumTbl,MATCH("R",SumKeys,0),MATCH($A8,SumHdr,0)) -> 0.018922941 | T8: =INDEX(SumTbl,MATCH("T",SumKeys,0),MATCH($A8,SumHdr,0)) -> -0.028478813 | U8: =INDEX(SumTbl,MATCH("U",SumKeys,0),MATCH($A8,SumHdr,0)) -> -0.0071552416 | V8: =INDEX(SumTbl,MATCH("P_gross",SumKeys,0),MATCH($A8,SumHdr,0)) -> 6.23 | W8: =INDEX(SumTbl,MATCH("tau",SumKeys,0),MATCH($A8,SumHdr,0)) -> 20 | X8: =INDEX(SumTbl,MATCH("ghg0",SumKeys,0),MATCH($A8,SumHdr,0)) -> 594.156 | Y8: =INDEX(SumTbl,MATCH("ind0",SumKeys,0),MATCH($A8,SumHdr,0)) -> 88.973 | Z8: =INDEX(SumTbl,MATCH("Efbase",SumKeys,0),MATCH($A8,SumHdr,0)) -> 27.602124 | AA8: =INDEX(SumTbl,MATCH("Epbase",SumKeys,0),MATCH($A8,SumHdr,0)) -> 34.821485 | AB8: =INDEX(SumTbl,MATCH("AB_cov",SumKeys,0),MATCH($A8,SumHdr,0)) -> 340.66 | AC8: =INDEX(SumTbl,MATCH("J",SumKeys,0),MATCH($A8,SumHdr,0)) -> 0.57335111 | AD8: =INDEX(SumTbl,MATCH("Ebase",SumKeys,0),MATCH($A8,SumHdr,0)) -> 62.42361 | AE8: =INDEX(SumTbl,MATCH("AE_cov",SumKeys,0),MATCH($A8,SumHdr,0)) -> 27.536962 | AF8: =INDEX(SumTbl,MATCH("dghg_adj",SumKeys,0),MATCH($A8,SumHdr,0)) -> -38.877 | AG8: =-INDEX(SumTbl,MATCH("dippu_adj",SumKeys,0),MATCH($A8,SumHdr,0)) -> 11.955 | AH8: =INDEX(SumTbl,MATCH("ippu_other",SumKeys,0),MATCH($A8,SumHdr,0)) -> 0 | AI8: =INDEX(SumTbl,MATCH("ERp",SumKeys,0),MATCH($A8,SumHdr,0)) -> 0 | AJ8: =INDEX(SumTbl,MATCH("emrq_proc",SumKeys,0),MATCH($A8,SumHdr,0)) -> -0.1844604 | AK8: =INDEX(SumTbl,MATCH("D_obr",SumKeys,0),MATCH($A8,SumHdr,0)) -> 0 | AL8: =INDEX(SumTbl,MATCH("F_fund",SumKeys,0),MATCH($A8,SumHdr,0)) -> 0 | AM8: =INDEX(SumTbl,MATCH("K_check",SumKeys,0),MATCH($A8,SumHdr,0)) -> 0 | AN8: =INDEX(SumTbl,MATCH("cbintchx",SumKeys,0),MATCH($A8,SumHdr,0)) -> -0.025530187 | AO8: =INDEX(SumTbl,MATCH("P_gross",SumKeys,0),MATCH($A8,SumHdr,0)) -> 6.23 | AP8: =INDEX(SumTbl,MATCH("rebate_bn",SumKeys,0),MATCH($A8,SumHdr,0)) -> 0 | AQ8: =INDEX(SumTbl,MATCH("O_full",SumKeys,0),MATCH($A8,SumHdr,0)) -> -0.23123967 | AR8: =INDEX(SumTbl,MATCH("AR",SumKeys,0),MATCH($A8,SumHdr,0)) -> 10.43 | AS8: 70-85% (IEA) | AT8: 0.0069 | AU8: 5.44362
A9: 2B | B9: =INDEX(BT_Scen,MATCH($A9,BT_Code,0)) -> EG2 | C9: Carbon levy on all fossil fuel consumption (upstream carbon price) + recycling to households | F9: Energy CO2 only all sectors: revenues per capita transfers | G9: $20 flat from 2027 | H9: =INDEX(SumTbl,MATCH("tau",SumKeys,0),MATCH($A9,SumHdr,0)) -> 20 | I9: Households | J9: =INDEX(SumTbl,MATCH("J",SumKeys,0),MATCH($A9,SumHdr,0)) -> 0.57335111 | K9: =INDEX(SumTbl,MATCH("K",SumKeys,0),MATCH($A9,SumHdr,0)) -> -28.62346 | L9: =INDEX(SumTbl,MATCH("L",SumKeys,0),MATCH($A9,SumHdr,0)) -> -0.048174992 | M9: =INDEX(SumTbl,MATCH("M",SumKeys,0),MATCH($A9,SumHdr,0)) -> 0.44113057 | N9: =INDEX(SumTbl,MATCH("N",SumKeys,0),MATCH($A9,SumHdr,0)) -> -0.021477246 | O9: =INDEX(SumTbl,MATCH("O",SumKeys,0),MATCH($A9,SumHdr,0)) -> -0.23123967 | P9: =INDEX(SumTbl,MATCH("P_net",SumKeys,0),MATCH($A9,SumHdr,0)) -> 6.19 | Q9: =INDEX(SumTbl,MATCH("Q_deaths",SumKeys,0),MATCH($A9,SumHdr,0)) -> 1631 | R9: =INDEX(SumTbl,MATCH("R",SumKeys,0),MATCH($A9,SumHdr,0)) -> 0.019733579 | T9: =INDEX(SumTbl,MATCH("T",SumKeys,0),MATCH($A9,SumHdr,0)) -> -0.028478813 | U9: =INDEX(SumTbl,MATCH("U",SumKeys,0),MATCH($A9,SumHdr,0)) -> -0.0071552416 | V9: =INDEX(SumTbl,MATCH("P_gross",SumKeys,0),MATCH($A9,SumHdr,0)) -> 6.19 | W9: =INDEX(SumTbl,MATCH("tau",SumKeys,0),MATCH($A9,SumHdr,0)) -> 20 | X9: =INDEX(SumTbl,MATCH("ghg0",SumKeys,0),MATCH($A9,SumHdr,0)) -> 594.156 | Y9: =INDEX(SumTbl,MATCH("ind0",SumKeys,0),MATCH($A9,SumHdr,0)) -> 88.973 | Z9: =INDEX(SumTbl,MATCH("Efbase",SumKeys,0),MATCH($A9,SumHdr,0)) -> 27.602124 | AA9: =INDEX(SumTbl,MATCH("Epbase",SumKeys,0),MATCH($A9,SumHdr,0)) -> 34.821485 | AB9: =INDEX(SumTbl,MATCH("AB_cov",SumKeys,0),MATCH($A9,SumHdr,0)) -> 340.66 | AC9: =INDEX(SumTbl,MATCH("J",SumKeys,0),MATCH($A9,SumHdr,0)) -> 0.57335111 | AD9: =INDEX(SumTbl,MATCH("Ebase",SumKeys,0),MATCH($A9,SumHdr,0)) -> 62.42361 | AE9: =INDEX(SumTbl,MATCH("AE_cov",SumKeys,0),MATCH($A9,SumHdr,0)) -> 27.536962 | AF9: =INDEX(SumTbl,MATCH("dghg_adj",SumKeys,0),MATCH($A9,SumHdr,0)) -> -41.002 | AG9: =-INDEX(SumTbl,MATCH("dippu_adj",SumKeys,0),MATCH($A9,SumHdr,0)) -> 12.563 | AH9: =INDEX(SumTbl,MATCH("ippu_other",SumKeys,0),MATCH($A9,SumHdr,0)) -> 0 | AI9: =INDEX(SumTbl,MATCH("ERp",SumKeys,0),MATCH($A9,SumHdr,0)) -> 0 | AJ9: =INDEX(SumTbl,MATCH("emrq_proc",SumKeys,0),MATCH($A9,SumHdr,0)) -> -0.1844604 | AK9: =INDEX(SumTbl,MATCH("D_obr",SumKeys,0),MATCH($A9,SumHdr,0)) -> 0 | AL9: =INDEX(SumTbl,MATCH("F_fund",SumKeys,0),MATCH($A9,SumHdr,0)) -> 0 | AM9: =INDEX(SumTbl,MATCH("K_check",SumKeys,0),MATCH($A9,SumHdr,0)) -> 0 | AN9: =INDEX(SumTbl,MATCH("cbintchx",SumKeys,0),MATCH($A9,SumHdr,0)) -> -0.025530187 | AO9: =INDEX(SumTbl,MATCH("P_gross",SumKeys,0),MATCH($A9,SumHdr,0)) -> 6.19 | AP9: =INDEX(SumTbl,MATCH("rebate_bn",SumKeys,0),MATCH($A9,SumHdr,0)) -> 0 | AQ9: =INDEX(SumTbl,MATCH("O_full",SumKeys,0),MATCH($A9,SumHdr,0)) -> -0.23123967 | AR9: =INDEX(SumTbl,MATCH("AR",SumKeys,0),MATCH($A9,SumHdr,0)) -> 10.62 | AS9: 70-85% (IEA) | AT9: 0.0066 | AU9: 5.44362
